Workbook

Sheet IBM Forecast T&M - AP07
A1: Billing Period Start Date | B1: 46202 | J1: HELP
A2: Billing Period End Date | B2: 46227
A3: Invoice Date | B3: 46246
A4: Billing Weeks | B4: 4 WEEKS
I6: Forecast AP07 | M6: Actuals AP07
H7: Values
A8: PO Owner | B8: PO# | C8: ProjectName | D8: ResourceName | E8: BillRate | F8: Location | G8: Comments | H8: ForecastedHours | I8: ForecastFee | J8: ForecastExpenses | K8: ForecastTotalFee | L8: ActualHours | M8: ActualFee | N8: ActualExpenses | O8: ActualTotalFee | P8: Accuracy | Q8: Expense %
A9: (blank) | B9: (blank) | C9: (blank) | D9: (blank) | E9: (blank) | F9: (blank) | G9: (blank)
B10: 9501219264 | C10: TPM - Transformation PM Support Ireland 2026 | D10: EAMONN KEATING | E10: 154 | F10: Onshore | G10: (blank) | H10: 184 | I10: 28336 | J10: 0 | K10: 28336 | M10: 0 | N10: 0 | O10: 0 | P10: 1 | Q10: 0
B11: 9501287494 | C11: SAP Concur (PT&E) Enhancement Germany Travel Allowance | D11: Sridharan K | E11: 61.75 | F11: Offshore | G11: (blank) | H11: 66 | I11: 4075.5 | J11: 0 | K11: 4075.5 | M11: 0 | N11: 0 | O11: 0 | P11: 1 | Q11: 0
A12: David McGettigan | B12: 9500905777/9501153096 | C12: SAP Application Managed Service - SAP BI Factory | D12: SHRUTI BIRE | E12: 29 | F12: Offshore | G12: (blank) | H12: 0 | I12: 0 | J12: 0 | K12: 0 | M12: 0 | N12: 0 | O12: 0 | P12: 1 | Q12: 0
D13: B MANOHAR | H13: 0 | I13: 0 | J13: 0 | K13: 0 | M13: 0 | N13: 0 | O13: 0 | P13: 1 | Q13: 0
C14: SAP Application Managed Service - SAP BI PCR 02 | D14: (blank) | E14: 47.5 | F14: Offshore | G14: (blank) | H14: 0 | I14: 0 | J14: 0 | K14: 0 | M14: 0 | N14: 0 | O14: 0 | P14: 1 | Q14: 0
C15: SAP Application Managed Service - SAP BI PCR 03 | D15: LAKSHMAN VATTURI | E15: 42.5 | F15: Offshore | G15: (blank) | H15: 0 | I15: 0 | J15: 0 | K15: 0 | M15: 0 | N15: 0 | O15: 0 | P15: 1 | Q15: 0
A16: Okan Serbest | B16: 9501070761 | C16: SAP Dalian Takeback | D16: TBD | E16: 84.5 | F16: (blank) | G16: (blank) | H16: 342 | I16: 28899 | J16: 0 | K16: 28899 | M16: 0 | N16: 0 | O16: 0 | P16: 2 | Q16: 0
D17: Hema Ghildiyal | E17: 61.75 | F17: (blank) | G17: (blank) | H17: 0 | I17: 0 | J17: 0 | K17: 0 | M17: 0 | N17: 0 | O17: 0 | P17: 1 | Q17: 0
D18: RAJAMALLU AMARAGONDA | E18: 47.5 | F18: (blank) | G18: (blank) | H18: 0 | I18: 0 | J18: 0 | K18: 0 | M18: 0 | N18: 0 | O18: 0 | P18: 1 | Q18: 0
D19: SANTOSH BAKALKAR | E19: 47.5 | F19: Offshore | G19: (blank) | H19: 0 | I19: 0 | J19: 0 | K19: 0 | M19: 0 | N19: 0 | O19: 0 | P19: 1 | Q19: 0
D20: AKHAND SINGH | E20: 47.5 | F20: (blank) | G20: (blank) | H20: 0 | I20: 0 | J20: 0 | K20: 0 | M20: 0 | N20: 0 | O20: 0 | P20: 1 | Q20: 0
D21: ASHLYN DSILVA | E21: 61.75 | F21: (blank) | G21: (blank) | H21: 0 | I21: 0 | J21: 0 | K21: 0 | M21: 0 | N21: 0 | O21: 0 | P21: 1 | Q21: 0
D22: KAVIN RAVI | E22: 47.5 | F22: (blank) | G22: (blank) | H22: 0 | I22: 0 | J22: 0 | K22: 0 | M22: 0 | N22: 0 | O22: 0 | P22: 1 | Q22: 0
D23: PRABHAKAR DHARMALA | E23: 61.75 | F23: (blank) | G23: (blank) | H23: 0 | I23: 0 | J23: 0 | K23: 0 | M23: 0 | N23: 0 | O23: 0 | P23: 1 | Q23: 0
D24: USHA KONGARA | E24: 47.5 | F24: (blank) | G24: (blank) | H24: 103.5 | I24: 4916.25 | J24: 0 | K24: 4916.25 | M24: 0 | N24: 0 | O24: 0 | P24: 1 | Q24: 0
D25: XIAO GUANG QUAN | E25: 84.5 | F25: (blank) | G25: (blank) | H25: 80 | I25: 6760 | J25: 0 | K25: 6760 | M25: 0 | N25: 0 | O25: 0 | P25: 1 | Q25: 0
D26: ARINDAM SINHA | E26: 61.75 | F26: (blank) | G26: (blank) | H26: 0 | I26: 0 | J26: 0 | K26: 0 | M26: 0 | N26: 0 | O26: 0 | P26: 1 | Q26: 0
D27: KIRANMAYEE DODLA | E27: 61.75 | F27: (blank) | G27: (blank) | H27: 0 | I27: 0 | J27: 0 | K27: 0 | M27: 0 | N27: 0 | O27: 0 | P27: 1 | Q27: 0
D28: Tony Ouyang | E28: 84.5 | F28: (blank) | G28: (blank) | H28: 171 | I28: 14449.5 | J28: 0 | K28: 14449.5 | M28: 0 | N28: 0 | O28: 0 | P28: 1 | Q28: 0
... D30: AMOL SHITOLE | E30: 61.75 | F30: (blank) | G30: (blank) | H30: 0 | I30: 0 | J30: 0 | K30: 0 | M30: 0 | N30: 0 | O30: 0 | P30: 1 | Q30: 0
C31: SAP Dalian Takeback $0 PCR | D31: LAURA DEININGER | E31: 265 | F31: Onshore | G31: (blank) | H31: 0 | I31: 0 | J31: 0 | K31: 0 | M31: 0 | N31: 0 | O31: 0 | P31: 1 | Q31: 0
D32: Dolly Osoba | E32: 307 | F32: Onshore | G32: (blank) | H32: 0 | I32: 0 | J32: 0 | K32: 0 | M32: 0 | N32: 0 | O32: 0 | P32: 1 | Q32: 0
B33: 9501140293 | C33: SAP FIN ACD 1H 2026 | D33: Swapan Sharma | E33: 205 | F33: Onshore | G33: (blank) | H33: 0 | I33: 0 | J33: 0 | K33: 0 | M33: 0 | N33: 0 | O33: 0 | P33: 1 | Q33: 0
D34: Prakash Thimmaiah | E34: 61.75 | F34: Offshore | G34: (blank) | H34: 0 | I34: 0 | J34: 0 | K34: 0 | M34: 0 | N34: 0 | O34: 0 | P34: 1 | Q34: 0
B35: 9501210950 | C35: Matsera ACD 1H 2026 Support | D35: Dolly Osoba | E35: 307 | F35: Onshore | G35: (blank) | H35: 0 | I35: 0 | J35: 0 | K35: 0 | M35: 0 | N35: 0 | O35: 0 | P35: 1 | Q35: 0
B36: 9501269309 | C36: FIN ACD 2H 2026 | D36: Swapan Sharma | E36: 205 | F36: Onshore | G36: (blank) | H36: 152 | I36: 31160 | J36: 0 | K36: 31160 | M36: 0 | N36: 0 | O36: 0 | P36: 1 | Q36: 0
D37: Prakash Thimmaiah | E37: 61.75 | F37: Offshore | G37: (blank) | H37: 171 | I37: 10559.25 | J37: 0 | K37: 10559.25 | M37: 0 | N37: 0 | O37: 0 | P37: 1 | Q37: 0
A38: Rajesh Hase | B38: 9501003131 | C38: SAP Brazil DRC Implementation | D38: TBD | E38: 47.5 | F38: Offshore | G38: (blank) | H38: 0 | I38: 0 | J38: 0 | K38: 0 | M38: 0 | N38: 0 | O38: 0 | P38: 3 | Q38: 0
D39: VENKATESULU THUMMALA | E39: 157 | F39: Onshore | G39: (blank) | H39: 0 | I39: 0 | J39: 0 | K39: 0 | M39: 0 | N39: 0 | O39: 0 | P39: 2 | Q39: 0
D40: CHANDRA JONNAGEDDALA | E40: 183 | F40: Onshore | G40: (blank) | H40: 0 | I40: 0 | J40: 0 | K40: 0 | M40: 0 | N40: 0 | O40: 0 | P40: 2 | Q40: 0
D41: VENKATESWARLU BASU | E41: 47.5 | F41: Offshore | G41: (blank) | H41: 0 | I41: 0 | J41: 0 | K41: 0 | M41: 0 | N41: 0 | O41: 0 | P41: 1 | Q41: 0
B42: 9501049922 | C42: SAP Agentic AI Implementation Delivery Team | D42: SANTHOSH R | E42: 61.75 | F42: Offshore | G42: (blank) | H42: 0 | I42: 0 | J42: 0 | K42: 0 | M42: 0 | N42: 0 | O42: 0 | P42: 1 | Q42: 0
B43: 9501169892 | C43: SAP Agentic AI – Ask SAP Phase 2 | D43: SHIV PRABAKAR | E43: 360 | F43: Onshore | G43: (blank) | H43: 0 | I43: 0 | J43: 0 | K43: 0 | M43: 0 | N43: 0 | O43: 0 | P43: 1 | Q43: 0
D44: CARLY SKLAR | E44: 207 | F44: Onshore | G44: (blank) | H44: 0 | I44: 0 | J44: 0 | K44: 0 | M44: 0 | N44: 0 | O44: 0 | P44: 1 | Q44: 0
D45: ANKITA SHARMA | E45: 47.5 | F45: Offshore | G45: (blank) | H45: 0 | I45: 0 | J45: 0 | K45: 0 | M45: 0 | N45: 0 | O45: 0 | P45: 1 | Q45: 0
D46: LAURA DEININGER | E46: 265 | F46: Onshore | G46: (blank) | H46: 0 | I46: 0 | J46: 0 | K46: 0 | M46: 0 | N46: 0 | O46: 0 | P46: 1 | Q46: 0
D47: SREERAM JAYARAM | E47: 307 | F47: Onshore | G47: (blank) | H47: 0 | I47: 0 | J47: 0 | K47: 0 | M47: 0 | N47: 0 | O47: 0 | P47: 1 | Q47: 0
D48: SANTHOSH R | E48: 47.5 | F48: Offshore | G48: (blank) | H48: 0 | I48: 0 | J48: 0 | K48: 0 | M48: 0 | N48: 0 | O48: 0 | P48: 1 | Q48: 0
D49: ASHISH KHANDELWAL | E49: 390 | F49: Onshore | G49: (blank) | H49: 0 | I49: 0 | J49: 0 | K49: 0 | M49: 0 | N49: 0 | O49: 0 | P49: 1 | Q49: 0
D50: Shreya Kataria | E50: 47.5 | F50: Onshore | G50: (blank) | H50: 0 | I50: 0 | J50: 0 | K50: 0 | M50: 0 | N50: 0 | O50: 0 | P50: 1 | Q50: 0
D51: SHUBHANGI JOSHI | E51: 61.75 | F51: Offshore | G51: (blank) | H51: 0 | I51: 0 | J51: 0 | K51: 0 | M51: 0 | N51: 0 | O51: 0 | P51: 1 | Q51: 0
D52: JUWIN PALLIPAT THOMAS | E52: 307 | F52: Onshore | G52: (blank) | H52: 0 | I52: 0 | J52: 0 | K52: 0 | M52: 0 | N52: 0 | O52: 0 | P52: 1 | Q52: 0
D53: Rajashekar Reddy R | E53: 47.5 | F53: Offshore | G53: (blank) | H53: 0 | I53: 0 | J53: 0 | K53: 0 | M53: 0 | N53: 0 | O53: 0 | P53: 1 | Q53: 0
D54: Faisal Choudary | E54: 47.5 | F54: Offshore | G54: (blank) | H54: 0 | I54: 0 | J54: 0 | K54: 0 | M54: 0 | N54: 0 | O54: 0 | P54: 1 | Q54: 0
B55: 9501169873 | C55: SAP Agentic AI Phase 2 - IEH Expansion | D55: LAURA DEININGER | E55: 265 | F55: Onshore | G55: (blank) | H55: 0 | I55: 0 | J55: 0 | K55: 0 | M55: 0 | N55: 0 | O55: 0 | P55: 1 | Q55: 0
D56: RANABRATA MONDAL | E56: 307 | F56: Onshore | G56: (blank) | H56: 62 | I56: 19034 | J56: 0 | K56: 19034 | M56: 0 | N56: 0 | O56: 0 | P56: 1 | Q56: 0
D57: SREERAM JAYARAM | E57: 307 | F57: Onshore | G57: (blank) | H57: 0 | I57: 0 | J57: 0 | K57: 0 | M57: 0 | N57: 0 | O57: 0 | P57: 1 | Q57: 0
D58: SACHIT ROHATGI | E58: 84 | F58: Offshore | G58: (blank) | H58: 126 | I58: 10584 | J58: 0 | K58: 10584 | M58: 0 | N58: 0 | O58: 0 | P58: 1 | Q58: 0
D59: Naresh Pola | E59: 47.5 | F59: Offshore | G59: (blank) | H59: 0 | I59: 0 | J59: 0 | K59: 0 | M59: 0 | N59: 0 | O59: 0 | P59: 1 | Q59: 0
D60: SANTHOSH R | E60: 47.5 | F60: Offshore | G60: (blank) | H60: 18 | I60: 855 | J60: 0 | K60: 855 | M60: 0 | N60: 0 | O60: 0 | P60: 1 | Q60: 0
D61: ASHISH KHANDELWAL | E61: 390 | F61: Onshore | G61: (blank) | H61: 0 | I61: 0 | J61: 0 | K61: 0 | M61: 0 | N61: 0 | O61: 0 | P61: 1 | Q61: 0
D62: Shreya Kataria | E62: 47.5 | F62: Offshore | G62: (blank) | H62: 0 | I62: 0 | J62: 0 | K62: 0 | M62: 0 | N62: 0 | O62: 0 | P62: 1 | Q62: 0
D63: CHAITANYA JALAGAM | E63: 47.5 | F63: Offshore | G63: (blank) | H63: 144 | I63: 6840 | J63: 0 | K63: 6840 | M63: 0 | N63: 0 | O63: 0 | P63: 1 | Q63: 0
D64: JUWIN PALLIPAT THOMAS | E64: 307 | F64: Onshore | G64: (blank) | H64: 0 | I64: 0 | J64: 0 | K64: 0 | M64: 0 | N64: 0 | O64: 0 | P64: 1 | Q64: 0
D65: Purushotham Thati | E65: 61.75 | F65: Offshore | G65: (blank) | H65: 144 | I65: 8892 | J65: 0 | K65: 8892 | M65: 0 | N65: 0 | O65: 0 | P65: 1 | Q65: 0
D66: Sri Satya Vineeth Nekkanti | E66: 47.5 | F66: Offshore | G66: (blank) | H66: 144 | I66: 6840 | J66: 0 | K66: 6840 | M66: 0 | N66: 0 | O66: 0 | P66: 1 | Q66: 0
D67: Md Nazir Ahmed | E67: 47.5 | F67: Offshore | G67: (blank) | H67: 90 | I67: 4275 | J67: 0 | K67: 4275 | M67: 0 | N67: 0 | O67: 0 | P67: 1 | Q67: 0
D68: VENKATESH MAHENDRAKAR | E68: 47.5 | F68: (blank) | G68: (blank) | H68: 0 | I68: 0 | J68: 0 | K68: 0 | M68: 0 | N68: 0 | O68: 0 | P68: 1 | Q68: 0
B69: 9501169881 | C69: SAP Agentic AI Phase 2 - Flex Agent | D69: RITESH KUMAR | E69: 185 | F69: Onshore | G69: (blank) | H69: 0 | I69: 0 | J69: 0 | K69: 0 | M69: 0 | N69: 0 | O69: 0 | P69: 1 | Q69: 0
D70: JOHN MILLER | E70: 307 | F70: Onshore | G70: (blank) | H70: 0 | I70: 0 | J70: 0 | K70: 0 | M70: 0 | N70: 0 | O70: 0 | P70: 1 | Q70: 0
D71: SREERAM JAYARAM | E71: 307 | F71: Onshore | G71: (blank) | H71: 0 | I71: 0 | J71: 0 | K71: 0 | M71: 0 | N71: 0 | O71: 0 | P71: 1 | Q71: 0
D72: Naresh Pola | E72: 61.75 | F72: Offshore | G72: (blank) | H72: 0 | I72: 0 | J72: 0 | K72: 0 | M72: 0 | N72: 0 | O72: 0 | P72: 1 | Q72: 0
D73: SUMIT KUMAR | E73: 47.5 | F73: Offshore | G73: (blank) | H73: 0 | I73: 0 | J73: 0 | K73: 0 | M73: 0 | N73: 0 | O73: 0 | P73: 1 | Q73: 0
D74: ASHISH KHANDELWAL | E74: 390 | F74: Onshore | G74: (blank) | H74: 0 | I74: 0 | J74: 0 | K74: 0 | M74: 0 | N74: 0 | O74: 0 | P74: 1 | Q74: 0
D75: Shreya Kataria | E75: 47.5 | F75: Offshore | G75: (blank) | H75: 0 | I75: 0 | J75: 0 | K75: 0 | M75: 0 | N75: 0 | O75: 0 | P75: 1 | Q75: 0
D76: SHUBHANGI JOSHI | E76: 61.75 | F76: Offshore | G76: (blank) | H76: 0 | I76: 0 | J76: 0 | K76: 0 | M76: 0 | N76: 0 | O76: 0 | P76: 1 | Q76: 0
D77: JUWIN PALLIPAT THOMAS | E77: 307 | F77: Onshore | G77: (blank) | H77: 0 | I77: 0 | J77: 0 | K77: 0 | M77: 0 | N77: 0 | O77: 0 | P77: 1 | Q77: 0
D78: Lekhan Patel | E78: 47.5 | F78: Offshore | G78: (blank) | H78: 0 | I78: 0 | J78: 0 | K78: 0 | M78: 0 | N78: 0 | O78: 0 | P78: 1 | Q78: 0
D79: Gulam Mohammed Irfani | E79: 47.5 | F79: Offshore | G79: (blank) | H79: 0 | I79: 0 | J79: 0 | K79: 0 | M79: 0 | N79: 0 | O79: 0 | P79: 1 | Q79: 0
D80: Md Nazir Ahmed | E80: 61.75 | F80: Offshore | G80: (blank) | H80: 0 | I80: 0 | J80: 0 | K80: 0 | M80: 0 | N80: 0 | O80: 0 | P80: 1 | Q80: 0
D81: Ashish Kumar Pandey | E81: 61.75 | F81: Offshore | G81: (blank) | H81: 0 | I81: 0 | J81: 0 | K81: 0 | M81: 0 | N81: 0 | O81: 0 | P81: 1 | Q81: 0
D82: Mothukuri Siva Krishna Prasad | E82: 61.75 | F82: Offshore | G82: (blank) | H82: 0 | I82: 0 | J82: 0 | K82: 0 | M82: 0 | N82: 0 | O82: 0 | P82: 1 | Q82: 0
C83: SAP Agentic AI Flex Agent PCR01 | D83: TBD | E83: 265 | F83: Offshore | G83: (blank) | H83: 0 | I83: 0 | J83: 0 | K83: 0 | M83: 0 | N83: 0 | O83: 0 | P83: 1 | Q83: 0
E84: 61.75 | F84: Offshore | G84: (blank) | H84: 0 | I84: 0 | J84: 0 | K84: 0 | M84: 0 | N84: 0 | O84: 0 | P84: 1 | Q84: 0
E85: 47.5 | F85: Offshore | G85: (blank) | H85: 0 | I85: 0 | J85: 0 | K85: 0 | M85: 0 | N85: 0 | O85: 0 | P85: 3 | Q85: 0
E86: 307 | F86: Onshore | G86: (blank) | H86: 0 | I86: 0 | J86: 0 | K86: 0 | M86: 0 | N86: 0 | O86: 0 | P86: 3 | Q86: 0
E87: 185 | F87: Onshore | G87: (blank) | H87: 0 | I87: 0 | J87: 0 | K87: 0 | M87: 0 | N87: 0 | O87: 0 | P87: 1 | Q87: 0
E88: 390 | F88: Onshore | G88: (blank) | H88: 0 | I88: 0 | J88: 0 | K88: 0 | M88: 0 | N88: 0 | O88: 0 | P88: 1 | Q88: 0
B89: 9501171343 | C89: SAP Agentic AI – Security Remediation | D89: RITESH KUMAR | E89: 165 | F89: Onshore | G89: (blank) | H89: 0 | I89: 0 | J89: 0 | K89: 0 | M89: 0 | N89: 0 | O89: 0 | P89: 1 | Q89: 0
D90: Akil K | E90: 47.5 | F90: Offshore | G90: (blank) | H90: 0 | I90: 0 | J90: 0 | K90: 0 | M90: 0 | N90: 0 | O90: 0 | P90: 1 | Q90: 0
D91: SANTHOSH R | E91: 47.5 | F91: Offshore | G91: (blank) | H91: 0 | I91: 0 | J91: 0 | K91: 0 | M91: 0 | N91: 0 | O91: 0 | P91: 1 | Q91: 0
D92: Rohan Sangave | E92: 47.5 | F92: Offshore | G92: (blank) | H92: 0 | I92: 0 | J92: 0 | K92: 0 | M92: 0 | N92: 0 | O92: 0 | P92: 1 | Q92: 0
D93: Purushotham Thati | E93: 47.5 | F93: Offshore | G93: (blank) | H93: 0 | I93: 0 | J93: 0 | K93: 0 | M93: 0 | N93: 0 | O93: 0 | P93: 1 | Q93: 0
D94: Jeet Rabadiya | E94: 47.5 | F94: Offshore | G94: (blank) | H94: 0 | I94: 0 | J94: 0 | K94: 0 | M94: 0 | N94: 0 | O94: 0 | P94: 1 | Q94: 0
D95: Meghana Kaluwar | E95: 47.5 | F95: Offshore | G95: (blank) | H95: 0 | I95: 0 | J95: 0 | K95: 0 | M95: 0 | N95: 0 | O95: 0 | P95: 1 | Q95: 0
D96: Chandra Prakash Rajput | E96: 47.5 | F96: Offshore | G96: (blank) | H96: 0 | I96: 0 | J96: 0 | K96: 0 | M96: 0 | N96: 0 | O96: 0 | P96: 1 | Q96: 0
D97: Arun Kumar Thatipalli | E97: 47.5 | F97: Offshore | G97: (blank) | H97: 0 | I97: 0 | J97: 0 | K97: 0 | M97: 0 | N97: 0 | O97: 0 | P97: 1 | Q97: 0
D98: Kadali Sriram | E98: 31.5 | F98: Offshore | G98: (blank) | H98: 0 | I98: 0 | J98: 0 | K98: 0 | M98: 0 | N98: 0 | O98: 0 | P98: 1 | Q98: 0
D99: Anusha Rajula | E99: 31.5 | F99: Offshore | G99: (blank) | H99: 0 | I99: 0 | J99: 0 | K99: 0 | M99: 0 | N99: 0 | O99: 0 | P99: 1 | Q99: 0
B100: Pending Po | C100: SAP Agentic AI IEH R3 | D100: Naresh Pola | E100: 47.5 | F100: Offshore | G100: (blank) | H100: 0 | I100: 0 | J100: 0 | K100: 0 | M100: 0 | N100: 0 | O100: 0 | P100: 1 | Q100: 0
D101: Santosh Ravi | E101: 47.5 | F101: Offshore | G101: (blank) | H101: 0 | I101: 0 | J101: 0 | K101: 0 | M101: 0 | N101: 0 | O101: 0 | P101: 1 | Q101: 0
D102: Rohan Sangave | E102: 47.5 | F102: Offshore | G102: (blank) | H102: 0 | I102: 0 | J102: 0 | K102: 0 | M102: 0 | N102: 0 | O102: 0 | P102: 1 | Q102: 0
...

Sheet IBM Forecast FP - AP07
A1: Billing Period Start Date | B1: ='IBM Forecast T&M - AP07'!B1 -> 46202
A2: Billing Period End Date | B2: ='IBM Forecast T&M - AP07'!B2 -> 46227
A3: Invoice Date | B3: ='IBM Forecast T&M - AP07'!B3 -> 46246
A4: Billing Weeks# | B4: ='IBM Forecast T&M - AP07'!B4 -> 4 WEEKS
A5: Pfizer Requested PO | B5: (All)
E6: Forecast AP07 | H6: Actuals AP07
E7: Values
A8: PO Owner | B8: PO # | C8: Project Name | D8: IBM PMA | E8: Forecast Fee $ | F8: Forecast Expenses $ | G8: Forecast Total $ | H8: Acual Fee $ | I8: Actual Expenses $ | J8: Actual Total $ | K8: Monthly Variance | L8: Forecast Accuracy | M8: Expense %
A9: Lynn Dehart | B9: 9501027309 | C9: Agentic AI Microsoft Dynamics - Extension | D9: Mansi | E9: 0 | G9: 0 | J9: 0 | K9: 0 | L9: 1 | M9: 0
C10: Agentic AI Microsoft Dynamics - PCR 2 | D10: Mansi | E10: 0 | G10: 0 | J10: 0 | K10: 0 | L10: 1 | M10: 0
A11: Andrew Alman | B11: 9501021314 | C11: Pfizer Serialization SAP ATTP/ICH 2025 2H Support | D11: Jaspal Singh | E11: 0 | G11: 0 | J11: 0 | K11: 0 | L11: 17 | M11: 0
A12: Jerome Robertson | B12: Pending PO | C12: BI AMS DI Support 2H 2026 | D12: Raju Parkala | E12: 9405 | G12: 9405 | J12: 0 | K12: -9405 | L12: 1 | M12: 0
B13: 9501160948 | C13: HBU IBP US Demand planning data ingestion to PGS UDH | D13: Jaspal Singh | E13: 0 | G13: 0 | J13: 0 | K13: 0 | L13: 1 | M13: 0
B14: 9501168669 | C14: BI: Network analytics APO CI | D14: Jaspal Singh | E14: 0 | G14: 0 | J14: 0 | K14: 0 | L14: 1 | M14: 0
B15: 9501168256 | C15: BI: Network analytics 1st Half 2026 | D15: Jaspal Singh | E15: 0 | G15: 0 | J15: 0 | K15: 0 | L15: 1 | M15: 0
B16: 9501143203 | C16: SAP Analytics Foundation - BDC-DataSphere Discovery | D16: Jaspal Singh | E16: 0 | G16: 0 | J16: 0 | K16: 0 | L16: 1 | M16: 0
A17: (blank) | B17: (blank) | C17: (blank) | D17: (blank)
B18: 9501142865 | C18: PGS Value Optimization- Project Manager- IT EOSL Device Remediation-2026 Kalmazoo MI ss | D18: Gagan | E18: 19066.67 | G18: 19066.67 | J18: 0 | K18: -19066.67 | L18: 1 | M18: 0
B19: 9501131945 | C19: Pfizer Value Optimization – 06 DSN 01 | D19: Gagan | E19: 45980 | G19: 45980 | J19: 0 | K19: -45980 | L19: 3 | M19: 0
B20: 9501173686 | C20: Network Security Engineer | D20: Gagan | E20: 19933 | G20: 19933 | J20: 0 | K20: -19933 | L20: 1 | M20: 0
B21: 9501179464 | C21: Catalyst Project - Onshore | D21: Gagan | E21: 0 | G21: 0 | J21: 0 | K21: 0 | L21: 2 | M21: 0
B22: PO Pending | C22: Consulting Services for Pfizer Counsel Related to DOJ Data Security Program Lead | D22: Mansi | E22: 59400 | G22: 59400 | J22: 0 | K22: -59400 | L22: 0 | M22: 0
B23: 9501119442, 9501168399 | C23: Procurement Services Phase 1 | D23: Mansi | E23: 507357 | G23: 507357 | J23: 0 | K23: -507357 | L23: 0 | M23: 0
B24: 9501296090 | C24: Build 20 Servers in ESXi Servers in Microsoft exchange | D24: Mansi | E24: 14668 | G24: 14668 | J24: 0 | K24: -14668 | L24: 0 | M24: 0
B25: 9501303360 | C25: Project Aegis – Network Vulnerability Management | D25: Mansi | E25: 53016 | G25: 53016 | J25: 0 | K25: -53016 | L25: 0 | M25: 0
A26: Paul Johnson | B26: 9500969299 | C26: iERP: HummingBird SOW - phase 4 2025 | D26: Jaspal Singh | E26: 0 | G26: 0 | J26: 0 | K26: 0 | L26: 1 | M26: 0
A27: Sasidhar V Mullangi | B27: PO Pending | C27: BI: Network Analytics Support 2nd half 2026 | D27: Jaspal Singh | E27: 83283.75 | G27: 83283.75 | J27: 0 | K27: -83283.75 | L27: 0 | M27: 0
C28: BI: External supply Master Data + Cyber Semester 2 2026 | D28: Jaspal Singh | E28: 29859 | G28: 29859 | J28: 0 | K28: -29859 | L28: 0 | M28: 0
C29: BI: T5-T6 - Strategic Digital Enablement (MS) Semester 2 2026 | D29: Jaspal Singh | E29: 50510.25 | G29: 50510.25 | J29: 0 | K29: -50510.25 | L29: 0 | M29: 0
C30: BI: ES Ops Portfolio Lifecycle Semester 2 2026 | D30: Jaspal Singh | E30: 71627 | G30: 71627 | J30: 0 | K30: -71627 | L30: 0 | M30: 0
C31: BI: CMO Integration Semester 2 2026 | D31: Jaspal Singh | E31: 57833.25 | G31: 57833.25 | J31: 0 | K31: -57833.25 | L31: 0 | M31: 0
C32: Supply Planning SIQ BAU Semester 2 | D32: Jaspal Singh | E32: 114700 | G32: 114700 | J32: 0 | K32: -114700 | L32: 0 | M32: 0
C33: Dalian Legacy Trackwise Data ingestion to PGS UDH | D33: Jaspal Singh | E33: 17907.5 | G33: 17907.5 | J33: 0 | K33: -17907.5 | L33: 0 | M33: 0
C34: KZO and Puurs SharePoint data to be ingested in PGS UDH | D34: Jaspal Singh | E34: 13893.5 | G34: 13893.5 | J34: 0 | K34: -13893.5 | L34: 0 | M34: 0
C35: SAIGE - Write Off Agentic AI Solution Phase II | D35: Jaspal Singh | E35: 79987.1 | G35: 79987.1 | J35: 0 | K35: -79987.1 | L35: 0 | M35: 0
C36: NWA BAU Support Semester 2 2026 | D36: Jaspal Singh | E36: 27225 | G36: 27225 | J36: 0 | K36: -27225 | L36: 0 | M36: 0
B37: 9501151669 | C37: BI: SAIGE - AI Summarization agent (Network Analytics) | D37: Jaspal Singh | E37: 68473.75 | G37: 68473.75 | J37: 0 | K37: -68473.75 | L37: 0 | M37: 0
B38: 9501287353 | C38: VMP project Snowflake IIC Developer | D38: Jaspal Singh | E38: 7532.14 | G38: 7532.14 | J38: 0 | K38: -7532.14 | L38: 0 | M38: 0
A39: Bharat Bangera | B39: 9501184708 | C39: BI:GMIS UDH Integration Enhancements and support 2026 | D39: Jaspal Singh | E39: 32936.87 | G39: 32936.87 | J39: 0 | K39: -32936.87 | L39: 0 | M39: 0
B40: 9501192891 | C40: BI: Network analytics Scrum Master Semester 1 2026 | D40: Jaspal Singh | E40: 0 | G40: 0 | J40: 0 | K40: 0 | L40: 1 | M40: 0
B41: 9501249412 | C41: SAIGE - NWA AI Ops | D41: Jaspal Singh | E41: 10154.45 | G41: 10154.45 | J41: 0 | K41: -10154.45 | L41: 0 | M41: 0
B42: 9501218129- on hold | C42: SAIGE : Agentic AI Solution for API Shortage | D42: Jaspal Singh | E42: 0 | G42: 0 | J42: 0 | K42: 0 | L42: 1 | M42: 0
B43: 9501218121 | C43: BI: Network Analytics Data quality checks 2026 | D43: Jaspal Singh | E43: 11423.75 | G43: 11423.75 | J43: 0 | K43: -11423.75 | L43: 0 | M43: 0
A44: Prabhakar Kothuru | B44: 9500936488 | C44: BI: Network Analytics Data quality checks PCR02 | D44: Jaspal Singh | E44: 0 | G44: 0 | J44: 0 | K44: 0 | L44: 1 | M44: 0
B45: 9501182055 | C45: BI: Packaging Solution CI | D45: Jaspal Singh | E45: 0 | G45: 0 | J45: 0 | K45: 0 | L45: 1 | M45: 0
B46: 9501181641 | C46: BI: Supply Planning SIQ | D46: Jaspal Singh | E46: 0 | G46: 0 | J46: 0 | K46: 0 | L46: 1 | M46: 0
B47: 9501206438 | C47: nGPS 2026 Enhancements | D47: Jaspal Singh | E47: 0 | G47: 0 | J47: 0 | K47: 0 | L47: 1 | M47: 0
B48: 9501141818 | C48: BI: HBU - SIQ Data ingestion | D48: Jaspal Singh | E48: 0 | G48: 0 | J48: 0 | K48: 0 | L48: 1 | M48: 0
B49: 9501134266 | C49: BI: SDS Data Ingestion into PGS UDH | D49: Jaspal Singh | E49: 0 | G49: 0 | J49: 0 | K49: 0 | L49: 1 | M49: 0
B50: 9501206306 | C50: PGS - IBM - BI PGS UDH APO CI nGPS Support | D50: Jaspal Singh | E50: 23206.25 | G50: 23206.25 | J50: 0 | K50: -23206.25 | L50: 0 | M50: 0
B51: 9501180872 | C51: BI: Supply Planning iFLOW Continuous Improvements | D51: Jaspal Singh | E51: 0 | G51: 0 | J51: 0 | K51: 0 | L51: 1 | M51: 0
A52: David McGettigan | B52: 9500926776 | C52: Infrastructure Support Services | D52: Mansi | E52: 854500 | G52: 854500 | J52: 0 | K52: -854500 | L52: 0 | M52: 0
B53: 9501190667 | C53: SAP Application Managed Service - SAP Core PCR 01 | D53: Raju Parkala | E53: 4166.67 | G53: 4166.67 | J53: 0 | K53: -4166.67 | L53: 0 | M53: 0
B54: 9500913079/9501166164 | C54: SAP Application Managed Service - SAP Core | D54: Raju Parkala | E54: 387633.33 | G54: 387633.33 | J54: 0 | K54: -387633.33 | L54: 0 | M54: 0
B55: 9500923118/9501158806 | C55: SAP Application Managed Service - Celonis | D55: Raju Parkala | E55: 31350 | G55: 31350 | J55: 0 | K55: -31350 | L55: 0 | M55: 0
B56: 9500920414/9501154259 | C56: SAP Application Managed Service - SAP BI Support | D56: Raju Parkala | E56: 96183.33 | G56: 96183.33 | J56: 0 | K56: -96183.33 | L56: 0 | M56: 0
C57: SAP Application Managed Service - SAP BI Support PCR03 | D57: Raju Parkala | E57: 10000 | G57: 10000 | J57: 0 | K57: -10000 | L57: 0 | M57: 0
B58: 9500920418/9501143253 | C58: SAP Application Managed Service - SAP BASIS | D58: Raju Parkala | E58: 29750 | G58: 29750 | J58: 0 | K58: -29750 | L58: 0 | M58: 0
B59: 9500914310/9501199822 | C59: SAP Application Managed Service - SAP Ariba BOD & Ariba On Prem | D59: Raju Parkala | E59: 88200 | G59: 88200 | J59: 0 | K59: -88200 | L59: 0 | M59: 0
B60: 9500913293/9501196824 | C60: SAP Application Managed Service - Concur(PT&E) | D60: Raju Parkala | E60: 36083.33 | G60: 36083.33 | J60: 0 | K60: -36083.33 | L60: 0 | M60: 0
B61: 9500920417/9501200677 | C61: SAP Application Managed Service - *Integration / Middleware / AutoSys | D61: Raju Parkala | E61: 122683.33 | G61: 122683.33 | J61: 0 | K61: -122683.33 | L61: 0 | M61: 0
B62: 9500914283/9501199827 | C62: SAP Application Managed Service - Additional Applications (10 Apps) | D62: Raju Parkala | E62: 48116.67 | G62: 48116.67 | J62: 0 | K62: -48116.67 | L62: 0 | M62: 0
B63: 9500913294/9501196865 | C63: SAP Application Managed Service - Delta Applications - FBO Scope | D63: Raju Parkala | E63: 27992 | G63: 27992 | J63: 0 | K63: -27992 | L63: 0 | M63: 0
A64: Pozath, Vasudevan | B64: 9501046636 | C64: iERP Data Archiving | D64: Jaspal Singh | E64: 0 | G64: 0 | J64: 0 | K64: 0 | L64: 1 | M64: 0
B65: 9501210568 | C65: BI: SAP Analytics: mRNA 2026 | D65: Jaspal Singh | E65: 0 | G65: 0 | J65: 0 | K65: 0 | L65: 1 | M65: 0
C66: BI: SAP Analytics: mRNA 2026 PCR 01 | D66: Jaspal Singh | E66: 10024.1 | G66: 10024.1 | J66: 0 | K66: -10024.1 | L66: 0 | M66: 0
A67: Jerry Mujica | B67: 9500839334 | C67: PGS Digital SC - IBP Kinaxis Seagen Integration Services | D67: Mansi | E67: 0 | G67: 0 | J67: 0 | K67: 0 | L67: 1 | M67: 0
B68: 9501243631 | C68: PGS Digital SC_Planning Seagen Support Services - Horizontal Planning | D68: Gagan | E68: 30000 | G68: 30000 | J68: 0 | K68: -30000 | L68: 0 | M68: 0
A69: Sachin Vaidya | B69: 9501004401 | C69: iERP: E2E Network Graph Phase 2 2025 | D69: Jaspal Singh | E69: 0 | G69: 0 | J69: 0 | K69: 0 | L69: 1 | M69: 0
A70: Rod | B70: 9501181921 | C70: BI: T5-T6 - Strategic Digital Enablement (MS) | D70: Jaspal Singh | E70: 0 | G70: 0 | J70: 0 | K70: 0 | L70: 1 | M70: 0
B71: 9501186523 | C71: BI: ES Ops Portfolio Lifecycle | D71: Jaspal Singh | E71: 0 | G71: 0 | J71: 0 | K71: 0 | L71: 1 | M71: 0
B72: 9501186948 | C72: BI: External Supply Master Data + Cyber | D72: Jaspal Singh | E72: 0 | G72: 0 | J72: 0 | K72: 0 | L72: 1 | M72: 0
A73: Jennifer Shufelt | B73: 9501151235 | C73: Device Engineering Complaint Investigations for Combination Products Extension of Steady State Support 2026 | D73: Mansi | E73: 0 | G73: 0 | J73: 0 | K73: 0 | L73: 1 | M73: 0
B74: 9501302634 | C74: Device Engineering Complaint Investigations for Combination Products July - December | D74: Mansi | E74: 131666.7 | G74: 131666.7 | J74: 0 | K74: -131666.7 | L74: 0 | M74: 0
A75: Shaun Herman | B75: 9501040718 | C75: PCR - Fieldglass Implementation - Ireland Blanket PO Support | D75: Raju Parkala | E75: 70000 | G75: 70000 | J75: 0 | K75: -70000 | L75: 0 | M75: 0
B76: 9501062399 | C76: SAP Application Managed Services – SAP Fieldglass | D76: Raju Parkala | E76: 0 | G76: 0 | J76: 0 | K76: 0 | L76: 1 | M76: 0
B77: 9500886333/9501040718 | C77: Vendor Management Solution (VMS) SAP Fieldglass Implementation -- OPEX | D77: Raju Parkala | E77: 0 | G77: 0 | J77: 0 | K77: 0 | L77: 1 | M77: 0
C78: Vendor Management Solution (VMS) SAP Fieldglass Implementation -- PCR 01 | D78: Raju Parkala | E78: 0 | G78: 0 | J78: 0 | K78: 0 | L78: 1 | M78: 0
C79: Fieldglass Implementation PCR02 | D79: Raju Parkala | E79: 10000 | G79: 10000 | J79: 0 | K79: -10000 | L79: 0 | M79: 0
C80: Vendor Management Solution (VMS) SAP Fieldglass Implementation | D80: Raju Parkala | E80: 0 | G80: 0 | J80: 0 | K80: 0 | L80: 11 | M80: 0
A81: Ryan Burnside | B81: 9501288626 | C81: PROJECT HERMES - 2026 ENHANCEMENTS | D81: Raju Parkala | E81: 26030 | G81: 26030 | J81: 0 | K81: -26030 | L81: 3 | M81: 0
A82: Jason Cava | B82: 9501144589 | C82: Pfizer PRIME Instance Deployment – Ex-US_PCR01 | D82: Raju Parkala | E82: 0 | G82: 0 | J82: 0 | K82: 0 | L82: 1 | M82: 0
B83: 9501215637 | C83: Pfizer PRIME Instance Deployment – Extension | D83: Raju Parkala | E83: 0 | G83: 0 | J83: 0 | K83: 0 | L83: 3 | M83: 0
B84: Penidng PO | C84: Project PRIME GCX Phase 3 & 4 | D84: Raju Parkala | E84: 57558.6 | G84: 57558.6 | J84: 0 | K84: -57558.6 | L84: 7 | M84: 0
A85: Kenneth R Stricker | B85: 9501171323 | C85: BI: Inter Company Analytics 1st Half 2026 | D85: Jaspal Singh | E85: 0 | G85: 0 | J85: 0 | K85: 0 | L85: 1 | M85: 0
A86: Venkat Ram Tamavada | B86: 9501212179 | C86: GLNS AMS 2026 | D86: Raju Parkala | E86: 29497.5 | G86: 29497.5 | J86: 0 | K86: -29497.5 | L86: 0 | M86: 0
B87: 9501033206/9501195328 | C87: SAP Application Managed Service - Seagen_Oracle | D87: Raju Parkala | E87: 3000 | G87: 3000 | J87: 0 | K87: -3000 | L87: 0 | M87: 0
B88: 9501250402_1H | C88: SAP_ATTP_AMS_2026 | D88: Raju Parkala | E88: 0 | G88: 0 | J88: 0 | K88: 0 | L88: 1 | M88: 0
B89: 9501250605 | C89: SAP AMS Autosys Upgrade | D89: Raju Parkala | E89: 0 | G89: 0 | J89: 0 | K89: 0 | L89: 1 | M89: 0
B90: 9501171002 | C90: Application Managed Services – ORO | D90: Raju Parkala | E90: 20000 | G90: 20000 | J90: 0 | K90: -20000 | L90: 0 | M90: 0
A91: Nikunj Patel | B91: 9501146176 | C91: SAP Serialization Security Support 2026 | D91: Raju Parkala | E91: 6521 | G91: 6521 | J91: 0 | K91: -6521 | L91: 1 | M91: 0
B92: 9501170707 | C92: SAP: Security CI 2026 | D92: Raju Parkala | E92: 24840 | G92: 24840 | J92: 0 | K92: -24840 | L92: 2 | M92: 0
C93: SAP Security CI 2026 Ext | D93: Raju Parkala | E93: 9405 | G93: 9405 | J93: 0 | K93: -9405 | L93: 2 | M93: 0
B94: 9501178705 | C94: SAP Security CI Jan 2026 | D94: Raju Parkala | E94: 0 | G94: 0 | J94: 0 | K94: 0 | L94: 2 | M94: 0
B95: 9501228202_Q1/9501228167_Q2 | C95: SAP Manufacturing Security CI 1H 2026 | D95: Raju Parkala | E95: 0 | G95: 0 | J95: 0 | K95: 0 | L95: 2 | M95: 0
A96: MICHAEL HOVANYETZ | B96: 9501027326 | C96: Pfizer PRIME Instance Deployment – Ex-US | D96: Raju Parkala | E96: 0 | G96: 0 | J96: 0 | K96: 0 | L96: 15 | M96: 0
C97: Pfizer PRIME Instance Deployment – Ex-US_PCR02 | D97: Raju Parkala | E97: 0 | G97: 0 | J97: 0 | K97: 0 | L97: 1 | M97: 0
B98: 9501156910 | C98: SAP: Prime PMO Support 1H 2026 | D98: Raju Parkala | E98: 0 | G98: 0 | J98: 0 | K98: 0 | L98: 4 | M98: 0
A99: Raymond Welgosh | B99: 9501197819 | C99: Flashstack Onboarding - Andover & Brandon - 167 Migrations - EOL VxRail Decom | D99: Mansi | E99: 0 | G99: 0 | J99: 0 | K99: 0 | L99: 1 | M99: 0
B100: 9501207588 | C100: Flashstack Onboarding – 6x PGS Flashstacks – 710 Migrations – 3x RecoverPoint – 6x VxRail Decom | D100: Mansi | E100: 26027 | G100: 26027 | J100: 0 | K100: -26027 | L100: 0 | M100: 0
...

Sheet IBM POs AP07
A1: PO# | B1: Old POs | C1: PO Name | D1: PO Owner | E1: Cost Center | F1: WBS | G1: Date Requested | H1: Comments | I1: Pfizer Owner | J1: IBM Owner | K1: Forecast Provided | L1: Forecast Provided T&M | M1: Forecast Provided FP | N1: Column1 | O1: Column2
A2: 8503164851 | C2: BI: Plant Migration to SAP: Rocky Mount & McPherson | D2: Farra, Sharon | F2: CE-BTS21076-02-10 | G2: 44682 | H2: BI | K2: =IF((L2=M2),"Not Forecasted","Forecasted") -> Not Forecasted | L2: =IF(ISNUMBER(VLOOKUP(A2,'T&M Details'!D:D,1,0)),"Forecasted","Not Forecasted") -> Not Forecasted | M2: =IF(ISNUMBER(VLOOKUP(B2,'Fixed Price Details'!D:D,1,0)),"Forecasted","Not Forecasted") -> Not Forecasted
A3: 8503222612 | C3: 2022 Serialization OpEx | D3: Beltz, Brandon | E3: 2329531 | F3: IT-PBT0113-OG-US-00 | G3: 44682 | H3: CLOSED ON PFIZER SIDE | I3: Robyn | K3: =IF((L3=M3),"Not Forecasted","Forecasted") -> Not Forecasted | L3: =IF(ISNUMBER(VLOOKUP(A3,'T&M Details'!D:D,1,0)),"Forecasted","Not Forecasted") -> Not Forecasted | M3: =IF(ISNUMBER(VLOOKUP(IBM_PO5[[#This Row],[PO'#]],'Fixed Price Details'!D:D,1,0)),"Forecasted","Not Forecasted") -> Not Forecasted
A4: 8503225962 | C4: IO Solutions Support 2022 | D4: Thomas, Immanual | E4: 2320521 | G4: 44682 | K4: =IF((L4=M4),"Not Forecasted","Forecasted") -> Not Forecasted | L4: =IF(ISNUMBER(VLOOKUP(A4,'T&M Details'!D:D,1,0)),"Forecasted","Not Forecasted") -> Not Forecasted | M4: =IF(ISNUMBER(VLOOKUP(IBM_PO5[[#This Row],[PO'#]],'Fixed Price Details'!D:D,1,0)),"Forecasted","Not Forecasted") -> Not Forecasted
A5: 8503225983 | C5: 2022 IO Solutions Resources for COVID | D5: Thomas, Immanual | F5: CE-BTS21065-02-10-10 | G5: 44682 | K5: =IF((L5=M5),"Not Forecasted","Forecasted") -> Not Forecasted | L5: =IF(ISNUMBER(VLOOKUP(A5,'T&M Details'!D:D,1,0)),"Forecasted","Not Forecasted") -> Not Forecasted | M5: =IF(ISNUMBER(VLOOKUP(IBM_PO5[[#This Row],[PO'#]],'Fixed Price Details'!D:D,1,0)),"Forecasted","Not Forecasted") -> Not Forecasted
A6: 8503228623 | C6: IO CPA 2022 | D6: Thomas, Immanual | F6: CE-BTS21004-02-10 | G6: 44682 | K6: =IF((L6=M6),"Not Forecasted","Forecasted") -> Not Forecasted | L6: =IF(ISNUMBER(VLOOKUP(A6,'T&M Details'!D:D,1,0)),"Forecasted","Not Forecasted") -> Not Forecasted | M6: =IF(ISNUMBER(VLOOKUP(IBM_PO5[[#This Row],[PO'#]],'Fixed Price Details'!D:D,1,0)),"Forecasted","Not Forecasted") -> Not Forecasted
A7: 8503238076 | C7: Rocky Mount McPherson SAP Deployment | D7: Jajodia, Amit | F7: CE-BTS21076-02-10 | G7: 44682 | K7: =IF((L7=M7),"Not Forecasted","Forecasted") -> Not Forecasted | L7: =IF(ISNUMBER(VLOOKUP(A7,'T&M Details'!D:D,1,0)),"Forecasted","Not Forecasted") -> Not Forecasted | M7: =IF(ISNUMBER(VLOOKUP(IBM_PO5[[#This Row],[PO'#]],'Fixed Price Details'!D:D,1,0)),"Forecasted","Not Forecasted") -> Not Forecasted
A8: 8503238189 | C8: ERP LOG CPA 2022 | D8: Aitha, Hari | F8: CE-BTS22009-02-10 | G8: 44682 | H8: CLOSED ON PFIZER SIDE | I8: KINJAL | K8: =IF((L8=M8),"Not Forecasted","Forecasted") -> Not Forecasted | L8: =IF(ISNUMBER(VLOOKUP(A8,'T&M Details'!D:D,1,0)),"Forecasted","Not Forecasted") -> Not Forecasted | M8: =IF(ISNUMBER(VLOOKUP(IBM_PO5[[#This Row],[PO'#]],'Fixed Price Details'!D:D,1,0)),"Forecasted","Not Forecasted") -> Not Forecasted
A9: 8503250261 | C9: 2022 SSCS Planning Continuous Improvement Project Mgt – Scrum Master | D9: White, Glenn | E9: 2351818 | G9: 44682 | H9: CLOSED ON PFIZER SIDE | I9: Michael | K9: =IF((L9=M9),"Not Forecasted","Forecasted") -> Not Forecasted | L9: =IF(ISNUMBER(VLOOKUP(A9,'T&M Details'!D:D,1,0)),"Forecasted","Not Forecasted") -> Not Forecasted | M9: =IF(ISNUMBER(VLOOKUP(IBM_PO5[[#This Row],[PO'#]],'Fixed Price Details'!D:D,1,0)),"Forecasted","Not Forecasted") -> Not Forecasted
A10: 8503250440 | C10: 2022 SSCS Planning Continuous Improvement | D10: White, Glenn | F10: CE-BTS22015-02-10 | G10: 44682 | H10: CLOSED ON PFIZER SIDE | I10: Michael | K10: =IF((L10=M10),"Not Forecasted","Forecasted") -> Not Forecasted | L10: =IF(ISNUMBER(VLOOKUP(A10,'T&M Details'!D:D,1,0)),"Forecasted","Not Forecasted") -> Not Forecasted | M10: =IF(ISNUMBER(VLOOKUP(IBM_PO5[[#This Row],[PO'#]],'Fixed Price Details'!D:D,1,0)),"Forecasted","Not Forecasted") -> Not Forecasted
A11: 8503253085 | C11: IBM SAP SUPPORT SERVICES: TEST AUTOMATIO | D11: Meadows, Leslie | E11: 2321403 | G11: 44682 | K11: =IF((L11=M11),"Not Forecasted","Forecasted") -> Not Forecasted | L11: =IF(ISNUMBER(VLOOKUP(A11,'T&M Details'!D:D,1,0)),"Forecasted","Not Forecasted") -> Not Forecasted | M11: =IF(ISNUMBER(VLOOKUP(IBM_PO5[[#This Row],[PO'#]],'Fixed Price Details'!D:D,1,0)),"Forecasted","Not Forecasted") -> Not Forecasted
A12: 8503257031 | C12: SAP Security Services 2022 | D12: Patel, Nikunj | F12: CE-BTS21064-02-10 | G12: 44682 | H12: CLOSED ON PFIZER SIDE | I12: Robyn | K12: =IF((L12=M12),"Not Forecasted","Forecasted") -> Not Forecasted | L12: =IF(ISNUMBER(VLOOKUP(A12,'T&M Details'!D:D,1,0)),"Forecasted","Not Forecasted") -> Not Forecasted | M12: =IF(ISNUMBER(VLOOKUP(IBM_PO5[[#This Row],[PO'#]],'Fixed Price Details'!D:D,1,0)),"Forecasted","Not Forecasted") -> Not Forecasted
A13: 9500010089 | C13: New Product Launch – Project Manager | D13: Vadassery, Laly | E13: 2351818 | F13: CE-BTS21059-02-EX | G13: 44682 | H13: Checking on status | I13: Robyn | K13: =IF((L13=M13),"Not Forecasted","Forecasted") -> Not Forecasted | L13: =IF(ISNUMBER(VLOOKUP(A13,'T&M Details'!D:D,1,0)),"Forecasted","Not Forecasted") -> Not Forecasted | M13: =IF(ISNUMBER(VLOOKUP(IBM_PO5[[#This Row],[PO'#]],'Fixed Price Details'!D:D,1,0)),"Forecasted","Not Forecasted") -> Not Forecasted
K14: =IF((L14=M14),"Not Forecasted","Forecasted") -> Not Forecasted | L14: =IF(ISNUMBER(VLOOKUP(A14,'T&M Details'!D:D,1,0)),"Forecasted","Not Forecasted") -> Not Forecasted | M14: =IF(ISNUMBER(VLOOKUP(IBM_PO5[[#This Row],[PO'#]],'Fixed Price Details'!D:D,1,0)),"Forecasted","Not Forecasted") -> Not Forecasted
A15: 9500011134 | C15: iERP Continuous Improvement and Support | D15: Pozath, Vasudevan | E15: 2329622 | F15: IT-FBT0504-OG-US-00 | G15: 44682 | H15: BI | K15: =IF((L15=M15),"Not Forecasted","Forecasted") -> Not Forecasted | L15: =IF(ISNUMBER(VLOOKUP(A15,'T&M Details'!D:D,1,0)),"Forecasted","Not Forecasted") -> Not Forecasted | M15: =IF(ISNUMBER(VLOOKUP(IBM_PO5[[#This Row],[PO'#]],'Fixed Price Details'!D:D,1,0)),"Forecasted","Not Forecasted") -> Not Forecasted
A16: 9500012274 | C16: PacOne UDH Datamining project PCR 01 | D16: Sasidhar V Mullangi | G16: 44682 | H16: BI | K16: =IF((L16=M16),"Not Forecasted","Forecasted") -> Not Forecasted | L16: =IF(ISNUMBER(VLOOKUP(A16,'T&M Details'!D:D,1,0)),"Forecasted","Not Forecasted") -> Not Forecasted | M16: =IF(ISNUMBER(VLOOKUP(IBM_PO5[[#This Row],[PO'#]],'Fixed Price Details'!D:D,1,0)),"Forecasted","Not Forecasted") -> Not Forecasted
A17: 9500019463 | B17: 8503143717 | C17: Serialization Solution Migration - Capital | D17: Beltz, Brandon | E17: 2320487 | G17: 44682 | H17: Finished; closure pending | I17: Robyn | K17: =IF((L17=M17),"Not Forecasted","Forecasted") -> Not Forecasted | L17: =IF(ISNUMBER(VLOOKUP(A17,'T&M Details'!D:D,1,0)),"Forecasted","Not Forecasted") -> Not Forecasted | M17: =IF(ISNUMBER(VLOOKUP(IBM_PO5[[#This Row],[PO'#]],'Fixed Price Details'!D:D,1,0)),"Forecasted","Not Forecasted") -> Not Forecasted
A18: 9500019648 | B18: 8503138178 | C18: Serialization Solution Migration - CCA | D18: Beltz, Brandon | E18: 2320487 | G18: 44682 | H18: Finished; closure pending | I18: Robyn | K18: =IF((L18=M18),"Not Forecasted","Forecasted") -> Not Forecasted | L18: =IF(ISNUMBER(VLOOKUP(A18,'T&M Details'!D:D,1,0)),"Forecasted","Not Forecasted") -> Not Forecasted | M18: =IF(ISNUMBER(VLOOKUP(IBM_PO5[[#This Row],[PO'#]],'Fixed Price Details'!D:D,1,0)),"Forecasted","Not Forecasted") -> Not Forecasted
A19: 9500019683 | B19: 8503142466 | C19: Serialization Solution Migration - Expense | D19: Beltz, Brandon | E19: 2320487 | G19: 44682 | H19: Finished; closure pending | I19: Robyn | K19: =IF((L19=M19),"Not Forecasted","Forecasted") -> Not Forecasted | L19: =IF(ISNUMBER(VLOOKUP(A19,'T&M Details'!D:D,1,0)),"Forecasted","Not Forecasted") -> Not Forecasted | M19: =IF(ISNUMBER(VLOOKUP(IBM_PO5[[#This Row],[PO'#]],'Fixed Price Details'!D:D,1,0)),"Forecasted","Not Forecasted") -> Not Forecasted
A20: 9500025724 | C20: IBM - Project NEO | D20: Davenport, Michael | E20: 2356784 | F20: AD-OFG120001-PG-G7-US | G20: 44682 | H20: EMEA | K20: =IF((L20=M20),"Not Forecasted","Forecasted") -> Not Forecasted | L20: =IF(ISNUMBER(VLOOKUP(A20,'T&M Details'!D:D,1,0)),"Forecasted","Not Forecasted") -> Not Forecasted | M20: =IF(ISNUMBER(VLOOKUP(IBM_PO5[[#This Row],[PO'#]],'Fixed Price Details'!D:D,1,0)),"Forecasted","Not Forecasted") -> Not Forecasted
A21: 9500026505 | C21: 2022 IO Solutions Covid Support | D21: Thomas, Immanual | E21: 2351818 | F21: IT-PBU0445-OT-US-00 | G21: 44682 | K21: =IF((L21=M21),"Not Forecasted","Forecasted") -> Not Forecasted | L21: =IF(ISNUMBER(VLOOKUP(A21,'T&M Details'!D:D,1,0)),"Forecasted","Not Forecasted") -> Not Forecasted | M21: =IF(ISNUMBER(VLOOKUP(IBM_PO5[[#This Row],[PO'#]],'Fixed Price Details'!D:D,1,0)),"Forecasted","Not Forecasted") -> Not Forecasted
A22: 9500026681 | C22: SCC Implementation – Consultants for Pilot Phase | D22: Hoffman, Kerry | F22: CCA22PGS03 | G22: 44682 | K22: =IF((L22=M22),"Not Forecasted","Forecasted") -> Not Forecasted | L22: =IF(ISNUMBER(VLOOKUP(A22,'T&M Details'!D:D,1,0)),"Forecasted","Not Forecasted") -> Not Forecasted | M22: =IF(ISNUMBER(VLOOKUP(IBM_PO5[[#This Row],[PO'#]],'Fixed Price Details'!D:D,1,0)),"Forecasted","Not Forecasted") -> Not Forecasted
A23: 9500026715 | C23: RM and McP ERP Deployment Expense (PM and Training) | D23: Jajodia, Amit | E23: 2351818 | F23: CE-BTS21076-02-EX | G23: 44682 | K23: =IF((L23=M23),"Not Forecasted","Forecasted") -> Not Forecasted | L23: =IF(ISNUMBER(VLOOKUP(A23,'T&M Details'!D:D,1,0)),"Forecasted","Not Forecasted") -> Not Forecasted | M23: =IF(ISNUMBER(VLOOKUP(IBM_PO5[[#This Row],[PO'#]],'Fixed Price Details'!D:D,1,0)),"Forecasted","Not Forecasted") -> Not Forecasted
A24: 9500026716 | B24: 8503263618 | C24: Offshore Resource for CI Work | D24: Musty, Prasad | E24: 2351818 | F24: IT-PBU0427-OT-US-00 | G24: 44682 | H24: CLOSED ON PFIZER SIDE | K24: =IF((L24=M24),"Not Forecasted","Forecasted") -> Not Forecasted | L24: =IF(ISNUMBER(VLOOKUP(A24,'T&M Details'!D:D,1,0)),"Forecasted","Not Forecasted") -> Not Forecasted | M24: =IF(ISNUMBER(VLOOKUP(IBM_PO5[[#This Row],[PO'#]],'Fixed Price Details'!D:D,1,0)),"Forecasted","Not Forecasted") -> Not Forecasted
A25: 9500026762 | B25: 8503263618 | C25: Mfg-Q2-Q4 -2022 Offshore Resource for MKT Work | D25: Musty, Prasad | F25: CE-BTS22037-02-10 | G25: 44682 | H25: CLOSED ON PFIZER SIDE | K25: =IF((L25=M25),"Not Forecasted","Forecasted") -> Not Forecasted | L25: =IF(ISNUMBER(VLOOKUP(A25,'T&M Details'!D:D,1,0)),"Forecasted","Not Forecasted") -> Not Forecasted | M25: =IF(ISNUMBER(VLOOKUP(IBM_PO5[[#This Row],[PO'#]],'Fixed Price Details'!D:D,1,0)),"Forecasted","Not Forecasted") -> Not Forecasted
A26: 9500030844 | C26: Technical Services for APO CI projects | D26: Emani, Phani | G26: 44699 | K26: =IF((L26=M26),"Not Forecasted","Forecasted") -> Not Forecasted | L26: =IF(ISNUMBER(VLOOKUP(A26,'T&M Details'!D:D,1,0)),"Forecasted","Not Forecasted") -> Not Forecasted | M26: =IF(ISNUMBER(VLOOKUP(IBM_PO5[[#This Row],[PO'#]],'Fixed Price Details'!D:D,1,0)),"Forecasted","Not Forecasted") -> Not Forecasted
A27: 9500027186 | B27: 8503261702 | C27: MFG CI QM 2022 | D27: Musty, Prasad | F27: CE-BTS22037-02-10 | G27: 44707 | H27: CLOSED ON PFIZER SIDE | K27: =IF((L27=M27),"Not Forecasted","Forecasted") -> Not Forecasted | L27: =IF(ISNUMBER(VLOOKUP(A27,'T&M Details'!D:D,1,0)),"Forecasted","Not Forecasted") -> Not Forecasted | M27: =IF(ISNUMBER(VLOOKUP(IBM_PO5[[#This Row],[PO'#]],'Fixed Price Details'!D:D,1,0)),"Forecasted","Not Forecasted") -> Not Forecasted
A28: 9500036775 | C28: 2022 SSCS Planning Network Change and Pfizer Connect | D28: White, Glenn | E28: 2340695 | G28: 44707 | H28: CLOSED ON PFIZER SIDE | I28: Michael | K28: =IF((L28=M28),"Not Forecasted","Forecasted") -> Not Forecasted | L28: =IF(ISNUMBER(VLOOKUP(A28,'T&M Details'!D:D,1,0)),"Forecasted","Not Forecasted") -> Not Forecasted | M28: =IF(ISNUMBER(VLOOKUP(IBM_PO5[[#This Row],[PO'#]],'Fixed Price Details'!D:D,1,0)),"Forecasted","Not Forecasted") -> Not Forecasted
A29: 8503272080 | C29: SAP Mobility 2022 | D29: Beltz, Brandon | F29: CE-PPK22001-04-01-04 | G29: 44713 | H29: CLOSED ON PFIZER SIDE | I29: Robyn | K29: =IF((L29=M29),"Not Forecasted","Forecasted") -> Not Forecasted | L29: =IF(ISNUMBER(VLOOKUP(A29,'T&M Details'!D:D,1,0)),"Forecasted","Not Forecasted") -> Not Forecasted | M29: =IF(ISNUMBER(VLOOKUP(IBM_PO5[[#This Row],[PO'#]],'Fixed Price Details'!D:D,1,0)),"Forecasted","Not Forecasted") -> Not Forecasted
A30: 9500028140 | C30: ATTP Project Coordinator | D30: Beltz, Brandon | E30: 2329531 | F30: CE-BTS21064-02-EX | G30: 44713 | H30: CLOSED ON PFIZER SIDE | I30: Robyn | K30: =IF((L30=M30),"Not Forecasted","Forecasted") -> Not Forecasted | L30: =IF(ISNUMBER(VLOOKUP(A30,'T&M Details'!D:D,1,0)),"Forecasted","Not Forecasted") -> Not Forecasted | M30: =IF(ISNUMBER(VLOOKUP(IBM_PO5[[#This Row],[PO'#]],'Fixed Price Details'!D:D,1,0)),"Forecasted","Not Forecasted") -> Not Forecasted
A31: 9500038160 | C31: Serialization ERP Functional SME | D31: Beltz, Brandon | F31: CE-PPK22001-04-01-04 | G31: 44713 | H31: CLOSED ON PFIZER SIDE | I31: Robyn | K31: =IF((L31=M31),"Not Forecasted","Forecasted") -> Not Forecasted | L31: =IF(ISNUMBER(VLOOKUP(A31,'T&M Details'!D:D,1,0)),"Forecasted","Not Forecasted") -> Not Forecasted | M31: =IF(ISNUMBER(VLOOKUP(IBM_PO5[[#This Row],[PO'#]],'Fixed Price Details'!D:D,1,0)),"Forecasted","Not Forecasted") -> Not Forecasted
A32: 9500029415 | B32: 9500024140 | C32: IBM-ERP Logistics COVID EMEA Support | D32: Aitha, Hari | G32: 44718 | H32: CLOSED ON PFIZER SIDE | I32: KINJAL | K32: =IF((L32=M32),"Not Forecasted","Forecasted") -> Not Forecasted | L32: =IF(ISNUMBER(VLOOKUP(A32,'T&M Details'!D:D,1,0)),"Forecasted","Not Forecasted") -> Not Forecasted | M32: =IF(ISNUMBER(VLOOKUP(IBM_PO5[[#This Row],[PO'#]],'Fixed Price Details'!D:D,1,0)),"Forecasted","Not Forecasted") -> Not Forecasted
A33: 9500030646 | C33: IBM - Procurement BOD 2022 [43] | D33: Senth Singaram | F33: CE-BTF17008-02-10 | G33: 44720 | K33: =IF((L33=M33),"Not Forecasted","Forecasted") -> Not Forecasted | L33: =IF(ISNUMBER(VLOOKUP(A33,'T&M Details'!D:D,1,0)),"Forecasted","Not Forecasted") -> Not Forecasted | M33: =IF(ISNUMBER(VLOOKUP(IBM_PO5[[#This Row],[PO'#]],'Fixed Price Details'!D:D,1,0)),"Forecasted","Not Forecasted") -> Not Forecasted
A34: 9500045006 | C34: ERP SAP ATTP Phase 2 Q2 2022 - CCA | D34: Beltz, Brandon | F34: CCA21PGS03 | G34: 44733 | H34: Finished; closure pending | I34: Robyn | K34: =IF((L34=M34),"Not Forecasted","Forecasted") -> Not Forecasted | L34: =IF(ISNUMBER(VLOOKUP(A34,'T&M Details'!D:D,1,0)),"Forecasted","Not Forecasted") -> Not Forecasted | M34: =IF(ISNUMBER(VLOOKUP(IBM_PO5[[#This Row],[PO'#]],'Fixed Price Details'!D:D,1,0)),"Forecasted","Not Forecasted") -> Not Forecasted
A35: 9500046249 | C35: ERP SAP ATTP Phase 2 Q2 2022 - Capital | D35: Beltz, Brandon | F35: CE-BTS21064-02-10 | G35: 44733 | H35: Finished; closure pending | I35: Robyn | K35: =IF((L35=M35),"Not Forecasted","Forecasted") -> Not Forecasted | L35: =IF(ISNUMBER(VLOOKUP(A35,'T&M Details'!D:D,1,0)),"Forecasted","Not Forecasted") -> Not Forecasted | M35: =IF(ISNUMBER(VLOOKUP(IBM_PO5[[#This Row],[PO'#]],'Fixed Price Details'!D:D,1,0)),"Forecasted","Not Forecasted") -> Not Forecasted
A36: 9500049432 | C36: IBM-MFG CI Support | D36: Attarde, Rahul | F36: CE-BTS22056-02-10 | G36: 44749 | H36: CLOSED ON PFIZER SIDE | K36: =IF((L36=M36),"Not Forecasted","Forecasted") -> Not Forecasted | L36: =IF(ISNUMBER(VLOOKUP(A36,'T&M Details'!D:D,1,0)),"Forecasted","Not Forecasted") -> Not Forecasted | M36: =IF(ISNUMBER(VLOOKUP(IBM_PO5[[#This Row],[PO'#]],'Fixed Price Details'!D:D,1,0)),"Forecasted","Not Forecasted") -> Not Forecasted
A37: 9500050997 | C37: MFG MES Extension Q2-Q4 2022 | D37: Attarde, Rahul | F37: CE-BTS22056-02-10 | G37: 44750 | H37: EMEA - CLOSED ON PFIZER SIDE | K37: =IF((L37=M37),"Not Forecasted","Forecasted") -> Not Forecasted | L37: =IF(ISNUMBER(VLOOKUP(A37,'T&M Details'!D:D,1,0)),"Forecasted","Not Forecasted") -> Not Forecasted | M37: =IF(ISNUMBER(VLOOKUP(IBM_PO5[[#This Row],[PO'#]],'Fixed Price Details'!D:D,1,0)),"Forecasted","Not Forecasted") -> Not Forecasted
A38: 9500056096 | C38: BI: iGES 2nd Half 2022 Analytics | D38: Bharat B. | G38: 44755 | H38: BI | K38: =IF((L38=M38),"Not Forecasted","Forecasted") -> Not Forecasted | L38: =IF(ISNUMBER(VLOOKUP(A38,'T&M Details'!D:D,1,0)),"Forecasted","Not Forecasted") -> Not Forecasted | M38: =IF(ISNUMBER(VLOOKUP(IBM_PO5[[#This Row],[PO'#]],'Fixed Price Details'!D:D,1,0)),"Forecasted","Not Forecasted") -> Not Forecasted
A39: 9500055768 | C39: BI MDG TINS Migration | D39: Zavala, Maria | G39: 44760 | H39: CLOSED ON PFIZER SIDE | I39: KINJAL | K39: =IF((L39=M39),"Not Forecasted","Forecasted") -> Not Forecasted | L39: =IF(ISNUMBER(VLOOKUP(A39,'T&M Details'!D:D,1,0)),"Forecasted","Not Forecasted") -> Not Forecasted | M39: =IF(ISNUMBER(VLOOKUP(IBM_PO5[[#This Row],[PO'#]],'Fixed Price Details'!D:D,1,0)),"Forecasted","Not Forecasted") -> Not Forecasted
A40: 9500053915 | C40: Serialization UDH Scrum Master | D40: Prabhakar Kothuru | F40: CE-PPK22001-04-01-04 | G40: 44763 | H40: CLOSED ON PFIZER SIDE | I40: Robyn | K40: =IF((L40=M40),"Not Forecasted","Forecasted") -> Not Forecasted | L40: =IF(ISNUMBER(VLOOKUP(A40,'T&M Details'!D:D,1,0)),"Forecasted","Not Forecasted") -> Not Forecasted | M40: =IF(ISNUMBER(VLOOKUP(IBM_PO5[[#This Row],[PO'#]],'Fixed Price Details'!D:D,1,0)),"Forecasted","Not Forecasted") -> Not Forecasted
A41: 9500058718 | C41: IBM - LOG COVID19 1H 2022 | D41: Aitha, Hari | F41: CE-BTS21065-02-10-10 | G41: 44770 | H41: CLOSED ON PFIZER SIDE | I41: KINJAL | K41: =IF((L41=M41),"Not Forecasted","Forecasted") -> Not Forecasted | L41: =IF(ISNUMBER(VLOOKUP(A41,'T&M Details'!D:D,1,0)),"Forecasted","Not Forecasted") -> Not Forecasted | M41: =IF(ISNUMBER(VLOOKUP(IBM_PO5[[#This Row],[PO'#]],'Fixed Price Details'!D:D,1,0)),"Forecasted","Not Forecasted") -> Not Forecasted
A42: 9500060121 | C42: ERP IBM Tech Dev GTIN Q3 and Q4 | D42: Zavala, Maria | G42: 44770 | H42: CLOSED ON PFIZER SIDE | I42: KINJAL | K42: =IF((L42=M42),"Not Forecasted","Forecasted") -> Not Forecasted | L42: =IF(ISNUMBER(VLOOKUP(A42,'T&M Details'!D:D,1,0)),"Forecasted","Not Forecasted") -> Not Forecasted | M42: =IF(ISNUMBER(VLOOKUP(IBM_PO5[[#This Row],[PO'#]],'Fixed Price Details'!D:D,1,0)),"Forecasted","Not Forecasted") -> Not Forecasted
A43: 9500057930 | C43: Baseline Analytics for Autonomous Planning July-December 2022 | D43: Andrew Raabe | F43: CE-BTS22088-02-10 | G43: 44775 | H43: EMEA | K43: =IF((L43=M43),"Not Forecasted","Forecasted") -> Not Forecasted | L43: =IF(ISNUMBER(VLOOKUP(A43,'T&M Details'!D:D,1,0)),"Forecasted","Not Forecasted") -> Not Forecasted | M43: =IF(ISNUMBER(VLOOKUP(IBM_PO5[[#This Row],[PO'#]],'Fixed Price Details'!D:D,1,0)),"Forecasted","Not Forecasted") -> Not Forecasted
A44: 9500058042 | C44: Visualization for Autonomous Planning Analysis | D44: Andrew Raabe | F44: CE-BTS22088-02-10 | G44: 44775 | K44: =IF((L44=M44),"Not Forecasted","Forecasted") -> Not Forecasted | L44: =IF(ISNUMBER(VLOOKUP(A44,'T&M Details'!D:D,1,0)),"Forecasted","Not Forecasted") -> Not Forecasted | M44: =IF(ISNUMBER(VLOOKUP(IBM_PO5[[#This Row],[PO'#]],'Fixed Price Details'!D:D,1,0)),"Forecasted","Not Forecasted") -> Not Forecasted
A45: 8503380907 | C45: Tuas Plant SAP carve out - Offshore Engagement | D45: Wang, Shijun Simon | G45: 44777 | K45: =IF((L45=M45),"Not Forecasted","Forecasted") -> Not Forecasted | L45: =IF(ISNUMBER(VLOOKUP(A45,'T&M Details'!D:D,1,0)),"Forecasted","Not Forecasted") -> Not Forecasted | M45: =IF(ISNUMBER(VLOOKUP(IBM_PO5[[#This Row],[PO'#]],'Fixed Price Details'!D:D,1,0)),"Forecasted","Not Forecasted") -> Not Forecasted
A46: 9500065385 | C46: Mfg-QM -Q4-2022 Resource for Onsite CI Work | D46: Musty, Prasad | E46: 2351818 | F46: IT-PBU0427-OT-US-00 | G46: 44777 | H46: CLOSED ON PFIZER SIDE | K46: =IF((L46=M46),"Not Forecasted","Forecasted") -> Not Forecasted | L46: =IF(ISNUMBER(VLOOKUP(A46,'T&M Details'!D:D,1,0)),"Forecasted","Not Forecasted") -> Not Forecasted | M46: =IF(ISNUMBER(VLOOKUP(IBM_PO5[[#This Row],[PO'#]],'Fixed Price Details'!D:D,1,0)),"Forecasted","Not Forecasted") -> Not Forecasted
A47: 9500043882 | C47: MFG Packaging Solution and ECM Deployment 2H 2022 | D47: Walsh, Angela | F47: CE-BTS22024-02-10 | G47: 44718 | H47: CLOSED ON PFIZER SIDE | I47: KINJAL | K47: =IF((L47=M47),"Not Forecasted","Forecasted") -> Not Forecasted | L47: =IF(ISNUMBER(VLOOKUP(A47,'T&M Details'!D:D,1,0)),"Forecasted","Not Forecasted") -> Not Forecasted | M47: =IF(ISNUMBER(VLOOKUP(IBM_PO5[[#This Row],[PO'#]],'Fixed Price Details'!D:D,1,0)),"Forecasted","Not Forecasted") -> Not Forecasted
A48: 9500043883 | C48: MFG MDG ES Data Collection Enhancement 2H 2022 | D48: Walsh, Angela | F48: CE-BTS20040-02-10 | G48: 44718 | K48: =IF((L48=M48),"Not Forecasted","Forecasted") -> Not Forecasted | L48: =IF(ISNUMBER(VLOOKUP(A48,'T&M Details'!D:D,1,0)),"Forecasted","Not Forecasted") -> Not Forecasted | M48: =IF(ISNUMBER(VLOOKUP(IBM_PO5[[#This Row],[PO'#]],'Fixed Price Details'!D:D,1,0)),"Forecasted","Not Forecasted") -> Not Forecasted
A49: 9500043943 | C49: 2022 IO Solutions Covid Support | D49: Thomas, Immanual | E49: 2351818 | F49: IT-PBU0445-OT-US-00 | G49: 44718 | K49: =IF((L49=M49),"Not Forecasted","Forecasted") -> Not Forecasted | L49: =IF(ISNUMBER(VLOOKUP(A49,'T&M Details'!D:D,1,0)),"Forecasted","Not Forecasted") -> Not Forecasted | M49: =IF(ISNUMBER(VLOOKUP(IBM_PO5[[#This Row],[PO'#]],'Fixed Price Details'!D:D,1,0)),"Forecasted","Not Forecasted") -> Not Forecasted
A50: 9500045111 | C50: Digital Supply Chain Solutions & ACD Global Serialization PM/BA Service | D50: Vadassery, Laly | E50: 3079012 | F50: AD-VIAEX0001-PG-05 | G50: 44719 | H50: CLOSED ON PFIZER SIDE | I50: Robyn | K50: =IF((L50=M50),"Not Forecasted","Forecasted") -> Not Forecasted | L50: =IF(ISNUMBER(VLOOKUP(A50,'T&M Details'!D:D,1,0)),"Forecasted","Not Forecasted") -> Not Forecasted | M50: =IF(ISNUMBER(VLOOKUP(IBM_PO5[[#This Row],[PO'#]],'Fixed Price Details'!D:D,1,0)),"Forecasted","Not Forecasted") -> Not Forecasted
A51: 9500049672 | C51: IBM - ERP IO Logistics Tech Strategy 2022 | D51: Attarde, Rahul | E51: 2340697 | G51: 44750 | H51: CLOSED ON PFIZER SIDE | K51: =IF((L51=M51),"Not Forecasted","Forecasted") -> Not Forecasted | L51: =IF(ISNUMBER(VLOOKUP(A51,'T&M Details'!D:D,1,0)),"Forecasted","Not Forecasted") -> Not Forecasted | M51: =IF(ISNUMBER(VLOOKUP(IBM_PO5[[#This Row],[PO'#]],'Fixed Price Details'!D:D,1,0)),"Forecasted","Not Forecasted") -> Not Forecasted
A52: 9500049737 | C52: ES&SC Support 2H-2022 | D52: Attarde, Rahul | E52: 2340694 | G52: 44750 | H52: CLOSED ON PFIZER SIDE | K52: =IF((L52=M52),"Not Forecasted","Forecasted") -> Not Forecasted | L52: =IF(ISNUMBER(VLOOKUP(A52,'T&M Details'!D:D,1,0)),"Forecasted","Not Forecasted") -> Not Forecasted | M52: =IF(ISNUMBER(VLOOKUP(IBM_PO5[[#This Row],[PO'#]],'Fixed Price Details'!D:D,1,0)),"Forecasted","Not Forecasted") -> Not Forecasted
A53: 9500051506 | C53: Mfg-QM2 – Q3-Q4 2022-Viatris Exit Quality Resource | D53: Musty, Prasad | E53: 3078659 | F53: AD-VIAEX0001-DI-07 | G53: 44750 | H53: CLOSED ON PFIZER SIDE | K53: =IF((L53=M53),"Not Forecasted","Forecasted") -> Not Forecasted | L53: =IF(ISNUMBER(VLOOKUP(A53,'T&M Details'!D:D,1,0)),"Forecasted","Not Forecasted") -> Not Forecasted | M53: =IF(ISNUMBER(VLOOKUP(IBM_PO5[[#This Row],[PO'#]],'Fixed Price Details'!D:D,1,0)),"Forecasted","Not Forecasted") -> Not Forecasted
A54: 9500051512 | C54: Mfg-QM – Q3-Q4 2022-Viatris Exit Emp Onsite Resource | D54: Musty, Prasad | E54: 3078659 | F54: AD-VIAEX0001-DI-07 | G54: 44750 | H54: CLOSED ON PFIZER SIDE | K54: =IF((L54=M54),"Not Forecasted","Forecasted") -> Not Forecasted | L54: =IF(ISNUMBER(VLOOKUP(A54,'T&M Details'!D:D,1,0)),"Forecasted","Not Forecasted") -> Not Forecasted | M54: =IF(ISNUMBER(VLOOKUP(IBM_PO5[[#This Row],[PO'#]],'Fixed Price Details'!D:D,1,0)),"Forecasted","Not Forecasted") -> Not Forecasted
A55: 9500051608 | C55: SCS Planning – Neo TSA and Exit. Second Half 2022 | D55: White, Glenn | E55: 3078659 | F55: AD-VIAEX0001-DI-07 | G55: 44750 | H55: CLOSED ON PFIZER SIDE | I55: Michael | K55: =IF((L55=M55),"Not Forecasted","Forecasted") -> Not Forecasted | L55: =IF(ISNUMBER(VLOOKUP(A55,'T&M Details'!D:D,1,0)),"Forecasted","Not Forecasted") -> Not Forecasted | M55: =IF(ISNUMBER(VLOOKUP(IBM_PO5[[#This Row],[PO'#]],'Fixed Price Details'!D:D,1,0)),"Forecasted","Not Forecasted") -> Not Forecasted
A56: 9500051729 | C56: Mfg-Procurement – Q3-Q4 2022-Viatris Exit Procurement Resources | D56: Musty, Prasad | E56: 3078659 | F56: AD-VIAEX0001-DI-07 | G56: 44750 | H56: CLOSED ON PFIZER SIDE | K56: =IF((L56=M56),"Not Forecasted","Forecasted") -> Not Forecasted | L56: =IF(ISNUMBER(VLOOKUP(A56,'T&M Details'!D:D,1,0)),"Forecasted","Not Forecasted") -> Not Forecasted | M56: =IF(ISNUMBER(VLOOKUP(IBM_PO5[[#This Row],[PO'#]],'Fixed Price Details'!D:D,1,0)),"Forecasted","Not Forecasted") -> Not Forecasted
A57: 9500052368 | C57: ERP Logistics_COVID19_Support-2022 | D57: Aitha, Hari | E57: 2351818 | F57: IT-PBU0445-OT-US-00 | G57: 44750 | H57: CLOSED ON PFIZER SIDE | I57: KINJAL | K57: =IF((L57=M57),"Not Forecasted","Forecasted") -> Not Forecasted | L57: =IF(ISNUMBER(VLOOKUP(A57,'T&M Details'!D:D,1,0)),"Forecasted","Not Forecasted") -> Not Forecasted | M57: =IF(ISNUMBER(VLOOKUP(IBM_PO5[[#This Row],[PO'#]],'Fixed Price Details'!D:D,1,0)),"Forecasted","Not Forecasted") -> Not Forecasted
A58: 9500052490 | C58: MFG PGS Product Master (December 2022) | D58: Walsh, Angela | F58: CE-BTS20040-02-10 | G58: 44750 | H58: Starting in Dec only | K58: =IF((L58=M58),"Not Forecasted","Forecasted") -> Not Forecasted | L58: =IF(ISNUMBER(VLOOKUP(A58,'T&M Details'!D:D,1,0)),"Forecasted","Not Forecasted") -> Not Forecasted | M58: =IF(ISNUMBER(VLOOKUP(IBM_PO5[[#This Row],[PO'#]],'Fixed Price Details'!D:D,1,0)),"Forecasted","Not Forecasted") -> Not Forecasted
A59: 9500052761 | C59: TINS MDG (July – November 2022 | D59: Walsh, Angela | E59: 2351818 | F59: IT-PBU0412-OT-US-00 | G59: 44750 | H59: CLOSED ON PFIZER SIDE | I59: KINJAL | K59: =IF((L59=M59),"Not Forecasted","Forecasted") -> Not Forecasted | L59: =IF(ISNUMBER(VLOOKUP(A59,'T&M Details'!D:D,1,0)),"Forecasted","Not Forecasted") -> Not Forecasted | M59: =IF(ISNUMBER(VLOOKUP(IBM_PO5[[#This Row],[PO'#]],'Fixed Price Details'!D:D,1,0)),"Forecasted","Not Forecasted") -> Not Forecasted
A60: 9500052870 | C60: MDG Offshore Support 2H 2022 | D60: Walsh, Angela | F60: CE-BTS20040-02-10 | G60: 44750 | H60: CLOSED ON PFIZER SIDE | K60: =IF((L60=M60),"Not Forecasted","Forecasted") -> Not Forecasted | L60: =IF(ISNUMBER(VLOOKUP(A60,'T&M Details'!D:D,1,0)),"Forecasted","Not Forecasted") -> Not Forecasted | M60: =IF(ISNUMBER(VLOOKUP(IBM_PO5[[#This Row],[PO'#]],'Fixed Price Details'!D:D,1,0)),"Forecasted","Not Forecasted") -> Not Forecasted
A61: 9500053081 | C61: MDG Packaging Solution 2H 2022 | D61: Fisher, Patrick | F61: CE-BTS22024-02-10 | G61: 44750 | H61: CLOSED ON PFIZER SIDE | I61: KINJAL | K61: =IF((L61=M61),"Not Forecasted","Forecasted") -> Not Forecasted | L61: =IF(ISNUMBER(VLOOKUP(A61,'T&M Details'!D:D,1,0)),"Forecasted","Not Forecasted") -> Not Forecasted | M61: =IF(ISNUMBER(VLOOKUP(IBM_PO5[[#This Row],[PO'#]],'Fixed Price Details'!D:D,1,0)),"Forecasted","Not Forecasted") -> Not Forecasted
A62: 9500053489 | C62: ES & SC CI EMEA 2022 – Landed Resource | D62: Hoffman, Kerry | E62: 2351818 | F62: CE-BTS22015-02-EX | G62: 44750 | H62: EMEA | K62: =IF((L62=M62),"Not Forecasted","Forecasted") -> Not Forecasted | L62: =IF(ISNUMBER(VLOOKUP(A62,'T&M Details'!D:D,1,0)),"Forecasted","Not Forecasted") -> Not Forecasted | M62: =IF(ISNUMBER(VLOOKUP(IBM_PO5[[#This Row],[PO'#]],'Fixed Price Details'!D:D,1,0)),"Forecasted","Not Forecasted") -> Not Forecasted
A63: 9500066627 | C63: Croatia Currency Conversion | D63: Jajodia, Amit | F63: "CE-BTS22095-02-10 72% CE-BTF22005-02-10 28%" | G63: 44781 | K63: =IF((L63=M63),"Not Forecasted","Forecasted") -> Not Forecasted | L63: =IF(ISNUMBER(VLOOKUP(A63,'T&M Details'!D:D,1,0)),"Forecasted","Not Forecasted") -> Not Forecasted | M63: =IF(ISNUMBER(VLOOKUP(IBM_PO5[[#This Row],[PO'#]],'Fixed Price Details'!D:D,1,0)),"Forecasted","Not Forecasted") -> Not Forecasted
A64: 9500072165 | C64: IBM Analytics conversion | D64: Immanual Thomas | G64: 44797 | H64: CLOSED ON PFIZER SIDE | K64: =IF((L64=M64),"Not Forecasted","Forecasted") -> Not Forecasted | L64: =IF(ISNUMBER(VLOOKUP(A64,'T&M Details'!D:D,1,0)),"Forecasted","Not Forecasted") -> Not Forecasted | M64: =IF(ISNUMBER(VLOOKUP(IBM_PO5[[#This Row],[PO'#]],'Fixed Price Details'!D:D,1,0)),"Forecasted","Not Forecasted") -> Not Forecasted
A65: 9500064305 | C65: SAP BI - Site Supply S2 | D65: PK | G65: 44797 | H65: BI | K65: =IF((L65=M65),"Not Forecasted","Forecasted") -> Not Forecasted | L65: =IF(ISNUMBER(VLOOKUP(A65,'T&M Details'!D:D,1,0)),"Forecasted","Not Forecasted") -> Not Forecasted | M65: =IF(ISNUMBER(VLOOKUP(IBM_PO5[[#This Row],[PO'#]],'Fixed Price Details'!D:D,1,0)),"Forecasted","Not Forecasted") -> Not Forecasted
A66: 9500061410 | C66: IBM Tech Dev EAH App Dev Q3 and Q4 | D66: Angela Walsh-Product master | G66: 44798 | H66: CLOSED ON PFIZER SIDE | K66: =IF((L66=M66),"Not Forecasted","Forecasted") -> Not Forecasted | L66: =IF(ISNUMBER(VLOOKUP(A66,'T&M Details'!D:D,1,0)),"Forecasted","Not Forecasted") -> Not Forecasted | M66: =IF(ISNUMBER(VLOOKUP(IBM_PO5[[#This Row],[PO'#]],'Fixed Price Details'!D:D,1,0)),"Forecasted","Not Forecasted") -> Not Forecasted
A67: 9500015733 | C67: IBM ERP LOG GME for 2022 | D67: Hari Aitha | G67: 44803 | H67: CLOSED ON PFIZER SIDE | I67: KINJAL | K67: =IF((L67=M67),"Not Forecasted","Forecasted") -> Not Forecasted | L67: =IF(ISNUMBER(VLOOKUP(A67,'T&M Details'!D:D,1,0)),"Forecasted","Not Forecasted") -> Not Forecasted | M67: =IF(ISNUMBER(VLOOKUP(IBM_PO5[[#This Row],[PO'#]],'Fixed Price Details'!D:D,1,0)),"Forecasted","Not Forecasted") -> Not Forecasted
A68: 9500058141 | C68: NEO TSA & Exit Project -Commercial 2H 2022 | D68: Paoli, Raymond | G68: 44803 | K68: =IF((L68=M68),"Not Forecasted","Forecasted") -> Not Forecasted | L68: =IF(ISNUMBER(VLOOKUP(A68,'T&M Details'!D:D,1,0)),"Forecasted","Not Forecasted") -> Not Forecasted | M68: =IF(ISNUMBER(VLOOKUP(IBM_PO5[[#This Row],[PO'#]],'Fixed Price Details'!D:D,1,0)),"Forecasted","Not Forecasted") -> Not Forecasted
A69: 9500047699 | C69: Neo TSA Exit Jul 2022 - Nov 2022 Finance Support | D69: Hase, Raj | G69: 44803 | K69: =IF((L69=M69),"Not Forecasted","Forecasted") -> Not Forecasted | L69: =IF(ISNUMBER(VLOOKUP(A69,'T&M Details'!D:D,1,0)),"Forecasted","Not Forecasted") -> Not Forecasted | M69: =IF(ISNUMBER(VLOOKUP(IBM_PO5[[#This Row],[PO'#]],'Fixed Price Details'!D:D,1,0)),"Forecasted","Not Forecasted") -> Not Forecasted
A70: 9500077333 | C70: IO Solutions Resource incremental for COVID | D70: Thomas, Immanual | F70: CE-BTS21065-02-10-10 | G70: 44812 | H70: CLOSED ON PFIZER SIDE | I70: KINJAL | K70: =IF((L70=M70),"Not Forecasted","Forecasted") -> Not Forecasted | L70: =IF(ISNUMBER(VLOOKUP(A70,'T&M Details'!D:D,1,0)),"Forecasted","Not Forecasted") -> Not Forecasted | M70: =IF(ISNUMBER(VLOOKUP(IBM_PO5[[#This Row],[PO'#]],'Fixed Price Details'!D:D,1,0)),"Forecasted","Not Forecasted") -> Not Forecasted
A71: 8503400574 | B71: 8503351514 | C71: PM Support with CJM Project | D71: Ingrid, Walgraef (Adrian Reedman) | E71: 2570885 | G71: 44812 | K71: =IF((L71=M71),"Not Forecasted","Forecasted") -> Not Forecasted | L71: =IF(ISNUMBER(VLOOKUP(A71,'T&M Details'!D:D,1,0)),"Forecasted","Not Forecasted") -> Not Forecasted | M71: =IF(ISNUMBER(VLOOKUP(IBM_PO5[[#This Row],[PO'#]],'Fixed Price Details'!D:D,1,0)),"Forecasted","Not Forecasted") -> Not Forecasted
A72: 9500076547 | C72: Serialization ERP ATTP Parallel Projects | D72: Brandon Beltz | F72: CE-PPK22001-02-10-01 | G72: 44823 | H72: CLOSED ON PFIZER SIDE | I72: Robyn | K72: =IF((L72=M72),"Not Forecasted","Forecasted") -> Not Forecasted | L72: =IF(ISNUMBER(VLOOKUP(A72,'T&M Details'!D:D,1,0)),"Forecasted","Not Forecasted") -> Not Forecasted | M72: =IF(ISNUMBER(VLOOKUP(IBM_PO5[[#This Row],[PO'#]],'Fixed Price Details'!D:D,1,0)),"Forecasted","Not Forecasted") -> Not Forecasted
A73: 9500051065 | C73: IBM - Covid Vaccine Semester 2 2Half of 2022 | D73: Paoli, Raymond | F73: CE-BTS21065-02-10-10 | G73: 44734 | H73: EMEA | K73: =IF((L73=M73),"Not Forecasted","Forecasted") -> Not Forecasted | L73: =IF(ISNUMBER(VLOOKUP(A73,'T&M Details'!D:D,1,0)),"Forecasted","Not Forecasted") -> Not Forecasted | M73: =IF(ISNUMBER(VLOOKUP(IBM_PO5[[#This Row],[PO'#]],'Fixed Price Details'!D:D,1,0)),"Forecasted","Not Forecasted") -> Not Forecasted
A74: 9500068677 | C74: Agile Scrum Master Support for iFlow | D74: Kothuru, Prabhaker | G74: 44825 | H74: EMEA | K74: =IF((L74=M74),"Not Forecasted","Forecasted") -> Not Forecasted | L74: =IF(ISNUMBER(VLOOKUP(A74,'T&M Details'!D:D,1,0)),"Forecasted","Not Forecasted") -> Not Forecasted | M74: =IF(ISNUMBER(VLOOKUP(IBM_PO5[[#This Row],[PO'#]],'Fixed Price Details'!D:D,1,0)),"Forecasted","Not Forecasted") -> Not Forecasted
A75: 8503428815 | B75: 8503419707 | C75: IO Solutions Resource for COVID - Dublin | D75: Thomas, Immanual | F75: CE-BTS21065-02-10-10 | G75: 44837 | H75: CLOSED ON PFIZER SIDE - BOTH PO's | I75: KINJAL | K75: =IF((L75=M75),"Not Forecasted","Forecasted") -> Not Forecasted | L75: =IF(ISNUMBER(VLOOKUP(A75,'T&M Details'!D:D,1,0)),"Forecasted","Not Forecasted") -> Not Forecasted | M75: =IF(ISNUMBER(VLOOKUP(IBM_PO5[[#This Row],[PO'#]],'Fixed Price Details'!D:D,1,0)),"Forecasted","Not Forecasted") -> Not Forecasted
A76: 9500053451 | C76: IBP Services for Gene Therapy | D76: White, Glenn | G76: 44848 | H76: CLOSED ON PFIZER SIDE | I76: Michael | K76: =IF((L76=M76),"Not Forecasted","Forecasted") -> Not Forecasted | L76: =IF(ISNUMBER(VLOOKUP(A76,'T&M Details'!D:D,1,0)),"Forecasted","Not Forecasted") -> Not Forecasted | M76: =IF(ISNUMBER(VLOOKUP(IBM_PO5[[#This Row],[PO'#]],'Fixed Price Details'!D:D,1,0)),"Forecasted","Not Forecasted") -> Not Forecasted
A77: 9500096322 | C77: IBM - Scrum Master | D77: Immanual Thomas | F77: CE-BTS20067-02-10 | G77: 44857 | H77: CLOSED ON PFIZER SIDE | I77: KINJAL | K77: =IF((L77=M77),"Not Forecasted","Forecasted") -> Not Forecasted | L77: =IF(ISNUMBER(VLOOKUP(A77,'T&M Details'!D:D,1,0)),"Forecasted","Not Forecasted") -> Not Forecasted | M77: =IF(ISNUMBER(VLOOKUP(IBM_PO5[[#This Row],[PO'#]],'Fixed Price Details'!D:D,1,0)),"Forecasted","Not Forecasted") -> Not Forecasted
A78: 9500087231 | C78: ATTP transition BTAMS support | D78: Beltz, Brandon | E78: 2351591 | G78: 44861 | H78: Active | I78: Robyn | K78: =IF((L78=M78),"Not Forecasted","Forecasted") -> Not Forecasted | L78: =IF(ISNUMBER(VLOOKUP(A78,'T&M Details'!D:D,1,0)),"Forecasted","Not Forecasted") -> Not Forecasted | M78: =IF(ISNUMBER(VLOOKUP(IBM_PO5[[#This Row],[PO'#]],'Fixed Price Details'!D:D,1,0)),"Forecasted","Not Forecasted") -> Not Forecasted
A79: 9500074970 | B79: 9500019444 | C79: Pfizer IMEx 2022-2 Material Supply Extension | D79: Farrell, James | E79: 2351818 | G79: 44804 | H79: EMEA | K79: =IF((L79=M79),"Not Forecasted","Forecasted") -> Not Forecasted | L79: =IF(ISNUMBER(VLOOKUP(A79,'T&M Details'!D:D,1,0)),"Forecasted","Not Forecasted") -> Not Forecasted | M79: =IF(ISNUMBER(VLOOKUP(IBM_PO5[[#This Row],[PO'#]],'Fixed Price Details'!D:D,1,0)),"Forecasted","Not Forecasted") -> Not Forecasted
A80: 9500079259 | C80: IBM - Finance CI Q4 2022 | D80: Ely, Mark | G80: 44817 | K80: =IF((L80=M80),"Not Forecasted","Forecasted") -> Not Forecasted | L80: =IF(ISNUMBER(VLOOKUP(A80,'T&M Details'!D:D,1,0)),"Forecasted","Not Forecasted") -> Not Forecasted | M80: =IF(ISNUMBER(VLOOKUP(IBM_PO5[[#This Row],[PO'#]],'Fixed Price Details'!D:D,1,0)),"Forecasted","Not Forecasted") -> Not Forecasted
A81: 9500095484 | C81: IBM - Procurement CI Q4 2022 | D81: Senth Singaram | G81: 44851 | K81: =IF((L81=M81),"Not Forecasted","Forecasted") -> Not Forecasted | L81: =IF(ISNUMBER(VLOOKUP(A81,'T&M Details'!D:D,1,0)),"Forecasted","Not Forecasted") -> Not Forecasted | M81: =IF(ISNUMBER(VLOOKUP(IBM_PO5[[#This Row],[PO'#]],'Fixed Price Details'!D:D,1,0)),"Forecasted","Not Forecasted") -> Not Forecasted
A82: 9500102110 | C82: Cyber Security Analytics for External supply business 2H 2022 | G82: 44876 | H82: BI | K82: =IF((L82=M82),"Not Forecasted","Forecasted") -> Not Forecasted | L82: =IF(ISNUMBER(VLOOKUP(A82,'T&M Details'!D:D,1,0)),"Forecasted","Not Forecasted") -> Not Forecasted | M82: =IF(ISNUMBER(VLOOKUP(IBM_PO5[[#This Row],[PO'#]],'Fixed Price Details'!D:D,1,0)),"Forecasted","Not Forecasted") -> Not Forecasted
A83: 9500080727 | C83: IBM - GTS Changes to Support Croatia Currency Conversion to Euro | G83: 44888 | H83: EMEA | K83: =IF((L83=M83),"Not Forecasted","Forecasted") -> Not Forecasted | L83: =IF(ISNUMBER(VLOOKUP(A83,'T&M Details'!D:D,1,0)),"Forecasted","Not Forecasted") -> Not Forecasted | M83: =IF(ISNUMBER(VLOOKUP(IBM_PO5[[#This Row],[PO'#]],'Fixed Price Details'!D:D,1,0)),"Forecasted","Not Forecasted") -> Not Forecasted
A84: 9500129015 | C84: 2023 IBM McP ERP Deployment Business Adoption | D84: Jajodia, Amit | E84: 2351818 | F84: CE-BTS21076-02-EX | G84: 44887 | H84: New PO for BA work in 2023, will add forecast in Jan cycle | K84: =IF((L84=M84),"Not Forecasted","Forecasted") -> Not Forecasted | L84: =IF(ISNUMBER(VLOOKUP(A84,'T&M Details'!D:D,1,0)),"Forecasted","Not Forecasted") -> Not Forecasted | M84: =IF(ISNUMBER(VLOOKUP(IBM_PO5[[#This Row],[PO'#]],'Fixed Price Details'!D:D,1,0)),"Forecasted","Not Forecasted") -> Not Forecasted
A85: 9500134344 | C85: 2023 IBM McP ERP Deployment Capital | D85: Jajodia, Amit | E85: 14266 | F85: CE-BTS21076-02-10 | G85: 44893 | H85: New PO for all Capital work - RM/McP ERP Deploment, will Forecast later, starts in Jan | K85: =IF((L85=M85),"Not Forecasted","Forecasted") -> Not Forecasted | L85: =IF(ISNUMBER(VLOOKUP(A85,'T&M Details'!D:D,1,0)),"Forecasted","Not Forecasted") -> Not Forecasted | M85: =IF(ISNUMBER(VLOOKUP(IBM_PO5[[#This Row],[PO'#]],'Fixed Price Details'!D:D,1,0)),"Forecasted","Not Forecasted") -> Not Forecasted
A86: 9500061420 | C86: IBM Tech Dev Supply Execution Market Restriction Q3 and Q4 | D86: Musty, Prasad | F86: CE-BTS22037-02-10 | G86: 44895 | H86: CLOSED ON PFIZER SIDE | K86: =IF((L86=M86),"Not Forecasted","Forecasted") -> Not Forecasted | L86: =IF(ISNUMBER(VLOOKUP(A86,'T&M Details'!D:D,1,0)),"Forecasted","Not Forecasted") -> Not Forecasted | M86: =IF(ISNUMBER(VLOOKUP(IBM_PO5[[#This Row],[PO'#]],'Fixed Price Details'!D:D,1,0)),"Forecasted","Not Forecasted") -> Not Forecasted
A87: 9500030886 | C87: IBM - Mfg-Q2- Q4-2022 PM Resource- for Market Restrictions | D87: Musty, Prasad | F87: CE-BTS22037-02-10 | G87: 44895 | H87: CLOSED ON PFIZER SIDE | K87: =IF((L87=M87),"Not Forecasted","Forecasted") -> Not Forecasted | L87: =IF(ISNUMBER(VLOOKUP(A87,'T&M Details'!D:D,1,0)),"Forecasted","Not Forecasted") -> Not Forecasted | M87: =IF(ISNUMBER(VLOOKUP(IBM_PO5[[#This Row],[PO'#]],'Fixed Price Details'!D:D,1,0)),"Forecasted","Not Forecasted") -> Not Forecasted
A88: 9500115835 | B88: 9500040457 | C88: ATTP iERP Reporting Support 2023 | D88: Vasudevan Pozath | F88: CE-BTS21064-02-10 | G88: 44895 | H88: Migrated to ATTP fixed fee contract; closure pending | I88: Robyn | K88: =IF((L88=M88),"Not Forecasted","Forecasted") -> Not Forecasted | L88: =IF(ISNUMBER(VLOOKUP(A88,'T&M Details'!D:D,1,0)),"Forecasted","Not Forecasted") -> Not Forecasted | M88: =IF(ISNUMBER(VLOOKUP(IBM_PO5[[#This Row],[PO'#]],'Fixed Price Details'!D:D,1,0)),"Forecasted","Not Forecasted") -> Not Forecasted
A89: 9500027295 | C89: Neo TSA Ongoing Support | D89: Serbest, Okan | G89: 44897 | K89: =IF((L89=M89),"Not Forecasted","Forecasted") -> Not Forecasted | L89: =IF(ISNUMBER(VLOOKUP(A89,'T&M Details'!D:D,1,0)),"Forecasted","Not Forecasted") -> Not Forecasted | M89: =IF(ISNUMBER(VLOOKUP(IBM_PO5[[#This Row],[PO'#]],'Fixed Price Details'!D:D,1,0)),"Forecasted","Not Forecasted") -> Not Forecasted
A90: 9500070203 | C90: ERP IBM Neo End State Enhancements | D90: Serbest, Okan | G90: 44897 | K90: =IF((L90=M90),"Not Forecasted","Forecasted") -> Not Forecasted | L90: =IF(ISNUMBER(VLOOKUP(A90,'T&M Details'!D:D,1,0)),"Forecasted","Not Forecasted") -> Not Forecasted | M90: =IF(ISNUMBER(VLOOKUP(IBM_PO5[[#This Row],[PO'#]],'Fixed Price Details'!D:D,1,0)),"Forecasted","Not Forecasted") -> Not Forecasted
A91: 9500049105 | C91: Viatris Data Services 2H2022 | D91: Serbest, Okan | G91: 44897 | K91: =IF((L91=M91),"Not Forecasted","Forecasted") -> Not Forecasted | L91: =IF(ISNUMBER(VLOOKUP(A91,'T&M Details'!D:D,1,0)),"Forecasted","Not Forecasted") -> Not Forecasted | M91: =IF(ISNUMBER(VLOOKUP(IBM_PO5[[#This Row],[PO'#]],'Fixed Price Details'!D:D,1,0)),"Forecasted","Not Forecasted") -> Not Forecasted
A92: 9500119695 | C92: Mfg-QM-CI-DEC2022 work | D92: Musty, Prasad | G92: 44900 | H92: CLOSED ON PFIZER SIDE | K92: =IF((L92=M92),"Not Forecasted","Forecasted") -> Not Forecasted | L92: =IF(ISNUMBER(VLOOKUP(A92,'T&M Details'!D:D,1,0)),"Forecasted","Not Forecasted") -> Not Forecasted | M92: =IF(ISNUMBER(VLOOKUP(IBM_PO5[[#This Row],[PO'#]],'Fixed Price Details'!D:D,1,0)),"Forecasted","Not Forecasted") -> Not Forecasted
A93: 9500122433 | B93: 9500028149 | C93: IBM - MFG NPL Microsoft Integration 3Q 2022 – Capital to Expense [21] | D93: Zavala, Maria/Laly | E93: 2351818 | F93: CE-BTS21059-02-EX | G93: 44909 | H93: Rob Jones PO | K93: =IF((L93=M93),"Not Forecasted","Forecasted") -> Not Forecasted | L93: =IF(ISNUMBER(VLOOKUP(A93,'T&M Details'!D:D,1,0)),"Forecasted","Not Forecasted") -> Not Forecasted | M93: =IF(ISNUMBER(VLOOKUP(IBM_PO5[[#This Row],[PO'#]],'Fixed Price Details'!D:D,1,0)),"Forecasted","Not Forecasted") -> Not Forecasted
A94: 9500141862 | D94: Phani/Prasad | G94: 45281 | H94: Sam | K94: =IF((L94=M94),"Not Forecasted","Forecasted") -> Not Forecasted | L94: =IF(ISNUMBER(VLOOKUP(A94,'T&M Details'!D:D,1,0)),"Forecasted","Not Forecasted") -> Not Forecasted | M94: =IF(ISNUMBER(VLOOKUP(IBM_PO5[[#This Row],[PO'#]],'Fixed Price Details'!D:D,1,0)),"Forecasted","Not Forecasted") -> Not Forecasted
A95: 9500144503 | C95: SAP ECC to S/4HANA Migration Capital | D95: Hase, Raj | F95: CE-BTF22001-02-10 | G95: 44932 | K95: =IF((L95=M95),"Not Forecasted","Forecasted") -> Not Forecasted | L95: =IF(ISNUMBER(VLOOKUP(A95,'T&M Details'!D:D,1,0)),"Forecasted","Not Forecasted") -> Not Forecasted | M95: =IF(ISNUMBER(VLOOKUP(IBM_PO5[[#This Row],[PO'#]],'Fixed Price Details'!D:D,1,0)),"Forecasted","Not Forecasted") -> Not Forecasted
A96: 9500161830 | C96: IO Solutions CI CPA 2023 | D96: Thomas, Immanual | F96: CE-BTS23012-02-10 | G96: 44932 | K96: =IF((L96=M96),"Not Forecasted","Forecasted") -> Not Forecasted | L96: =IF(ISNUMBER(VLOOKUP(A96,'T&M Details'!D:D,1,0)),"Forecasted","Not Forecasted") -> Not Forecasted | M96: =IF(ISNUMBER(VLOOKUP(IBM_PO5[[#This Row],[PO'#]],'Fixed Price Details'!D:D,1,0)),"Forecasted","Not Forecasted") -> Not Forecasted
A97: 9500161652 | C97: 2023 IO Solutions Support | D97: Thomas, Immanual | E97: 2320521 | F97: IT-FBT0397-OG-US-00 | G97: 44932 | K97: =IF((L97=M97),"Not Forecasted","Forecasted") -> Not Forecasted | L97: =IF(ISNUMBER(VLOOKUP(A97,'T&M Details'!D:D,1,0)),"Forecasted","Not Forecasted") -> Not Forecasted | M97: =IF(ISNUMBER(VLOOKUP(IBM_PO5[[#This Row],[PO'#]],'Fixed Price Details'!D:D,1,0)),"Forecasted","Not Forecasted") -> Not Forecasted
A98: 9500161349 | C98: IO Solutions RTM 2023 | D98: Thomas, Immanual | F98: CE-BTS23013-02-10 | G98: 44932 | K98: =IF((L98=M98),"Not Forecasted","Forecasted") -> Not Forecasted | L98: =IF(ISNUMBER(VLOOKUP(A98,'T&M Details'!D:D,1,0)),"Forecasted","Not Forecasted") -> Not Forecasted | M98: =IF(ISNUMBER(VLOOKUP(IBM_PO5[[#This Row],[PO'#]],'Fixed Price Details'!D:D,1,0)),"Forecasted","Not Forecasted") -> Not Forecasted
A99: 9500157163 | C99: Project Covid SOM 1H 2023_Landed | D99: Vaidya, Sachin | E99: 2340696 | G99: 44932 | K99: =IF((L99=M99),"Not Forecasted","Forecasted") -> Not Forecasted | L99: =IF(ISNUMBER(VLOOKUP(A99,'T&M Details'!D:D,1,0)),"Forecasted","Not Forecasted") -> Not Forecasted | M99: =IF(ISNUMBER(VLOOKUP(IBM_PO5[[#This Row],[PO'#]],'Fixed Price Details'!D:D,1,0)),"Forecasted","Not Forecasted") -> Not Forecasted
A100: 9500156876 | C100: SAP ECC to S/4HANA Migration Expense | D100: Hase, Raj | E100: 2329609 | F100: CE-BTF22001-02-EX | G100: 44932 | K100: =IF((L100=M100),"Not Forecasted","Forecasted") -> Not Forecasted | L100: =IF(ISNUMBER(VLOOKUP(A100,'T&M Details'!D:D,1,0)),"Forecasted","Not Forecasted") -> Not Forecasted | M100: =IF(ISNUMBER(VLOOKUP(IBM_PO5[[#This Row],[PO'#]],'Fixed Price Details'!D:D,1,0)),"Forecasted","Not Forecasted") -> Not Forecasted
...

Sheet T&M Details
A1: Pfizer requested PO | B1: PMA | C1: PO Owner | D1: PO # | E1: Work Code | F1: Project Name | G1: Project Start Date | H1: Project End Date | I1: Resource Talent Id | J1: Resource Name | K1: Bill Rate | L1: Location | M1: Resource Status | N1: Forecast Month Hours | O1: Forecast Fee $ | P1: Forecast Expenses $ | Q1: Forecast Total $ | R1: Actual Month Hours | S1: Acual Fee $ | T1: Actual Expenses $ | U1: Actual Total $ | V1: Monthly Hours Variance | W1: Hours Billed Flag | X1: Forecast Accuracy | Y1: Expense% | Z1: Comments | AA1: Total Forecast Hours 2025 | AB1: Jan 2026 - FFHours | AC1: Feb 2026 - FHours | AD1: March 2026 - FHours | AE1: April 2026 - FHours | AF1: May 2026 - FHours | AG1: June 2026 - FHours | AH1: July 2026 - FHours | AI1: Aug 2026 - FHours | AJ1: Sep 2026 - FHours | AK1: Oct 2026 - FHours | AL1: Nov 2026 - FHours | AM1: Dec 2026 - FHours | AN1: 2026 Forecast total Fee | AO1: Jan 2026 - FFee | AP1: Feb 2026 - FFee | AQ1: March 2026 - FFee | AR1: April 2026 - FFee | AS1: May 2026 - FFee | AT1: June 2026 - FFee | AU1: July 2026 - FFee | AV1: Aug 2026 - FFee | AW1: Sep 2026 - FFee | AX1: Oct 2026 - FFee | AY1: Nov 2026 - FFee | AZ1: Dec 2026 - FFee | BA1: 2026 Total Forecast Expenses | BB1: Jan 2026 - FExpenses | BC1: Feb 2026 - FExpenses | BD1: March 2026 - FExpenses | BE1: April 2026 - FExpenses | BF1: May 2026 - FExpenses | BG1: June 2026 - FExpenses | BH1: July 2026 - FExpenses | BI1: Aug 2026 - FExpenses | BJ1: Sep 2026 - FExpenses | BK1: Oct 2026 - FExpenses | BL1: Nov 2026 - FExpenses | BM1: Dec 2026 - FExpenses | BN1: Forecast Total 2026 | BO1: Jan 2026 - FTotal | BP1: Feb 2026 - FTotal | BQ1: March 2026 - FTotal | BR1: April 2026 - FTotal | BS1: May 2026 - FTotal | BT1: June 2026 - FTotal | BU1: July 2026 - FTotal | BV1: Aug 2026 - FTotal | BW1: Sep 2026 - FTotal | BX1: Oct 2026 - FTotal | BY1: Nov 2026 - FTotal | BZ1: Dec 2026 - FTotal
A2: =IF(ISNUMBER(INDEX('IBM POs AP07'!$A:$A, MATCH(D2,'IBM POs AP07'!$A:$A,0),1)),"Yes","No") -> No | B2: Raju Parkala | C2: David McGettigan | D2: 9500905777/9501153096 | E2: W3F1Z | F2: SAP Application Managed Service - SAP BI Factory | G2: 45717 | H2: 47542 | I2: 005P89 | J2: B MANOHAR | K2: 29 | L2: Offshore | N2: =AH2 -> 0 | O2: =N2*K2 -> 0 | P2: =BF2 -> 0 | Q2: =O2+P2 -> 0 | S2: =R2*K2 -> 0 | T2: 0 | U2: =S2+T2 -> 0 | V2: =Q2-U2 -> 0 | W2: =IF(AND(L2="Offshore",R2>N2),"Red Flag",IF(AND(OR(L2="Onshore",L2="EMEA"),R2>N2),"Red Flag","")) | X2: 1 | Y2: 0 | AA2: =SUM(AB2:AM2) -> 668 | AB2: 162 | AC2: 162 | AD2: 192 | AE2: 152 | AF2: 0 | AG2: 0 | AH2: 0 | AI2: 0 | AJ2: 0 | AK2: 0 | AL2: 0 | AM2: 0 | AN2: =SUM(AO2:AZ2) -> 19372 | AO2: =AB2*$K2 -> 4698 | AP2: =AC2*$K2 -> 4698 | AQ2: =AD2*$K2 -> 5568 | AR2: =AE2*$K2 -> 4408 | AS2: =AF2*$K2 -> 0 | AT2: =AG2*$K2 -> 0 | AU2: =AH2*$K2 -> 0 | AV2: =AI2*$K2 -> 0 | ... AZ2: =AM2*$K2 -> 0 | BA2: =SUM(BB2:BM2) -> 0 | BB2: 0 | BC2: 0 | BD2: 0 | BE2: 0 | BF2: 0 | BG2: 0 | BH2: 0 | BI2: 0 | BJ2: 0 | BK2: 0 | BL2: 0 | BM2: 0 | BN2: =SUM(BO2:BZ2) -> 19372 | BO2: =BB2+AO2 -> 4698 | BP2: =BC2+AP2 -> 4698 | BQ2: =BD2+AQ2 -> 5568 | BR2: =BE2+AR2 -> 4408 | BS2: =BF2+AS2 -> 0 | BT2: =BG2+AT2 -> 0 | BU2: =BH2+AU2 -> 0 | BV2: =BI2+AV2 -> 0 | ... BZ2: =BM2+AZ2 -> 0
A3: =IF(ISNUMBER(INDEX('IBM POs AP07'!$A:$A, MATCH(D3,'IBM POs AP07'!$A:$A,0),1)),"Yes","No") -> No | B3: Raju Parkala | C3: David McGettigan | D3: 9500905777/9501153096 | E3: W3F1Z | F3: SAP Application Managed Service - SAP BI Factory | G3: 45717 | H3: 47542 | I3: 005JV3 | J3: SHRUTI BIRE | K3: 29 | L3: Offshore | N3: =AH3 -> 0 | O3: =N3*K3 -> 0 | P3: =BF3 -> 0 | Q3: =O3+P3 -> 0 | S3: =R3*K3 -> 0 | T3: 0 | U3: =S3+T3 -> 0 | V3: =Q3-U3 -> 0 | W3: =IF(AND(L3="Offshore",R3>N3),"Red Flag",IF(AND(OR(L3="Onshore",L3="EMEA"),R3>N3),"Red Flag","")) | X3: 1 | Y3: 0 | AA3: =SUM(AB3:AM3) -> 624 | AB3: 144 | AC3: 153 | AD3: 192 | AE3: 135 | AF3: 0 | AG3: 0 | AN3: =SUM(AO3:AZ3) -> 18096 | AO3: =AB3*$K3 -> 4176 | AP3: =AC3*$K3 -> 4437 | AQ3: =AD3*$K3 -> 5568 | AR3: =AE3*$K3 -> 3915 | AS3: =AF3*$K3 -> 0 | AT3: =AG3*$K3 -> 0 | AU3: =AH3*$K3 -> 0 | AV3: =AI3*$K3 -> 0 | ... AZ3: =AM3*$K3 -> 0 | BA3: =SUM(BB3:BM3) -> 0 | BB3: 0 | BC3: 0 | BD3: 0 | BE3: 0 | BF3: 0 | BG3: 0 | BH3: 0 | BI3: 0 | BJ3: 0 | BK3: 0 | BL3: 0 | BM3: 0 | BN3: =SUM(BO3:BZ3) -> 18096 | BO3: =BB3+AO3 -> 4176 | BP3: =BC3+AP3 -> 4437 | BQ3: =BD3+AQ3 -> 5568 | BR3: =BE3+AR3 -> 3915 | BS3: =BF3+AS3 -> 0 | BT3: =BG3+AT3 -> 0 | BU3: =BH3+AU3 -> 0 | BV3: =BI3+AV3 -> 0 | ... BZ3: =BM3+AZ3 -> 0
A4: =IF(ISNUMBER(INDEX('IBM POs AP07'!$A:$A, MATCH(D4,'IBM POs AP07'!$A:$A,0),1)),"Yes","No") -> No | B4: Raju Parkala | C4: David McGettigan | D4: 9500905777/9501153096 | E4: W3F1Z | F4: SAP Application Managed Service - SAP BI PCR 02 | G4: 45717 | H4: 47542 | K4: 47.5 | L4: Offshore | N4: =AH4 -> 0 | O4: =N4*K4 -> 0 | P4: =BF4 -> 0 | Q4: =O4+P4 -> 0 | S4: =R4*K4 -> 0 | T4: 0 | U4: =S4+T4 -> 0 | V4: =Q4-U4 -> 0 | W4: =IF(AND(L4="Offshore",R4>N4),"Red Flag",IF(AND(OR(L4="Onshore",L4="EMEA"),R4>N4),"Red Flag","")) | X4: 1 | Y4: 0 | AA4: =SUM(AB4:AM4) -> 16 | AB4: 16 | AN4: =SUM(AO4:AZ4) -> 760 | AO4: =AB4*$K4 -> 760 | AP4: =AC4*$K4 -> 0 | AQ4: =AD4*$K4 -> 0 | AR4: =AE4*$K4 -> 0 | AS4: =AF4*$K4 -> 0 | AT4: =AG4*$K4 -> 0 | AU4: =AH4*$K4 -> 0 | AV4: =AI4*$K4 -> 0 | ... AZ4: =AM4*$K4 -> 0 | BA4: =SUM(BB4:BM4) -> 0 | BB4: 0 | BC4: 0 | BD4: 0 | BE4: 0 | BF4: 0 | BG4: 0 | BH4: 0 | BI4: 0 | BJ4: 0 | BK4: 0 | BL4: 0 | BM4: 0 | BN4: =SUM(BO4:BZ4) -> 760 | BO4: =BB4+AO4 -> 760 | BP4: =BC4+AP4 -> 0 | BQ4: =BD4+AQ4 -> 0 | BR4: =BE4+AR4 -> 0 | BS4: =BF4+AS4 -> 0 | BT4: =BG4+AT4 -> 0 | BU4: =BH4+AU4 -> 0 | BV4: =BI4+AV4 -> 0 | ... BZ4: =BM4+AZ4 -> 0
A5: =IF(ISNUMBER(INDEX('IBM POs AP07'!$A:$A, MATCH(D5,'IBM POs AP07'!$A:$A,0),1)),"Yes","No") -> No | B5: Raju Parkala | C5: David McGettigan | D5: 9500905777/9501153096 | E5: W3F1Z | F5: SAP Application Managed Service - SAP BI PCR 03 | G5: 45717 | H5: 47542 | I5: 00547P | J5: LAKSHMAN VATTURI | K5: 42.5 | L5: Offshore | N5: =AH5 -> 0 | O5: =N5*K5 -> 0 | P5: =BF5 -> 0 | Q5: =O5+P5 -> 0 | S5: =R5*K5 -> 0 | T5: 0 | U5: =S5+T5 -> 0 | V5: =Q5-U5 -> 0 | W5: =IF(AND(L5="Offshore",R5>N5),"Red Flag",IF(AND(OR(L5="Onshore",L5="EMEA"),R5>N5),"Red Flag","")) | X5: 1 | Y5: 0 | AA5: =SUM(AB5:AM5) -> 693 | AB5: 162 | AC5: 162 | AD5: 207 | AE5: 162 | AF5: 0 | AG5: 0 | AH5: 0 | AI5: 0 | AJ5: 0 | AK5: 0 | AL5: 0 | AM5: 0 | AN5: =SUM(AO5:AZ5) -> 29452.5 | AO5: =AB5*$K5 -> 6885 | AP5: =AC5*$K5 -> 6885 | AQ5: =AD5*$K5 -> 8797.5 | AR5: =AE5*$K5 -> 6885 | AS5: =AF5*$K5 -> 0 | AT5: =AG5*$K5 -> 0 | AU5: =AH5*$K5 -> 0 | AV5: =AI5*$K5 -> 0 | ... AZ5: =AM5*$K5 -> 0 | BA5: =SUM(BB5:BM5) -> 0 | BB5: 0 | BC5: 0 | BD5: 0 | BE5: 0 | BF5: 0 | BG5: 0 | BH5: 0 | BI5: 0 | BJ5: 0 | BK5: 0 | BL5: 0 | BM5: 0 | BN5: =SUM(BO5:BZ5) -> 29452.5 | BO5: =BB5+AO5 -> 6885 | BP5: =BC5+AP5 -> 6885 | BQ5: =BD5+AQ5 -> 8797.5 | BR5: =BE5+AR5 -> 6885 | BS5: =BF5+AS5 -> 0 | BT5: =BG5+AT5 -> 0 | BU5: =BH5+AU5 -> 0 | BV5: =BI5+AV5 -> 0 | ... BZ5: =BM5+AZ5 -> 0
A6: =IF(ISNUMBER(INDEX('IBM POs AP07'!$A:$A, MATCH(D6,'IBM POs AP07'!$A:$A,0),1)),"Yes","No") -> No | B6: Raju Parkala | C6: Jerome Roberton | D6: Pending Po | E6: YAMVJB | F6: SAP AMS BW Enhancement Requests | G6: 46153 | H6: 46234 | J6: HarshaTej Jadi | K6: 47.5 | N6: =AH6 -> 180 | O6: =N6*K6 -> 8550 | P6: =BF6 -> 0 | Q6: =O6+P6 -> 8550 | S6: =R6*K6 -> 0 | T6: 0 | U6: =S6+T6 -> 0 | V6: =Q6-U6 -> 8550 | W6: =IF(AND(L6="Offshore",R6>N6),"Red Flag",IF(AND(OR(L6="Onshore",L6="EMEA"),R6>N6),"Red Flag","")) | X6: 1 | Y6: 0 | AA6: =SUM(AB6:AM6) -> 504 | AF6: 90 | AG6: 216 | AH6: 180 | AI6: 18 | AN6: =SUM(AO6:AZ6) -> 23940 | AO6: =AB6*$K6 -> 0 | AP6: =AC6*$K6 -> 0 | AQ6: =AD6*$K6 -> 0 | AR6: =AE6*$K6 -> 0 | AS6: =AF6*$K6 -> 4275 | AT6: =AG6*$K6 -> 10260 | AU6: =AH6*$K6 -> 8550 | AV6: =AI6*$K6 -> 855 | ... AZ6: =AM6*$K6 -> 0 | BA6: =SUM(BB6:BM6) -> 0 | BB6: 0 | BC6: 0 | BD6: 0 | BE6: 0 | BF6: 0 | BG6: 0 | BH6: 0 | BI6: 0 | BJ6: 0 | BK6: 0 | BL6: 0 | BM6: 0 | BN6: =SUM(BO6:BZ6) -> 23940 | BO6: =BB6+AO6 -> 0 | BP6: =BC6+AP6 -> 0 | BQ6: =BD6+AQ6 -> 0 | BR6: =BE6+AR6 -> 0 | BS6: =BF6+AS6 -> 4275 | BT6: =BG6+AT6 -> 10260 | BU6: =BH6+AU6 -> 8550 | BV6: =BI6+AV6 -> 855 | ... BZ6: =BM6+AZ6 -> 0
A7: =IF(ISNUMBER(INDEX('IBM POs AP07'!$A:$A, MATCH(D7,'IBM POs AP07'!$A:$A,0),1)),"Yes","No") -> No | B7: Raju Parkala | C7: Ryan Burnside | D7: 9501252591 | E7: YALMFB | F7: SAP SVO CI ES&SC Q2 2026 | G7: 46113 | H7: 46387 | I7: 003GKH | J7: Dheenadhayalan Magendran | K7: 47.5 | L7: Offshore | N7: =AH7 -> 153 | O7: =N7*K7 -> 7267.5 | P7: =BF7 -> 0 | Q7: =O7+P7 -> 7267.5 | S7: =R7*K7 -> 0 | T7: 0 | U7: =S7+T7 -> 0 | V7: =Q7-U7 -> 7267.5 | W7: =IF(AND(L7="Offshore",R7>N7),"Red Flag",IF(AND(OR(L7="Onshore",L7="EMEA"),R7>N7),"Red Flag","")) | X7: 1 | Y7: 0 | AA7: =SUM(AB7:AM7) -> 1188 | AE7: 0 | AF7: 0 | AG7: 0 | AH7: 153 | AI7: 225 | AJ7: 180 | AK7: 180 | AL7: 225 | AM7: 225 | AN7: =SUM(AO7:AZ7) -> 56430 | AO7: =AB7*$K7 -> 0 | AP7: =AC7*$K7 -> 0 | AQ7: =AD7*$K7 -> 0 | AR7: =AE7*$K7 -> 0 | AS7: =AF7*$K7 -> 0 | AT7: =AG7*$K7 -> 0 | AU7: =AH7*$K7 -> 7267.5 | AV7: =AI7*$K7 -> 10687.5 | ... AZ7: =AM7*$K7 -> 10687.5 | BA7: =SUM(BB7:BM7) -> 0 | BB7: 0 | BC7: 0 | BD7: 0 | BE7: 0 | BF7: 0 | BG7: 0 | BH7: 0 | BI7: 0 | BJ7: 0 | BK7: 0 | BL7: 0 | BM7: 0 | BN7: =SUM(BO7:BZ7) -> 56430 | BO7: =BB7+AO7 -> 0 | BP7: =BC7+AP7 -> 0 | BQ7: =BD7+AQ7 -> 0 | BR7: =BE7+AR7 -> 0 | BS7: =BF7+AS7 -> 0 | BT7: =BG7+AT7 -> 0 | BU7: =BH7+AU7 -> 7267.5 | BV7: =BI7+AV7 -> 10687.5 | ... BZ7: =BM7+AZ7 -> 10687.5
A8: =IF(ISNUMBER(INDEX('IBM POs AP07'!$A:$A, MATCH(D8,'IBM POs AP07'!$A:$A,0),1)),"Yes","No") -> No | B8: Raju Parkala | C8: Ryan Burnside | D8: 9501252591 | E8: YALMFB | F8: SAP SVO CI ES&SC Q2 2026 | G8: 46113 | H8: 46387 | I8: 224422 | J8: Mirajgaonkar, Sanjay | K8: 61.75 | L8: Offshore | N8: =AH8 -> 0 | O8: =N8*K8 -> 0 | P8: =BF8 -> 0 | Q8: =O8+P8 -> 0 | S8: =R8*K8 -> 0 | T8: 0 | U8: =S8+T8 -> 0 | V8: =Q8-U8 -> 0 | W8: =IF(AND(L8="Offshore",R8>N8),"Red Flag",IF(AND(OR(L8="Onshore",L8="EMEA"),R8>N8),"Red Flag","")) | X8: 1 | Y8: 0 | AA8: =SUM(AB8:AM8) -> 0 | AE8: 0 | AF8: 0 | AG8: 0 | AH8: 0 | AI8: 0 | AJ8: 0 | AK8: 0 | AL8: 0 | AM8: 0 | AN8: =SUM(AO8:AZ8) -> 0 | AO8: =AB8*$K8 -> 0 | AP8: =AC8*$K8 -> 0 | AQ8: =AD8*$K8 -> 0 | AR8: =AE8*$K8 -> 0 | AS8: =AF8*$K8 -> 0 | AT8: =AG8*$K8 -> 0 | AU8: =AH8*$K8 -> 0 | AV8: =AI8*$K8 -> 0 | ... AZ8: =AM8*$K8 -> 0 | BA8: =SUM(BB8:BM8) -> 0 | BB8: 0 | BC8: 0 | BD8: 0 | BE8: 0 | BF8: 0 | BG8: 0 | BH8: 0 | BI8: 0 | BJ8: 0 | BK8: 0 | BL8: 0 | BM8: 0 | BN8: =SUM(BO8:BZ8) -> 0 | BO8: =BB8+AO8 -> 0 | BP8: =BC8+AP8 -> 0 | BQ8: =BD8+AQ8 -> 0 | BR8: =BE8+AR8 -> 0 | BS8: =BF8+AS8 -> 0 | BT8: =BG8+AT8 -> 0 | BU8: =BH8+AU8 -> 0 | BV8: =BI8+AV8 -> 0 | ... BZ8: =BM8+AZ8 -> 0
A9: =IF(ISNUMBER(INDEX('IBM POs AP07'!$A:$A, MATCH(D9,'IBM POs AP07'!$A:$A,0),1)),"Yes","No") -> No | B9: Raju Parkala | C9: Ryan Burnside | D9: 9501252591 | E9: YALMFB | F9: SAP SVO CI ES&SC Q2 2026 | G9: 46113 | H9: 46387 | I9: 0345C7 | J9: SANTOSH BAKALKAR | K9: 61.75 | L9: Offshore | N9: =AH9 -> 171 | O9: =N9*K9 -> 10559.25 | P9: =BF9 -> 0 | Q9: =O9+P9 -> 10559.25 | S9: =R9*K9 -> 0 | T9: 0 | U9: =S9+T9 -> 0 | V9: =Q9-U9 -> 10559.25 | W9: =IF(AND(L9="Offshore",R9>N9),"Red Flag",IF(AND(OR(L9="Onshore",L9="EMEA"),R9>N9),"Red Flag","")) | X9: 1 | Y9: 0 | AA9: =SUM(AB9:AM9) -> 1524 | AE9: 0 | AF9: 120 | AG9: 198 | AH9: 171 | AI9: 225 | AJ9: 180 | AK9: 180 | AL9: 225 | AM9: 225 | AN9: =SUM(AO9:AZ9) -> 94107 | AO9: =AB9*$K9 -> 0 | AP9: =AC9*$K9 -> 0 | AQ9: =AD9*$K9 -> 0 | AR9: =AE9*$K9 -> 0 | AS9: =AF9*$K9 -> 7410 | AT9: =AG9*$K9 -> 12226.5 | AU9: =AH9*$K9 -> 10559.25 | AV9: =AI9*$K9 -> 13893.75 | ... AZ9: =AM9*$K9 -> 13893.75 | BA9: =SUM(BB9:BM9) -> 0 | BB9: 0 | BC9: 0 | BD9: 0 | BE9: 0 | BF9: 0 | BG9: 0 | BH9: 0 | BI9: 0 | BJ9: 0 | BK9: 0 | BL9: 0 | BM9: 0 | BN9: =SUM(BO9:BZ9) -> 94107 | BO9: =BB9+AO9 -> 0 | BP9: =BC9+AP9 -> 0 | BQ9: =BD9+AQ9 -> 0 | BR9: =BE9+AR9 -> 0 | BS9: =BF9+AS9 -> 7410 | BT9: =BG9+AT9 -> 12226.5 | BU9: =BH9+AU9 -> 10559.25 | BV9: =BI9+AV9 -> 13893.75 | ... BZ9: =BM9+AZ9 -> 13893.75
A10: =IF(ISNUMBER(INDEX('IBM POs AP07'!$A:$A, MATCH(D10,'IBM POs AP07'!$A:$A,0),1)),"Yes","No") -> No | B10: Raju Parkala | C10: Ryan Burnside | D10: 9501252591 | E10: YALMFB | F10: SAP SVO CI ES&SC Q2 2026 | G10: 46113 | H10: 46387 | I10: 34937 | J10: VASUDEVA THIMMAIAH | K10: 180 | L10: Onshore | N10: =AH10 -> 0 | O10: =N10*K10 -> 0 | P10: =BF10 -> 0 | Q10: =O10+P10 -> 0 | S10: =R10*K10 -> 0 | T10: 0 | U10: =S10+T10 -> 0 | V10: =Q10-U10 -> 0 | W10: =IF(AND(L10="Offshore",R10>N10),"Red Flag",IF(AND(OR(L10="Onshore",L10="EMEA"),R10>N10),"Red Flag","")) | X10: 1 | Y10: 0 | AA10: =SUM(AB10:AM10) -> 176 | AE10: 144 | AF10: 32 | AN10: =SUM(AO10:AZ10) -> 31680 | AO10: =AB10*$K10 -> 0 | AP10: =AC10*$K10 -> 0 | AQ10: =AD10*$K10 -> 0 | AR10: =AE10*$K10 -> 25920 | AS10: =AF10*$K10 -> 5760 | AT10: =AG10*$K10 -> 0 | AU10: =AH10*$K10 -> 0 | AV10: =AI10*$K10 -> 0 | ... AZ10: =AM10*$K10 -> 0 | BA10: =SUM(BB10:BM10) -> 0 | BB10: 0 | BC10: 0 | BD10: 0 | BE10: 0 | BF10: 0 | BG10: 0 | BH10: 0 | BI10: 0 | BJ10: 0 | BK10: 0 | BL10: 0 | BM10: 0 | BN10: =SUM(BO10:BZ10) -> 31680 | BO10: =BB10+AO10 -> 0 | BP10: =BC10+AP10 -> 0 | BQ10: =BD10+AQ10 -> 0 | BR10: =BE10+AR10 -> 25920 | BS10: =BF10+AS10 -> 5760 | BT10: =BG10+AT10 -> 0 | BU10: =BH10+AU10 -> 0 | BV10: =BI10+AV10 -> 0 | ... BZ10: =BM10+AZ10 -> 0
A11: =IF(ISNUMBER(INDEX('IBM POs AP07'!$A:$A, MATCH(D11,'IBM POs AP07'!$A:$A,0),1)),"Yes","No") -> No | B11: Raju Parkala | C11: Ryan Burnside | D11: 9501252591 | E11: YALMFB | F11: SAP SVO CI ES&SC Q2 2026 | G11: 46113 | H11: 46387 | I11: 01906H | J11: RAHUL SHIROTE | K11: 47.5 | N11: =AH11 -> 153 | O11: =N11*K11 -> 7267.5 | P11: =BF11 -> 0 | Q11: =O11+P11 -> 7267.5 | S11: =R11*K11 -> 0 | T11: 0 | U11: =S11+T11 -> 0 | V11: =Q11-U11 -> 7267.5 | W11: =IF(AND(L11="Offshore",R11>N11),"Red Flag",IF(AND(OR(L11="Onshore",L11="EMEA"),R11>N11),"Red Flag","")) | X11: 1 | Y11: 0 | AA11: =SUM(AB11:AM11) -> 1188 | AH11: 153 | AI11: 225 | AJ11: 180 | AK11: 180 | AL11: 225 | AM11: 225 | AN11: =SUM(AO11:AZ11) -> 56430 | AO11: =AB11*$K11 -> 0 | AP11: =AC11*$K11 -> 0 | AQ11: =AD11*$K11 -> 0 | AR11: =AE11*$K11 -> 0 | AS11: =AF11*$K11 -> 0 | AT11: =AG11*$K11 -> 0 | AU11: =AH11*$K11 -> 7267.5 | AV11: =AI11*$K11 -> 10687.5 | ... AZ11: =AM11*$K11 -> 10687.5 | BA11: =SUM(BB11:BM11) -> 0 | BB11: 0 | BC11: 0 | BD11: 0 | BE11: 0 | BF11: 0 | BG11: 0 | BH11: 0 | BI11: 0 | BJ11: 0 | BK11: 0 | BL11: 0 | BM11: 0 | BN11: =SUM(BO11:BZ11) -> 56430 | BO11: =BB11+AO11 -> 0 | BP11: =BC11+AP11 -> 0 | BQ11: =BD11+AQ11 -> 0 | BR11: =BE11+AR11 -> 0 | BS11: =BF11+AS11 -> 0 | BT11: =BG11+AT11 -> 0 | BU11: =BH11+AU11 -> 7267.5 | BV11: =BI11+AV11 -> 10687.5 | ... BZ11: =BM11+AZ11 -> 10687.5
A12: =IF(ISNUMBER(INDEX('IBM POs AP07'!$A:$A, MATCH(D12,'IBM POs AP07'!$A:$A,0),1)),"Yes","No") -> No | B12: Raju Parkala | C12: Ryan Burnside | D12: 9501252591 | E12: YALMFB | F12: SAP SVO CI ES&SC Q2 2026 | G12: 46113 | H12: 46387 | I12: 0042UQ | J12: RADHA GANDRAKOTA | K12: 47.5 | N12: =AH12 -> 0 | O12: =N12*K12 -> 0 | P12: =BF12 -> 0 | Q12: =O12+P12 -> 0 | S12: =R12*K12 -> 0 | T12: 0 | U12: =S12+T12 -> 0 | V12: =Q12-U12 -> 0 | W12: =IF(AND(L12="Offshore",R12>N12),"Red Flag",IF(AND(OR(L12="Onshore",L12="EMEA"),R12>N12),"Red Flag","")) | X12: 1 | Y12: 0 | AA12: =SUM(AB12:AM12) -> 585 | AK12: 135 | AL12: 225 | AM12: 225 | AN12: =SUM(AO12:AZ12) -> 27787.5 | AO12: =AB12*$K12 -> 0 | AP12: =AC12*$K12 -> 0 | AQ12: =AD12*$K12 -> 0 | AR12: =AE12*$K12 -> 0 | AS12: =AF12*$K12 -> 0 | AT12: =AG12*$K12 -> 0 | AU12: =AH12*$K12 -> 0 | AV12: =AI12*$K12 -> 0 | ... AZ12: =AM12*$K12 -> 10687.5 | BA12: =SUM(BB12:BM12) -> 0 | BB12: 0 | BC12: 0 | BD12: 0 | BE12: 0 | BF12: 0 | BG12: 0 | BH12: 0 | BI12: 0 | BJ12: 0 | BK12: 0 | BL12: 0 | BM12: 0 | BN12: =SUM(BO12:BZ12) -> 27787.5 | BO12: =BB12+AO12 -> 0 | BP12: =BC12+AP12 -> 0 | BQ12: =BD12+AQ12 -> 0 | BR12: =BE12+AR12 -> 0 | BS12: =BF12+AS12 -> 0 | BT12: =BG12+AT12 -> 0 | BU12: =BH12+AU12 -> 0 | BV12: =BI12+AV12 -> 0 | ... BZ12: =BM12+AZ12 -> 10687.5
A13: =IF(ISNUMBER(INDEX('IBM POs AP07'!$A:$A, MATCH(D13,'IBM POs AP07'!$A:$A,0),1)),"Yes","No") -> No | B13: Raju Parkala | C13: Amit Jajodia | D13: 9501273936 | E13: YAMWDB | F13: SAP SVO BRM QM Q2 2026 | G13: 46113 | H13: 46203 | I13: 005XI6 | J13: AMOL SHITOLE | K13: 87 | N13: =AH13 -> 18 | O13: =N13*K13 -> 1566 | P13: =BF13 -> 0 | Q13: =O13+P13 -> 1566 | S13: =R13*K13 -> 0 | T13: 0 | U13: =S13+T13 -> 0 | V13: =Q13-U13 -> 1566 | W13: =IF(AND(L13="Offshore",R13>N13),"Red Flag",IF(AND(OR(L13="Onshore",L13="EMEA"),R13>N13),"Red Flag","")) | X13: 1 | Y13: 0 | AA13: =SUM(AB13:AM13) -> 387 | AE13: 0 | AF13: 171 | AG13: 198 | AH13: 18 | AN13: =SUM(AO13:AZ13) -> 33669 | AO13: =AB13*$K13 -> 0 | AP13: =AC13*$K13 -> 0 | AQ13: =AD13*$K13 -> 0 | AR13: =AE13*$K13 -> 0 | AS13: =AF13*$K13 -> 14877 | AT13: =AG13*$K13 -> 17226 | AU13: =AH13*$K13 -> 1566 | AV13: =AI13*$K13 -> 0 | ... AZ13: =AM13*$K13 -> 0 | BA13: =SUM(BB13:BM13) -> 0 | BB13: 0 | BC13: 0 | BD13: 0 | BE13: 0 | BF13: 0 | BG13: 0 | BH13: 0 | BI13: 0 | BJ13: 0 | BK13: 0 | BL13: 0 | BM13: 0 | BN13: =SUM(BO13:BZ13) -> 33669 | BO13: =BB13+AO13 -> 0 | BP13: =BC13+AP13 -> 0 | BQ13: =BD13+AQ13 -> 0 | BR13: =BE13+AR13 -> 0 | BS13: =BF13+AS13 -> 14877 | BT13: =BG13+AT13 -> 17226 | BU13: =BH13+AU13 -> 1566 | BV13: =BI13+AV13 -> 0 | ... BZ13: =BM13+AZ13 -> 0
A14: =IF(ISNUMBER(INDEX('IBM POs AP07'!$A:$A, MATCH(D14,'IBM POs AP07'!$A:$A,0),1)),"Yes","No") -> No | B14: Raju Parkala | C14: Amit Jajodia | D14: 9501274181 | E14: YAMWDB | F14: SAP SVO BRM QM Q2 2026 | G14: 46113 | H14: 46203 | I14: SV5XWG | J14: RAM KUMAR VEPURI | K14: 47.5 | N14: =AH14 -> 18 | O14: =N14*K14 -> 855 | P14: =BF14 -> 0 | Q14: =O14+P14 -> 855 | S14: =R14*K14 -> 0 | T14: 0 | U14: =S14+T14 -> 0 | V14: =Q14-U14 -> 855 | W14: =IF(AND(L14="Offshore",R14>N14),"Red Flag",IF(AND(OR(L14="Onshore",L14="EMEA"),R14>N14),"Red Flag","")) | X14: 1 | Y14: 0 | AA14: =SUM(AB14:AM14) -> 234 | AG14: 216 | AH14: 18 | AN14: =SUM(AO14:AZ14) -> 11115 | AO14: =AB14*$K14 -> 0 | AP14: =AC14*$K14 -> 0 | AQ14: =AD14*$K14 -> 0 | AR14: =AE14*$K14 -> 0 | AS14: =AF14*$K14 -> 0 | AT14: =AG14*$K14 -> 10260 | AU14: =AH14*$K14 -> 855 | AV14: =AI14*$K14 -> 0 | ... AZ14: =AM14*$K14 -> 0 | BA14: =SUM(BB14:BM14) -> 0 | BB14: 0 | BC14: 0 | BD14: 0 | BE14: 0 | BF14: 0 | BG14: 0 | BH14: 0 | BI14: 0 | BJ14: 0 | BK14: 0 | BL14: 0 | BM14: 0 | BN14: =SUM(BO14:BZ14) -> 11115 | BO14: =BB14+AO14 -> 0 | BP14: =BC14+AP14 -> 0 | BQ14: =BD14+AQ14 -> 0 | BR14: =BE14+AR14 -> 0 | BS14: =BF14+AS14 -> 0 | BT14: =BG14+AT14 -> 10260 | BU14: =BH14+AU14 -> 855 | BV14: =BI14+AV14 -> 0 | ... BZ14: =BM14+AZ14 -> 0
A15: =IF(ISNUMBER(INDEX('IBM POs AP07'!$A:$A, MATCH(D15,'IBM POs AP07'!$A:$A,0),1)),"Yes","No") -> No | B15: Raju Parkala | C15: Amit Jajodia | D15: 9501182078 | E15: YAMT9B | F15: SAP SVO QM gLIMS Q2 2026 | G15: 46113 | H15: 46203 | I15: 003XA1 | J15: Palas Sinhamahapatra | K15: 61.75 | N15: =AH15 -> 18 | O15: =N15*K15 -> 1111.5 | P15: =BF15 -> 0 | Q15: =O15+P15 -> 1111.5 | S15: =R15*K15 -> 0 | T15: 0 | U15: =S15+T15 -> 0 | V15: =Q15-U15 -> 1111.5 | W15: =IF(AND(L15="Offshore",R15>N15),"Red Flag",IF(AND(OR(L15="Onshore",L15="EMEA"),R15>N15),"Red Flag","")) | X15: 1 | Y15: 0 | AA15: =SUM(AB15:AM15) -> 558 | AE15: 135 | AF15: 180 | AG15: 225 | AH15: 18 | AN15: =SUM(AO15:AZ15) -> 34456.5 | AO15: =AB15*$K15 -> 0 | AP15: =AC15*$K15 -> 0 | AQ15: =AD15*$K15 -> 0 | AR15: =AE15*$K15 -> 8336.25 | AS15: =AF15*$K15 -> 11115 | AT15: =AG15*$K15 -> 13893.75 | AU15: =AH15*$K15 -> 1111.5 | AV15: =AI15*$K15 -> 0 | ... AZ15: =AM15*$K15 -> 0 | BA15: =SUM(BB15:BM15) -> 0 | BB15: 0 | BC15: 0 | BD15: 0 | BE15: 0 | BF15: 0 | BG15: 0 | BH15: 0 | BI15: 0 | BJ15: 0 | BK15: 0 | BL15: 0 | BM15: 0 | BN15: =SUM(BO15:BZ15) -> 34456.5 | BO15: =BB15+AO15 -> 0 | BP15: =BC15+AP15 -> 0 | BQ15: =BD15+AQ15 -> 0 | BR15: =BE15+AR15 -> 8336.25 | BS15: =BF15+AS15 -> 11115 | BT15: =BG15+AT15 -> 13893.75 | BU15: =BH15+AU15 -> 1111.5 | BV15: =BI15+AV15 -> 0 | ... BZ15: =BM15+AZ15 -> 0
A16: =IF(ISNUMBER(INDEX('IBM POs AP07'!$A:$A, MATCH(D16,'IBM POs AP07'!$A:$A,0),1)),"Yes","No") -> No | B16: Raju Parkala | C16: Amit Jajodia | D16: 9501276525 | E16: YANDLB | F16: AP SVO QM Projects and Support 2026 ` | G16: 46113 | H16: 46203 | I16: 005PC1 | J16: NIMBALKAR NAGANATH DADASO | K16: 31.5 | N16: =AH16 -> 18 | O16: =N16*K16 -> 567 | P16: =BF16 -> 0 | Q16: =O16+P16 -> 567 | S16: =R16*K16 -> 0 | T16: 0 | U16: =S16+T16 -> 0 | V16: =Q16-U16 -> 567 | W16: =IF(AND(L16="Offshore",R16>N16),"Red Flag",IF(AND(OR(L16="Onshore",L16="EMEA"),R16>N16),"Red Flag","")) | X16: 1 | Y16: 0 | AA16: =SUM(AB16:AM16) -> 423 | AF16: 180 | AG16: 225 | AH16: 18 | AN16: =SUM(AO16:AZ16) -> 13324.5 | AO16: =AB16*$K16 -> 0 | AP16: =AC16*$K16 -> 0 | AQ16: =AD16*$K16 -> 0 | AR16: =AE16*$K16 -> 0 | AS16: =AF16*$K16 -> 5670 | AT16: =AG16*$K16 -> 7087.5 | AU16: =AH16*$K16 -> 567 | AV16: =AI16*$K16 -> 0 | ... AZ16: =AM16*$K16 -> 0 | BA16: =SUM(BB16:BM16) -> 0 | BB16: 0 | BC16: 0 | BD16: 0 | BE16: 0 | BF16: 0 | BG16: 0 | BH16: 0 | BI16: 0 | BJ16: 0 | BK16: 0 | BL16: 0 | BM16: 0 | BN16: =SUM(BO16:BZ16) -> 13324.5 | BO16: =BB16+AO16 -> 0 | BP16: =BC16+AP16 -> 0 | BQ16: =BD16+AQ16 -> 0 | BR16: =BE16+AR16 -> 0 | BS16: =BF16+AS16 -> 5670 | BT16: =BG16+AT16 -> 7087.5 | BU16: =BH16+AU16 -> 567 | BV16: =BI16+AV16 -> 0 | ... BZ16: =BM16+AZ16 -> 0
A17: =IF(ISNUMBER(INDEX('IBM POs AP07'!$A:$A, MATCH(D17,'IBM POs AP07'!$A:$A,0),1)),"Yes","No") -> No | B17: Raju Parkala | C17: Amit Jajodia | D17: 9501276525 | E17: YANDLB | F17: AP SVO QM Projects and Support 2026 ` | G17: 46113 | H17: 46203 | I17: 006AX4 | J17: LAKSHMI KOPPULA | K17: 31.5 | N17: =AH17 -> 18 | O17: =N17*K17 -> 567 | P17: =BF17 -> 0 | Q17: =O17+P17 -> 567 | S17: =R17*K17 -> 0 | T17: 0 | U17: =S17+T17 -> 0 | V17: =Q17-U17 -> 567 | W17: =IF(AND(L17="Offshore",R17>N17),"Red Flag",IF(AND(OR(L17="Onshore",L17="EMEA"),R17>N17),"Red Flag","")) | X17: 1 | Y17: 0 | AA17: =SUM(AB17:AM17) -> 342 | AF17: 99 | AG17: 225 | AH17: 18 | AN17: =SUM(AO17:AZ17) -> 10773 | AO17: =AB17*$K17 -> 0 | AP17: =AC17*$K17 -> 0 | AQ17: =AD17*$K17 -> 0 | AR17: =AE17*$K17 -> 0 | AS17: =AF17*$K17 -> 3118.5 | AT17: =AG17*$K17 -> 7087.5 | AU17: =AH17*$K17 -> 567 | AV17: =AI17*$K17 -> 0 | ... AZ17: =AM17*$K17 -> 0 | BA17: =SUM(BB17:BM17) -> 0 | BB17: 0 | BC17: 0 | BD17: 0 | BE17: 0 | BF17: 0 | BG17: 0 | BH17: 0 | BI17: 0 | BJ17: 0 | BK17: 0 | BL17: 0 | BM17: 0 | BN17: =SUM(BO17:BZ17) -> 10773 | BO17: =BB17+AO17 -> 0 | BP17: =BC17+AP17 -> 0 | BQ17: =BD17+AQ17 -> 0 | BR17: =BE17+AR17 -> 0 | BS17: =BF17+AS17 -> 3118.5 | BT17: =BG17+AT17 -> 7087.5 | BU17: =BH17+AU17 -> 567 | BV17: =BI17+AV17 -> 0 | ... BZ17: =BM17+AZ17 -> 0
A18: =IF(ISNUMBER(INDEX('IBM POs AP07'!$A:$A, MATCH(D18,'IBM POs AP07'!$A:$A,0),1)),"Yes","No") -> No | B18: Raju Parkala | C18: Amit Jajodia | D18: 9501285236 | E18: YANDLB | F18: AP SVO QM Projects and Support 2026 ` | G18: 46113 | H18: 46203 | I18: SVKYIE | J18: MIRIYALA GANESH | K18: 31.5 | N18: =AH18 -> 18 | O18: =N18*K18 -> 567 | P18: =BF18 -> 0 | Q18: =O18+P18 -> 567 | S18: =R18*K18 -> 0 | T18: 0 | U18: =S18+T18 -> 0 | V18: =Q18-U18 -> 567 | W18: =IF(AND(L18="Offshore",R18>N18),"Red Flag",IF(AND(OR(L18="Onshore",L18="EMEA"),R18>N18),"Red Flag","")) | X18: 1 | Y18: 0 | AA18: =SUM(AB18:AM18) -> 423 | AF18: 180 | AG18: 225 | AH18: 18 | AN18: =SUM(AO18:AZ18) -> 13324.5 | AO18: =AB18*$K18 -> 0 | AP18: =AC18*$K18 -> 0 | AQ18: =AD18*$K18 -> 0 | AR18: =AE18*$K18 -> 0 | AS18: =AF18*$K18 -> 5670 | AT18: =AG18*$K18 -> 7087.5 | AU18: =AH18*$K18 -> 567 | AV18: =AI18*$K18 -> 0 | ... AZ18: =AM18*$K18 -> 0 | BA18: =SUM(BB18:BM18) -> 0 | BB18: 0 | BC18: 0 | BD18: 0 | BE18: 0 | BF18: 0 | BG18: 0 | BH18: 0 | BI18: 0 | BJ18: 0 | BK18: 0 | BL18: 0 | BM18: 0 | BN18: =SUM(BO18:BZ18) -> 13324.5 | BO18: =BB18+AO18 -> 0 | BP18: =BC18+AP18 -> 0 | BQ18: =BD18+AQ18 -> 0 | BR18: =BE18+AR18 -> 0 | BS18: =BF18+AS18 -> 5670 | BT18: =BG18+AT18 -> 7087.5 | BU18: =BH18+AU18 -> 567 | BV18: =BI18+AV18 -> 0 | ... BZ18: =BM18+AZ18 -> 0
A19: =IF(ISNUMBER(INDEX('IBM POs AP07'!$A:$A, MATCH(D19,'IBM POs AP07'!$A:$A,0),1)),"Yes","No") -> No | B19: Raju Parkala | C19: Amit Jajodia | D19: 9501292172 | E19: YANDLB | F19: AP SVO QM Projects and Support 2026 ` | G19: 46113 | H19: 46203 | J19: Kiran Gaddam / TBD33 / SAP QM Projects and Support | K19: 47.5 | N19: =AH19 -> 18 | O19: =N19*K19 -> 855 | P19: =BF19 -> 0 | Q19: =O19+P19 -> 855 | S19: =R19*K19 -> 0 | T19: 0 | U19: =S19+T19 -> 0 | V19: =Q19-U19 -> 855 | W19: =IF(AND(L19="Offshore",R19>N19),"Red Flag",IF(AND(OR(L19="Onshore",L19="EMEA"),R19>N19),"Red Flag","")) | X19: 1 | Y19: 0 | AA19: =SUM(AB19:AM19) -> 558 | AE19: 135 | AF19: 180 | AG19: 225 | AH19: 18 | AN19: =SUM(AO19:AZ19) -> 26505 | AO19: =AB19*$K19 -> 0 | AP19: =AC19*$K19 -> 0 | AQ19: =AD19*$K19 -> 0 | AR19: =AE19*$K19 -> 6412.5 | AS19: =AF19*$K19 -> 8550 | AT19: =AG19*$K19 -> 10687.5 | AU19: =AH19*$K19 -> 855 | AV19: =AI19*$K19 -> 0 | ... AZ19: =AM19*$K19 -> 0 | BA19: =SUM(BB19:BM19) -> 0 | BB19: 0 | BC19: 0 | BD19: 0 | BE19: 0 | BF19: 0 | BG19: 0 | BH19: 0 | BI19: 0 | BJ19: 0 | BK19: 0 | BL19: 0 | BM19: 0 | BN19: =SUM(BO19:BZ19) -> 26505 | BO19: =BB19+AO19 -> 0 | BP19: =BC19+AP19 -> 0 | BQ19: =BD19+AQ19 -> 0 | BR19: =BE19+AR19 -> 6412.5 | BS19: =BF19+AS19 -> 8550 | BT19: =BG19+AT19 -> 10687.5 | BU19: =BH19+AU19 -> 855 | BV19: =BI19+AV19 -> 0 | ... BZ19: =BM19+AZ19 -> 0
A20: =IF(ISNUMBER(INDEX('IBM POs AP07'!$A:$A, MATCH(D20,'IBM POs AP07'!$A:$A,0),1)),"Yes","No") -> No | B20: Raju Parkala | C20: Amit Jajodia | D20: 9501276524 | E20: YANDLB | F20: AP SVO QM Projects and Support 2026 ` | G20: 46113 | H20: 46203 | I20: 005OH4 | J20: BHAVANA DWARAKAMAI | K20: 47.5 | N20: =AH20 -> 18 | O20: =N20*K20 -> 855 | P20: =BF20 -> 0 | Q20: =O20+P20 -> 855 | S20: =R20*K20 -> 0 | T20: 0 | U20: =S20+T20 -> 0 | V20: =Q20-U20 -> 855 | W20: =IF(AND(L20="Offshore",R20>N20),"Red Flag",IF(AND(OR(L20="Onshore",L20="EMEA"),R20>N20),"Red Flag","")) | X20: 1 | Y20: 0 | AA20: =SUM(AB20:AM20) -> 423 | AF20: 180 | AG20: 225 | AH20: 18 | AN20: =SUM(AO20:AZ20) -> 20092.5 | AO20: =AB20*$K20 -> 0 | AP20: =AC20*$K20 -> 0 | AQ20: =AD20*$K20 -> 0 | AR20: =AE20*$K20 -> 0 | AS20: =AF20*$K20 -> 8550 | AT20: =AG20*$K20 -> 10687.5 | AU20: =AH20*$K20 -> 855 | AV20: =AI20*$K20 -> 0 | ... AZ20: =AM20*$K20 -> 0 | BA20: =SUM(BB20:BM20) -> 0 | BB20: 0 | BC20: 0 | BD20: 0 | BE20: 0 | BF20: 0 | BG20: 0 | BH20: 0 | BI20: 0 | BJ20: 0 | BK20: 0 | BL20: 0 | BM20: 0 | BN20: =SUM(BO20:BZ20) -> 20092.5 | BO20: =BB20+AO20 -> 0 | BP20: =BC20+AP20 -> 0 | BQ20: =BD20+AQ20 -> 0 | BR20: =BE20+AR20 -> 0 | BS20: =BF20+AS20 -> 8550 | BT20: =BG20+AT20 -> 10687.5 | BU20: =BH20+AU20 -> 855 | BV20: =BI20+AV20 -> 0 | ... BZ20: =BM20+AZ20 -> 0
A21: =IF(ISNUMBER(INDEX('IBM POs AP07'!$A:$A, MATCH(D21,'IBM POs AP07'!$A:$A,0),1)),"Yes","No") -> No | B21: Raju Parkala | C21: Sachin Vaidya | D21: 9501173555 | E21: YALQJB | F21: SAP SVO CI Commercial 2026 | G21: 46113 | H21: 46387 | I21: 06048A | J21: DILIP PAMMINA | K21: 180 | L21: Onshore | N21: =AH21 -> 152 | O21: =N21*K21 -> 27360 | P21: =BF21 -> 0 | Q21: =O21+P21 -> 27360 | S21: =R21*K21 -> 0 | T21: 0 | U21: =S21+T21 -> 0 | V21: =Q21-U21 -> 27360 | W21: =IF(AND(L21="Offshore",R21>N21),"Red Flag",IF(AND(OR(L21="Onshore",L21="EMEA"),R21>N21),"Red Flag","")) | X21: 1 | Y21: 0 | AA21: =SUM(AB21:AM21) -> 1493 | AE21: 144 | AF21: 160 | AG21: 184 | AH21: 152 | AI21: 192 | AJ21: 152 | AK21: 152 | AL21: 184 | AM21: 173 | AN21: =SUM(AO21:AZ21) -> 268740 | AO21: =AB21*$K21 -> 0 | AP21: =AC21*$K21 -> 0 | AQ21: =AD21*$K21 -> 0 | AR21: =AE21*$K21 -> 25920 | AS21: =AF21*$K21 -> 28800 | AT21: =AG21*$K21 -> 33120 | AU21: =AH21*$K21 -> 27360 | AV21: =AI21*$K21 -> 34560 | ... AZ21: =AM21*$K21 -> 31140 | BA21: =SUM(BB21:BM21) -> 0 | BB21: 0 | BC21: 0 | BD21: 0 | BE21: 0 | BF21: 0 | BG21: 0 | BH21: 0 | BI21: 0 | BJ21: 0 | BK21: 0 | BL21: 0 | BM21: 0 | BN21: =SUM(BO21:BZ21) -> 268740 | BO21: =BB21+AO21 -> 0 | BP21: =BC21+AP21 -> 0 | BQ21: =BD21+AQ21 -> 0 | BR21: =BE21+AR21 -> 25920 | BS21: =BF21+AS21 -> 28800 | BT21: =BG21+AT21 -> 33120 | BU21: =BH21+AU21 -> 27360 | BV21: =BI21+AV21 -> 34560 | ... BZ21: =BM21+AZ21 -> 31140
A22: =IF(ISNUMBER(INDEX('IBM POs AP07'!$A:$A, MATCH(D22,'IBM POs AP07'!$A:$A,0),1)),"Yes","No") -> No | B22: Raju Parkala | C22: Sachin Vaidya | D22: 9501173555 | E22: YALQJB | F22: SAP SVO CI Commercial 2026 | G22: 46113 | H22: 46387 | I22: 06788J | J22: DEVENDRA DESHPANDE | K22: 180 | L22: Onshore | N22: =AH22 -> 60 | O22: =N22*K22 -> 10800 | P22: =BF22 -> 0 | Q22: =O22+P22 -> 10800 | S22: =R22*K22 -> 0 | T22: 0 | U22: =S22+T22 -> 0 | V22: =Q22-U22 -> 10800 | W22: =IF(AND(L22="Offshore",R22>N22),"Red Flag",IF(AND(OR(L22="Onshore",L22="EMEA"),R22>N22),"Red Flag","")) | X22: 1 | Y22: 0 | AA22: =SUM(AB22:AM22) -> 544 | AE22: 40 | AF22: 64 | AG22: 80 | AH22: 60 | AI22: 60 | AJ22: 60 | AK22: 60 | AL22: 60 | AM22: 60 | AN22: =SUM(AO22:AZ22) -> 97920 | AO22: =AB22*$K22 -> 0 | AP22: =AC22*$K22 -> 0 | AQ22: =AD22*$K22 -> 0 | AR22: =AE22*$K22 -> 7200 | AS22: =AF22*$K22 -> 11520 | AT22: =AG22*$K22 -> 14400 | AU22: =AH22*$K22 -> 10800 | AV22: =AI22*$K22 -> 10800 | ... AZ22: =AM22*$K22 -> 10800 | BA22: =SUM(BB22:BM22) -> 0 | BB22: 0 | BC22: 0 | BD22: 0 | BE22: 0 | BF22: 0 | BG22: 0 | BH22: 0 | BI22: 0 | BJ22: 0 | BK22: 0 | BL22: 0 | BM22: 0 | BN22: =SUM(BO22:BZ22) -> 97920 | BO22: =BB22+AO22 -> 0 | BP22: =BC22+AP22 -> 0 | BQ22: =BD22+AQ22 -> 0 | BR22: =BE22+AR22 -> 7200 | BS22: =BF22+AS22 -> 11520 | BT22: =BG22+AT22 -> 14400 | BU22: =BH22+AU22 -> 10800 | BV22: =BI22+AV22 -> 10800 | ... BZ22: =BM22+AZ22 -> 10800
A23: =IF(ISNUMBER(INDEX('IBM POs AP07'!$A:$A, MATCH(D23,'IBM POs AP07'!$A:$A,0),1)),"Yes","No") -> No | B23: Raju Parkala | C23: Sachin Vaidya | D23: 9501173555 | E23: YALQJB | F23: SAP SVO CI Commercial 2026 | G23: 46113 | H23: 46387 | I23: 06292L | J23: VIVEK GURUNG | K23: 180 | L23: Onshore | N23: =AH23 -> 152 | O23: =N23*K23 -> 27360 | P23: =BF23 -> 0 | Q23: =O23+P23 -> 27360 | S23: =R23*K23 -> 0 | T23: 0 | U23: =S23+T23 -> 0 | V23: =Q23-U23 -> 27360 | W23: =IF(AND(L23="Offshore",R23>N23),"Red Flag",IF(AND(OR(L23="Onshore",L23="EMEA"),R23>N23),"Red Flag","")) | X23: 1 | Y23: 0 | AA23: =SUM(AB23:AM23) -> 1493 | AE23: 144 | AF23: 160 | AG23: 184 | AH23: 152 | AI23: 192 | AJ23: 152 | AK23: 152 | AL23: 184 | AM23: 173 | AN23: =SUM(AO23:AZ23) -> 268740 | AO23: =AB23*$K23 -> 0 | AP23: =AC23*$K23 -> 0 | AQ23: =AD23*$K23 -> 0 | AR23: =AE23*$K23 -> 25920 | AS23: =AF23*$K23 -> 28800 | AT23: =AG23*$K23 -> 33120 | AU23: =AH23*$K23 -> 27360 | AV23: =AI23*$K23 -> 34560 | ... AZ23: =AM23*$K23 -> 31140 | BA23: =SUM(BB23:BM23) -> 0 | BB23: 0 | BC23: 0 | BD23: 0 | BE23: 0 | BF23: 0 | BG23: 0 | BH23: 0 | BI23: 0 | BJ23: 0 | BK23: 0 | BL23: 0 | BM23: 0 | BN23: =SUM(BO23:BZ23) -> 268740 | BO23: =BB23+AO23 -> 0 | BP23: =BC23+AP23 -> 0 | BQ23: =BD23+AQ23 -> 0 | BR23: =BE23+AR23 -> 25920 | BS23: =BF23+AS23 -> 28800 | BT23: =BG23+AT23 -> 33120 | BU23: =BH23+AU23 -> 27360 | BV23: =BI23+AV23 -> 34560 | ... BZ23: =BM23+AZ23 -> 31140
A24: =IF(ISNUMBER(INDEX('IBM POs AP07'!$A:$A, MATCH(D24,'IBM POs AP07'!$A:$A,0),1)),"Yes","No") -> No | B24: Raju Parkala | C24: Sachin Vaidya | D24: 9501173555 | E24: YALQJB | F24: SAP SVO CI Commercial 2026 | G24: 46113 | H24: 46387 | I24: 0K2815 | J24: NIHAR SWAIN | K24: 165 | L24: Onshore | N24: =AH24 -> 152 | O24: =N24*K24 -> 25080 | P24: =BF24 -> 0 | Q24: =O24+P24 -> 25080 | S24: =R24*K24 -> 0 | T24: 0 | U24: =S24+T24 -> 0 | V24: =Q24-U24 -> 25080 | W24: =IF(AND(L24="Offshore",R24>N24),"Red Flag",IF(AND(OR(L24="Onshore",L24="EMEA"),R24>N24),"Red Flag","")) | X24: 1 | Y24: 0 | AA24: =SUM(AB24:AM24) -> 1493 | AE24: 144 | AF24: 160 | AG24: 184 | AH24: 152 | AI24: 192 | AJ24: 152 | AK24: 152 | AL24: 184 | AM24: 173 | AN24: =SUM(AO24:AZ24) -> 246345 | AO24: =AB24*$K24 -> 0 | AP24: =AC24*$K24 -> 0 | AQ24: =AD24*$K24 -> 0 | AR24: =AE24*$K24 -> 23760 | AS24: =AF24*$K24 -> 26400 | AT24: =AG24*$K24 -> 30360 | AU24: =AH24*$K24 -> 25080 | AV24: =AI24*$K24 -> 31680 | ... AZ24: =AM24*$K24 -> 28545 | BA24: =SUM(BB24:BM24) -> 0 | BB24: 0 | BC24: 0 | BD24: 0 | BE24: 0 | BF24: 0 | BG24: 0 | BH24: 0 | BI24: 0 | BJ24: 0 | BK24: 0 | BL24: 0 | BM24: 0 | BN24: =SUM(BO24:BZ24) -> 246345 | BO24: =BB24+AO24 -> 0 | BP24: =BC24+AP24 -> 0 | BQ24: =BD24+AQ24 -> 0 | BR24: =BE24+AR24 -> 23760 | BS24: =BF24+AS24 -> 26400 | BT24: =BG24+AT24 -> 30360 | BU24: =BH24+AU24 -> 25080 | BV24: =BI24+AV24 -> 31680 | ... BZ24: =BM24+AZ24 -> 28545
A25: =IF(ISNUMBER(INDEX('IBM POs AP07'!$A:$A, MATCH(D25,'IBM POs AP07'!$A:$A,0),1)),"Yes","No") -> No | B25: Raju Parkala | C25: Sachin Vaidya | D25: 9501173555 | E25: YALQJB | F25: SAP SVO CI Commercial 2026 | G25: 46113 | H25: 46387 | I25: 04322A | J25: MOHAN PAWAR | K25: 180 | L25: Onshore | N25: =AH25 -> 152 | O25: =N25*K25 -> 27360 | P25: =BF25 -> 0 | Q25: =O25+P25 -> 27360 | S25: =R25*K25 -> 0 | T25: 0 | U25: =S25+T25 -> 0 | V25: =Q25-U25 -> 27360 | W25: =IF(AND(L25="Offshore",R25>N25),"Red Flag",IF(AND(OR(L25="Onshore",L25="EMEA"),R25>N25),"Red Flag","")) | X25: 1 | Y25: 0 | AA25: =SUM(AB25:AM25) -> 1493 | AE25: 144 | AF25: 160 | AG25: 184 | AH25: 152 | AI25: 192 | AJ25: 152 | AK25: 152 | AL25: 184 | AM25: 173 | AN25: =SUM(AO25:AZ25) -> 268740 | AO25: =AB25*$K25 -> 0 | AP25: =AC25*$K25 -> 0 | AQ25: =AD25*$K25 -> 0 | AR25: =AE25*$K25 -> 25920 | AS25: =AF25*$K25 -> 28800 | AT25: =AG25*$K25 -> 33120 | AU25: =AH25*$K25 -> 27360 | AV25: =AI25*$K25 -> 34560 | ... AZ25: =AM25*$K25 -> 31140 | BA25: =SUM(BB25:BM25) -> 0 | BB25: 0 | BC25: 0 | BD25: 0 | BE25: 0 | BF25: 0 | BG25: 0 | BH25: 0 | BI25: 0 | BJ25: 0 | BK25: 0 | BL25: 0 | BM25: 0 | BN25: =SUM(BO25:BZ25) -> 268740 | BO25: =BB25+AO25 -> 0 | BP25: =BC25+AP25 -> 0 | BQ25: =BD25+AQ25 -> 0 | BR25: =BE25+AR25 -> 25920 | BS25: =BF25+AS25 -> 28800 | BT25: =BG25+AT25 -> 33120 | BU25: =BH25+AU25 -> 27360 | BV25: =BI25+AV25 -> 34560 | ... BZ25: =BM25+AZ25 -> 31140
A26: =IF(ISNUMBER(INDEX('IBM POs AP07'!$A:$A, MATCH(D26,'IBM POs AP07'!$A:$A,0),1)),"Yes","No") -> No | B26: Raju Parkala | C26: Sachin Vaidya | D26: 9501173555 | E26: YALQJB | F26: SAP SVO CI Commercial 2026 | G26: 46113 | H26: 46387 | I26: 05384K | J26: SUBHRA DAS | K26: 180 | L26: Onshore | N26: =AH26 -> 152 | O26: =N26*K26 -> 27360 | P26: =BF26 -> 0 | Q26: =O26+P26 -> 27360 | S26: =R26*K26 -> 0 | T26: 0 | U26: =S26+T26 -> 0 | V26: =Q26-U26 -> 27360 | W26: =IF(AND(L26="Offshore",R26>N26),"Red Flag",IF(AND(OR(L26="Onshore",L26="EMEA"),R26>N26),"Red Flag","")) | X26: 1 | Y26: 0 | AA26: =SUM(AB26:AM26) -> 1493 | AE26: 144 | AF26: 160 | AG26: 184 | AH26: 152 | AI26: 192 | AJ26: 152 | AK26: 152 | AL26: 184 | AM26: 173 | AN26: =SUM(AO26:AZ26) -> 268740 | AO26: =AB26*$K26 -> 0 | AP26: =AC26*$K26 -> 0 | AQ26: =AD26*$K26 -> 0 | AR26: =AE26*$K26 -> 25920 | AS26: =AF26*$K26 -> 28800 | AT26: =AG26*$K26 -> 33120 | AU26: =AH26*$K26 -> 27360 | AV26: =AI26*$K26 -> 34560 | ... AZ26: =AM26*$K26 -> 31140 | BA26: =SUM(BB26:BM26) -> 0 | BB26: 0 | BC26: 0 | BD26: 0 | BE26: 0 | BF26: 0 | BG26: 0 | BH26: 0 | BI26: 0 | BJ26: 0 | BK26: 0 | BL26: 0 | BM26: 0 | BN26: =SUM(BO26:BZ26) -> 268740 | BO26: =BB26+AO26 -> 0 | BP26: =BC26+AP26 -> 0 | BQ26: =BD26+AQ26 -> 0 | BR26: =BE26+AR26 -> 25920 | BS26: =BF26+AS26 -> 28800 | BT26: =BG26+AT26 -> 33120 | BU26: =BH26+AU26 -> 27360 | BV26: =BI26+AV26 -> 34560 | ... BZ26: =BM26+AZ26 -> 31140
A27: =IF(ISNUMBER(INDEX('IBM POs AP07'!$A:$A, MATCH(D27,'IBM POs AP07'!$A:$A,0),1)),"Yes","No") -> No | B27: Raju Parkala | C27: Sachin Vaidya | D27: 9501173555 | E27: YALQJB | F27: SAP SVO CI Commercial 2026 | G27: 46113 | H27: 46387 | I27: 93609 | J27: ANKAN DHAR | K27: 61.75 | L27: Offshore | N27: =AH27 -> 171 | O27: =N27*K27 -> 10559.25 | P27: =BF27 -> 0 | Q27: =O27+P27 -> 10559.25 | S27: =R27*K27 -> 0 | T27: 0 | U27: =S27+T27 -> 0 | V27: =Q27-U27 -> 10559.25 | W27: =IF(AND(L27="Offshore",R27>N27),"Red Flag",IF(AND(OR(L27="Onshore",L27="EMEA"),R27>N27),"Red Flag","")) | X27: 1 | Y27: 0 | AA27: =SUM(AB27:AM27) -> 1661 | AE27: 165 | AF27: 173 | AG27: 198 | AH27: 171 | AI27: 216 | AJ27: 171 | AK27: 171 | AL27: 207 | AM27: 189 | AN27: =SUM(AO27:AZ27) -> 102566.75 | AO27: =AB27*$K27 -> 0 | AP27: =AC27*$K27 -> 0 | AQ27: =AD27*$K27 -> 0 | AR27: =AE27*$K27 -> 10188.75 | AS27: =AF27*$K27 -> 10682.75 | AT27: =AG27*$K27 -> 12226.5 | AU27: =AH27*$K27 -> 10559.25 | AV27: =AI27*$K27 -> 13338 | ... AZ27: =AM27*$K27 -> 11670.75 | BA27: =SUM(BB27:BM27) -> 0 | BB27: 0 | BC27: 0 | BD27: 0 | BE27: 0 | BF27: 0 | BG27: 0 | BH27: 0 | BI27: 0 | BJ27: 0 | BK27: 0 | BL27: 0 | BM27: 0 | BN27: =SUM(BO27:BZ27) -> 102566.75 | BO27: =BB27+AO27 -> 0 | BP27: =BC27+AP27 -> 0 | BQ27: =BD27+AQ27 -> 0 | BR27: =BE27+AR27 -> 10188.75 | BS27: =BF27+AS27 -> 10682.75 | BT27: =BG27+AT27 -> 12226.5 | BU27: =BH27+AU27 -> 10559.25 | BV27: =BI27+AV27 -> 13338 | ... BZ27: =BM27+AZ27 -> 11670.75
A28: =IF(ISNUMBER(INDEX('IBM POs AP07'!$A:$A, MATCH(D28,'IBM POs AP07'!$A:$A,0),1)),"Yes","No") -> No | B28: Raju Parkala | C28: Sachin Vaidya | D28: 9501173555 | E28: YALQJB | F28: SAP SVO CI Commercial 2026 | G28: 46113 | H28: 46387 | I28: 06810V | J28: KATTULA ANIRUDH VENKATA SAI | K28: 47.5 | L28: Offshore | N28: =AH28 -> 171 | O28: =N28*K28 -> 8122.5 | P28: =BF28 -> 0 | Q28: =O28+P28 -> 8122.5 | S28: =R28*K28 -> 0 | T28: 0 | U28: =S28+T28 -> 0 | V28: =Q28-U28 -> 8122.5 | W28: =IF(AND(L28="Offshore",R28>N28),"Red Flag",IF(AND(OR(L28="Onshore",L28="EMEA"),R28>N28),"Red Flag","")) | X28: 1 | Y28: 0 | AA28: =SUM(AB28:AM28) -> 1660 | AE28: 162 | AF28: 175 | AG28: 198 | AH28: 171 | AI28: 216 | AJ28: 171 | AK28: 171 | AL28: 207 | AM28: 189 | AN28: =SUM(AO28:AZ28) -> 78850 | AO28: =AB28*$K28 -> 0 | AP28: =AC28*$K28 -> 0 | AQ28: =AD28*$K28 -> 0 | AR28: =AE28*$K28 -> 7695 | AS28: =AF28*$K28 -> 8312.5 | AT28: =AG28*$K28 -> 9405 | AU28: =AH28*$K28 -> 8122.5 | AV28: =AI28*$K28 -> 10260 | ... AZ28: =AM28*$K28 -> 8977.5 | BA28: =SUM(BB28:BM28) -> 0 | BB28: 0 | BC28: 0 | BD28: 0 | BE28: 0 | BF28: 0 | BG28: 0 | BH28: 0 | BI28: 0 | BJ28: 0 | BK28: 0 | BL28: 0 | BM28: 0 | BN28: =SUM(BO28:BZ28) -> 78850 | BO28: =BB28+AO28 -> 0 | BP28: =BC28+AP28 -> 0 | BQ28: =BD28+AQ28 -> 0 | BR28: =BE28+AR28 -> 7695 | BS28: =BF28+AS28 -> 8312.5 | BT28: =BG28+AT28 -> 9405 | BU28: =BH28+AU28 -> 8122.5 | BV28: =BI28+AV28 -> 10260 | ... BZ28: =BM28+AZ28 -> 8977.5
A29: =IF(ISNUMBER(INDEX('IBM POs AP07'!$A:$A, MATCH(D29,'IBM POs AP07'!$A:$A,0),1)),"Yes","No") -> No | B29: Raju Parkala | C29: Sachin Vaidya | D29: 9501173555 | E29: YALQJB | F29: SAP SVO CI Commercial 2026 | G29: 46113 | H29: 46387 | I29: 06952X | J29: SHUBHAM SAHA | K29: 47.5 | L29: Offshore | N29: =AH29 -> 171 | O29: =N29*K29 -> 8122.5 | P29: =BF29 -> 0 | Q29: =O29+P29 -> 8122.5 | S29: =R29*K29 -> 0 | T29: 0 | U29: =S29+T29 -> 0 | V29: =Q29-U29 -> 8122.5 | W29: =IF(AND(L29="Offshore",R29>N29),"Red Flag",IF(AND(OR(L29="Onshore",L29="EMEA"),R29>N29),"Red Flag","")) | X29: 1 | Y29: 0 | AA29: =SUM(AB29:AM29) -> 1645 | AE29: 157 | AF29: 165 | AG29: 198 | AH29: 171 | AI29: 216 | AJ29: 171 | AK29: 171 | AL29: 207 | AM29: 189 | AN29: =SUM(AO29:AZ29) -> 78137.5 | AO29: =AB29*$K29 -> 0 | AP29: =AC29*$K29 -> 0 | AQ29: =AD29*$K29 -> 0 | AR29: =AE29*$K29 -> 7457.5 | AS29: =AF29*$K29 -> 7837.5 | AT29: =AG29*$K29 -> 9405 | AU29: =AH29*$K29 -> 8122.5 | AV29: =AI29*$K29 -> 10260 | ... AZ29: =AM29*$K29 -> 8977.5 | BA29: =SUM(BB29:BM29) -> 0 | BB29: 0 | BC29: 0 | BD29: 0 | BE29: 0 | BF29: 0 | BG29: 0 | BH29: 0 | BI29: 0 | BJ29: 0 | BK29: 0 | BL29: 0 | BM29: 0 | BN29: =SUM(BO29:BZ29) -> 78137.5 | BO29: =BB29+AO29 -> 0 | BP29: =BC29+AP29 -> 0 | BQ29: =BD29+AQ29 -> 0 | BR29: =BE29+AR29 -> 7457.5 | BS29: =BF29+AS29 -> 7837.5 | BT29: =BG29+AT29 -> 9405 | BU29: =BH29+AU29 -> 8122.5 | BV29: =BI29+AV29 -> 10260 | ... BZ29: =BM29+AZ29 -> 8977.5
A30: =IF(ISNUMBER(INDEX('IBM POs AP07'!$A:$A, MATCH(D30,'IBM POs AP07'!$A:$A,0),1)),"Yes","No") -> No | B30: Raju Parkala | C30: Sachin Vaidya | D30: 9501173555 | E30: YALQJB | F30: SAP SVO CI Commercial 2026 | G30: 46113 | H30: 46387 | I30: 01057K | J30: SRINIVASARAO PEDDI | K30: 61.75 | L30: Offshore | N30: =AH30 -> 171 | O30: =N30*K30 -> 10559.25 | P30: =BF30 -> 0 | Q30: =O30+P30 -> 10559.25 | S30: =R30*K30 -> 0 | T30: 0 | U30: =S30+T30 -> 0 | V30: =Q30-U30 -> 10559.25 | W30: =IF(AND(L30="Offshore",R30>N30),"Red Flag",IF(AND(OR(L30="Onshore",L30="EMEA"),R30>N30),"Red Flag","")) | X30: 1 | Y30: 0 | AA30: =SUM(AB30:AM30) -> 1676 | AE30: 172 | AF30: 181 | AG30: 198 | AH30: 171 | AI30: 216 | AJ30: 171 | AK30: 171 | AL30: 207 | AM30: 189 | AN30: =SUM(AO30:AZ30) -> 103493 | AO30: =AB30*$K30 -> 0 | AP30: =AC30*$K30 -> 0 | AQ30: =AD30*$K30 -> 0 | AR30: =AE30*$K30 -> 10621 | AS30: =AF30*$K30 -> 11176.75 | AT30: =AG30*$K30 -> 12226.5 | AU30: =AH30*$K30 -> 10559.25 | AV30: =AI30*$K30 -> 13338 | ... AZ30: =AM30*$K30 -> 11670.75 | BA30: =SUM(BB30:BM30) -> 0 | BB30: 0 | BC30: 0 | BD30: 0 | BE30: 0 | BF30: 0 | BG30: 0 | BH30: 0 | BI30: 0 | BJ30: 0 | BK30: 0 | BL30: 0 | BM30: 0 | BN30: =SUM(BO30:BZ30) -> 103493 | BO30: =BB30+AO30 -> 0 | BP30: =BC30+AP30 -> 0 | BQ30: =BD30+AQ30 -> 0 | BR30: =BE30+AR30 -> 10621 | BS30: =BF30+AS30 -> 11176.75 | BT30: =BG30+AT30 -> 12226.5 | BU30: =BH30+AU30 -> 10559.25 | BV30: =BI30+AV30 -> 13338 | ... BZ30: =BM30+AZ30 -> 11670.75
A31: =IF(ISNUMBER(INDEX('IBM POs AP07'!$A:$A, MATCH(D31,'IBM POs AP07'!$A:$A,0),1)),"Yes","No") -> No | B31: Raju Parkala | C31: Sachin Vaidya | D31: 9501173555 | E31: YALQJB | F31: SAP SVO CI Commercial 2026 | G31: 46113 | H31: 46387 | I31: 07849N | J31: SUBRAT BEHERA | K31: 61.75 | L31: Offshore | N31: =AH31 -> 171 | O31: =N31*K31 -> 10559.25 | P31: =BF31 -> 0 | Q31: =O31+P31 -> 10559.25 | S31: =R31*K31 -> 0 | T31: 0 | U31: =S31+T31 -> 0 | V31: =Q31-U31 -> 10559.25 | W31: =IF(AND(L31="Offshore",R31>N31),"Red Flag",IF(AND(OR(L31="Onshore",L31="EMEA"),R31>N31),"Red Flag","")) | X31: 1 | Y31: 0 | AA31: =SUM(AB31:AM31) -> 1652 | AE31: 162 | AF31: 167 | AG31: 198 | AH31: 171 | AI31: 216 | AJ31: 171 | AK31: 171 | AL31: 207 | AM31: 189 | AN31: =SUM(AO31:AZ31) -> 102011 | AO31: =AB31*$K31 -> 0 | AP31: =AC31*$K31 -> 0 | AQ31: =AD31*$K31 -> 0 | AR31: =AE31*$K31 -> 10003.5 | AS31: =AF31*$K31 -> 10312.25 | AT31: =AG31*$K31 -> 12226.5 | AU31: =AH31*$K31 -> 10559.25 | AV31: =AI31*$K31 -> 13338 | ... AZ31: =AM31*$K31 -> 11670.75 | BA31: =SUM(BB31:BM31) -> 0 | BB31: 0 | BC31: 0 | BD31: 0 | BE31: 0 | BF31: 0 | BG31: 0 | BH31: 0 | BI31: 0 | BJ31: 0 | BK31: 0 | BL31: 0 | BM31: 0 | BN31: =SUM(BO31:BZ31) -> 102011 | BO31: =BB31+AO31 -> 0 | BP31: =BC31+AP31 -> 0 | BQ31: =BD31+AQ31 -> 0 | BR31: =BE31+AR31 -> 10003.5 | BS31: =BF31+AS31 -> 10312.25 | BT31: =BG31+AT31 -> 12226.5 | BU31: =BH31+AU31 -> 10559.25 | BV31: =BI31+AV31 -> 13338 | ... BZ31: =BM31+AZ31 -> 11670.75
A32: =IF(ISNUMBER(INDEX('IBM POs AP07'!$A:$A, MATCH(D32,'IBM POs AP07'!$A:$A,0),1)),"Yes","No") -> No | B32: Raju Parkala | C32: Sachin Vaidya | D32: 9501173555 | E32: YALQJB | F32: SAP SVO CI Commercial 2026 | G32: 46113 | H32: 46387 | I32: 005XOY | J32: UJJWAL CHATTOPADHYAY | K32: 87 | L32: Offshore | N32: =AH32 -> 171 | O32: =N32*K32 -> 14877 | P32: =BF32 -> 0 | Q32: =O32+P32 -> 14877 | S32: =R32*K32 -> 0 | T32: 0 | U32: =S32+T32 -> 0 | V32: =Q32-U32 -> 14877 | W32: =IF(AND(L32="Offshore",R32>N32),"Red Flag",IF(AND(OR(L32="Onshore",L32="EMEA"),R32>N32),"Red Flag","")) | X32: 1 | Y32: 0 | AA32: =SUM(AB32:AM32) -> 1636 | AE32: 157 | AF32: 156 | AG32: 198 | AH32: 171 | AI32: 216 | AJ32: 171 | AK32: 171 | AL32: 207 | AM32: 189 | AN32: =SUM(AO32:AZ32) -> 142332 | AO32: =AB32*$K32 -> 0 | AP32: =AC32*$K32 -> 0 | AQ32: =AD32*$K32 -> 0 | AR32: =AE32*$K32 -> 13659 | AS32: =AF32*$K32 -> 13572 | AT32: =AG32*$K32 -> 17226 | AU32: =AH32*$K32 -> 14877 | AV32: =AI32*$K32 -> 18792 | ... AZ32: =AM32*$K32 -> 16443 | BA32: =SUM(BB32:BM32) -> 0 | BB32: 0 | BC32: 0 | BD32: 0 | BE32: 0 | BF32: 0 | BG32: 0 | BH32: 0 | BI32: 0 | BJ32: 0 | BK32: 0 | BL32: 0 | BM32: 0 | BN32: =SUM(BO32:BZ32) -> 142332 | BO32: =BB32+AO32 -> 0 | BP32: =BC32+AP32 -> 0 | BQ32: =BD32+AQ32 -> 0 | BR32: =BE32+AR32 -> 13659 | BS32: =BF32+AS32 -> 13572 | BT32: =BG32+AT32 -> 17226 | BU32: =BH32+AU32 -> 14877 | BV32: =BI32+AV32 -> 18792 | ... BZ32: =BM32+AZ32 -> 16443
A33: =IF(ISNUMBER(INDEX('IBM POs AP07'!$A:$A, MATCH(D33,'IBM POs AP07'!$A:$A,0),1)),"Yes","No") -> No | B33: Raju Parkala | C33: Sachin Vaidya | D33: 9501173555 | E33: YALQJB | F33: SAP SVO CI Commercial 2026 | G33: 46113 | H33: 46387 | I33: C-JDPH | J33: SUNIL SHIVALINGAIAH | K33: 172 | L33: Onshore | N33: =AH33 -> 0 | O33: =N33*K33 -> 0 | P33: =BF33 -> 0 | Q33: =O33+P33 -> 0 | S33: =R33*K33 -> 0 | T33: 0 | U33: =S33+T33 -> 0 | V33: =Q33-U33 -> 0 | W33: =IF(AND(L33="Offshore",R33>N33),"Red Flag",IF(AND(OR(L33="Onshore",L33="EMEA"),R33>N33),"Red Flag","")) | X33: 1 | Y33: 0 | AA33: =SUM(AB33:AM33) -> 264 | AE33: 144 | AF33: 120 | AG33: 0 | AH33: 0 | AI33: 0 | AJ33: 0 | AK33: 0 | AL33: 0 | AM33: 0 | AN33: =SUM(AO33:AZ33) -> 45408 | AO33: =AB33*$K33 -> 0 | AP33: =AC33*$K33 -> 0 | AQ33: =AD33*$K33 -> 0 | AR33: =AE33*$K33 -> 24768 | AS33: =AF33*$K33 -> 20640 | AT33: =AG33*$K33 -> 0 | AU33: =AH33*$K33 -> 0 | AV33: =AI33*$K33 -> 0 | ... AZ33: =AM33*$K33 -> 0 | BA33: =SUM(BB33:BM33) -> 0 | BB33: 0 | BC33: 0 | BD33: 0 | BE33: 0 | BF33: 0 | BG33: 0 | BH33: 0 | BI33: 0 | BJ33: 0 | BK33: 0 | BL33: 0 | BM33: 0 | BN33: =SUM(BO33:BZ33) -> 45408 | BO33: =BB33+AO33 -> 0 | BP33: =BC33+AP33 -> 0 | BQ33: =BD33+AQ33 -> 0 | BR33: =BE33+AR33 -> 24768 | BS33: =BF33+AS33 -> 20640 | BT33: =BG33+AT33 -> 0 | BU33: =BH33+AU33 -> 0 | BV33: =BI33+AV33 -> 0 | ... BZ33: =BM33+AZ33 -> 0
A34: =IF(ISNUMBER(INDEX('IBM POs AP07'!$A:$A, MATCH(D34,'IBM POs AP07'!$A:$A,0),1)),"Yes","No") -> No | B34: Raju Parkala | C34: Sachin Vaidya | D34: 9501173555 | E34: YALQJB | F34: SAP SVO CI Commercial 2026 | G34: 46113 | H34: 46387 | I34: C-JDPJ | J34: SUNIL PRABHAKAR | K34: 172 | L34: Onshore | N34: =AH34 -> 0 | O34: =N34*K34 -> 0 | P34: =BF34 -> 0 | Q34: =O34+P34 -> 0 | S34: =R34*K34 -> 0 | T34: 0 | U34: =S34+T34 -> 0 | V34: =Q34-U34 -> 0 | W34: =IF(AND(L34="Offshore",R34>N34),"Red Flag",IF(AND(OR(L34="Onshore",L34="EMEA"),R34>N34),"Red Flag","")) | X34: 1 | Y34: 0 | AA34: =SUM(AB34:AM34) -> 264 | AE34: 144 | AF34: 120 | AG34: 0 | AH34: 0 | AI34: 0 | AJ34: 0 | AK34: 0 | AL34: 0 | AM34: 0 | AN34: =SUM(AO34:AZ34) -> 45408 | AO34: =AB34*$K34 -> 0 | AP34: =AC34*$K34 -> 0 | AQ34: =AD34*$K34 -> 0 | AR34: =AE34*$K34 -> 24768 | AS34: =AF34*$K34 -> 20640 | AT34: =AG34*$K34 -> 0 | AU34: =AH34*$K34 -> 0 | AV34: =AI34*$K34 -> 0 | ... AZ34: =AM34*$K34 -> 0 | BA34: =SUM(BB34:BM34) -> 0 | BB34: 0 | BC34: 0 | BD34: 0 | BE34: 0 | BF34: 0 | BG34: 0 | BH34: 0 | BI34: 0 | BJ34: 0 | BK34: 0 | BL34: 0 | BM34: 0 | BN34: =SUM(BO34:BZ34) -> 45408 | BO34: =BB34+AO34 -> 0 | BP34: =BC34+AP34 -> 0 | BQ34: =BD34+AQ34 -> 0 | BR34: =BE34+AR34 -> 24768 | BS34: =BF34+AS34 -> 20640 | BT34: =BG34+AT34 -> 0 | BU34: =BH34+AU34 -> 0 | BV34: =BI34+AV34 -> 0 | ... BZ34: =BM34+AZ34 -> 0
A35: =IF(ISNUMBER(INDEX('IBM POs AP07'!$A:$A, MATCH(D35,'IBM POs AP07'!$A:$A,0),1)),"Yes","No") -> No | B35: Raju Parkala | C35: Sachin Vaidya | D35: 9501173555 | E35: YALQJB | F35: SAP SVO CI Commercial 2026 | G35: 46113 | H35: 46387 | I35: C-LGLV | J35: RAMKRISHNA HOSURSRINIVAS | K35: 172 | L35: Onshore | N35: =AH35 -> 16 | O35: =N35*K35 -> 2752 | P35: =BF35 -> 0 | Q35: =O35+P35 -> 2752 | S35: =R35*K35 -> 0 | T35: 0 | U35: =S35+T35 -> 0 | V35: =Q35-U35 -> 2752 | W35: =IF(AND(L35="Offshore",R35>N35),"Red Flag",IF(AND(OR(L35="Onshore",L35="EMEA"),R35>N35),"Red Flag","")) | X35: 1 | Y35: 0 | AA35: =SUM(AB35:AM35) -> 504 | AE35: 144 | AF35: 160 | AG35: 184 | AH35: 16 | AI35: 0 | AJ35: 0 | AK35: 0 | AL35: 0 | AM35: 0 | AN35: =SUM(AO35:AZ35) -> 86688 | AO35: =AB35*$K35 -> 0 | AP35: =AC35*$K35 -> 0 | AQ35: =AD35*$K35 -> 0 | AR35: =AE35*$K35 -> 24768 | AS35: =AF35*$K35 -> 27520 | AT35: =AG35*$K35 -> 31648 | AU35: =AH35*$K35 -> 2752 | AV35: =AI35*$K35 -> 0 | ... AZ35: =AM35*$K35 -> 0 | BA35: =SUM(BB35:BM35) -> 0 | BB35: 0 | BC35: 0 | BD35: 0 | BE35: 0 | BF35: 0 | BG35: 0 | BH35: 0 | BI35: 0 | BJ35: 0 | BK35: 0 | BL35: 0 | BM35: 0 | BN35: =SUM(BO35:BZ35) -> 86688 | BO35: =BB35+AO35 -> 0 | BP35: =BC35+AP35 -> 0 | BQ35: =BD35+AQ35 -> 0 | BR35: =BE35+AR35 -> 24768 | BS35: =BF35+AS35 -> 27520 | BT35: =BG35+AT35 -> 31648 | BU35: =BH35+AU35 -> 2752 | BV35: =BI35+AV35 -> 0 | ... BZ35: =BM35+AZ35 -> 0
A36: =IF(ISNUMBER(INDEX('IBM POs AP07'!$A:$A, MATCH(D36,'IBM POs AP07'!$A:$A,0),1)),"Yes","No") -> No | B36: Raju Parkala | C36: Sachin Vaidya | D36: 9501173555 | E36: YALQJB | F36: SAP SVO CI Commercial 2026 | G36: 46113 | H36: 46387 | I36: C-JDPG | J36: VIJAY GUMMADI | K36: 210 | L36: Onshore | N36: =AH36 -> 16 | O36: =N36*K36 -> 3360 | P36: =BF36 -> 0 | Q36: =O36+P36 -> 3360 | S36: =R36*K36 -> 0 | T36: 0 | U36: =S36+T36 -> 0 | V36: =Q36-U36 -> 3360 | W36: =IF(AND(L36="Offshore",R36>N36),"Red Flag",IF(AND(OR(L36="Onshore",L36="EMEA"),R36>N36),"Red Flag","")) | X36: 1 | Y36: 0 | AA36: =SUM(AB36:AM36) -> 504 | AE36: 144 | AF36: 160 | AG36: 184 | AH36: 16 | AI36: 0 | AJ36: 0 | AK36: 0 | AL36: 0 | AM36: 0 | AN36: =SUM(AO36:AZ36) -> 105840 | AO36: =AB36*$K36 -> 0 | AP36: =AC36*$K36 -> 0 | AQ36: =AD36*$K36 -> 0 | AR36: =AE36*$K36 -> 30240 | AS36: =AF36*$K36 -> 33600 | AT36: =AG36*$K36 -> 38640 | AU36: =AH36*$K36 -> 3360 | AV36: =AI36*$K36 -> 0 | ... AZ36: =AM36*$K36 -> 0 | BA36: =SUM(BB36:BM36) -> 0 | BB36: 0 | BC36: 0 | BD36: 0 | BE36: 0 | BF36: 0 | BG36: 0 | BH36: 0 | BI36: 0 | BJ36: 0 | BK36: 0 | BL36: 0 | BM36: 0 | BN36: =SUM(BO36:BZ36) -> 105840 | BO36: =BB36+AO36 -> 0 | BP36: =BC36+AP36 -> 0 | BQ36: =BD36+AQ36 -> 0 | BR36: =BE36+AR36 -> 30240 | BS36: =BF36+AS36 -> 33600 | BT36: =BG36+AT36 -> 38640 | BU36: =BH36+AU36 -> 3360 | BV36: =BI36+AV36 -> 0 | ... BZ36: =BM36+AZ36 -> 0
A37: =IF(ISNUMBER(INDEX('IBM POs AP07'!$A:$A, MATCH(D37,'IBM POs AP07'!$A:$A,0),1)),"Yes","No") -> No | B37: Raju Parkala | C37: Sachin Vaidya | D37: 9501173555 | E37: YALQJB | F37: SAP SVO CI Commercial 2026 | G37: 46113 | H37: 46387 | I37: C-P3JE | J37: SOUMITRA ROY | K37: 200 | L37: Onshore | N37: =AH37 -> 16 | O37: =N37*K37 -> 3200 | P37: =BF37 -> 0 | Q37: =O37+P37 -> 3200 | S37: =R37*K37 -> 0 | T37: 0 | U37: =S37+T37 -> 0 | V37: =Q37-U37 -> 3200 | W37: =IF(AND(L37="Offshore",R37>N37),"Red Flag",IF(AND(OR(L37="Onshore",L37="EMEA"),R37>N37),"Red Flag","")) | X37: 1 | Y37: 0 | AA37: =SUM(AB37:AM37) -> 504 | AE37: 144 | AF37: 160 | AG37: 184 | AH37: 16 | AI37: 0 | AJ37: 0 | AK37: 0 | AL37: 0 | AM37: 0 | AN37: =SUM(AO37:AZ37) -> 100800 | AO37: =AB37*$K37 -> 0 | AP37: =AC37*$K37 -> 0 | AQ37: =AD37*$K37 -> 0 | AR37: =AE37*$K37 -> 28800 | AS37: =AF37*$K37 -> 32000 | AT37: =AG37*$K37 -> 36800 | AU37: =AH37*$K37 -> 3200 | AV37: =AI37*$K37 -> 0 | ... AZ37: =AM37*$K37 -> 0 | BA37: =SUM(BB37:BM37) -> 0 | BB37: 0 | BC37: 0 | BD37: 0 | BE37: 0 | BF37: 0 | BG37: 0 | BH37: 0 | BI37: 0 | BJ37: 0 | BK37: 0 | BL37: 0 | BM37: 0 | BN37: =SUM(BO37:BZ37) -> 100800 | BO37: =BB37+AO37 -> 0 | BP37: =BC37+AP37 -> 0 | BQ37: =BD37+AQ37 -> 0 | BR37: =BE37+AR37 -> 28800 | BS37: =BF37+AS37 -> 32000 | BT37: =BG37+AT37 -> 36800 | BU37: =BH37+AU37 -> 3200 | BV37: =BI37+AV37 -> 0 | ... BZ37: =BM37+AZ37 -> 0
A38: =IF(ISNUMBER(INDEX('IBM POs AP07'!$A:$A, MATCH(D38,'IBM POs AP07'!$A:$A,0),1)),"Yes","No") -> No | B38: Raju Parkala | C38: Sachin Vaidya | D38: 9501173555 | E38: YALQJB | F38: SAP SVO CI Commercial 2026 | G38: 46113 | H38: 46387 | I38: C-VKG0 | J38: RAMASHANKAR GANJI | K38: 165 | L38: Onshore | N38: =AH38 -> 152 | O38: =N38*K38 -> 25080 | P38: =BF38 -> 0 | Q38: =O38+P38 -> 25080 | S38: =R38*K38 -> 0 | T38: 0 | U38: =S38+T38 -> 0 | V38: =Q38-U38 -> 25080 | W38: =IF(AND(L38="Offshore",R38>N38),"Red Flag",IF(AND(OR(L38="Onshore",L38="EMEA"),R38>N38),"Red Flag","")) | X38: 1 | Y38: 0 | AA38: =SUM(AB38:AM38) -> 1501 | AE38: 144 | AF38: 160 | AG38: 192 | AH38: 152 | AI38: 192 | AJ38: 152 | AK38: 152 | AL38: 184 | AM38: 173 | AN38: =SUM(AO38:AZ38) -> 247665 | AO38: =AB38*$K38 -> 0 | AP38: =AC38*$K38 -> 0 | AQ38: =AD38*$K38 -> 0 | AR38: =AE38*$K38 -> 23760 | AS38: =AF38*$K38 -> 26400 | AT38: =AG38*$K38 -> 31680 | AU38: =AH38*$K38 -> 25080 | AV38: =AI38*$K38 -> 31680 | ... AZ38: =AM38*$K38 -> 28545 | BA38: =SUM(BB38:BM38) -> 0 | BB38: 0 | BC38: 0 | BD38: 0 | BE38: 0 | BF38: 0 | BG38: 0 | BH38: 0 | BI38: 0 | BJ38: 0 | BK38: 0 | BL38: 0 | BM38: 0 | BN38: =SUM(BO38:BZ38) -> 247665 | BO38: =BB38+AO38 -> 0 | BP38: =BC38+AP38 -> 0 | BQ38: =BD38+AQ38 -> 0 | BR38: =BE38+AR38 -> 23760 | BS38: =BF38+AS38 -> 26400 | BT38: =BG38+AT38 -> 31680 | BU38: =BH38+AU38 -> 25080 | BV38: =BI38+AV38 -> 31680 | ... BZ38: =BM38+AZ38 -> 28545
A39: =IF(ISNUMBER(INDEX('IBM POs AP07'!$A:$A, MATCH(D39,'IBM POs AP07'!$A:$A,0),1)),"Yes","No") -> No | B39: Raju Parkala | C39: Sachin Vaidya | D39: 9501173555 | E39: YALQJB | F39: SAP SVO CI Commercial 2026 | G39: 46113 | H39: 46387 | I39: 004QEL | J39: PADMAVATHY VASUDEVAN | K39: 61.75 | L39: Offshore | N39: =AH39 -> 171 | O39: =N39*K39 -> 10559.25 | P39: =BF39 -> 0 | Q39: =O39+P39 -> 10559.25 | S39: =R39*K39 -> 0 | T39: 0 | U39: =S39+T39 -> 0 | V39: =Q39-U39 -> 10559.25 | W39: =IF(AND(L39="Offshore",R39>N39),"Red Flag",IF(AND(OR(L39="Onshore",L39="EMEA"),R39>N39),"Red Flag","")) | X39: 1 | Y39: 0 | AA39: =SUM(AB39:AM39) -> 1634 | AE39: 132 | AF39: 179 | AG39: 198 | AH39: 171 | AI39: 216 | AJ39: 171 | AK39: 171 | AL39: 207 | AM39: 189 | AN39: =SUM(AO39:AZ39) -> 100899.5 | AO39: =AB39*$K39 -> 0 | AP39: =AC39*$K39 -> 0 | AQ39: =AD39*$K39 -> 0 | AR39: =AE39*$K39 -> 8151 | AS39: =AF39*$K39 -> 11053.25 | AT39: =AG39*$K39 -> 12226.5 | AU39: =AH39*$K39 -> 10559.25 | AV39: =AI39*$K39 -> 13338 | ... AZ39: =AM39*$K39 -> 11670.75 | BA39: =SUM(BB39:BM39) -> 0 | BB39: 0 | BC39: 0 | BD39: 0 | BE39: 0 | BF39: 0 | BG39: 0 | BH39: 0 | BI39: 0 | BJ39: 0 | BK39: 0 | BL39: 0 | BM39: 0 | BN39: =SUM(BO39:BZ39) -> 100899.5 | BO39: =BB39+AO39 -> 0 | BP39: =BC39+AP39 -> 0 | BQ39: =BD39+AQ39 -> 0 | BR39: =BE39+AR39 -> 8151 | BS39: =BF39+AS39 -> 11053.25 | BT39: =BG39+AT39 -> 12226.5 | BU39: =BH39+AU39 -> 10559.25 | BV39: =BI39+AV39 -> 13338 | ... BZ39: =BM39+AZ39 -> 11670.75
A40: =IF(ISNUMBER(INDEX('IBM POs AP07'!$A:$A, MATCH(D40,'IBM POs AP07'!$A:$A,0),1)),"Yes","No") -> No | B40: Raju Parkala | C40: Sachin Vaidya | D40: 9501173555 | E40: YALQJB | F40: SAP SVO CI Commercial 2026 | G40: 46113 | H40: 46387 | I40: 590930 | J40: VIKAS PARASHAR | K40: 61.75 | L40: Offshore | N40: =AH40 -> 171 | O40: =N40*K40 -> 10559.25 | P40: =BF40 -> 0 | Q40: =O40+P40 -> 10559.25 | S40: =R40*K40 -> 0 | T40: 0 | U40: =S40+T40 -> 0 | V40: =Q40-U40 -> 10559.25 | W40: =IF(AND(L40="Offshore",R40>N40),"Red Flag",IF(AND(OR(L40="Onshore",L40="EMEA"),R40>N40),"Red Flag","")) | X40: 1 | Y40: 0 | AA40: =SUM(AB40:AM40) -> 1659 | AE40: 162 | AF40: 174 | AG40: 198 | AH40: 171 | AI40: 216 | AJ40: 171 | AK40: 171 | AL40: 207 | AM40: 189 | AN40: =SUM(AO40:AZ40) -> 102443.25 | AO40: =AB40*$K40 -> 0 | AP40: =AC40*$K40 -> 0 | AQ40: =AD40*$K40 -> 0 | AR40: =AE40*$K40 -> 10003.5 | AS40: =AF40*$K40 -> 10744.5 | AT40: =AG40*$K40 -> 12226.5 | AU40: =AH40*$K40 -> 10559.25 | AV40: =AI40*$K40 -> 13338 | ... AZ40: =AM40*$K40 -> 11670.75 | BA40: =SUM(BB40:BM40) -> 0 | BB40: 0 | BC40: 0 | BD40: 0 | BE40: 0 | BF40: 0 | BG40: 0 | BH40: 0 | BI40: 0 | BJ40: 0 | BK40: 0 | BL40: 0 | BM40: 0 | BN40: =SUM(BO40:BZ40) -> 102443.25 | BO40: =BB40+AO40 -> 0 | BP40: =BC40+AP40 -> 0 | BQ40: =BD40+AQ40 -> 0 | BR40: =BE40+AR40 -> 10003.5 | BS40: =BF40+AS40 -> 10744.5 | BT40: =BG40+AT40 -> 12226.5 | BU40: =BH40+AU40 -> 10559.25 | BV40: =BI40+AV40 -> 13338 | ... BZ40: =BM40+AZ40 -> 11670.75
A41: =IF(ISNUMBER(INDEX('IBM POs AP07'!$A:$A, MATCH(D41,'IBM POs AP07'!$A:$A,0),1)),"Yes","No") -> No | B41: Raju Parkala | C41: Sachin Vaidya | D41: 9501173555 | E41: YALQJB | F41: SAP SVO CI Commercial 2026 | G41: 46113 | H41: 46387 | I41: 0063AW | J41: SWARUP MOHANTY | K41: 47.5 | L41: Offshore | N41: =AH41 -> 171 | O41: =N41*K41 -> 8122.5 | P41: =BF41 -> 0 | Q41: =O41+P41 -> 8122.5 | S41: =R41*K41 -> 0 | T41: 0 | U41: =S41+T41 -> 0 | V41: =Q41-U41 -> 8122.5 | W41: =IF(AND(L41="Offshore",R41>N41),"Red Flag",IF(AND(OR(L41="Onshore",L41="EMEA"),R41>N41),"Red Flag","")) | X41: 1 | Y41: 0 | AA41: =SUM(AB41:AM41) -> 1534 | AE41: 144 | AF41: 171 | AG41: 198 | AH41: 171 | AI41: 198 | AJ41: 171 | AK41: 171 | AL41: 182 | AM41: 128 | AN41: =SUM(AO41:AZ41) -> 72865 | AO41: =AB41*$K41 -> 0 | AP41: =AC41*$K41 -> 0 | AQ41: =AD41*$K41 -> 0 | AR41: =AE41*$K41 -> 6840 | AS41: =AF41*$K41 -> 8122.5 | AT41: =AG41*$K41 -> 9405 | AU41: =AH41*$K41 -> 8122.5 | AV41: =AI41*$K41 -> 9405 | ... AZ41: =AM41*$K41 -> 6080 | BA41: =SUM(BB41:BM41) -> 0 | BB41: 0 | BC41: 0 | BD41: 0 | BE41: 0 | BF41: 0 | BG41: 0 | BH41: 0 | BI41: 0 | BJ41: 0 | BK41: 0 | BL41: 0 | BM41: 0 | BN41: =SUM(BO41:BZ41) -> 72865 | BO41: =BB41+AO41 -> 0 | BP41: =BC41+AP41 -> 0 | BQ41: =BD41+AQ41 -> 0 | BR41: =BE41+AR41 -> 6840 | BS41: =BF41+AS41 -> 8122.5 | BT41: =BG41+AT41 -> 9405 | BU41: =BH41+AU41 -> 8122.5 | BV41: =BI41+AV41 -> 9405 | ... BZ41: =BM41+AZ41 -> 6080
A42: =IF(ISNUMBER(INDEX('IBM POs AP07'!$A:$A, MATCH(D42,'IBM POs AP07'!$A:$A,0),1)),"Yes","No") -> No | B42: Raju Parkala | C42: Sachin Vaidya | D42: 9501173555 | E42: YALQJB | F42: SAP SVO CI Commercial 2026 | G42: 46113 | H42: 46387 | I42: 0063XI | J42: JADDA SIVANNARAYANA | K42: 47.5 | L42: Offshore | N42: =AH42 -> 171 | O42: =N42*K42 -> 8122.5 | P42: =BF42 -> 0 | Q42: =O42+P42 -> 8122.5 | S42: =R42*K42 -> 0 | T42: 0 | U42: =S42+T42 -> 0 | V42: =Q42-U42 -> 8122.5 | W42: =IF(AND(L42="Offshore",R42>N42),"Red Flag",IF(AND(OR(L42="Onshore",L42="EMEA"),R42>N42),"Red Flag","")) | X42: 1 | Y42: 0 | AA42: =SUM(AB42:AM42) -> 1264 | AE42: 81 | AG42: 162 | AH42: 171 | AI42: 198 | AJ42: 171 | AK42: 171 | AL42: 182 | AM42: 128 | AN42: =SUM(AO42:AZ42) -> 60040 | AO42: =AB42*$K42 -> 0 | AP42: =AC42*$K42 -> 0 | AQ42: =AD42*$K42 -> 0 | AR42: =AE42*$K42 -> 3847.5 | AS42: =AF42*$K42 -> 0 | AT42: =AG42*$K42 -> 7695 | AU42: =AH42*$K42 -> 8122.5 | AV42: =AI42*$K42 -> 9405 | ... AZ42: =AM42*$K42 -> 6080 | BA42: =SUM(BB42:BM42) -> 0 | BB42: 0 | BC42: 0 | BD42: 0 | BE42: 0 | BF42: 0 | BG42: 0 | BH42: 0 | BI42: 0 | BJ42: 0 | BK42: 0 | BL42: 0 | BM42: 0 | BN42: =SUM(BO42:BZ42) -> 60040 | BO42: =BB42+AO42 -> 0 | BP42: =BC42+AP42 -> 0 | BQ42: =BD42+AQ42 -> 0 | BR42: =BE42+AR42 -> 3847.5 | BS42: =BF42+AS42 -> 0 | BT42: =BG42+AT42 -> 7695 | BU42: =BH42+AU42 -> 8122.5 | BV42: =BI42+AV42 -> 9405 | ... BZ42: =BM42+AZ42 -> 6080
A43: =IF(ISNUMBER(INDEX('IBM POs AP07'!$A:$A, MATCH(D43,'IBM POs AP07'!$A:$A,0),1)),"Yes","No") -> No | B43: Raju Parkala | C43: Sachin Vaidya | D43: 9501173555 | E43: YALQJB | F43: SAP SVO CI Commercial 2026 | G43: 46113 | H43: 46387 | I43: 005SCW | J43: PALLAVI BAVISKAR | K43: 47.5 | L43: Offshore | N43: =AH43 -> 171 | O43: =N43*K43 -> 8122.5 | P43: =BF43 -> 0 | Q43: =O43+P43 -> 8122.5 | S43: =R43*K43 -> 0 | T43: 0 | U43: =S43+T43 -> 0 | V43: =Q43-U43 -> 8122.5 | W43: =IF(AND(L43="Offshore",R43>N43),"Red Flag",IF(AND(OR(L43="Onshore",L43="EMEA"),R43>N43),"Red Flag","")) | X43: 1 | Y43: 0 | AA43: =SUM(AB43:AM43) -> 1074 | AH43: 171 | AI43: 198 | AJ43: 171 | AK43: 171 | AL43: 182 | AM43: 181 | AN43: =SUM(AO43:AZ43) -> 51015 | AO43: =AB43*$K43 -> 0 | AP43: =AC43*$K43 -> 0 | AQ43: =AD43*$K43 -> 0 | AR43: =AE43*$K43 -> 0 | AS43: =AF43*$K43 -> 0 | AT43: =AG43*$K43 -> 0 | AU43: =AH43*$K43 -> 8122.5 | AV43: =AI43*$K43 -> 9405 | ... AZ43: =AM43*$K43 -> 8597.5 | BA43: =SUM(BB43:BM43) -> 0 | BB43: 0 | BC43: 0 | BD43: 0 | BE43: 0 | BF43: 0 | BG43: 0 | BH43: 0 | BI43: 0 | BJ43: 0 | BK43: 0 | BL43: 0 | BM43: 0 | BN43: =SUM(BO43:BZ43) -> 51015 | BO43: =BB43+AO43 -> 0 | BP43: =BC43+AP43 -> 0 | BQ43: =BD43+AQ43 -> 0 | BR43: =BE43+AR43 -> 0 | BS43: =BF43+AS43 -> 0 | BT43: =BG43+AT43 -> 0 | BU43: =BH43+AU43 -> 8122.5 | BV43: =BI43+AV43 -> 9405 | ... BZ43: =BM43+AZ43 -> 8597.5
A44: =IF(ISNUMBER(INDEX('IBM POs AP07'!$A:$A, MATCH(D44,'IBM POs AP07'!$A:$A,0),1)),"Yes","No") -> No | B44: Raju Parkala | C44: Sachin Vaidya | D44: 9501173555 | E44: YALQJB | F44: SAP SVO CI Commercial 2026 | G44: 46113 | H44: 46387 | I44: 005T0F | J44: PRACHI DEOTE | K44: 47.5 | L44: Offshore | N44: =AH44 -> 171 | O44: =N44*K44 -> 8122.5 | P44: =BF44 -> 0 | Q44: =O44+P44 -> 8122.5 | S44: =R44*K44 -> 0 | T44: 0 | U44: =S44+T44 -> 0 | V44: =Q44-U44 -> 8122.5 | W44: =IF(AND(L44="Offshore",R44>N44),"Red Flag",IF(AND(OR(L44="Onshore",L44="EMEA"),R44>N44),"Red Flag","")) | X44: 1 | Y44: 0 | AA44: =SUM(AB44:AM44) -> 1407 | AF44: 135 | AG44: 198 | AH44: 171 | AI44: 198 | AJ44: 171 | AK44: 171 | AL44: 182 | AM44: 181 | AN44: =SUM(AO44:AZ44) -> 66832.5 | AO44: =AB44*$K44 -> 0 | AP44: =AC44*$K44 -> 0 | AQ44: =AD44*$K44 -> 0 | AR44: =AE44*$K44 -> 0 | AS44: =AF44*$K44 -> 6412.5 | AT44: =AG44*$K44 -> 9405 | AU44: =AH44*$K44 -> 8122.5 | AV44: =AI44*$K44 -> 9405 | ... AZ44: =AM44*$K44 -> 8597.5 | BA44: =SUM(BB44:BM44) -> 0 | BB44: 0 | BC44: 0 | BD44: 0 | BE44: 0 | BF44: 0 | BG44: 0 | BH44: 0 | BI44: 0 | BJ44: 0 | BK44: 0 | BL44: 0 | BM44: 0 | BN44: =SUM(BO44:BZ44) -> 66832.5 | BO44: =BB44+AO44 -> 0 | BP44: =BC44+AP44 -> 0 | BQ44: =BD44+AQ44 -> 0 | BR44: =BE44+AR44 -> 0 | BS44: =BF44+AS44 -> 6412.5 | BT44: =BG44+AT44 -> 9405 | BU44: =BH44+AU44 -> 8122.5 | BV44: =BI44+AV44 -> 9405 | ... BZ44: =BM44+AZ44 -> 8597.5
A45: =IF(ISNUMBER(INDEX('IBM POs AP07'!$A:$A, MATCH(D45,'IBM POs AP07'!$A:$A,0),1)),"Yes","No") -> No | B45: Raju Parkala | C45: Sachin Vaidya | D45: 9501173555 | E45: YALQJB | F45: SAP SVO CI Commercial 2026 | G45: 46113 | H45: 46387 | I45: 004I38 | J45: ABHISHEK KUMAR | K45: 47.5 | L45: Offshore | N45: =AH45 -> 171 | O45: =N45*K45 -> 8122.5 | P45: =BF45 -> 0 | Q45: =O45+P45 -> 8122.5 | S45: =R45*K45 -> 0 | T45: 0 | U45: =S45+T45 -> 0 | V45: =Q45-U45 -> 8122.5 | W45: =IF(AND(L45="Offshore",R45>N45),"Red Flag",IF(AND(OR(L45="Onshore",L45="EMEA"),R45>N45),"Red Flag","")) | X45: 1 | Y45: 0 | AA45: =SUM(AB45:AM45) -> 1611 | AE45: 153 | AF45: 135 | AG45: 198 | AH45: 171 | AI45: 216 | AJ45: 171 | AK45: 171 | AL45: 207 | AM45: 189 | AN45: =SUM(AO45:AZ45) -> 76522.5 | AO45: =AB45*$K45 -> 0 | AP45: =AC45*$K45 -> 0 | AQ45: =AD45*$K45 -> 0 | AR45: =AE45*$K45 -> 7267.5 | AS45: =AF45*$K45 -> 6412.5 | AT45: =AG45*$K45 -> 9405 | AU45: =AH45*$K45 -> 8122.5 | AV45: =AI45*$K45 -> 10260 | ... AZ45: =AM45*$K45 -> 8977.5 | BA45: =SUM(BB45:BM45) -> 0 | BB45: 0 | BC45: 0 | BD45: 0 | BE45: 0 | BF45: 0 | BG45: 0 | BH45: 0 | BI45: 0 | BJ45: 0 | BK45: 0 | BL45: 0 | BM45: 0 | BN45: =SUM(BO45:BZ45) -> 76522.5 | BO45: =BB45+AO45 -> 0 | BP45: =BC45+AP45 -> 0 | BQ45: =BD45+AQ45 -> 0 | BR45: =BE45+AR45 -> 7267.5 | BS45: =BF45+AS45 -> 6412.5 | BT45: =BG45+AT45 -> 9405 | BU45: =BH45+AU45 -> 8122.5 | BV45: =BI45+AV45 -> 10260 | ... BZ45: =BM45+AZ45 -> 8977.5
A46: =IF(ISNUMBER(INDEX('IBM POs AP07'!$A:$A, MATCH(D46,'IBM POs AP07'!$A:$A,0),1)),"Yes","No") -> No | B46: Raju Parkala | C46: Sachin Vaidya | D46: Pending PO | E46: YALQJB | F46: SAP SVO CI Commercial 2026_PCR01 | G46: 46113 | H46: 46387 | I46: C-LGLV | J46: RAMKRISHNA HOSURSRINIVAS | K46: 172 | L46: Offshore | N46: =AH46 -> 136 | O46: =N46*K46 -> 23392 | P46: =BF46 -> 0 | Q46: =O46+P46 -> 23392 | S46: =R46*K46 -> 0 | T46: 0 | U46: =S46+T46 -> 0 | V46: =Q46-U46 -> 23392 | W46: =IF(AND(L46="Offshore",R46>N46),"Red Flag",IF(AND(OR(L46="Onshore",L46="EMEA"),R46>N46),"Red Flag","")) | X46: 1 | Y46: 0 | AA46: =SUM(AB46:AM46) -> 504 | AH46: 136 | AI46: 192 | AJ46: 152 | AK46: 24 | AN46: =SUM(AO46:AZ46) -> 86688 | AO46: =AB46*$K46 -> 0 | AP46: =AC46*$K46 -> 0 | AQ46: =AD46*$K46 -> 0 | AR46: =AE46*$K46 -> 0 | AS46: =AF46*$K46 -> 0 | AT46: =AG46*$K46 -> 0 | AU46: =AH46*$K46 -> 23392 | AV46: =AI46*$K46 -> 33024 | ... AZ46: =AM46*$K46 -> 0 | BA46: =SUM(BB46:BM46) -> 0 | BB46: 0 | BC46: 0 | BD46: 0 | BE46: 0 | BF46: 0 | BG46: 0 | BH46: 0 | BI46: 0 | BJ46: 0 | BK46: 0 | BL46: 0 | BM46: 0 | BN46: =SUM(BO46:BZ46) -> 86688 | BO46: =BB46+AO46 -> 0 | BP46: =BC46+AP46 -> 0 | BQ46: =BD46+AQ46 -> 0 | BR46: =BE46+AR46 -> 0 | BS46: =BF46+AS46 -> 0 | BT46: =BG46+AT46 -> 0 | BU46: =BH46+AU46 -> 23392 | BV46: =BI46+AV46 -> 33024 | ... BZ46: =BM46+AZ46 -> 0
A47: =IF(ISNUMBER(INDEX('IBM POs AP07'!$A:$A, MATCH(D47,'IBM POs AP07'!$A:$A,0),1)),"Yes","No") -> No | B47: Raju Parkala | C47: Sachin Vaidya | D47: Pending PO | E47: YALQJB | F47: SAP SVO CI Commercial 2026_PCR01 | G47: 46113 | H47: 46387 | I47: C-JDPG | J47: VIJAY GUMMADI | K47: 210 | L47: Offshore | N47: =AH47 -> 136 | O47: =N47*K47 -> 28560 | P47: =BF47 -> 0 | Q47: =O47+P47 -> 28560 | S47: =R47*K47 -> 0 | T47: 0 | U47: =S47+T47 -> 0 | V47: =Q47-U47 -> 28560 | W47: =IF(AND(L47="Offshore",R47>N47),"Red Flag",IF(AND(OR(L47="Onshore",L47="EMEA"),R47>N47),"Red Flag","")) | X47: 1 | Y47: 0 | AA47: =SUM(AB47:AM47) -> 344 | AH47: 136 | AI47: 200 | AJ47: 8 | AN47: =SUM(AO47:AZ47) -> 72240 | AO47: =AB47*$K47 -> 0 | AP47: =AC47*$K47 -> 0 | AQ47: =AD47*$K47 -> 0 | AR47: =AE47*$K47 -> 0 | AS47: =AF47*$K47 -> 0 | AT47: =AG47*$K47 -> 0 | AU47: =AH47*$K47 -> 28560 | AV47: =AI47*$K47 -> 42000 | ... AZ47: =AM47*$K47 -> 0 | BA47: =SUM(BB47:BM47) -> 0 | BB47: 0 | BC47: 0 | BD47: 0 | BE47: 0 | BF47: 0 | BG47: 0 | BH47: 0 | BI47: 0 | BJ47: 0 | BK47: 0 | BL47: 0 | BM47: 0 | BN47: =SUM(BO47:BZ47) -> 72240 | BO47: =BB47+AO47 -> 0 | BP47: =BC47+AP47 -> 0 | BQ47: =BD47+AQ47 -> 0 | BR47: =BE47+AR47 -> 0 | BS47: =BF47+AS47 -> 0 | BT47: =BG47+AT47 -> 0 | BU47: =BH47+AU47 -> 28560 | BV47: =BI47+AV47 -> 42000 | ... BZ47: =BM47+AZ47 -> 0
A48: =IF(ISNUMBER(INDEX('IBM POs AP07'!$A:$A, MATCH(D48,'IBM POs AP07'!$A:$A,0),1)),"Yes","No") -> No | B48: Raju Parkala | C48: William Li | D48: Pending PO | E48: YANFLB | F48: SAP SVO CI GTS 2026 | G48: 46113 | H48: 46387 | I48: 7J3366 | J48: Karthikeyan Murugesan | K48: 180 | L48: Onshore | N48: =AH48 -> 152 | O48: =N48*K48 -> 27360 | P48: =BF48 -> 0 | Q48: =O48+P48 -> 27360 | S48: =R48*K48 -> 0 | T48: 0 | U48: =S48+T48 -> 0 | V48: =Q48-U48 -> 27360 | W48: =IF(AND(L48="Offshore",R48>N48),"Red Flag",IF(AND(OR(L48="Onshore",L48="EMEA"),R48>N48),"Red Flag","")) | X48: 1 | Y48: 0 | AA48: =SUM(AB48:AM48) -> 1485 | AE48: 136 | AF48: 152 | AG48: 192 | AH48: 152 | AI48: 192 | AJ48: 152 | AK48: 152 | AL48: 184 | AM48: 173 | AN48: =SUM(AO48:AZ48) -> 267300 | AO48: =AB48*$K48 -> 0 | AP48: =AC48*$K48 -> 0 | AQ48: =AD48*$K48 -> 0 | AR48: =AE48*$K48 -> 24480 | AS48: =AF48*$K48 -> 27360 | AT48: =AG48*$K48 -> 34560 | AU48: =AH48*$K48 -> 27360 | AV48: =AI48*$K48 -> 34560 | ... AZ48: =AM48*$K48 -> 31140 | BA48: =SUM(BB48:BM48) -> 0 | BB48: 0 | BC48: 0 | BD48: 0 | BE48: 0 | BF48: 0 | BG48: 0 | BH48: 0 | BI48: 0 | BJ48: 0 | BK48: 0 | BL48: 0 | BM48: 0 | BN48: =SUM(BO48:BZ48) -> 267300 | BO48: =BB48+AO48 -> 0 | BP48: =BC48+AP48 -> 0 | BQ48: =BD48+AQ48 -> 0 | BR48: =BE48+AR48 -> 24480 | BS48: =BF48+AS48 -> 27360 | BT48: =BG48+AT48 -> 34560 | BU48: =BH48+AU48 -> 27360 | BV48: =BI48+AV48 -> 34560 | ... BZ48: =BM48+AZ48 -> 31140
A49: =IF(ISNUMBER(INDEX('IBM POs AP07'!$A:$A, MATCH(D49,'IBM POs AP07'!$A:$A,0),1)),"Yes","No") -> Yes | B49: Raju Parkala | C49: Rao Nakkella | D49: 9501252524 | E49: YALWFB | F49: SAP SVO CI Finance Q2 2026 | G49: 46113 | H49: 46203 | I49: 4G9243 | J49: HARINDRANATH GUTTA | K49: 360 | N49: =AH49 -> 0 | O49: =N49*K49 -> 0 | P49: =BF49 -> 0 | Q49: =O49+P49 -> 0 | S49: =R49*K49 -> 0 | T49: 0 | U49: =S49+T49 -> 0 | V49: =Q49-U49 -> 0 | W49: =IF(AND(L49="Offshore",R49>N49),"Red Flag",IF(AND(OR(L49="Onshore",L49="EMEA"),R49>N49),"Red Flag","")) | X49: 1 | Y49: 0 | AA49: =SUM(AB49:AM49) -> 0 | AN49: =SUM(AO49:AZ49) -> 0 | AO49: =AB49*$K49 -> 0 | AP49: =AC49*$K49 -> 0 | AQ49: =AD49*$K49 -> 0 | AR49: =AE49*$K49 -> 0 | AS49: =AF49*$K49 -> 0 | AT49: =AG49*$K49 -> 0 | AU49: =AH49*$K49 -> 0 | AV49: =AI49*$K49 -> 0 | ... AZ49: =AM49*$K49 -> 0 | BA49: =SUM(BB49:BM49) -> 0 | BB49: 0 | BC49: 0 | BD49: 0 | BE49: 0 | BF49: 0 | BG49: 0 | BH49: 0 | BI49: 0 | BJ49: 0 | BK49: 0 | BL49: 0 | BM49: 0 | BN49: =SUM(BO49:BZ49) -> 0 | BO49: =BB49+AO49 -> 0 | BP49: =BC49+AP49 -> 0 | BQ49: =BD49+AQ49 -> 0 | BR49: =BE49+AR49 -> 0 | BS49: =BF49+AS49 -> 0 | BT49: =BG49+AT49 -> 0 | BU49: =BH49+AU49 -> 0 | BV49: =BI49+AV49 -> 0 | ... BZ49: =BM49+AZ49 -> 0
A50: =IF(ISNUMBER(INDEX('IBM POs AP07'!$A:$A, MATCH(D50,'IBM POs AP07'!$A:$A,0),1)),"Yes","No") -> Yes | B50: Raju Parkala | C50: Rao Nakkella | D50: 9501252524 | E50: YALWFB | F50: SAP SVO CI Finance Q2 2026 | G50: 46113 | H50: 46203 | I50: C-RWNH | J50: CHANDRA JONNAGEDDALA | K50: 183 | N50: =AH50 -> 16 | O50: =N50*K50 -> 2928 | P50: =BF50 -> 0 | Q50: =O50+P50 -> 2928 | S50: =R50*K50 -> 0 | T50: 0 | U50: =S50+T50 -> 0 | V50: =Q50-U50 -> 2928 | W50: =IF(AND(L50="Offshore",R50>N50),"Red Flag",IF(AND(OR(L50="Onshore",L50="EMEA"),R50>N50),"Red Flag","")) | X50: 1 | Y50: 0 | AA50: =SUM(AB50:AM50) -> 512 | AE50: 144 | AF50: 160 | AG50: 192 | AH50: 16 | AN50: =SUM(AO50:AZ50) -> 93696 | AO50: =AB50*$K50 -> 0 | AP50: =AC50*$K50 -> 0 | AQ50: =AD50*$K50 -> 0 | AR50: =AE50*$K50 -> 26352 | AS50: =AF50*$K50 -> 29280 | AT50: =AG50*$K50 -> 35136 | AU50: =AH50*$K50 -> 2928 | AV50: =AI50*$K50 -> 0 | ... AZ50: =AM50*$K50 -> 0 | BA50: =SUM(BB50:BM50) -> 0 | BB50: 0 | BC50: 0 | BD50: 0 | BE50: 0 | BF50: 0 | BG50: 0 | BH50: 0 | BI50: 0 | BJ50: 0 | BK50: 0 | BL50: 0 | BM50: 0 | BN50: =SUM(BO50:BZ50) -> 93696 | BO50: =BB50+AO50 -> 0 | BP50: =BC50+AP50 -> 0 | BQ50: =BD50+AQ50 -> 0 | BR50: =BE50+AR50 -> 26352 | BS50: =BF50+AS50 -> 29280 | BT50: =BG50+AT50 -> 35136 | BU50: =BH50+AU50 -> 2928 | BV50: =BI50+AV50 -> 0 | ... BZ50: =BM50+AZ50 -> 0
A51: =IF(ISNUMBER(INDEX('IBM POs AP07'!$A:$A, MATCH(D51,'IBM POs AP07'!$A:$A,0),1)),"Yes","No") -> Yes | B51: Raju Parkala | C51: Rao Nakkella | D51: 9501252524 | E51: YALWFB | F51: SAP SVO CI Finance Q2 2026 | G51: 46113 | H51: 46203 | I51: 08781B | J51: EASHWAR SESHADRI | K51: 182 | N51: =AH51 -> 16 | O51: =N51*K51 -> 2912 | P51: =BF51 -> 0 | Q51: =O51+P51 -> 2912 | S51: =R51*K51 -> 0 | T51: 0 | U51: =S51+T51 -> 0 | V51: =Q51-U51 -> 2912 | W51: =IF(AND(L51="Offshore",R51>N51),"Red Flag",IF(AND(OR(L51="Onshore",L51="EMEA"),R51>N51),"Red Flag","")) | X51: 1 | Y51: 0 | AA51: =SUM(AB51:AM51) -> 512 | AE51: 144 | AF51: 160 | AG51: 192 | AH51: 16 | AN51: =SUM(AO51:AZ51) -> 93184 | AO51: =AB51*$K51 -> 0 | AP51: =AC51*$K51 -> 0 | AQ51: =AD51*$K51 -> 0 | AR51: =AE51*$K51 -> 26208 | AS51: =AF51*$K51 -> 29120 | AT51: =AG51*$K51 -> 34944 | AU51: =AH51*$K51 -> 2912 | AV51: =AI51*$K51 -> 0 | ... AZ51: =AM51*$K51 -> 0 | BA51: =SUM(BB51:BM51) -> 0 | BB51: 0 | BC51: 0 | BD51: 0 | BE51: 0 | BF51: 0 | BG51: 0 | BH51: 0 | BI51: 0 | BJ51: 0 | BK51: 0 | BL51: 0 | BM51: 0 | BN51: =SUM(BO51:BZ51) -> 93184 | BO51: =BB51+AO51 -> 0 | BP51: =BC51+AP51 -> 0 | BQ51: =BD51+AQ51 -> 0 | BR51: =BE51+AR51 -> 26208 | BS51: =BF51+AS51 -> 29120 | BT51: =BG51+AT51 -> 34944 | BU51: =BH51+AU51 -> 2912 | BV51: =BI51+AV51 -> 0 | ... BZ51: =BM51+AZ51 -> 0
A52: =IF(ISNUMBER(INDEX('IBM POs AP07'!$A:$A, MATCH(D52,'IBM POs AP07'!$A:$A,0),1)),"Yes","No") -> Yes | B52: Raju Parkala | C52: Rao Nakkella | D52: 9501252524 | E52: YALWFB | F52: SAP SVO CI Finance Q2 2026 | G52: 46113 | H52: 46203 | I52: 9D5534 | J52: VINOD MURALI | K52: 307 | N52: =AH52 -> 16 | O52: =N52*K52 -> 4912 | P52: =BF52 -> 0 | Q52: =O52+P52 -> 4912 | S52: =R52*K52 -> 0 | T52: 0 | U52: =S52+T52 -> 0 | V52: =Q52-U52 -> 4912 | W52: =IF(AND(L52="Offshore",R52>N52),"Red Flag",IF(AND(OR(L52="Onshore",L52="EMEA"),R52>N52),"Red Flag","")) | X52: 1 | Y52: 0 | AA52: =SUM(AB52:AM52) -> 172 | AF52: 0 | AG52: 156 | AH52: 16 | AN52: =SUM(AO52:AZ52) -> 52804 | AO52: =AB52*$K52 -> 0 | AP52: =AC52*$K52 -> 0 | AQ52: =AD52*$K52 -> 0 | AR52: =AE52*$K52 -> 0 | AS52: =AF52*$K52 -> 0 | AT52: =AG52*$K52 -> 47892 | AU52: =AH52*$K52 -> 4912 | AV52: =AI52*$K52 -> 0 | ... AZ52: =AM52*$K52 -> 0 | BA52: =SUM(BB52:BM52) -> 0 | BB52: 0 | BC52: 0 | BD52: 0 | BE52: 0 | BF52: 0 | BG52: 0 | BH52: 0 | BI52: 0 | BJ52: 0 | BK52: 0 | BL52: 0 | BM52: 0 | BN52: =SUM(BO52:BZ52) -> 52804 | BO52: =BB52+AO52 -> 0 | BP52: =BC52+AP52 -> 0 | BQ52: =BD52+AQ52 -> 0 | BR52: =BE52+AR52 -> 0 | BS52: =BF52+AS52 -> 0 | BT52: =BG52+AT52 -> 47892 | BU52: =BH52+AU52 -> 4912 | BV52: =BI52+AV52 -> 0 | ... BZ52: =BM52+AZ52 -> 0
A53: =IF(ISNUMBER(INDEX('IBM POs AP07'!$A:$A, MATCH(D53,'IBM POs AP07'!$A:$A,0),1)),"Yes","No") -> Yes | B53: Raju Parkala | C53: Rao Nakkella | D53: 9501252524 | E53: YALWFB | F53: SAP SVO CI Finance Q2 2026 | G53: 46113 | H53: 46203 | I53: 4J5042 | J53: SURYA JAKKA | K53: 307 | N53: =AH53 -> 16 | O53: =N53*K53 -> 4912 | P53: =BF53 -> 0 | Q53: =O53+P53 -> 4912 | S53: =R53*K53 -> 0 | T53: 0 | U53: =S53+T53 -> 0 | V53: =Q53-U53 -> 4912 | W53: =IF(AND(L53="Offshore",R53>N53),"Red Flag",IF(AND(OR(L53="Onshore",L53="EMEA"),R53>N53),"Red Flag","")) | X53: 1 | Y53: 0 | AA53: =SUM(AB53:AM53) -> 356 | AF53: 156 | AG53: 184 | AH53: 16 | AN53: =SUM(AO53:AZ53) -> 109292 | AO53: =AB53*$K53 -> 0 | AP53: =AC53*$K53 -> 0 | AQ53: =AD53*$K53 -> 0 | AR53: =AE53*$K53 -> 0 | AS53: =AF53*$K53 -> 47892 | AT53: =AG53*$K53 -> 56488 | AU53: =AH53*$K53 -> 4912 | AV53: =AI53*$K53 -> 0 | ... AZ53: =AM53*$K53 -> 0 | BA53: =SUM(BB53:BM53) -> 0 | BB53: 0 | BC53: 0 | BD53: 0 | BE53: 0 | BF53: 0 | BG53: 0 | BH53: 0 | BI53: 0 | BJ53: 0 | BK53: 0 | BL53: 0 | BM53: 0 | BN53: =SUM(BO53:BZ53) -> 109292 | BO53: =BB53+AO53 -> 0 | BP53: =BC53+AP53 -> 0 | BQ53: =BD53+AQ53 -> 0 | BR53: =BE53+AR53 -> 0 | BS53: =BF53+AS53 -> 47892 | BT53: =BG53+AT53 -> 56488 | BU53: =BH53+AU53 -> 4912 | BV53: =BI53+AV53 -> 0 | ... BZ53: =BM53+AZ53 -> 0
A54: =IF(ISNUMBER(INDEX('IBM POs AP07'!$A:$A, MATCH(D54,'IBM POs AP07'!$A:$A,0),1)),"Yes","No") -> Yes | B54: Raju Parkala | C54: Rao Nakkella | D54: 9501252524 | E54: YALWFB | F54: SAP SVO CI Finance Q2 2026 | G54: 46113 | H54: 46203 | I54: 03506C | J54: NARSAIAH PULI | K54: 61.75 | N54: =AH54 -> 18 | O54: =N54*K54 -> 1111.5 | P54: =BF54 -> 0 | Q54: =O54+P54 -> 1111.5 | S54: =R54*K54 -> 0 | T54: 0 | U54: =S54+T54 -> 0 | V54: =Q54-U54 -> 1111.5 | W54: =IF(AND(L54="Offshore",R54>N54),"Red Flag",IF(AND(OR(L54="Onshore",L54="EMEA"),R54>N54),"Red Flag","")) | X54: 1 | Y54: 0 | AA54: =SUM(AB54:AM54) -> 551 | AE54: 162 | AF54: 162 | AG54: 209 | AH54: 18 | AN54: =SUM(AO54:AZ54) -> 34024.25 | AO54: =AB54*$K54 -> 0 | AP54: =AC54*$K54 -> 0 | AQ54: =AD54*$K54 -> 0 | AR54: =AE54*$K54 -> 10003.5 | AS54: =AF54*$K54 -> 10003.5 | AT54: =AG54*$K54 -> 12905.75 | AU54: =AH54*$K54 -> 1111.5 | AV54: =AI54*$K54 -> 0 | ... AZ54: =AM54*$K54 -> 0 | BA54: =SUM(BB54:BM54) -> 0 | BB54: 0 | BC54: 0 | BD54: 0 | BE54: 0 | BF54: 0 | BG54: 0 | BH54: 0 | BI54: 0 | BJ54: 0 | BK54: 0 | BL54: 0 | BM54: 0 | BN54: =SUM(BO54:BZ54) -> 34024.25 | BO54: =BB54+AO54 -> 0 | BP54: =BC54+AP54 -> 0 | BQ54: =BD54+AQ54 -> 0 | BR54: =BE54+AR54 -> 10003.5 | BS54: =BF54+AS54 -> 10003.5 | BT54: =BG54+AT54 -> 12905.75 | BU54: =BH54+AU54 -> 1111.5 | BV54: =BI54+AV54 -> 0 | ... BZ54: =BM54+AZ54 -> 0
A55: =IF(ISNUMBER(INDEX('IBM POs AP07'!$A:$A, MATCH(D55,'IBM POs AP07'!$A:$A,0),1)),"Yes","No") -> Yes | B55: Raju Parkala | C55: Rao Nakkella | D55: 9501252524 | E55: YALWFB | F55: SAP SVO CI Finance Q2 2026 | G55: 46113 | H55: 46203 | I55: 002WVB | J55: VENKATESWARLU BASU | K55: 47.5 | N55: =AH55 -> 18 | O55: =N55*K55 -> 855 | P55: =BF55 -> 0 | Q55: =O55+P55 -> 855 | S55: =R55*K55 -> 0 | T55: 0 | U55: =S55+T55 -> 0 | V55: =Q55-U55 -> 855 | W55: =IF(AND(L55="Offshore",R55>N55),"Red Flag",IF(AND(OR(L55="Onshore",L55="EMEA"),R55>N55),"Red Flag","")) | X55: 1 | Y55: 0 | AA55: =SUM(AB55:AM55) -> 555 | AE55: 162 | AF55: 170 | AG55: 205 | AH55: 18 | AN55: =SUM(AO55:AZ55) -> 26362.5 | AO55: =AB55*$K55 -> 0 | AP55: =AC55*$K55 -> 0 | AQ55: =AD55*$K55 -> 0 | AR55: =AE55*$K55 -> 7695 | AS55: =AF55*$K55 -> 8075 | AT55: =AG55*$K55 -> 9737.5 | AU55: =AH55*$K55 -> 855 | AV55: =AI55*$K55 -> 0 | ... AZ55: =AM55*$K55 -> 0 | BA55: =SUM(BB55:BM55) -> 0 | BB55: 0 | BC55: 0 | BD55: 0 | BE55: 0 | BF55: 0 | BG55: 0 | BH55: 0 | BI55: 0 | BJ55: 0 | BK55: 0 | BL55: 0 | BM55: 0 | BN55: =SUM(BO55:BZ55) -> 26362.5 | BO55: =BB55+AO55 -> 0 | BP55: =BC55+AP55 -> 0 | BQ55: =BD55+AQ55 -> 0 | BR55: =BE55+AR55 -> 7695 | BS55: =BF55+AS55 -> 8075 | BT55: =BG55+AT55 -> 9737.5 | BU55: =BH55+AU55 -> 855 | BV55: =BI55+AV55 -> 0 | ... BZ55: =BM55+AZ55 -> 0
A56: =IF(ISNUMBER(INDEX('IBM POs AP07'!$A:$A, MATCH(D56,'IBM POs AP07'!$A:$A,0),1)),"Yes","No") -> Yes | B56: Raju Parkala | C56: Rao Nakkella | D56: 9501252524 | E56: YALWFB | F56: SAP SVO CI Finance Q2 2026 | G56: 46113 | H56: 46203 | I56: 003OWR | J56: SURESH N | K56: 47.5 | N56: =AH56 -> 18 | O56: =N56*K56 -> 855 | P56: =BF56 -> 0 | Q56: =O56+P56 -> 855 | S56: =R56*K56 -> 0 | T56: 0 | U56: =S56+T56 -> 0 | V56: =Q56-U56 -> 855 | W56: =IF(AND(L56="Offshore",R56>N56),"Red Flag",IF(AND(OR(L56="Onshore",L56="EMEA"),R56>N56),"Red Flag","")) | X56: 1 | Y56: 0 | AA56: =SUM(AB56:AM56) -> 559 | AE56: 145 | AF56: 175 | AG56: 221 | AH56: 18 | AN56: =SUM(AO56:AZ56) -> 26552.5 | AO56: =AB56*$K56 -> 0 | AP56: =AC56*$K56 -> 0 | AQ56: =AD56*$K56 -> 0 | AR56: =AE56*$K56 -> 6887.5 | AS56: =AF56*$K56 -> 8312.5 | AT56: =AG56*$K56 -> 10497.5 | AU56: =AH56*$K56 -> 855 | AV56: =AI56*$K56 -> 0 | ... AZ56: =AM56*$K56 -> 0 | BA56: =SUM(BB56:BM56) -> 0 | BB56: 0 | BC56: 0 | BD56: 0 | BE56: 0 | BF56: 0 | BG56: 0 | BH56: 0 | BI56: 0 | BJ56: 0 | BK56: 0 | BL56: 0 | BM56: 0 | BN56: =SUM(BO56:BZ56) -> 26552.5 | BO56: =BB56+AO56 -> 0 | BP56: =BC56+AP56 -> 0 | BQ56: =BD56+AQ56 -> 0 | BR56: =BE56+AR56 -> 6887.5 | BS56: =BF56+AS56 -> 8312.5 | BT56: =BG56+AT56 -> 10497.5 | BU56: =BH56+AU56 -> 855 | BV56: =BI56+AV56 -> 0 | ... BZ56: =BM56+AZ56 -> 0
A57: =IF(ISNUMBER(INDEX('IBM POs AP07'!$A:$A, MATCH(D57,'IBM POs AP07'!$A:$A,0),1)),"Yes","No") -> Yes | B57: Raju Parkala | C57: Rao Nakkella | D57: 9501252524 | E57: YALWFB | F57: SAP SVO CI Finance Q2 2026 | G57: 46113 | H57: 46203 | I57: 0056OJ | J57: MEGHANA K | K57: 31.5 | N57: =AH57 -> 18 | O57: =N57*K57 -> 567 | P57: =BF57 -> 0 | Q57: =O57+P57 -> 567 | S57: =R57*K57 -> 0 | T57: 0 | U57: =S57+T57 -> 0 | V57: =Q57-U57 -> 567 | W57: =IF(AND(L57="Offshore",R57>N57),"Red Flag",IF(AND(OR(L57="Onshore",L57="EMEA"),R57>N57),"Red Flag","")) | X57: 1 | Y57: 0 | AA57: =SUM(AB57:AM57) -> 522 | AE57: 153 | AF57: 144 | AG57: 207 | AH57: 18 | AN57: =SUM(AO57:AZ57) -> 16443 | AO57: =AB57*$K57 -> 0 | AP57: =AC57*$K57 -> 0 | AQ57: =AD57*$K57 -> 0 | AR57: =AE57*$K57 -> 4819.5 | AS57: =AF57*$K57 -> 4536 | AT57: =AG57*$K57 -> 6520.5 | AU57: =AH57*$K57 -> 567 | AV57: =AI57*$K57 -> 0 | ... AZ57: =AM57*$K57 -> 0 | BA57: =SUM(BB57:BM57) -> 0 | BB57: 0 | BC57: 0 | BD57: 0 | BE57: 0 | BF57: 0 | BG57: 0 | BH57: 0 | BI57: 0 | BJ57: 0 | BK57: 0 | BL57: 0 | BM57: 0 | BN57: =SUM(BO57:BZ57) -> 16443 | BO57: =BB57+AO57 -> 0 | BP57: =BC57+AP57 -> 0 | BQ57: =BD57+AQ57 -> 0 | BR57: =BE57+AR57 -> 4819.5 | BS57: =BF57+AS57 -> 4536 | BT57: =BG57+AT57 -> 6520.5 | BU57: =BH57+AU57 -> 567 | BV57: =BI57+AV57 -> 0 | ... BZ57: =BM57+AZ57 -> 0
A58: =IF(ISNUMBER(INDEX('IBM POs AP07'!$A:$A, MATCH(D58,'IBM POs AP07'!$A:$A,0),1)),"Yes","No") -> Yes | B58: Raju Parkala | C58: Rao Nakkella | D58: 9501252524 | E58: YALWFB | F58: SAP SVO CI Finance Q2 2026 | G58: 46113 | H58: 46203 | I58: C-W6KJ | J58: VENKATESULU THUMMALA | K58: 157 | N58: =AH58 -> 0 | O58: =N58*K58 -> 0 | P58: =BF58 -> 0 | Q58: =O58+P58 -> 0 | S58: =R58*K58 -> 0 | T58: 0 | U58: =S58+T58 -> 0 | V58: =Q58-U58 -> 0 | W58: =IF(AND(L58="Offshore",R58>N58),"Red Flag",IF(AND(OR(L58="Onshore",L58="EMEA"),R58>N58),"Red Flag","")) | X58: 1 | Y58: 0 | AA58: =SUM(AB58:AM58) -> 344 | AE58: 144 | AF58: 160 | AG58: 40 | AN58: =SUM(AO58:AZ58) -> 54008 | AO58: =AB58*$K58 -> 0 | AP58: =AC58*$K58 -> 0 | AQ58: =AD58*$K58 -> 0 | AR58: =AE58*$K58 -> 22608 | AS58: =AF58*$K58 -> 25120 | AT58: =AG58*$K58 -> 6280 | AU58: =AH58*$K58 -> 0 | AV58: =AI58*$K58 -> 0 | ... AZ58: =AM58*$K58 -> 0 | BA58: =SUM(BB58:BM58) -> 0 | BB58: 0 | BC58: 0 | BD58: 0 | BE58: 0 | BF58: 0 | BG58: 0 | BH58: 0 | BI58: 0 | BJ58: 0 | BK58: 0 | BL58: 0 | BM58: 0 | BN58: =SUM(BO58:BZ58) -> 54008 | BO58: =BB58+AO58 -> 0 | BP58: =BC58+AP58 -> 0 | BQ58: =BD58+AQ58 -> 0 | BR58: =BE58+AR58 -> 22608 | BS58: =BF58+AS58 -> 25120 | BT58: =BG58+AT58 -> 6280 | BU58: =BH58+AU58 -> 0 | BV58: =BI58+AV58 -> 0 | ... BZ58: =BM58+AZ58 -> 0
A59: =IF(ISNUMBER(INDEX('IBM POs AP07'!$A:$A, MATCH(D59,'IBM POs AP07'!$A:$A,0),1)),"Yes","No") -> Yes | B59: Raju Parkala | C59: Rao Nakkella | D59: 9501252524 | E59: YALWFB | F59: SAP SVO CI Finance Q2 2026 | G59: 46113 | H59: 46203 | I59: 0015KG | J59: SAGAR GULHANE | K59: 61.75 | N59: =AH59 -> 18 | O59: =N59*K59 -> 1111.5 | P59: =BF59 -> 0 | Q59: =O59+P59 -> 1111.5 | S59: =R59*K59 -> 0 | T59: 0 | U59: =S59+T59 -> 0 | V59: =Q59-U59 -> 1111.5 | W59: =IF(AND(L59="Offshore",R59>N59),"Red Flag",IF(AND(OR(L59="Onshore",L59="EMEA"),R59>N59),"Red Flag","")) | X59: 1 | Y59: 0 | AA59: =SUM(AB59:AM59) -> 575 | AE59: 162 | AF59: 175 | AG59: 220 | AH59: 18 | AN59: =SUM(AO59:AZ59) -> 35506.25 | AO59: =AB59*$K59 -> 0 | AP59: =AC59*$K59 -> 0 | AQ59: =AD59*$K59 -> 0 | AR59: =AE59*$K59 -> 10003.5 | AS59: =AF59*$K59 -> 10806.25 | AT59: =AG59*$K59 -> 13585 | AU59: =AH59*$K59 -> 1111.5 | AV59: =AI59*$K59 -> 0 | ... AZ59: =AM59*$K59 -> 0 | BA59: =SUM(BB59:BM59) -> 0 | BB59: 0 | BC59: 0 | BD59: 0 | BE59: 0 | BF59: 0 | BG59: 0 | BH59: 0 | BI59: 0 | BJ59: 0 | BK59: 0 | BL59: 0 | BM59: 0 | BN59: =SUM(BO59:BZ59) -> 35506.25 | BO59: =BB59+AO59 -> 0 | BP59: =BC59+AP59 -> 0 | BQ59: =BD59+AQ59 -> 0 | BR59: =BE59+AR59 -> 10003.5 | BS59: =BF59+AS59 -> 10806.25 | BT59: =BG59+AT59 -> 13585 | BU59: =BH59+AU59 -> 1111.5 | BV59: =BI59+AV59 -> 0 | ... BZ59: =BM59+AZ59 -> 0
A60: =IF(ISNUMBER(INDEX('IBM POs AP07'!$A:$A, MATCH(D60,'IBM POs AP07'!$A:$A,0),1)),"Yes","No") -> Yes | B60: Raju Parkala | C60: Rao Nakkella | D60: 9501252524 | E60: YALWFB | F60: SAP SVO CI Finance Q2 2026 | G60: 46113 | H60: 46203 | I60: 003PJ4 | J60: SUNIL P | K60: 61.75 | N60: =AH60 -> 18 | O60: =N60*K60 -> 1111.5 | P60: =BF60 -> 0 | Q60: =O60+P60 -> 1111.5 | S60: =R60*K60 -> 0 | T60: 0 | U60: =S60+T60 -> 0 | V60: =Q60-U60 -> 1111.5 | W60: =IF(AND(L60="Offshore",R60>N60),"Red Flag",IF(AND(OR(L60="Onshore",L60="EMEA"),R60>N60),"Red Flag","")) | X60: 1 | Y60: 0 | AA60: =SUM(AB60:AM60) -> 543 | AE60: 135 | AF60: 170 | AG60: 220 | AH60: 18 | AN60: =SUM(AO60:AZ60) -> 33530.25 | AO60: =AB60*$K60 -> 0 | AP60: =AC60*$K60 -> 0 | AQ60: =AD60*$K60 -> 0 | AR60: =AE60*$K60 -> 8336.25 | AS60: =AF60*$K60 -> 10497.5 | AT60: =AG60*$K60 -> 13585 | AU60: =AH60*$K60 -> 1111.5 | AV60: =AI60*$K60 -> 0 | ... AZ60: =AM60*$K60 -> 0 | BA60: =SUM(BB60:BM60) -> 0 | BB60: 0 | BC60: 0 | BD60: 0 | BE60: 0 | BF60: 0 | BG60: 0 | BH60: 0 | BI60: 0 | BJ60: 0 | BK60: 0 | BL60: 0 | BM60: 0 | BN60: =SUM(BO60:BZ60) -> 33530.25 | BO60: =BB60+AO60 -> 0 | BP60: =BC60+AP60 -> 0 | BQ60: =BD60+AQ60 -> 0 | BR60: =BE60+AR60 -> 8336.25 | BS60: =BF60+AS60 -> 10497.5 | BT60: =BG60+AT60 -> 13585 | BU60: =BH60+AU60 -> 1111.5 | BV60: =BI60+AV60 -> 0 | ... BZ60: =BM60+AZ60 -> 0
A61: =IF(ISNUMBER(INDEX('IBM POs AP07'!$A:$A, MATCH(D61,'IBM POs AP07'!$A:$A,0),1)),"Yes","No") -> Yes | B61: Raju Parkala | C61: Rao Nakkella | D61: 9501252524 | E61: YALWFB | F61: SAP SVO CI Finance Q2 2026 | G61: 46113 | H61: 46203 | I61: 01301F | J61: FAYEZ KAZI | K61: 61.75 | N61: =AH61 -> 0 | O61: =N61*K61 -> 0 | P61: =BF61 -> 0 | Q61: =O61+P61 -> 0 | S61: =R61*K61 -> 0 | T61: 0 | U61: =S61+T61 -> 0 | V61: =Q61-U61 -> 0 | W61: =IF(AND(L61="Offshore",R61>N61),"Red Flag",IF(AND(OR(L61="Onshore",L61="EMEA"),R61>N61),"Red Flag","")) | X61: 1 | Y61: 0 | AA61: =SUM(AB61:AM61) -> 189 | AE61: 162 | AF61: 27 | AN61: =SUM(AO61:AZ61) -> 11670.75 | AO61: =AB61*$K61 -> 0 | AP61: =AC61*$K61 -> 0 | AQ61: =AD61*$K61 -> 0 | AR61: =AE61*$K61 -> 10003.5 | AS61: =AF61*$K61 -> 1667.25 | AT61: =AG61*$K61 -> 0 | AU61: =AH61*$K61 -> 0 | AV61: =AI61*$K61 -> 0 | ... AZ61: =AM61*$K61 -> 0 | BA61: =SUM(BB61:BM61) -> 0 | BB61: 0 | BC61: 0 | BD61: 0 | BE61: 0 | BF61: 0 | BG61: 0 | BH61: 0 | BI61: 0 | BJ61: 0 | BK61: 0 | BL61: 0 | BM61: 0 | BN61: =SUM(BO61:BZ61) -> 11670.75 | BO61: =BB61+AO61 -> 0 | BP61: =BC61+AP61 -> 0 | BQ61: =BD61+AQ61 -> 0 | BR61: =BE61+AR61 -> 10003.5 | BS61: =BF61+AS61 -> 1667.25 | BT61: =BG61+AT61 -> 0 | BU61: =BH61+AU61 -> 0 | BV61: =BI61+AV61 -> 0 | ... BZ61: =BM61+AZ61 -> 0
A62: =IF(ISNUMBER(INDEX('IBM POs AP07'!$A:$A, MATCH(D62,'IBM POs AP07'!$A:$A,0),1)),"Yes","No") -> Yes | B62: Raju Parkala | C62: Rao Nakkella | D62: 9501252524 | E62: YALWFB | F62: SAP SVO CI Finance Q2 2026 | G62: 46113 | H62: 46203 | I62: 005PX3 | J62: RAGHAVENDER PRODDUTURI | K62: 31.5 | N62: =AH62 -> 18 | O62: =N62*K62 -> 567 | P62: =BF62 -> 0 | Q62: =O62+P62 -> 567 | S62: =R62*K62 -> 0 | T62: 0 | U62: =S62+T62 -> 0 | V62: =Q62-U62 -> 567 | W62: =IF(AND(L62="Offshore",R62>N62),"Red Flag",IF(AND(OR(L62="Onshore",L62="EMEA"),R62>N62),"Red Flag","")) | X62: 1 | Y62: 0 | AA62: =SUM(AB62:AM62) -> 405 | AF62: 171 | AG62: 216 | AH62: 18 | AN62: =SUM(AO62:AZ62) -> 12757.5 | AO62: =AB62*$K62 -> 0 | AP62: =AC62*$K62 -> 0 | AQ62: =AD62*$K62 -> 0 | AR62: =AE62*$K62 -> 0 | AS62: =AF62*$K62 -> 5386.5 | AT62: =AG62*$K62 -> 6804 | AU62: =AH62*$K62 -> 567 | AV62: =AI62*$K62 -> 0 | ... AZ62: =AM62*$K62 -> 0 | BA62: =SUM(BB62:BM62) -> 0 | BB62: 0 | BC62: 0 | BD62: 0 | BE62: 0 | BF62: 0 | BG62: 0 | BH62: 0 | BI62: 0 | BJ62: 0 | BK62: 0 | BL62: 0 | BM62: 0 | BN62: =SUM(BO62:BZ62) -> 12757.5 | BO62: =BB62+AO62 -> 0 | BP62: =BC62+AP62 -> 0 | BQ62: =BD62+AQ62 -> 0 | BR62: =BE62+AR62 -> 0 | BS62: =BF62+AS62 -> 5386.5 | BT62: =BG62+AT62 -> 6804 | BU62: =BH62+AU62 -> 567 | BV62: =BI62+AV62 -> 0 | ... BZ62: =BM62+AZ62 -> 0
A63: =IF(ISNUMBER(INDEX('IBM POs AP07'!$A:$A, MATCH(D63,'IBM POs AP07'!$A:$A,0),1)),"Yes","No") -> No | B63: Raju Parkala | C63: Rao Nakkella | D63: 9501304116 | E63: YAPTGB | F63: SAP SVO CI Finance Q3 2026 | G63: 46204 | H63: 46295 | I63: 4G9243 | J63: HARINDRANATH GUTTA | K63: 360 | N63: =AH63 -> 0 | O63: =N63*K63 -> 0 | P63: =BF63 -> 0 | Q63: =O63+P63 -> 0 | S63: =R63*K63 -> 0 | T63: 0 | U63: =S63+T63 -> 0 | V63: =Q63-U63 -> 0 | W63: =IF(AND(L63="Offshore",R63>N63),"Red Flag",IF(AND(OR(L63="Onshore",L63="EMEA"),R63>N63),"Red Flag","")) | X63: 1 | Y63: 0 | AA63: =SUM(AB63:AM63) -> 84 | AH63: 0 | AI63: 42 | AJ63: 42 | AN63: =SUM(AO63:AZ63) -> 30240 | AO63: =AB63*$K63 -> 0 | AP63: =AC63*$K63 -> 0 | AQ63: =AD63*$K63 -> 0 | AR63: =AE63*$K63 -> 0 | AS63: =AF63*$K63 -> 0 | AT63: =AG63*$K63 -> 0 | AU63: =AH63*$K63 -> 0 | AV63: =AI63*$K63 -> 15120 | ... AZ63: =AM63*$K63 -> 0 | BA63: =SUM(BB63:BM63) -> 0 | BB63: 0 | BC63: 0 | BD63: 0 | BE63: 0 | BF63: 0 | BG63: 0 | BH63: 0 | BI63: 0 | BJ63: 0 | BK63: 0 | BL63: 0 | BM63: 0 | BN63: =SUM(BO63:BZ63) -> 30240 | BO63: =BB63+AO63 -> 0 | BP63: =BC63+AP63 -> 0 | BQ63: =BD63+AQ63 -> 0 | BR63: =BE63+AR63 -> 0 | BS63: =BF63+AS63 -> 0 | BT63: =BG63+AT63 -> 0 | BU63: =BH63+AU63 -> 0 | BV63: =BI63+AV63 -> 15120 | ... BZ63: =BM63+AZ63 -> 0
A64: =IF(ISNUMBER(INDEX('IBM POs AP07'!$A:$A, MATCH(D64,'IBM POs AP07'!$A:$A,0),1)),"Yes","No") -> No | B64: Raju Parkala | C64: Rao Nakkella | D64: 9501304116 | E64: YAPTGB | F64: SAP SVO CI Finance Q3 2026 | G64: 46204 | H64: 46295 | I64: C-RWNH | J64: CHANDRA JONNAGEDDALA | K64: 183 | N64: =AH64 -> 136 | O64: =N64*K64 -> 24888 | P64: =BF64 -> 0 | Q64: =O64+P64 -> 24888 | S64: =R64*K64 -> 0 | T64: 0 | U64: =S64+T64 -> 0 | V64: =Q64-U64 -> 24888 | W64: =IF(AND(L64="Offshore",R64>N64),"Red Flag",IF(AND(OR(L64="Onshore",L64="EMEA"),R64>N64),"Red Flag","")) | X64: 1 | Y64: 0 | AA64: =SUM(AB64:AM64) -> 520 | AH64: 136 | AI64: 200 | AJ64: 160 | AK64: 24 | AN64: =SUM(AO64:AZ64) -> 95160 | AO64: =AB64*$K64 -> 0 | AP64: =AC64*$K64 -> 0 | AQ64: =AD64*$K64 -> 0 | AR64: =AE64*$K64 -> 0 | AS64: =AF64*$K64 -> 0 | AT64: =AG64*$K64 -> 0 | AU64: =AH64*$K64 -> 24888 | AV64: =AI64*$K64 -> 36600 | ... AZ64: =AM64*$K64 -> 0 | BA64: =SUM(BB64:BM64) -> 0 | BB64: 0 | BC64: 0 | BD64: 0 | BE64: 0 | BF64: 0 | BG64: 0 | BH64: 0 | BI64: 0 | BJ64: 0 | BK64: 0 | BL64: 0 | BM64: 0 | BN64: =SUM(BO64:BZ64) -> 95160 | BO64: =BB64+AO64 -> 0 | BP64: =BC64+AP64 -> 0 | BQ64: =BD64+AQ64 -> 0 | BR64: =BE64+AR64 -> 0 | BS64: =BF64+AS64 -> 0 | BT64: =BG64+AT64 -> 0 | BU64: =BH64+AU64 -> 24888 | BV64: =BI64+AV64 -> 36600 | ... BZ64: =BM64+AZ64 -> 0
A65: =IF(ISNUMBER(INDEX('IBM POs AP07'!$A:$A, MATCH(D65,'IBM POs AP07'!$A:$A,0),1)),"Yes","No") -> No | B65: Raju Parkala | C65: Rao Nakkella | D65: 9501304116 | E65: YAPTGB | F65: SAP SVO CI Finance Q3 2026 | G65: 46204 | H65: 46295 | I65: 08781B | J65: EASHWAR SESHADRI | K65: 182 | N65: =AH65 -> 136 | O65: =N65*K65 -> 24752 | P65: =BF65 -> 0 | Q65: =O65+P65 -> 24752 | S65: =R65*K65 -> 0 | T65: 0 | U65: =S65+T65 -> 0 | V65: =Q65-U65 -> 24752 | W65: =IF(AND(L65="Offshore",R65>N65),"Red Flag",IF(AND(OR(L65="Onshore",L65="EMEA"),R65>N65),"Red Flag","")) | X65: 1 | Y65: 0 | AA65: =SUM(AB65:AM65) -> 520 | AH65: 136 | AI65: 200 | AJ65: 160 | AK65: 24 | AN65: =SUM(AO65:AZ65) -> 94640 | AO65: =AB65*$K65 -> 0 | AP65: =AC65*$K65 -> 0 | AQ65: =AD65*$K65 -> 0 | AR65: =AE65*$K65 -> 0 | AS65: =AF65*$K65 -> 0 | AT65: =AG65*$K65 -> 0 | AU65: =AH65*$K65 -> 24752 | AV65: =AI65*$K65 -> 36400 | ... AZ65: =AM65*$K65 -> 0 | BA65: =SUM(BB65:BM65) -> 0 | BB65: 0 | BC65: 0 | BD65: 0 | BE65: 0 | BF65: 0 | BG65: 0 | BH65: 0 | BI65: 0 | BJ65: 0 | BK65: 0 | BL65: 0 | BM65: 0 | BN65: =SUM(BO65:BZ65) -> 94640 | BO65: =BB65+AO65 -> 0 | BP65: =BC65+AP65 -> 0 | BQ65: =BD65+AQ65 -> 0 | BR65: =BE65+AR65 -> 0 | BS65: =BF65+AS65 -> 0 | BT65: =BG65+AT65 -> 0 | BU65: =BH65+AU65 -> 24752 | BV65: =BI65+AV65 -> 36400 | ... BZ65: =BM65+AZ65 -> 0
A66: =IF(ISNUMBER(INDEX('IBM POs AP07'!$A:$A, MATCH(D66,'IBM POs AP07'!$A:$A,0),1)),"Yes","No") -> No | B66: Raju Parkala | C66: Rao Nakkella | D66: 9501304116 | E66: YAPTGB | F66: SAP SVO CI Finance Q3 2026 | G66: 46204 | H66: 46295 | I66: 9D5534 | J66: VINOD MURALI | K66: 307 | N66: =AH66 -> 0 | O66: =N66*K66 -> 0 | P66: =BF66 -> 0 | Q66: =O66+P66 -> 0 | S66: =R66*K66 -> 0 | T66: 0 | U66: =S66+T66 -> 0 | V66: =Q66-U66 -> 0 | W66: =IF(AND(L66="Offshore",R66>N66),"Red Flag",IF(AND(OR(L66="Onshore",L66="EMEA"),R66>N66),"Red Flag","")) | X66: 1 | Y66: 0 | AA66: =SUM(AB66:AM66) -> 304 | AH66: 0 | AI66: 120 | AJ66: 160 | AK66: 24 | AN66: =SUM(AO66:AZ66) -> 93328 | AO66: =AB66*$K66 -> 0 | AP66: =AC66*$K66 -> 0 | AQ66: =AD66*$K66 -> 0 | AR66: =AE66*$K66 -> 0 | AS66: =AF66*$K66 -> 0 | AT66: =AG66*$K66 -> 0 | AU66: =AH66*$K66 -> 0 | AV66: =AI66*$K66 -> 36840 | ... AZ66: =AM66*$K66 -> 0 | BA66: =SUM(BB66:BM66) -> 0 | BB66: 0 | BC66: 0 | BD66: 0 | BE66: 0 | BF66: 0 | BG66: 0 | BH66: 0 | BI66: 0 | BJ66: 0 | BK66: 0 | BL66: 0 | BM66: 0 | BN66: =SUM(BO66:BZ66) -> 93328 | BO66: =BB66+AO66 -> 0 | BP66: =BC66+AP66 -> 0 | BQ66: =BD66+AQ66 -> 0 | BR66: =BE66+AR66 -> 0 | BS66: =BF66+AS66 -> 0 | BT66: =BG66+AT66 -> 0 | BU66: =BH66+AU66 -> 0 | BV66: =BI66+AV66 -> 36840 | ... BZ66: =BM66+AZ66 -> 0
A67: =IF(ISNUMBER(INDEX('IBM POs AP07'!$A:$A, MATCH(D67,'IBM POs AP07'!$A:$A,0),1)),"Yes","No") -> No | B67: Raju Parkala | C67: Rao Nakkella | D67: 9501304116 | E67: YAPTGB | F67: SAP SVO CI Finance Q3 2026 | G67: 46204 | H67: 46295 | I67: 4J5042 | J67: SURYA JAKKA | K67: 307 | N67: =AH67 -> 88 | O67: =N67*K67 -> 27016 | P67: =BF67 -> 0 | Q67: =O67+P67 -> 27016 | S67: =R67*K67 -> 0 | T67: 0 | U67: =S67+T67 -> 0 | V67: =Q67-U67 -> 27016 | W67: =IF(AND(L67="Offshore",R67>N67),"Red Flag",IF(AND(OR(L67="Onshore",L67="EMEA"),R67>N67),"Red Flag","")) | X67: 1 | Y67: 0 | AA67: =SUM(AB67:AM67) -> 256 | AH67: 88 | AI67: 84 | AJ67: 84 | AN67: =SUM(AO67:AZ67) -> 78592 | AO67: =AB67*$K67 -> 0 | AP67: =AC67*$K67 -> 0 | AQ67: =AD67*$K67 -> 0 | AR67: =AE67*$K67 -> 0 | AS67: =AF67*$K67 -> 0 | AT67: =AG67*$K67 -> 0 | AU67: =AH67*$K67 -> 27016 | AV67: =AI67*$K67 -> 25788 | ... AZ67: =AM67*$K67 -> 0 | BA67: =SUM(BB67:BM67) -> 0 | BB67: 0 | BC67: 0 | BD67: 0 | BE67: 0 | BF67: 0 | BG67: 0 | BH67: 0 | BI67: 0 | BJ67: 0 | BK67: 0 | BL67: 0 | BM67: 0 | BN67: =SUM(BO67:BZ67) -> 78592 | BO67: =BB67+AO67 -> 0 | BP67: =BC67+AP67 -> 0 | BQ67: =BD67+AQ67 -> 0 | BR67: =BE67+AR67 -> 0 | BS67: =BF67+AS67 -> 0 | BT67: =BG67+AT67 -> 0 | BU67: =BH67+AU67 -> 27016 | BV67: =BI67+AV67 -> 25788 | ... BZ67: =BM67+AZ67 -> 0
A68: =IF(ISNUMBER(INDEX('IBM POs AP07'!$A:$A, MATCH(D68,'IBM POs AP07'!$A:$A,0),1)),"Yes","No") -> No | B68: Raju Parkala | C68: Rao Nakkella | D68: 9501304116 | E68: YAPTGB | F68: SAP SVO CI Finance Q3 2026 | G68: 46204 | H68: 46295 | I68: 05660P | J68: AMIT PAUL | K68: 61.75 | N68: =AH68 -> 153 | O68: =N68*K68 -> 9447.75 | P68: =BF68 -> 0 | Q68: =O68+P68 -> 9447.75 | S68: =R68*K68 -> 0 | T68: 0 | U68: =S68+T68 -> 0 | V68: =Q68-U68 -> 9447.75 | W68: =IF(AND(L68="Offshore",R68>N68),"Red Flag",IF(AND(OR(L68="Onshore",L68="EMEA"),R68>N68),"Red Flag","")) | X68: 1 | Y68: 0 | AA68: =SUM(AB68:AM68) -> 585 | AH68: 153 | AI68: 225 | AJ68: 180 | AK68: 27 | AN68: =SUM(AO68:AZ68) -> 36123.75 | AO68: =AB68*$K68 -> 0 | AP68: =AC68*$K68 -> 0 | AQ68: =AD68*$K68 -> 0 | AR68: =AE68*$K68 -> 0 | AS68: =AF68*$K68 -> 0 | AT68: =AG68*$K68 -> 0 | AU68: =AH68*$K68 -> 9447.75 | AV68: =AI68*$K68 -> 13893.75 | ... AZ68: =AM68*$K68 -> 0 | BA68: =SUM(BB68:BM68) -> 0 | BB68: 0 | BC68: 0 | BD68: 0 | BE68: 0 | BF68: 0 | BG68: 0 | BH68: 0 | BI68: 0 | BJ68: 0 | BK68: 0 | BL68: 0 | BM68: 0 | BN68: =SUM(BO68:BZ68) -> 36123.75 | BO68: =BB68+AO68 -> 0 | BP68: =BC68+AP68 -> 0 | BQ68: =BD68+AQ68 -> 0 | BR68: =BE68+AR68 -> 0 | BS68: =BF68+AS68 -> 0 | BT68: =BG68+AT68 -> 0 | BU68: =BH68+AU68 -> 9447.75 | BV68: =BI68+AV68 -> 13893.75 | ... BZ68: =BM68+AZ68 -> 0
A69: =IF(ISNUMBER(INDEX('IBM POs AP07'!$A:$A, MATCH(D69,'IBM POs AP07'!$A:$A,0),1)),"Yes","No") -> No | B69: Raju Parkala | C69: Rao Nakkella | D69: 9501304116 | E69: YAPTGB | F69: SAP SVO CI Finance Q3 2026 | G69: 46204 | H69: 46295 | I69: 03506C | J69: NARSAIAH PULI | K69: 61.75 | N69: =AH69 -> 153 | O69: =N69*K69 -> 9447.75 | P69: =BF69 -> 0 | Q69: =O69+P69 -> 9447.75 | S69: =R69*K69 -> 0 | T69: 0 | U69: =S69+T69 -> 0 | V69: =Q69-U69 -> 9447.75 | W69: =IF(AND(L69="Offshore",R69>N69),"Red Flag",IF(AND(OR(L69="Onshore",L69="EMEA"),R69>N69),"Red Flag","")) | X69: 1 | Y69: 0 | AA69: =SUM(AB69:AM69) -> 585 | AH69: 153 | AI69: 225 | AJ69: 180 | AK69: 27 | AN69: =SUM(AO69:AZ69) -> 36123.75 | AO69: =AB69*$K69 -> 0 | AP69: =AC69*$K69 -> 0 | AQ69: =AD69*$K69 -> 0 | AR69: =AE69*$K69 -> 0 | AS69: =AF69*$K69 -> 0 | AT69: =AG69*$K69 -> 0 | AU69: =AH69*$K69 -> 9447.75 | AV69: =AI69*$K69 -> 13893.75 | ... AZ69: =AM69*$K69 -> 0 | BA69: =SUM(BB69:BM69) -> 0 | BB69: 0 | BC69: 0 | BD69: 0 | BE69: 0 | BF69: 0 | BG69: 0 | BH69: 0 | BI69: 0 | BJ69: 0 | BK69: 0 | BL69: 0 | BM69: 0 | BN69: =SUM(BO69:BZ69) -> 36123.75 | BO69: =BB69+AO69 -> 0 | BP69: =BC69+AP69 -> 0 | BQ69: =BD69+AQ69 -> 0 | BR69: =BE69+AR69 -> 0 | BS69: =BF69+AS69 -> 0 | BT69: =BG69+AT69 -> 0 | BU69: =BH69+AU69 -> 9447.75 | BV69: =BI69+AV69 -> 13893.75 | ... BZ69: =BM69+AZ69 -> 0
A70: =IF(ISNUMBER(INDEX('IBM POs AP07'!$A:$A, MATCH(D70,'IBM POs AP07'!$A:$A,0),1)),"Yes","No") -> No | B70: Raju Parkala | C70: Rao Nakkella | D70: 9501304116 | E70: YAPTGB | F70: SAP SVO CI Finance Q3 2026 | G70: 46204 | H70: 46295 | I70: 005PBO | J70: Ramanath Reddy Annavaram | K70: 61.75 | N70: =AH70 -> 153 | O70: =N70*K70 -> 9447.75 | P70: =BF70 -> 0 | Q70: =O70+P70 -> 9447.75 | S70: =R70*K70 -> 0 | T70: 0 | U70: =S70+T70 -> 0 | V70: =Q70-U70 -> 9447.75 | W70: =IF(AND(L70="Offshore",R70>N70),"Red Flag",IF(AND(OR(L70="Onshore",L70="EMEA"),R70>N70),"Red Flag","")) | X70: 1 | Y70: 0 | AA70: =SUM(AB70:AM70) -> 585 | AH70: 153 | AI70: 225 | AJ70: 180 | AK70: 27 | AN70: =SUM(AO70:AZ70) -> 36123.75 | AO70: =AB70*$K70 -> 0 | AP70: =AC70*$K70 -> 0 | AQ70: =AD70*$K70 -> 0 | AR70: =AE70*$K70 -> 0 | AS70: =AF70*$K70 -> 0 | AT70: =AG70*$K70 -> 0 | AU70: =AH70*$K70 -> 9447.75 | AV70: =AI70*$K70 -> 13893.75 | ... AZ70: =AM70*$K70 -> 0 | BA70: =SUM(BB70:BM70) -> 0 | BB70: 0 | BC70: 0 | BD70: 0 | BE70: 0 | BF70: 0 | BG70: 0 | BH70: 0 | BI70: 0 | BJ70: 0 | BK70: 0 | BL70: 0 | BM70: 0 | BN70: =SUM(BO70:BZ70) -> 36123.75 | BO70: =BB70+AO70 -> 0 | BP70: =BC70+AP70 -> 0 | BQ70: =BD70+AQ70 -> 0 | BR70: =BE70+AR70 -> 0 | BS70: =BF70+AS70 -> 0 | BT70: =BG70+AT70 -> 0 | BU70: =BH70+AU70 -> 9447.75 | BV70: =BI70+AV70 -> 13893.75 | ... BZ70: =BM70+AZ70 -> 0
A71: =IF(ISNUMBER(INDEX('IBM POs AP07'!$A:$A, MATCH(D71,'IBM POs AP07'!$A:$A,0),1)),"Yes","No") -> No | B71: Raju Parkala | C71: Rao Nakkella | D71: 9501304116 | E71: YAPTGB | F71: SAP SVO CI Finance Q3 2026 | G71: 46204 | H71: 46295 | I71: 0004JN | J71: RAJAMALLU AMARAGONDA | K71: 47.5 | N71: =AH71 -> 0 | O71: =N71*K71 -> 0 | P71: =BF71 -> 0 | Q71: =O71+P71 -> 0 | S71: =R71*K71 -> 0 | T71: 0 | U71: =S71+T71 -> 0 | V71: =Q71-U71 -> 0 | W71: =IF(AND(L71="Offshore",R71>N71),"Red Flag",IF(AND(OR(L71="Onshore",L71="EMEA"),R71>N71),"Red Flag","")) | X71: 1 | Y71: 0 | AA71: =SUM(AB71:AM71) -> 198 | AH71: 0 | AI71: 0 | AJ71: 171 | AK71: 27 | AN71: =SUM(AO71:AZ71) -> 9405 | AO71: =AB71*$K71 -> 0 | AP71: =AC71*$K71 -> 0 | AQ71: =AD71*$K71 -> 0 | AR71: =AE71*$K71 -> 0 | AS71: =AF71*$K71 -> 0 | AT71: =AG71*$K71 -> 0 | AU71: =AH71*$K71 -> 0 | AV71: =AI71*$K71 -> 0 | ... AZ71: =AM71*$K71 -> 0 | BA71: =SUM(BB71:BM71) -> 0 | BB71: 0 | BC71: 0 | BD71: 0 | BE71: 0 | BF71: 0 | BG71: 0 | BH71: 0 | BI71: 0 | BJ71: 0 | BK71: 0 | BL71: 0 | BM71: 0 | BN71: =SUM(BO71:BZ71) -> 9405 | BO71: =BB71+AO71 -> 0 | BP71: =BC71+AP71 -> 0 | BQ71: =BD71+AQ71 -> 0 | BR71: =BE71+AR71 -> 0 | BS71: =BF71+AS71 -> 0 | BT71: =BG71+AT71 -> 0 | BU71: =BH71+AU71 -> 0 | BV71: =BI71+AV71 -> 0 | ... BZ71: =BM71+AZ71 -> 0
A72: =IF(ISNUMBER(INDEX('IBM POs AP07'!$A:$A, MATCH(D72,'IBM POs AP07'!$A:$A,0),1)),"Yes","No") -> No | B72: Raju Parkala | C72: Rao Nakkella | D72: 9501304116 | E72: YAPTGB | F72: SAP SVO CI Finance Q3 2026 | G72: 46204 | H72: 46295 | I72: 002WVB | J72: VENKATESWARLU BASU | K72: 47.5 | N72: =AH72 -> 153 | O72: =N72*K72 -> 7267.5 | P72: =BF72 -> 0 | Q72: =O72+P72 -> 7267.5 | S72: =R72*K72 -> 0 | T72: 0 | U72: =S72+T72 -> 0 | V72: =Q72-U72 -> 7267.5 | W72: =IF(AND(L72="Offshore",R72>N72),"Red Flag",IF(AND(OR(L72="Onshore",L72="EMEA"),R72>N72),"Red Flag","")) | X72: 1 | Y72: 0 | AA72: =SUM(AB72:AM72) -> 585 | AH72: 153 | AI72: 225 | AJ72: 180 | AK72: 27 | AN72: =SUM(AO72:AZ72) -> 27787.5 | AO72: =AB72*$K72 -> 0 | AP72: =AC72*$K72 -> 0 | AQ72: =AD72*$K72 -> 0 | AR72: =AE72*$K72 -> 0 | AS72: =AF72*$K72 -> 0 | AT72: =AG72*$K72 -> 0 | AU72: =AH72*$K72 -> 7267.5 | AV72: =AI72*$K72 -> 10687.5 | ... AZ72: =AM72*$K72 -> 0 | BA72: =SUM(BB72:BM72) -> 0 | BB72: 0 | BC72: 0 | BD72: 0 | BE72: 0 | BF72: 0 | BG72: 0 | BH72: 0 | BI72: 0 | BJ72: 0 | BK72: 0 | BL72: 0 | BM72: 0 | BN72: =SUM(BO72:BZ72) -> 27787.5 | BO72: =BB72+AO72 -> 0 | BP72: =BC72+AP72 -> 0 | BQ72: =BD72+AQ72 -> 0 | BR72: =BE72+AR72 -> 0 | BS72: =BF72+AS72 -> 0 | BT72: =BG72+AT72 -> 0 | BU72: =BH72+AU72 -> 7267.5 | BV72: =BI72+AV72 -> 10687.5 | ... BZ72: =BM72+AZ72 -> 0
A73: =IF(ISNUMBER(INDEX('IBM POs AP07'!$A:$A, MATCH(D73,'IBM POs AP07'!$A:$A,0),1)),"Yes","No") -> No | B73: Raju Parkala | C73: Rao Nakkella | D73: 9501304116 | E73: YAPTGB | F73: SAP SVO CI Finance Q3 2026 | G73: 46204 | H73: 46295 | I73: 005PX3 | J73: RAGHAVENDER PRODDUTURI | K73: 31.5 | N73: =AH73 -> 153 | O73: =N73*K73 -> 4819.5 | P73: =BF73 -> 0 | Q73: =O73+P73 -> 4819.5 | S73: =R73*K73 -> 0 | T73: 0 | U73: =S73+T73 -> 0 | V73: =Q73-U73 -> 4819.5 | W73: =IF(AND(L73="Offshore",R73>N73),"Red Flag",IF(AND(OR(L73="Onshore",L73="EMEA"),R73>N73),"Red Flag","")) | X73: 1 | Y73: 0 | AA73: =SUM(AB73:AM73) -> 585 | AH73: 153 | AI73: 225 | AJ73: 180 | AK73: 27 | AN73: =SUM(AO73:AZ73) -> 18427.5 | AO73: =AB73*$K73 -> 0 | AP73: =AC73*$K73 -> 0 | AQ73: =AD73*$K73 -> 0 | AR73: =AE73*$K73 -> 0 | AS73: =AF73*$K73 -> 0 | AT73: =AG73*$K73 -> 0 | AU73: =AH73*$K73 -> 4819.5 | AV73: =AI73*$K73 -> 7087.5 | ... AZ73: =AM73*$K73 -> 0 | BA73: =SUM(BB73:BM73) -> 0 | BB73: 0 | BC73: 0 | BD73: 0 | BE73: 0 | BF73: 0 | BG73: 0 | BH73: 0 | BI73: 0 | BJ73: 0 | BK73: 0 | BL73: 0 | BM73: 0 | BN73: =SUM(BO73:BZ73) -> 18427.5 | BO73: =BB73+AO73 -> 0 | BP73: =BC73+AP73 -> 0 | BQ73: =BD73+AQ73 -> 0 | BR73: =BE73+AR73 -> 0 | BS73: =BF73+AS73 -> 0 | BT73: =BG73+AT73 -> 0 | BU73: =BH73+AU73 -> 4819.5 | BV73: =BI73+AV73 -> 7087.5 | ... BZ73: =BM73+AZ73 -> 0
A74: =IF(ISNUMBER(INDEX('IBM POs AP07'!$A:$A, MATCH(D74,'IBM POs AP07'!$A:$A,0),1)),"Yes","No") -> No | B74: Raju Parkala | C74: Rao Nakkella | D74: 9501304116 | E74: YAPTGB | F74: SAP SVO CI Finance Q3 2026 | G74: 46204 | H74: 46295 | I74: 0056OJ | J74: MEGHANA K | K74: 31.5 | N74: =AH74 -> 153 | O74: =N74*K74 -> 4819.5 | P74: =BF74 -> 0 | Q74: =O74+P74 -> 4819.5 | S74: =R74*K74 -> 0 | T74: 0 | U74: =S74+T74 -> 0 | V74: =Q74-U74 -> 4819.5 | W74: =IF(AND(L74="Offshore",R74>N74),"Red Flag",IF(AND(OR(L74="Onshore",L74="EMEA"),R74>N74),"Red Flag","")) | X74: 1 | Y74: 0 | AA74: =SUM(AB74:AM74) -> 585 | AH74: 153 | AI74: 225 | AJ74: 180 | AK74: 27 | AN74: =SUM(AO74:AZ74) -> 18427.5 | AO74: =AB74*$K74 -> 0 | AP74: =AC74*$K74 -> 0 | AQ74: =AD74*$K74 -> 0 | AR74: =AE74*$K74 -> 0 | AS74: =AF74*$K74 -> 0 | AT74: =AG74*$K74 -> 0 | AU74: =AH74*$K74 -> 4819.5 | AV74: =AI74*$K74 -> 7087.5 | ... AZ74: =AM74*$K74 -> 0 | BA74: =SUM(BB74:BM74) -> 0 | BB74: 0 | BC74: 0 | BD74: 0 | BE74: 0 | BF74: 0 | BG74: 0 | BH74: 0 | BI74: 0 | BJ74: 0 | BK74: 0 | BL74: 0 | BM74: 0 | BN74: =SUM(BO74:BZ74) -> 18427.5 | BO74: =BB74+AO74 -> 0 | BP74: =BC74+AP74 -> 0 | BQ74: =BD74+AQ74 -> 0 | BR74: =BE74+AR74 -> 0 | BS74: =BF74+AS74 -> 0 | BT74: =BG74+AT74 -> 0 | BU74: =BH74+AU74 -> 4819.5 | BV74: =BI74+AV74 -> 7087.5 | ... BZ74: =BM74+AZ74 -> 0
A75: =IF(ISNUMBER(INDEX('IBM POs AP07'!$A:$A, MATCH(D75,'IBM POs AP07'!$A:$A,0),1)),"Yes","No") -> No | B75: Raju Parkala | C75: Leslie Meadows | D75: 9501258229 | E75: YAMBZB | F75: SAP Testing COE - Automation | G75: 46143 | H75: 47208 | I75: 002AV4 | J75: SRIMANTI KAR | K75: 45 | N75: =AH75 -> 171 | O75: =N75*K75 -> 7695 | P75: =BF75 -> 0 | Q75: =O75+P75 -> 7695 | S75: =R75*K75 -> 0 | T75: 0 | U75: =S75+T75 -> 0 | V75: =Q75-U75 -> 7695 | W75: =IF(AND(L75="Offshore",R75>N75),"Red Flag",IF(AND(OR(L75="Onshore",L75="EMEA"),R75>N75),"Red Flag","")) | X75: 1 | Y75: 0 | AA75: =SUM(AB75:AM75) -> 1494 | AF75: 135 | AG75: 198 | AH75: 171 | AI75: 180 | AJ75: 225 | AK75: 180 | AL75: 225 | AM75: 180 | AN75: =SUM(AO75:AZ75) -> 67230 | AO75: =AB75*$K75 -> 0 | AP75: =AC75*$K75 -> 0 | AQ75: =AD75*$K75 -> 0 | AR75: =AE75*$K75 -> 0 | AS75: =AF75*$K75 -> 6075 | AT75: =AG75*$K75 -> 8910 | AU75: =AH75*$K75 -> 7695 | AV75: =AI75*$K75 -> 8100 | ... AZ75: =AM75*$K75 -> 8100 | BA75: =SUM(BB75:BM75) -> 0 | BB75: 0 | BC75: 0 | BD75: 0 | BE75: 0 | BF75: 0 | BG75: 0 | BH75: 0 | BI75: 0 | BJ75: 0 | BK75: 0 | BL75: 0 | BM75: 0 | BN75: =SUM(BO75:BZ75) -> 67230 | BO75: =BB75+AO75 -> 0 | BP75: =BC75+AP75 -> 0 | BQ75: =BD75+AQ75 -> 0 | BR75: =BE75+AR75 -> 0 | BS75: =BF75+AS75 -> 6075 | BT75: =BG75+AT75 -> 8910 | BU75: =BH75+AU75 -> 7695 | BV75: =BI75+AV75 -> 8100 | ... BZ75: =BM75+AZ75 -> 8100
A76: =IF(ISNUMBER(INDEX('IBM POs AP07'!$A:$A, MATCH(D76,'IBM POs AP07'!$A:$A,0),1)),"Yes","No") -> No | B76: Raju Parkala | C76: Leslie Meadows | D76: 9501258229 | E76: YAMBZB | F76: SAP Testing COE - Automation | G76: 46143 | H76: 47208 | I76: 0045JC | J76: RAJASHREE PALANIKUMAR | K76: 35 | N76: =AH76 -> 171 | O76: =N76*K76 -> 5985 | P76: =BF76 -> 0 | Q76: =O76+P76 -> 5985 | S76: =R76*K76 -> 0 | T76: 0 | U76: =S76+T76 -> 0 | V76: =Q76-U76 -> 5985 | W76: =IF(AND(L76="Offshore",R76>N76),"Red Flag",IF(AND(OR(L76="Onshore",L76="EMEA"),R76>N76),"Red Flag","")) | X76: 1 | Y76: 0 | AA76: =SUM(AB76:AM76) -> 1494 | AF76: 135 | AG76: 198 | AH76: 171 | AI76: 180 | AJ76: 225 | AK76: 180 | AL76: 225 | AM76: 180 | AN76: =SUM(AO76:AZ76) -> 52290 | AO76: =AB76*$K76 -> 0 | AP76: =AC76*$K76 -> 0 | AQ76: =AD76*$K76 -> 0 | AR76: =AE76*$K76 -> 0 | AS76: =AF76*$K76 -> 4725 | AT76: =AG76*$K76 -> 6930 | AU76: =AH76*$K76 -> 5985 | AV76: =AI76*$K76 -> 6300 | ... AZ76: =AM76*$K76 -> 6300 | BA76: =SUM(BB76:BM76) -> 0 | BB76: 0 | BC76: 0 | BD76: 0 | BE76: 0 | BF76: 0 | BG76: 0 | BH76: 0 | BI76: 0 | BJ76: 0 | BK76: 0 | BL76: 0 | BM76: 0 | BN76: =SUM(BO76:BZ76) -> 52290 | BO76: =BB76+AO76 -> 0 | BP76: =BC76+AP76 -> 0 | BQ76: =BD76+AQ76 -> 0 | BR76: =BE76+AR76 -> 0 | BS76: =BF76+AS76 -> 4725 | BT76: =BG76+AT76 -> 6930 | BU76: =BH76+AU76 -> 5985 | BV76: =BI76+AV76 -> 6300 | ... BZ76: =BM76+AZ76 -> 6300
A77: =IF(ISNUMBER(INDEX('IBM POs AP07'!$A:$A, MATCH(D77,'IBM POs AP07'!$A:$A,0),1)),"Yes","No") -> No | B77: Raju Parkala | C77: Leslie Meadows | D77: 9501258229 | E77: YAMBZB | F77: SAP Testing COE - Automation | G77: 46143 | H77: 47208 | I77: 003KCG | J77: SUGURU SURESH | K77: 25 | N77: =AH77 -> 171 | O77: =N77*K77 -> 4275 | P77: =BF77 -> 0 | Q77: =O77+P77 -> 4275 | S77: =R77*K77 -> 0 | T77: 0 | U77: =S77+T77 -> 0 | V77: =Q77-U77 -> 4275 | W77: =IF(AND(L77="Offshore",R77>N77),"Red Flag",IF(AND(OR(L77="Onshore",L77="EMEA"),R77>N77),"Red Flag","")) | X77: 1 | Y77: 0 | AA77: =SUM(AB77:AM77) -> 1431 | AF77: 72 | AG77: 198 | AH77: 171 | AI77: 180 | AJ77: 225 | AK77: 180 | AL77: 225 | AM77: 180 | AN77: =SUM(AO77:AZ77) -> 35775 | AO77: =AB77*$K77 -> 0 | AP77: =AC77*$K77 -> 0 | AQ77: =AD77*$K77 -> 0 | AR77: =AE77*$K77 -> 0 | AS77: =AF77*$K77 -> 1800 | AT77: =AG77*$K77 -> 4950 | AU77: =AH77*$K77 -> 4275 | AV77: =AI77*$K77 -> 4500 | ... AZ77: =AM77*$K77 -> 4500 | BA77: =SUM(BB77:BM77) -> 0 | BB77: 0 | BC77: 0 | BD77: 0 | BE77: 0 | BF77: 0 | BG77: 0 | BH77: 0 | BI77: 0 | BJ77: 0 | BK77: 0 | BL77: 0 | BM77: 0 | BN77: =SUM(BO77:BZ77) -> 35775 | BO77: =BB77+AO77 -> 0 | BP77: =BC77+AP77 -> 0 | BQ77: =BD77+AQ77 -> 0 | BR77: =BE77+AR77 -> 0 | BS77: =BF77+AS77 -> 1800 | BT77: =BG77+AT77 -> 4950 | BU77: =BH77+AU77 -> 4275 | BV77: =BI77+AV77 -> 4500 | ... BZ77: =BM77+AZ77 -> 4500
A78: =IF(ISNUMBER(INDEX('IBM POs AP07'!$A:$A, MATCH(D78,'IBM POs AP07'!$A:$A,0),1)),"Yes","No") -> No | B78: Raju Parkala | C78: Leslie Meadows | D78: 9501258235 | E78: YAMGCB | F78: SAP Testing COE | G78: 46143 | H78: 47208 | I78: 003SER | J78: SHAKUNTALA . | K78: 21 | N78: =AH78 -> 171 | O78: =N78*K78 -> 3591 | P78: =BF78 -> 0 | Q78: =O78+P78 -> 3591 | S78: =R78*K78 -> 0 | T78: 0 | U78: =S78+T78 -> 0 | V78: =Q78-U78 -> 3591 | W78: =IF(AND(L78="Offshore",R78>N78),"Red Flag",IF(AND(OR(L78="Onshore",L78="EMEA"),R78>N78),"Red Flag","")) | X78: 1 | Y78: 0 | AA78: =SUM(AB78:AM78) -> 1503 | AF78: 126 | AG78: 216 | AH78: 171 | AI78: 180 | AJ78: 225 | AK78: 180 | AL78: 225 | AM78: 180 | AN78: =SUM(AO78:AZ78) -> 31563 | AO78: =AB78*$K78 -> 0 | AP78: =AC78*$K78 -> 0 | AQ78: =AD78*$K78 -> 0 | AR78: =AE78*$K78 -> 0 | AS78: =AF78*$K78 -> 2646 | AT78: =AG78*$K78 -> 4536 | AU78: =AH78*$K78 -> 3591 | AV78: =AI78*$K78 -> 3780 | ... AZ78: =AM78*$K78 -> 3780 | BA78: =SUM(BB78:BM78) -> 0 | BB78: 0 | BC78: 0 | BD78: 0 | BE78: 0 | BF78: 0 | BG78: 0 | BH78: 0 | BI78: 0 | BJ78: 0 | BK78: 0 | BL78: 0 | BM78: 0 | BN78: =SUM(BO78:BZ78) -> 31563 | BO78: =BB78+AO78 -> 0 | BP78: =BC78+AP78 -> 0 | BQ78: =BD78+AQ78 -> 0 | BR78: =BE78+AR78 -> 0 | BS78: =BF78+AS78 -> 2646 | BT78: =BG78+AT78 -> 4536 | BU78: =BH78+AU78 -> 3591 | BV78: =BI78+AV78 -> 3780 | ... BZ78: =BM78+AZ78 -> 3780
A79: =IF(ISNUMBER(INDEX('IBM POs AP07'!$A:$A, MATCH(D79,'IBM POs AP07'!$A:$A,0),1)),"Yes","No") -> No | B79: Raju Parkala | C79: Leslie Meadows | D79: 9501258235 | E79: YAMGCB | F79: SAP Testing COE | G79: 46143 | H79: 47208 | I79: 0040QY | J79: ANTHONY ANU | K79: 21 | N79: =AH79 -> 171 | O79: =N79*K79 -> 3591 | P79: =BF79 -> 0 | Q79: =O79+P79 -> 3591 | S79: =R79*K79 -> 0 | T79: 0 | U79: =S79+T79 -> 0 | V79: =Q79-U79 -> 3591 | W79: =IF(AND(L79="Offshore",R79>N79),"Red Flag",IF(AND(OR(L79="Onshore",L79="EMEA"),R79>N79),"Red Flag","")) | X79: 1 | Y79: 0 | AA79: =SUM(AB79:AM79) -> 1422 | AF79: 90 | AG79: 171 | AH79: 171 | AI79: 180 | AJ79: 225 | AK79: 180 | AL79: 225 | AM79: 180 | AN79: =SUM(AO79:AZ79) -> 29862 | AO79: =AB79*$K79 -> 0 | AP79: =AC79*$K79 -> 0 | AQ79: =AD79*$K79 -> 0 | AR79: =AE79*$K79 -> 0 | AS79: =AF79*$K79 -> 1890 | AT79: =AG79*$K79 -> 3591 | AU79: =AH79*$K79 -> 3591 | AV79: =AI79*$K79 -> 3780 | ... AZ79: =AM79*$K79 -> 3780 | BA79: =SUM(BB79:BM79) -> 0 | BB79: 0 | BC79: 0 | BD79: 0 | BE79: 0 | BF79: 0 | BG79: 0 | BH79: 0 | BI79: 0 | BJ79: 0 | BK79: 0 | BL79: 0 | BM79: 0 | BN79: =SUM(BO79:BZ79) -> 29862 | BO79: =BB79+AO79 -> 0 | BP79: =BC79+AP79 -> 0 | BQ79: =BD79+AQ79 -> 0 | BR79: =BE79+AR79 -> 0 | BS79: =BF79+AS79 -> 1890 | BT79: =BG79+AT79 -> 3591 | BU79: =BH79+AU79 -> 3591 | BV79: =BI79+AV79 -> 3780 | ... BZ79: =BM79+AZ79 -> 3780
A80: =IF(ISNUMBER(INDEX('IBM POs AP07'!$A:$A, MATCH(D80,'IBM POs AP07'!$A:$A,0),1)),"Yes","No") -> No | B80: Raju Parkala | C80: Leslie Meadows | D80: 9501258235 | E80: YAMGCB | F80: SAP Testing COE | G80: 46143 | H80: 47208 | I80: 005LSC | J80: RAJULA ANUSHA | K80: 21 | N80: =AH80 -> 171 | O80: =N80*K80 -> 3591 | P80: =BF80 -> 0 | Q80: =O80+P80 -> 3591 | S80: =R80*K80 -> 0 | T80: 0 | U80: =S80+T80 -> 0 | V80: =Q80-U80 -> 3591 | W80: =IF(AND(L80="Offshore",R80>N80),"Red Flag",IF(AND(OR(L80="Onshore",L80="EMEA"),R80>N80),"Red Flag","")) | X80: 1 | Y80: 0 | AA80: =SUM(AB80:AM80) -> 1467 | AF80: 108 | AG80: 198 | AH80: 171 | AI80: 180 | AJ80: 225 | AK80: 180 | AL80: 225 | AM80: 180 | AN80: =SUM(AO80:AZ80) -> 30807 | AO80: =AB80*$K80 -> 0 | AP80: =AC80*$K80 -> 0 | AQ80: =AD80*$K80 -> 0 | AR80: =AE80*$K80 -> 0 | AS80: =AF80*$K80 -> 2268 | AT80: =AG80*$K80 -> 4158 | AU80: =AH80*$K80 -> 3591 | AV80: =AI80*$K80 -> 3780 | ... AZ80: =AM80*$K80 -> 3780 | BA80: =SUM(BB80:BM80) -> 0 | BB80: 0 | BC80: 0 | BD80: 0 | BE80: 0 | BF80: 0 | BG80: 0 | BH80: 0 | BI80: 0 | BJ80: 0 | BK80: 0 | BL80: 0 | BM80: 0 | BN80: =SUM(BO80:BZ80) -> 30807 | BO80: =BB80+AO80 -> 0 | BP80: =BC80+AP80 -> 0 | BQ80: =BD80+AQ80 -> 0 | BR80: =BE80+AR80 -> 0 | BS80: =BF80+AS80 -> 2268 | BT80: =BG80+AT80 -> 4158 | BU80: =BH80+AU80 -> 3591 | BV80: =BI80+AV80 -> 3780 | ... BZ80: =BM80+AZ80 -> 3780
A81: =IF(ISNUMBER(INDEX('IBM POs AP07'!$A:$A, MATCH(D81,'IBM POs AP07'!$A:$A,0),1)),"Yes","No") -> No | B81: Raju Parkala | C81: Leslie Meadows | D81: 9501258235 | E81: YAMGCB | F81: SAP Testing COE | G81: 46143 | H81: 47208 | I81: 0042RH | J81: POOJA GILBILE | K81: 21 | N81: =AH81 -> 171 | O81: =N81*K81 -> 3591 | P81: =BF81 -> 0 | Q81: =O81+P81 -> 3591 | S81: =R81*K81 -> 0 | T81: 0 | U81: =S81+T81 -> 0 | V81: =Q81-U81 -> 3591 | W81: =IF(AND(L81="Offshore",R81>N81),"Red Flag",IF(AND(OR(L81="Onshore",L81="EMEA"),R81>N81),"Red Flag","")) | X81: 1 | Y81: 0 | AA81: =SUM(AB81:AM81) -> 1476 | AF81: 108 | AG81: 207 | AH81: 171 | AI81: 180 | AJ81: 225 | AK81: 180 | AL81: 225 | AM81: 180 | AN81: =SUM(AO81:AZ81) -> 30996 | AO81: =AB81*$K81 -> 0 | AP81: =AC81*$K81 -> 0 | AQ81: =AD81*$K81 -> 0 | AR81: =AE81*$K81 -> 0 | AS81: =AF81*$K81 -> 2268 | AT81: =AG81*$K81 -> 4347 | AU81: =AH81*$K81 -> 3591 | AV81: =AI81*$K81 -> 3780 | ... AZ81: =AM81*$K81 -> 3780 | BA81: =SUM(BB81:BM81) -> 0 | BB81: 0 | BC81: 0 | BD81: 0 | BE81: 0 | BF81: 0 | BG81: 0 | BH81: 0 | BI81: 0 | BJ81: 0 | BK81: 0 | BL81: 0 | BM81: 0 | BN81: =SUM(BO81:BZ81) -> 30996 | BO81: =BB81+AO81 -> 0 | BP81: =BC81+AP81 -> 0 | BQ81: =BD81+AQ81 -> 0 | BR81: =BE81+AR81 -> 0 | BS81: =BF81+AS81 -> 2268 | BT81: =BG81+AT81 -> 4347 | BU81: =BH81+AU81 -> 3591 | BV81: =BI81+AV81 -> 3780 | ... BZ81: =BM81+AZ81 -> 3780
A82: =IF(ISNUMBER(INDEX('IBM POs AP07'!$A:$A, MATCH(D82,'IBM POs AP07'!$A:$A,0),1)),"Yes","No") -> No | B82: Raju Parkala | C82: Jean-Francois Bouthillier | D82: Pending PO | E82: YAMKQB | F82: SAP SVO CI nGPS Integration Support Services May - Dec 2026 | G82: 46143 | H82: 46388 | I82: 000QKN | J82: HAREESH N | K82: 61.75 | N82: =AH82 -> 171 | O82: =N82*K82 -> 10559.25 | P82: =BF82 -> 0 | Q82: =O82+P82 -> 10559.25 | S82: =R82*K82 -> 0 | T82: 0 | U82: =S82+T82 -> 0 | V82: =Q82-U82 -> 10559.25 | W82: =IF(AND(L82="Offshore",R82>N82),"Red Flag",IF(AND(OR(L82="Onshore",L82="EMEA"),R82>N82),"Red Flag","")) | X82: 1 | Y82: 0 | AA82: =SUM(AB82:AM82) -> 1494 | AG82: 333 | AH82: 171 | AI82: 180 | AJ82: 225 | AK82: 180 | AL82: 225 | AM82: 180 | AN82: =SUM(AO82:AZ82) -> 92254.5 | AO82: =AB82*$K82 -> 0 | AP82: =AC82*$K82 -> 0 | AQ82: =AD82*$K82 -> 0 | AR82: =AE82*$K82 -> 0 | AS82: =AF82*$K82 -> 0 | AT82: =AG82*$K82 -> 20562.75 | AU82: =AH82*$K82 -> 10559.25 | AV82: =AI82*$K82 -> 11115 | ... AZ82: =AM82*$K82 -> 11115 | BA82: =SUM(BB82:BM82) -> 0 | BB82: 0 | BC82: 0 | BD82: 0 | BE82: 0 | BF82: 0 | BG82: 0 | BH82: 0 | BI82: 0 | BJ82: 0 | BK82: 0 | BL82: 0 | BM82: 0 | BN82: =SUM(BO82:BZ82) -> 92254.5 | BO82: =BB82+AO82 -> 0 | BP82: =BC82+AP82 -> 0 | BQ82: =BD82+AQ82 -> 0 | BR82: =BE82+AR82 -> 0 | BS82: =BF82+AS82 -> 0 | BT82: =BG82+AT82 -> 20562.75 | BU82: =BH82+AU82 -> 10559.25 | BV82: =BI82+AV82 -> 11115 | ... BZ82: =BM82+AZ82 -> 11115
A83: =IF(ISNUMBER(INDEX('IBM POs AP07'!$A:$A, MATCH(D83,'IBM POs AP07'!$A:$A,0),1)),"Yes","No") -> No | B83: Raju Parkala | C83: Harish Jakkilinki | D83: 9501235789 | E83: YAMKXB | F83: SAP SVO ABAP NPL CI Services May - June 2026 | G83: 46143 | H83: 46203 | I83: 002OKS | J83: Venkatrao Pamidi | K83: 47.5 | L83: Offshore | N83: =AH83 -> 18 | O83: =N83*K83 -> 855 | P83: =BF83 -> 0 | Q83: =O83+P83 -> 855 | S83: =R83*K83 -> 0 | T83: 0 | U83: =S83+T83 -> 0 | V83: =Q83-U83 -> 855 | W83: =IF(AND(L83="Offshore",R83>N83),"Red Flag",IF(AND(OR(L83="Onshore",L83="EMEA"),R83>N83),"Red Flag","")) | X83: 1 | Y83: 0 | AA83: =SUM(AB83:AM83) -> 360 | AF83: 126 | AG83: 216 | AH83: 18 | AN83: =SUM(AO83:AZ83) -> 17100 | AO83: =AB83*$K83 -> 0 | AP83: =AC83*$K83 -> 0 | AQ83: =AD83*$K83 -> 0 | AR83: =AE83*$K83 -> 0 | AS83: =AF83*$K83 -> 5985 | AT83: =AG83*$K83 -> 10260 | AU83: =AH83*$K83 -> 855 | AV83: =AI83*$K83 -> 0 | ... AZ83: =AM83*$K83 -> 0 | BA83: =SUM(BB83:BM83) -> 0 | BB83: 0 | BC83: 0 | BD83: 0 | BE83: 0 | BF83: 0 | BG83: 0 | BH83: 0 | BI83: 0 | BJ83: 0 | BK83: 0 | BL83: 0 | BM83: 0 | BN83: =SUM(BO83:BZ83) -> 17100 | BO83: =BB83+AO83 -> 0 | BP83: =BC83+AP83 -> 0 | BQ83: =BD83+AQ83 -> 0 | BR83: =BE83+AR83 -> 0 | BS83: =BF83+AS83 -> 5985 | BT83: =BG83+AT83 -> 10260 | BU83: =BH83+AU83 -> 855 | BV83: =BI83+AV83 -> 0 | ... BZ83: =BM83+AZ83 -> 0
A84: =IF(ISNUMBER(INDEX('IBM POs AP07'!$A:$A, MATCH(D84,'IBM POs AP07'!$A:$A,0),1)),"Yes","No") -> No | B84: Raju Parkala | C84: Harish Jakkilinki | D84: 9501290342 | E84: YAMLBB | F84: SAP SVO CI TechDev MDG Q2 2026 | G84: 46118 | H84: 46206 | I84: C-XY6P | J84: Ojas Sonkusare | K84: 43 | N84: =AH84 -> 45 | O84: =N84*K84 -> 1935 | P84: =BF84 -> 0 | Q84: =O84+P84 -> 1935 | S84: =R84*K84 -> 0 | T84: 0 | U84: =S84+T84 -> 0 | V84: =Q84-U84 -> 1935 | W84: =IF(AND(L84="Offshore",R84>N84),"Red Flag",IF(AND(OR(L84="Onshore",L84="EMEA"),R84>N84),"Red Flag","")) | X84: 1 | Y84: 0 | AA84: =SUM(AB84:AM84) -> 540 | AE84: 117 | AF84: 162 | AG84: 216 | AH84: 45 | AN84: =SUM(AO84:AZ84) -> 23220 | AO84: =AB84*$K84 -> 0 | AP84: =AC84*$K84 -> 0 | AQ84: =AD84*$K84 -> 0 | AR84: =AE84*$K84 -> 5031 | AS84: =AF84*$K84 -> 6966 | AT84: =AG84*$K84 -> 9288 | AU84: =AH84*$K84 -> 1935 | AV84: =AI84*$K84 -> 0 | ... AZ84: =AM84*$K84 -> 0 | BA84: =SUM(BB84:BM84) -> 0 | BB84: 0 | BC84: 0 | BD84: 0 | BE84: 0 | BF84: 0 | BG84: 0 | BH84: 0 | BI84: 0 | BJ84: 0 | BK84: 0 | BL84: 0 | BM84: 0 | BN84: =SUM(BO84:BZ84) -> 23220 | BO84: =BB84+AO84 -> 0 | BP84: =BC84+AP84 -> 0 | BQ84: =BD84+AQ84 -> 0 | BR84: =BE84+AR84 -> 5031 | BS84: =BF84+AS84 -> 6966 | BT84: =BG84+AT84 -> 9288 | BU84: =BH84+AU84 -> 1935 | BV84: =BI84+AV84 -> 0 | ... BZ84: =BM84+AZ84 -> 0
A85: =IF(ISNUMBER(INDEX('IBM POs AP07'!$A:$A, MATCH(D85,'IBM POs AP07'!$A:$A,0),1)),"Yes","No") -> No | B85: Raju Parkala | C85: Matthew Alunkal | D85: 9501306331 | E85: YAPTHB | F85: SAP SVO SCM IBP CI Services July - Dec 2026 | G85: 46204 | H85: 46388 | J85: Vijaya Bharathi | K85: 47.5 | N85: =AH85 -> 153 | O85: =N85*K85 -> 7267.5 | P85: =BF85 -> 0 | Q85: =O85+P85 -> 7267.5 | S85: =R85*K85 -> 0 | T85: 0 | U85: =S85+T85 -> 0 | V85: =Q85-U85 -> 7267.5 | W85: =IF(AND(L85="Offshore",R85>N85),"Red Flag",IF(AND(OR(L85="Onshore",L85="EMEA"),R85>N85),"Red Flag","")) | X85: 1 | Y85: 0 | AA85: =SUM(AB85:AM85) -> 1143 | AH85: 153 | AI85: 180 | AJ85: 225 | AK85: 180 | AL85: 225 | AM85: 180 | AN85: =SUM(AO85:AZ85) -> 54292.5 | AO85: =AB85*$K85 -> 0 | AP85: =AC85*$K85 -> 0 | AQ85: =AD85*$K85 -> 0 | AR85: =AE85*$K85 -> 0 | AS85: =AF85*$K85 -> 0 | AT85: =AG85*$K85 -> 0 | AU85: =AH85*$K85 -> 7267.5 | AV85: =AI85*$K85 -> 8550 | ... AZ85: =AM85*$K85 -> 8550 | BA85: =SUM(BB85:BM85) -> 0 | BB85: 0 | BC85: 0 | BD85: 0 | BE85: 0 | BF85: 0 | BG85: 0 | BH85: 0 | BI85: 0 | BJ85: 0 | BK85: 0 | BL85: 0 | BM85: 0 | BN85: =SUM(BO85:BZ85) -> 54292.5 | BO85: =BB85+AO85 -> 0 | BP85: =BC85+AP85 -> 0 | BQ85: =BD85+AQ85 -> 0 | BR85: =BE85+AR85 -> 0 | BS85: =BF85+AS85 -> 0 | BT85: =BG85+AT85 -> 0 | BU85: =BH85+AU85 -> 7267.5 | BV85: =BI85+AV85 -> 8550 | ... BZ85: =BM85+AZ85 -> 8550
A86: =IF(ISNUMBER(INDEX('IBM POs AP07'!$A:$A, MATCH(D86,'IBM POs AP07'!$A:$A,0),1)),"Yes","No") -> No | B86: Raju Parkala | C86: Senth A Singaram | D86: 9501265890 | E86: YAMMPB | F86: SAP SVO CI Indirect Procurement Q2 2026 | G86: 46113 | H86: 46203 | I86: 005XVE | J86: ANIL ZAGADE | K86: 47.5 | N86: =AH86 -> 18 | O86: =N86*K86 -> 855 | P86: =BF86 -> 0 | Q86: =O86+P86 -> 855 | S86: =R86*K86 -> 0 | T86: 0 | U86: =S86+T86 -> 0 | V86: =Q86-U86 -> 855 | W86: =IF(AND(L86="Offshore",R86>N86),"Red Flag",IF(AND(OR(L86="Onshore",L86="EMEA"),R86>N86),"Red Flag","")) | X86: 1 | Y86: 0 | AA86: =SUM(AB86:AM86) -> 351 | AF86: 135 | AG86: 198 | AH86: 18 | AN86: =SUM(AO86:AZ86) -> 16672.5 | AO86: =AB86*$K86 -> 0 | AP86: =AC86*$K86 -> 0 | AQ86: =AD86*$K86 -> 0 | AR86: =AE86*$K86 -> 0 | AS86: =AF86*$K86 -> 6412.5 | AT86: =AG86*$K86 -> 9405 | AU86: =AH86*$K86 -> 855 | AV86: =AI86*$K86 -> 0 | ... AZ86: =AM86*$K86 -> 0 | BA86: =SUM(BB86:BM86) -> 0 | BB86: 0 | BC86: 0 | BD86: 0 | BE86: 0 | BF86: 0 | BG86: 0 | BH86: 0 | BI86: 0 | BJ86: 0 | BK86: 0 | BL86: 0 | BM86: 0 | BN86: =SUM(BO86:BZ86) -> 16672.5 | BO86: =BB86+AO86 -> 0 | BP86: =BC86+AP86 -> 0 | BQ86: =BD86+AQ86 -> 0 | BR86: =BE86+AR86 -> 0 | BS86: =BF86+AS86 -> 6412.5 | BT86: =BG86+AT86 -> 9405 | BU86: =BH86+AU86 -> 855 | BV86: =BI86+AV86 -> 0 | ... BZ86: =BM86+AZ86 -> 0
A87: =IF(ISNUMBER(INDEX('IBM POs AP07'!$A:$A, MATCH(D87,'IBM POs AP07'!$A:$A,0),1)),"Yes","No") -> No | B87: Raju Parkala | C87: Senth A Singaram | D87: 9501265890 | E87: YAMMPB | F87: SAP SVO CI Indirect Procurement Q2 2026 | G87: 46113 | H87: 46203 | I87: 005I9O | J87: AMIT KAMBLE | K87: 47.5 | N87: =AH87 -> 18 | O87: =N87*K87 -> 855 | P87: =BF87 -> 0 | Q87: =O87+P87 -> 855 | S87: =R87*K87 -> 0 | T87: 0 | U87: =S87+T87 -> 0 | V87: =Q87-U87 -> 855 | W87: =IF(AND(L87="Offshore",R87>N87),"Red Flag",IF(AND(OR(L87="Onshore",L87="EMEA"),R87>N87),"Red Flag","")) | X87: 1 | Y87: 0 | AA87: =SUM(AB87:AM87) -> 360 | AF87: 144 | AG87: 198 | AH87: 18 | AN87: =SUM(AO87:AZ87) -> 17100 | AO87: =AB87*$K87 -> 0 | AP87: =AC87*$K87 -> 0 | AQ87: =AD87*$K87 -> 0 | AR87: =AE87*$K87 -> 0 | AS87: =AF87*$K87 -> 6840 | AT87: =AG87*$K87 -> 9405 | AU87: =AH87*$K87 -> 855 | AV87: =AI87*$K87 -> 0 | ... AZ87: =AM87*$K87 -> 0 | BA87: =SUM(BB87:BM87) -> 0 | BB87: 0 | BC87: 0 | BD87: 0 | BE87: 0 | BF87: 0 | BG87: 0 | BH87: 0 | BI87: 0 | BJ87: 0 | BK87: 0 | BL87: 0 | BM87: 0 | BN87: =SUM(BO87:BZ87) -> 17100 | BO87: =BB87+AO87 -> 0 | BP87: =BC87+AP87 -> 0 | BQ87: =BD87+AQ87 -> 0 | BR87: =BE87+AR87 -> 0 | BS87: =BF87+AS87 -> 6840 | BT87: =BG87+AT87 -> 9405 | BU87: =BH87+AU87 -> 855 | BV87: =BI87+AV87 -> 0 | ... BZ87: =BM87+AZ87 -> 0
A88: =IF(ISNUMBER(INDEX('IBM POs AP07'!$A:$A, MATCH(D88,'IBM POs AP07'!$A:$A,0),1)),"Yes","No") -> No | B88: Raju Parkala | C88: Senth A Singaram | D88: 9501265890 | E88: YAMMPB | F88: SAP SVO CI Indirect Procurement Q2 2026 | G88: 46113 | H88: 46203 | I88: 005WLZ | J88: NANDHINI SARAVANAN | K88: 47.5 | N88: =AH88 -> 18 | O88: =N88*K88 -> 855 | P88: =BF88 -> 0 | Q88: =O88+P88 -> 855 | S88: =R88*K88 -> 0 | T88: 0 | U88: =S88+T88 -> 0 | V88: =Q88-U88 -> 855 | W88: =IF(AND(L88="Offshore",R88>N88),"Red Flag",IF(AND(OR(L88="Onshore",L88="EMEA"),R88>N88),"Red Flag","")) | X88: 1 | Y88: 0 | AA88: =SUM(AB88:AM88) -> 531 | AE88: 131 | AF88: 175 | AG88: 207 | AH88: 18 | AN88: =SUM(AO88:AZ88) -> 25222.5 | AO88: =AB88*$K88 -> 0 | AP88: =AC88*$K88 -> 0 | AQ88: =AD88*$K88 -> 0 | AR88: =AE88*$K88 -> 6222.5 | AS88: =AF88*$K88 -> 8312.5 | AT88: =AG88*$K88 -> 9832.5 | AU88: =AH88*$K88 -> 855 | AV88: =AI88*$K88 -> 0 | ... AZ88: =AM88*$K88 -> 0 | BA88: =SUM(BB88:BM88) -> 0 | BB88: 0 | BC88: 0 | BD88: 0 | BE88: 0 | BF88: 0 | BG88: 0 | BH88: 0 | BI88: 0 | BJ88: 0 | BK88: 0 | BL88: 0 | BM88: 0 | BN88: =SUM(BO88:BZ88) -> 25222.5 | BO88: =BB88+AO88 -> 0 | BP88: =BC88+AP88 -> 0 | BQ88: =BD88+AQ88 -> 0 | BR88: =BE88+AR88 -> 6222.5 | BS88: =BF88+AS88 -> 8312.5 | BT88: =BG88+AT88 -> 9832.5 | BU88: =BH88+AU88 -> 855 | BV88: =BI88+AV88 -> 0 | ... BZ88: =BM88+AZ88 -> 0
A89: =IF(ISNUMBER(INDEX('IBM POs AP07'!$A:$A, MATCH(D89,'IBM POs AP07'!$A:$A,0),1)),"Yes","No") -> No | B89: Raju Parkala | C89: Senth A Singaram | D89: 9501265890 | E89: YAMMPB | F89: SAP SVO CI Indirect Procurement Q2 2026 | G89: 46113 | H89: 46203 | I89: 39320 | J89: Zahir Abbas Shaikh | K89: 182 | N89: =AH89 -> 0 | O89: =N89*K89 -> 0 | P89: =BF89 -> 0 | Q89: =O89+P89 -> 0 | S89: =R89*K89 -> 0 | T89: 0 | U89: =S89+T89 -> 0 | V89: =Q89-U89 -> 0 | W89: =IF(AND(L89="Offshore",R89>N89),"Red Flag",IF(AND(OR(L89="Onshore",L89="EMEA"),R89>N89),"Red Flag","")) | X89: 1 | Y89: 0 | AA89: =SUM(AB89:AM89) -> 336 | AE89: 144 | AF89: 160 | AG89: 32 | AN89: =SUM(AO89:AZ89) -> 61152 | AO89: =AB89*$K89 -> 0 | AP89: =AC89*$K89 -> 0 | AQ89: =AD89*$K89 -> 0 | AR89: =AE89*$K89 -> 26208 | AS89: =AF89*$K89 -> 29120 | AT89: =AG89*$K89 -> 5824 | AU89: =AH89*$K89 -> 0 | AV89: =AI89*$K89 -> 0 | ... AZ89: =AM89*$K89 -> 0 | BA89: =SUM(BB89:BM89) -> 0 | BB89: 0 | BC89: 0 | BD89: 0 | BE89: 0 | BF89: 0 | BG89: 0 | BH89: 0 | BI89: 0 | BJ89: 0 | BK89: 0 | BL89: 0 | BM89: 0 | BN89: =SUM(BO89:BZ89) -> 61152 | BO89: =BB89+AO89 -> 0 | BP89: =BC89+AP89 -> 0 | BQ89: =BD89+AQ89 -> 0 | BR89: =BE89+AR89 -> 26208 | BS89: =BF89+AS89 -> 29120 | BT89: =BG89+AT89 -> 5824 | BU89: =BH89+AU89 -> 0 | BV89: =BI89+AV89 -> 0 | ... BZ89: =BM89+AZ89 -> 0
A90: =IF(ISNUMBER(INDEX('IBM POs AP07'!$A:$A, MATCH(D90,'IBM POs AP07'!$A:$A,0),1)),"Yes","No") -> No | B90: Raju Parkala | C90: Senth A Singaram | D90: 9501289302 | E90: YANPVB | F90: SAP SVO Indirect Procurement MDG Upgrade | G90: 46181 | H90: 46387 | I90: 005WLZ | J90: NANDHINI SARAVANAN | K90: 47.5 | N90: =AH90 -> 135 | O90: =N90*K90 -> 6412.5 | P90: =BF90 -> 0 | Q90: =O90+P90 -> 6412.5 | S90: =R90*K90 -> 0 | T90: 0 | U90: =S90+T90 -> 0 | V90: =Q90-U90 -> 6412.5 | W90: =IF(AND(L90="Offshore",R90>N90),"Red Flag",IF(AND(OR(L90="Onshore",L90="EMEA"),R90>N90),"Red Flag","")) | X90: 1 | Y90: 0 | AA90: =SUM(AB90:AM90) -> 1116 | AG90: 0 | AH90: 135 | AI90: 207 | AJ90: 180 | AK90: 180 | AL90: 207 | AM90: 207 | AN90: =SUM(AO90:AZ90) -> 53010 | AO90: =AB90*$K90 -> 0 | AP90: =AC90*$K90 -> 0 | AQ90: =AD90*$K90 -> 0 | AR90: =AE90*$K90 -> 0 | AS90: =AF90*$K90 -> 0 | AT90: =AG90*$K90 -> 0 | AU90: =AH90*$K90 -> 6412.5 | AV90: =AI90*$K90 -> 9832.5 | ... AZ90: =AM90*$K90 -> 9832.5 | BA90: =SUM(BB90:BM90) -> 0 | BB90: 0 | BC90: 0 | BD90: 0 | BE90: 0 | BF90: 0 | BG90: 0 | BH90: 0 | BI90: 0 | BJ90: 0 | BK90: 0 | BL90: 0 | BM90: 0 | BN90: =SUM(BO90:BZ90) -> 53010 | BO90: =BB90+AO90 -> 0 | BP90: =BC90+AP90 -> 0 | BQ90: =BD90+AQ90 -> 0 | BR90: =BE90+AR90 -> 0 | BS90: =BF90+AS90 -> 0 | BT90: =BG90+AT90 -> 0 | BU90: =BH90+AU90 -> 6412.5 | BV90: =BI90+AV90 -> 9832.5 | ... BZ90: =BM90+AZ90 -> 9832.5
A91: =IF(ISNUMBER(INDEX('IBM POs AP07'!$A:$A, MATCH(D91,'IBM POs AP07'!$A:$A,0),1)),"Yes","No") -> No | B91: Raju Parkala | C91: Senth A Singaram | D91: 9501289302 | E91: YANPVB | F91: SAP SVO Indirect Procurement MDG Upgrade | G91: 46181 | H91: 46387 | J91: Annmaria Mathew | K91: 47.5 | N91: =AH91 -> 171 | O91: =N91*K91 -> 8122.5 | P91: =BF91 -> 0 | Q91: =O91+P91 -> 8122.5 | S91: =R91*K91 -> 0 | T91: 0 | U91: =S91+T91 -> 0 | V91: =Q91-U91 -> 8122.5 | W91: =IF(AND(L91="Offshore",R91>N91),"Red Flag",IF(AND(OR(L91="Onshore",L91="EMEA"),R91>N91),"Red Flag","")) | X91: 1 | Y91: 0 | AA91: =SUM(AB91:AM91) -> 1262 | AG91: 128 | AH91: 171 | AI91: 207 | AJ91: 171 | AK91: 171 | AL91: 207 | AM91: 207 | AN91: =SUM(AO91:AZ91) -> 59945 | AO91: =AB91*$K91 -> 0 | AP91: =AC91*$K91 -> 0 | AQ91: =AD91*$K91 -> 0 | AR91: =AE91*$K91 -> 0 | AS91: =AF91*$K91 -> 0 | AT91: =AG91*$K91 -> 6080 | AU91: =AH91*$K91 -> 8122.5 | AV91: =AI91*$K91 -> 9832.5 | ... AZ91: =AM91*$K91 -> 9832.5 | BA91: =SUM(BB91:BM91) -> 0 | BB91: 0 | BC91: 0 | BD91: 0 | BE91: 0 | BF91: 0 | BG91: 0 | BH91: 0 | BI91: 0 | BJ91: 0 | BK91: 0 | BL91: 0 | BM91: 0 | BN91: =SUM(BO91:BZ91) -> 59945 | BO91: =BB91+AO91 -> 0 | BP91: =BC91+AP91 -> 0 | BQ91: =BD91+AQ91 -> 0 | BR91: =BE91+AR91 -> 0 | BS91: =BF91+AS91 -> 0 | BT91: =BG91+AT91 -> 6080 | BU91: =BH91+AU91 -> 8122.5 | BV91: =BI91+AV91 -> 9832.5 | ... BZ91: =BM91+AZ91 -> 9832.5
