Workbook

Sheet Interim2 Pvt
A2: Expense Category | B2: Match | C2: Project Code* | D2: Grouping | E2: Sum of 2026 LE0 | F2: Sum of LE2 Final Submission | G2: Sum of LE3 Final Submission | H2: Sum of LE4 Final Submission | I2: Sum of AP01 | J2: Sum of AP02 | K2: Sum of AP03 | L2: Sum of AP04 | M2: Sum of AP05 | N2: Sum of AP06 | O2: Sum of AP07 | P2: Sum of AP08 | Q2: Sum of AP09 | R2: Sum of AP10 | S2: Sum of AP11 | T2: Sum of AP12 | U2: Sum of 2026 Working Total | V2: Sum of 2026 Working Total to Budget/LE
A3: Expense Category | B3: Match | C3: Project Code* | D3: Grouping | E3: Sum of 2026 LE0 | F3: Sum of LE2 Final Submission | G3: Sum of LE3 Final Submission | H3: Sum of LE4 Final Submission | I3: Sum of AP01 | J3: Sum of AP02 | K3: Sum of AP03 | L3: Sum of AP04 | M3: Sum of AP05 | N3: Sum of AP06 | O3: Sum of AP07 | P3: Sum of AP08 | Q3: Sum of AP09 | R3: Sum of AP10 | S3: Sum of AP11 | T3: Sum of AP12 | U3: Sum of 2026 Working Total | V3: Sum of 2026 Working Total to Budget/LE
A4: COMPENSATION | B4: Dougherty, Chris_COMPENSATION_CompBenefits001 | C4: CompBenefits001 | D4: None | E4: 3920122.7 | F4: 0 | L4: 0 | M4: 0 | N4: 0 | O4: 0 | P4: 0 | Q4: 0 | R4: 0 | S4: 0 | T4: 0 | U4: 0 | V4: 0
B5: Dougherty, Chris_COMPENSATION_CompBonus001 | C5: CompBonus001 | D5: None | E5: 1729258.8 | F5: 0 | L5: 0 | M5: 0 | N5: 0 | O5: 0 | P5: 0 | Q5: 0 | R5: 0 | S5: 0 | T5: 0 | U5: 0 | V5: 0
B6: Dougherty, Chris_COMPENSATION_CompSalary001 | C6: CompSalary001 | D6: None | E6: 9831851.3 | F6: 15406113 | I6: 1402914.4 | J6: 1397677.6 | K6: 1375284.8 | L6: 1433399.5 | M6: 1510809.2 | N6: 1433646.3 | O6: 1208851.7 | P6: 1221091.4 | Q6: 1194419.3 | R6: 1239489.3 | S6: 1239489.3 | T6: 1254635.1 | U6: 15911708 | V6: 505595.34
B7: Ganesan, Srinivasan_COMPENSATION_CompBenefits001 | C7: CompBenefits001 | D7: None | E7: 0 | F7: 0 | L7: 0 | M7: 0 | N7: 0 | O7: 0 | P7: 0 | Q7: 0 | R7: 0 | S7: 0 | T7: 0 | U7: 0 | V7: 0
B8: Ganesan, Srinivasan_COMPENSATION_CompBonus001 | C8: CompBonus001 | D8: None | E8: 0 | F8: 0 | L8: 0 | M8: 0 | N8: 0 | O8: 0 | P8: 0 | Q8: 0 | R8: 0 | S8: 0 | T8: 0 | U8: 0 | V8: 0
B9: Ganesan, Srinivasan_COMPENSATION_CompSalary001 | C9: CompSalary001 | D9: None | E9: 0 | F9: 0 | N9: 11264.34 | O9: 0 | P9: 0 | Q9: 0 | R9: 0 | S9: 0 | T9: 0 | U9: 11264.34 | V9: 11264.34
B10: Hase, Raj_COMPENSATION_CompSalary001 | C10: CompSalary001 | D10: None | E10: 16484281 | F10: 21816550 | I10: 1733431 | J10: 2659121.5 | K10: 1591278.2 | L10: 2358182.7 | M10: 54442.76 | N10: 1905380.4 | O10: 1785306.7 | P10: 1781851.7 | Q10: 1807055.8 | R10: 1862531.5 | S10: 1871210 | T10: 1871210 | U10: 21281002 | V10: -535547.68
B11: Jajodia, Amit_COMPENSATION_CompBenefits001 | C11: CompBenefits001 | D11: None | E11: 0 | F11: 0 | L11: 0 | M11: 0 | N11: 0 | O11: 0 | P11: 0 | Q11: 0 | R11: 0 | S11: 0 | T11: 0 | U11: 0 | V11: 0
B12: Jajodia, Amit_COMPENSATION_CompBonus001 | C12: CompBonus001 | D12: None | E12: 0 | F12: 0 | L12: 0 | M12: 0 | N12: 0 | O12: 0 | P12: 0 | Q12: 0 | R12: 0 | S12: 0 | T12: 0 | U12: 0 | V12: 0
B13: Jajodia, Amit_COMPENSATION_CompSalary001 | C13: CompSalary001 | D13: None | E13: 0 | F13: 0 | N13: 14481.86 | O13: 0 | P13: 0 | Q13: 0 | R13: 0 | S13: 0 | T13: 0 | U13: 14481.86 | V13: 14481.86
B14: Patel, Apurva_COMPENSATION_CompBenefits001 | C14: CompBenefits001 | D14: None | E14: 7282938.3 | F14: 0 | L14: 0 | M14: 0 | N14: 0 | U14: 0 | V14: 0
B15: Patel, Apurva_COMPENSATION_CompBenefitsCar001 | C15: CompBenefitsCar001 | D15: None | E15: 144000 | F15: 108000 | L15: 0 | M15: 0 | N15: 0 | O15: 12000 | P15: 12000 | Q15: 12000 | R15: 12000 | S15: 12000 | T15: 12000 | U15: 72000 | V15: -36000
B16: Patel, Apurva_COMPENSATION_CompBonus001 | C16: CompBonus001 | D16: None | E16: 3070616.4 | F16: 0 | L16: 0 | M16: 0 | N16: 0 | U16: 0 | V16: 0
B17: Patel, Apurva_COMPENSATION_CompSalary001 | C17: CompSalary001 | D17: None | E17: 794938.18 | F17: 806177.42 | I17: 358290.86 | J17: -25689.76 | K17: 41090.67 | L17: 85849.4 | M17: -59378.36 | N17: -23605.23 | O17: 55233.75 | P17: 55233.75 | Q17: 55233.75 | R17: 55233.75 | S17: 55233.75 | T17: 55233.75 | U17: 707960.08 | V17: -98217.34
B18: Patel, Apurva_COMPENSATION_VacancyFactor001 | C18: VacancyFactor001 | D18: Reserve | E18: -472222.21 | F18: -160000 | L18: 0 | M18: 0 | N18: 0 | O18: -20000 | P18: -20000 | Q18: -20000 | R18: -20000 | S18: -20000 | T18: -20000 | U18: -120000 | V18: 40000
B19: Robertson, Jerome_COMPENSATION_CompBenefits001 | C19: CompBenefits001 | D19: None | E19: 763217.95 | F19: 0 | L19: 0 | M19: 0 | N19: 0 | U19: 0 | V19: 0
B20: Robertson, Jerome_COMPENSATION_CompBonus001 | C20: CompBonus001 | D20: None | E20: 355072.04 | F20: 0 | L20: 0 | M20: 0 | N20: 0 | U20: 0 | V20: 0
B21: Robertson, Jerome_COMPENSATION_CompSalary001 | C21: CompSalary001 | D21: None | E21: 2029390.9 | F21: 3060870.8 | I21: 238474.07 | J21: 255306.3 | K21: 190399.43 | L21: 293204.89 | M21: 312206.58 | N21: 165290.4 | O21: 239240.84 | P21: 265188.33 | Q21: 265188.33 | R21: 278462.33 | S21: 278462.33 | T21: 278462.33 | U21: 3059886.2 | V21: -984.69814
A22: COMPENSATION Total | E22: 45933465 | F22: 41037711 | I22: 3733110.3 | J22: 4286415.7 | K22: 3198053.1 | L22: 4170636.5 | M22: 1818080.2 | N22: 3506458.1 | O22: 3280633 | P22: 3315365.2 | Q22: 3313897.1 | R22: 3427716.8 | S22: 3436395.3 | T22: 3451541.1 | U22: 40938303 | V22: -99408.184
A23: CONTRACTORS | B23: Dougherty, Chris_CONTRACTORS_ColleagueSolutions001 | C23: ColleagueSolutions001 | D23: None | E23: 3014.4 | F23: 4510.8 | L23: 0 | M23: 0 | N23: 0 | O23: 101.2 | P23: 101.2 | Q23: 101.2 | R23: 101.2 | S23: 101.2 | T23: 101.2 | U23: 607.2 | V23: -3903.6
B24: Dougherty, Chris_CONTRACTORS_EnhanceChargeout001 | C24: EnhanceChargeout001 | D24: None | E24: -694940 | F24: -708903.73 | I24: 44340 | J24: -102307.86 | K24: -95095.87 | L24: 157664 | M24: -158270 | N24: -154824 | O24: -11640 | P24: -116400 | Q24: -75000 | R24: -75000 | S24: -75000 | T24: -75000 | U24: -736533.73 | V24: -27630
D25: (blank) | L25: 24147 | M25: -46130 | N25: -215360 | U25: -237343 | V25: -237343
B26: Dougherty, Chris_CONTRACTORS_EP&SCharges001 | C26: EP&SCharges001 | D26: EP&S | E26: 0 | F26: 1080 | I26: 360 | J26: 360 | K26: 360 | L26: 0 | M26: 0 | N26: 0 | O26: 0 | P26: 0 | Q26: 0 | R26: 0 | S26: 0 | T26: 0 | U26: 1080 | V26: 0
D27: (blank) | M27: 550 | N27: 0 | U27: 550 | V27: 550
B28: Dougherty, Chris_CONTRACTORS_IT-CTR0044-OG-US-00 | C28: IT-CTR0044-OG-US-00 | D28: None | E28: 551723.04 | F28: 460642 | L28: 0 | M28: 29102.65 | N28: 67355.9 | O28: 58020 | P28: 58020 | Q28: 62525 | R28: 48020 | S28: 42525 | T28: 34020 | U28: 399588.55 | V28: -61053.45
B29: Dougherty, Chris_CONTRACTORS_IT-CTR0067-OG-CR-00 | C29: IT-CTR0067-OG-CR-00 | D29: None | E29: 0 | F29: 214.49 | I29: 215.71 | J29: -1.22 | K29: 0 | L29: 0 | M29: 0 | N29: 0 | O29: 0 | P29: 0 | Q29: 0 | R29: 0 | S29: 0 | T29: 0 | U29: 214.49 | V29: 0
B30: Dougherty, Chris_CONTRACTORS_IT-CTR0093-OG-US-00 | C30: IT-CTR0093-OG-US-00 | D30: 2024 Transfer | E30: 345518.86 | F30: 345670.24 | I30: 35812 | J30: 40109.44 | K30: 50136.8 | L30: 40109.45 | M30: 40109.45 | N30: 29136.78 | O30: 22297 | P30: 19127 | Q30: 19127 | R30: 19127 | S30: 19127 | T30: 19127 | U30: 353345.92 | V30: 7675.68
B31: Dougherty, Chris_CONTRACTORS_IT-CTR0094-OG-US-00 | C31: IT-CTR0094-OG-US-00 | D31: SAP | E31: 216000 | F31: 197423.06 | I31: 14166 | J31: 18835.37 | K31: 16863.69 | L31: 15866.15 | M31: 15866.16 | N31: 19832.69 | O31: 17000 | P31: 17000 | Q31: 17000 | R31: 17000 | S31: 17000 | T31: 17000 | U31: 203430.06 | V31: 6007
B32: Dougherty, Chris_CONTRACTORS_IT-CTR0096-OG-US-00 | C32: IT-CTR0096-OG-US-00 | D32: SAP | E32: 237888 | F32: 236045.4 | I32: 16372 | J32: 18336.62 | K32: 22920.78 | L32: 18336.63 | M32: 18336.63 | N32: 22920.78 | O32: 19824 | P32: 19824 | Q32: 19824 | R32: 19824 | S32: 19824 | T32: 19824 | U32: 236167.44 | V32: 122.04
B33: Dougherty, Chris_CONTRACTORS_IT-CTR0097-OG-US-00 | C33: IT-CTR0097-OG-US-00 | D33: 2024 Transfer | E33: 230004 | F33: 211390.3 | I33: 14973 | J33: 18162.76 | K33: 19567.54 | L33: 16769.23 | M33: 16769.23 | N33: -21713.76 | O33: 17440 | P33: 17440 | Q33: 17440 | R33: 17440 | S33: 17440 | T33: 17440 | U33: 169168 | V33: -42222.3
B34: Dougherty, Chris_CONTRACTORS_IT-CTR0098-OG-US-00 | C34: IT-CTR0098-OG-US-00 | D34: 2024 Transfer | E34: 187200 | F34: 185657.15 | I34: 12857 | J34: 18823.15 | K34: 13577 | L34: 14400 | M34: 17263 | N34: 36956.74 | O34: 15600 | P34: 15600 | Q34: 15600 | R34: 15600 | S34: 15600 | T34: 15600 | U34: 207476.89 | V34: 21819.74
B35: Dougherty, Chris_CONTRACTORS_IT-CTR0099-OG-US-00 | C35: IT-CTR0099-OG-US-00 | D35: 2024 Transfer | E35: 141310.95 | F35: 132735.51 | I35: 9654 | J35: 14825.74 | K35: 12851.77 | L35: 7463.62 | M35: 16343.61 | N35: 13997.28 | O35: 6534 | P35: 6534 | Q35: 6534 | R35: 6534 | S35: 6534 | T35: 6534 | U35: 114340.02 | V35: -18395.49
B36: Dougherty, Chris_CONTRACTORS_IT-CTR0101-OG-US-00 | C36: IT-CTR0101-OG-US-00 | D36: None | E36: 97500 | F36: 90751.67 | I36: 10704.42 | J36: 11988.8 | K36: 9558.45 | L36: 6923.07 | M36: 8819.08 | N36: 6012.11 | O36: 6000 | P36: 6000 | Q36: 6000 | R36: 7500 | S36: 7500 | T36: 7500 | U36: 94505.93 | V36: 3754.26
B37: Dougherty, Chris_CONTRACTORS_IT-CTR0102-OG-US-00 | C37: IT-CTR0102-OG-US-00 | D37: None | E37: 107910 | F37: 99679.13 | I37: 6841 | J37: 9759.2 | K37: 7478.93 | L37: 7661.53 | M37: 9759.54 | N37: 8299.79 | O37: 8300 | P37: 8300 | Q37: 8300 | R37: 8300 | S37: 8300 | T37: 8300 | U37: 99599.99 | V37: -79.14
B38: Dougherty, Chris_CONTRACTORS_IT-CTR0103-OG-US-00 | C38: IT-CTR0103-OG-US-00 | D38: None | E38: 87360 | F38: 83873.7 | I38: 11538 | J38: 8258.77 | K38: 1796.93 | L38: 5175.54 | M38: 10565.53 | N38: 3972.93 | O38: 7000 | P38: 7000 | Q38: 7000 | R38: 7000 | S38: 7000 | T38: 7000 | U38: 83307.7 | V38: -566
B39: Dougherty, Chris_CONTRACTORS_IT-CTR0105-OG-US-00 | C39: IT-CTR0105-OG-US-00 | D39: None | E39: 750 | F39: 0 | L39: 0 | M39: 0 | N39: 0 | U39: 0 | V39: 0
B40: Dougherty, Chris_CONTRACTORS_IT-CTR0130-OG-US-00 | C40: IT-CTR0130-OG-US-00 | D40: None | E40: 357000 | F40: 356999.8 | I40: 24570 | J40: 27517.44 | K40: 34397.36 | L40: 27517.89 | M40: 27517.89 | N40: 34397.36 | O40: 29750 | P40: 29750 | Q40: 37050 | R40: 29750 | S40: 29750 | T40: 29750 | U40: 361717.94 | V40: 4718.14
B41: Dougherty, Chris_CONTRACTORS_IT-CTR0132-OT-US-00 | C41: IT-CTR0132-OT-US-00 | D41: None | E41: 1678341.6 | F41: 1647348.4 | I41: 113142.14 | J41: 160853.86 | K41: 137841.36 | L41: 0 | M41: 274558.24 | N41: 137279.12 | O41: 0 | P41: 274558 | Q41: 137279 | R41: 0 | S41: 274558 | T41: 137279 | U41: 1647348.7 | V41: 0.36
B42: Dougherty, Chris_CONTRACTORS_IT-CTR0132-OT-US-00/BDC | C42: IT-CTR0132-OT-US-00/BDC | D42: None | E42: 0 | F42: 0 | L42: 0 | M42: 0 | N42: 0 | O42: 0 | P42: 0 | Q42: 0 | R42: 0 | S42: 0 | U42: 0 | V42: 0
B43: Dougherty, Chris_CONTRACTORS_IT-CTR0132-OT-US-00/Colalborate 360 | C43: IT-CTR0132-OT-US-00/Colalborate 360 | D43: None | E43: 0 | F43: 0 | L43: 0 | M43: 0 | N43: 0 | O43: 0 | P43: 0 | Q43: 0 | R43: 0 | S43: 0 | U43: 0 | V43: 0
B44: Dougherty, Chris_CONTRACTORS_IT-CTR0132-OT-US-00/iERP | C44: IT-CTR0132-OT-US-00/iERP | D44: None | E44: 0 | F44: 0 | L44: 0 | M44: 0 | N44: 0 | O44: 0 | P44: 0 | Q44: 0 | R44: 0 | S44: 0 | U44: 0 | V44: 0
B45: Dougherty, Chris_CONTRACTORS_IT-CTR0132-OT-US-00/S4 Innovation | C45: IT-CTR0132-OT-US-00/S4 Innovation | D45: None | E45: 0 | F45: 0 | L45: 0 | M45: 0 | N45: 0 | O45: 0 | P45: 0 | Q45: 0 | R45: 0 | S45: 0 | U45: 0 | V45: 0
B46: Dougherty, Chris_CONTRACTORS_IT-CTR0132-OT-US-01 | C46: IT-CTR0132-OT-US-01 | D46: None | E46: 0 | F46: -76110 | L46: 0 | M46: -76110 | N46: 0 | O46: 0 | P46: 0 | Q46: 0 | R46: 0 | S46: 0 | T46: 0 | U46: -76110 | V46: 0
B47: Dougherty, Chris_CONTRACTORS_IT-CTR0132-OT-US-02 | C47: IT-CTR0132-OT-US-02 | D47: None | E47: 0 | F47: -136110 | K47: -60000 | L47: 0 | M47: -76110 | N47: 0 | O47: 0 | P47: 0 | Q47: 0 | R47: 0 | S47: 0 | T47: 0 | U47: -136110 | V47: 0
B48: Dougherty, Chris_CONTRACTORS_IT-CTR0132-OT-US-03 | C48: IT-CTR0132-OT-US-03 | D48: None | E48: 0 | F48: -91332 | L48: 0 | M48: -91332 | N48: 0 | O48: 0 | P48: 0 | Q48: 0 | R48: 0 | S48: 0 | T48: 0 | U48: -91332 | V48: 0
B49: Dougherty, Chris_CONTRACTORS_IT-CTR0132-OT-US-04 | C49: IT-CTR0132-OT-US-04 | D49: None | E49: 0 | F49: -213108 | L49: 0 | M49: -213108 | N49: 0 | O49: 0 | P49: 0 | Q49: 0 | R49: 0 | S49: 0 | T49: 0 | U49: -213108 | V49: 0
B50: Dougherty, Chris_CONTRACTORS_IT-CTR0140-OT-US-00 | C50: IT-CTR0140-OT-US-00 | D50: None | E50: 1 | F50: 0 | L50: 0 | M50: 0 | N50: 0 | O50: 0 | P50: 0 | Q50: 0 | R50: 0 | S50: 0 | T50: 0 | U50: 0 | V50: 0
B51: Dougherty, Chris_CONTRACTORS_IT-CTR0147-OG-US-00 | C51: IT-CTR0147-OG-US-00 | D51: None | E51: 178000 | F51: 136206.92 | J51: 53852.77 | K51: 35563.15 | L51: 1016.08 | M51: -9701 | N51: 0 | O51: 0 | P51: 0 | Q51: 0 | R51: 0 | S51: 0 | T51: 0 | U51: 80731 | V51: -55475.92
B52: Dougherty, Chris_CONTRACTORS_IT-CTR0148-OG-US-00 | C52: IT-CTR0148-OG-US-00 | D52: None | E52: 222000 | F52: 134302.4 | J52: 72114.23 | K52: 40652.34 | L52: 64472.48 | M52: -4813.73 | N52: -14788.65 | O52: 0 | P52: 0 | Q52: 0 | R52: 0 | S52: 0 | T52: 0 | U52: 157636.67 | V52: 23334.27
B53: Dougherty, Chris_CONTRACTORS_IT-CTR0150-OG-US-00 | C53: IT-CTR0150-OG-US-00 | D53: None | E53: 100000 | F53: 100000 | L53: 0 | M53: 0 | N53: 0 | O53: 14286 | P53: 14286 | Q53: 14286 | R53: 14286 | S53: 14286 | T53: 14286 | U53: 85716 | V53: -14284
B54: Dougherty, Chris_CONTRACTORS_IT-FBT0066-OG-IN-00 | C54: IT-FBT0066-OG-IN-00 | D54: India | E54: 39781 | F54: 37314.43 | I54: 3217.02 | J54: 2578.49 | K54: 2874.84 | L54: 3540.9 | M54: 2797.94 | N54: 2743.02 | O54: 3159 | P54: 3190 | Q54: 3150 | R54: 3150 | S54: 3150 | T54: 3150 | U54: 36701.21 | V54: -613.22
B55: Dougherty, Chris_CONTRACTORS_IT-FBT0213-OG-US-00 | C55: IT-FBT0213-OG-US-00 | D55: SAP | E55: 948000 | F55: 948000.73 | I55: 59013 | J55: 227334.86 | K55: 185217.87 | L55: 0 | M55: 0 | N55: 0 | O55: 79161 | P55: 79161 | Q55: 79161 | R55: 79161 | S55: 79161 | T55: 80630 | U55: 948000.73 | V55: 0
B56: Dougherty, Chris_CONTRACTORS_IT-FBT0219-OG-US-00 | C56: IT-FBT0219-OG-US-00 | D56: MuleSoft | E56: 71440 | F56: 71440 | L56: 0 | M56: 0 | N56: 0 | P56: 71440 | Q56: 0 | R56: 0 | S56: 0 | T56: 0 | U56: 71440 | V56: 0
B57: Dougherty, Chris_CONTRACTORS_IT-FBT0245-OG-US-00 | C57: IT-FBT0245-OG-US-00 | D57: EIH | E57: 150000 | F57: 149999.65 | I57: 10113 | J57: 11863.11 | K57: 14621.54 | L57: 17284.68 | M57: 12179.44 | N57: 11999.99 | O57: 12000 | P57: 12000 | Q57: 12000 | R57: 12000 | S57: 12000 | T57: 12000 | U57: 150061.76 | V57: 62.11
B58: Dougherty, Chris_CONTRACTORS_IT-FBT0393-OG-JP-00 | C58: IT-FBT0393-OG-JP-00 | D58: (blank) | O58: 9500 | P58: 10125 | Q58: 9500 | R58: 9500 | S58: 10125 | T58: 10125 | U58: 58875 | V58: 58875
B59: Dougherty, Chris_CONTRACTORS_IT-FBT0509-OG-US-00 | C59: IT-FBT0509-OG-US-00 | D59: BlueBoot | E59: 115200 | F59: 89600 | L59: 0 | M59: 0 | N59: 0 | O59: 16400 | P59: 16400 | Q59: 12800 | R59: 12800 | S59: 12800 | T59: 12800 | U59: 84000 | V59: -5600
B60: Dougherty, Chris_CONTRACTORS_IT-FBT0636-OG-IN-00 | C60: IT-FBT0636-OG-IN-00 | D60: India | E60: 73711 | F60: 70191.98 | I60: 5439.05 | J60: 4406.87 | K60: 5062.8 | L60: 6561.09 | M60: 5184.41 | N60: 5082.65 | O60: 6142.58 | P60: 6200 | Q60: 6200 | R60: 6200 | S60: 6200 | T60: 6200 | U60: 68879.45 | V60: -1312.53
B61: Dougherty, Chris_CONTRACTORS_IT-FBT0637-OG-IN-00 | C61: IT-FBT0637-OG-IN-00 | D61: India | E61: 9592 | F61: 9470.88 | I61: 844.81 | J61: 677.12 | K61: 754.94 | L61: 991.85 | M61: 673.53 | N61: 720.34 | O61: 799.33 | P61: 799.33 | Q61: 799.33 | R61: 799.33 | S61: 799.33 | T61: 799.37 | U61: 9458.61 | V61: -12.27
B62: Dougherty, Chris_CONTRACTORS_IT-FBT0770-OT-US-00 | C62: IT-FBT0770-OT-US-00 | D62: (blank) | M62: 28.36 | N62: 0 | U62: 28.36 | V62: 28.36
B63: Dougherty, Chris_CONTRACTORS_IT-FBT0780-OT-US-00 | C63: IT-FBT0780-OT-US-00 | D63: None | E63: 499304.04 | F63: 502636.17 | I63: 30113.96 | J63: 19240.66 | K63: 44681.55 | L63: 28059.24 | M63: 37177.21 | N63: -26229.88 | O63: 11200 | P63: 14000 | Q63: 11200 | R63: 14000 | S63: 11200 | T63: 12000 | U63: 206642.74 | V63: -295993.43
B64: Dougherty, Chris_CONTRACTORS_IT-FBT0801-OG-US-00 | C64: IT-FBT0801-OG-US-00 | D64: None | E64: 216000 | F64: 178669.02 | I64: 13712.98 | J64: 15359.13 | K64: 67493.54 | L64: 42271.62 | M64: 42271.62 | N64: -40929.35 | U64: 140179.54 | V64: -38489.48
B65: Dougherty, Chris_CONTRACTORS_IT-FBT0826-OG-US-00 | C65: IT-FBT0826-OG-US-00 | D65: None | E65: 96720 | F65: 96720.44 | I65: 6643.44 | J65: 5644 | K65: 8304 | L65: 6762 | M65: 9499 | N65: 8310.96 | O65: 8600 | P65: 7900 | Q65: 8600 | R65: 8600 | S65: 8600 | T65: 8968 | U65: 96431.4 | V65: -289.04
B66: Dougherty, Chris_CONTRACTORS_IT-FBT0831-OT-US-00 | C66: IT-FBT0831-OT-US-00 | D66: None | E66: 49000 | F66: 48800.63 | I66: 3356.36 | J66: 3758.72 | K66: 4698.63 | L66: 3758.9 | M66: 659.46 | N66: 4698.63 | O66: 0 | P66: 0 | R66: 12250 | S66: 12250 | T66: 8000 | U66: 53430.7 | V66: 4630.07
B67: Dougherty, Chris_CONTRACTORS_IT-FBT0832-OT-US-00 | C67: IT-FBT0832-OT-US-00 | D67: None | E67: 23000 | F67: 21621.64 | I67: 1355 | J67: 1517.05 | K67: 1896.64 | L67: 4517.3 | M67: -462.14 | N67: 1896.64 | O67: 0 | P67: 0 | R67: 9000 | S67: 3852.95 | T67: 0 | U67: 23573.44 | V67: 1951.8
B68: Dougherty, Chris_CONTRACTORS_IT-MGS0168-OG-US-00 | C68: IT-MGS0168-OG-US-00 | D68: None | E68: 1472196 | F68: 0 | L68: 0 | M68: 0 | N68: 0 | O68: 0 | P68: 0 | Q68: 0 | R68: 0 | S68: 0 | T68: 0 | U68: 0 | V68: 0
B69: Dougherty, Chris_CONTRACTORS_MISC001 | C69: MISC001 | D69: None | E69: 0 | F69: 6251.29 | I69: 20761.89 | J69: 22512.72 | K69: -37023.32 | L69: 128.95 | M69: 288.73 | N69: 8316.07 | O69: 0 | P69: 0 | Q69: 0 | R69: 0 | S69: 0 | T69: 0 | U69: 14985.04 | V69: 8733.75
B70: Dougherty, Chris_CONTRACTORS_POClosure001 | C70: POClosure001 | D70: None | E70: 0 | F70: -30860.66 | I70: 0.34 | J70: -10499.16 | K70: -20361.84 | L70: 0 | M70: 0 | N70: 0 | O70: 0 | P70: 0 | Q70: 0 | R70: 0 | S70: 0 | T70: 0 | U70: -30860.66 | V70: 0
B71: Ganesan, Srinivasan_CONTRACTORS_2026-XFR-0023-A | C71: 2026-XFR-0023-A | D71: 2026 Budget Transfer | E71: 70000 | F71: 0 | L71: 0 | M71: 0 | N71: 0 | O71: 0 | P71: 0 | Q71: 0 | R71: 0 | S71: 0 | T71: 0 | U71: 0 | V71: 0
B72: Ganesan, Srinivasan_CONTRACTORS_2026-XFR-0024-A | C72: 2026-XFR-0024-A | D72: 2026 Budget Transfer | E72: 120000 | F72: 0 | L72: 0 | M72: 0 | N72: 0 | O72: 0 | P72: 0 | Q72: 0 | R72: 0 | S72: 0 | T72: 0 | U72: 0 | V72: 0
B73: Ganesan, Srinivasan_CONTRACTORS_2026-XFR-0043-A | C73: 2026-XFR-0043-A | D73: 2026 Budget Transfer | E73: 70000 | F73: 0 | L73: 0 | M73: 0 | N73: 0 | O73: 0 | P73: 0 | Q73: 0 | R73: 0 | S73: 0 | T73: 0 | U73: 0 | V73: 0
B74: Ganesan, Srinivasan_CONTRACTORS_2026-XFR-0051-A | C74: 2026-XFR-0051-A | D74: 2026 Budget Transfer | E74: 140000 | F74: 0 | L74: 0 | M74: 0 | N74: 0 | O74: 0 | P74: 0 | Q74: 0 | R74: 0 | S74: 0 | T74: 0 | U74: 0 | V74: 0
B75: Ganesan, Srinivasan_CONTRACTORS_EnhanceChargeout001 | C75: EnhanceChargeout001 | D75: None | E75: 0 | F75: 130143 | I75: 91657 | J75: -50311 | K75: 88797 | L75: 142812 | M75: -181452 | N75: 124380 | O75: 0 | P75: 0 | Q75: 0 | R75: 0 | S75: 0 | T75: 38640 | U75: 254523 | V75: 124380
B76: Ganesan, Srinivasan_CONTRACTORS_IT-CTR0040-OG-US-00 | C76: IT-CTR0040-OG-US-00 | D76: None | E76: 0 | F76: 0.15 | J76: -16768 | K76: 12756.15 | L76: 6266.17 | M76: 6266.17 | N76: 7832.72 | O76: -8520 | P76: 0 | Q76: 0 | R76: 0 | S76: 0 | T76: 0 | U76: 7833.21 | V76: 7833.06
B77: Ganesan, Srinivasan_CONTRACTORS_IT-CTR0045-OG-US-00 | C77: IT-CTR0045-OG-US-00 | D77: None | E77: 0 | F77: 3558.41 | I77: 3558.41 | J77: 0 | K77: 0 | L77: 0 | M77: 0 | N77: 0 | O77: 0 | P77: 0 | Q77: 0 | R77: 0 | S77: 0 | T77: 0 | U77: 3558.41 | V77: 0
B78: Ganesan, Srinivasan_CONTRACTORS_IT-CTR0049-OG-US-00 | C78: IT-CTR0049-OG-US-00 | D78: 2026 Budget Transfer | E78: 50000 | F78: 50000 | L78: 0 | M78: 0 | N78: 0 | O78: 8520 | P78: 10000 | Q78: 10000 | R78: 10000 | S78: 11480 | T78: 0 | U78: 50000 | V78: 0
B79: Ganesan, Srinivasan_CONTRACTORS_IT-CTR0075-OG-MX-00 | C79: IT-CTR0075-OG-MX-00 | D79: None | E79: 6000 | F79: 6000 | L79: 0 | M79: 0 | N79: 0 | Q79: 6000 | R79: 0 | S79: 0 | T79: 0 | U79: 6000 | V79: 0
B80: Ganesan, Srinivasan_CONTRACTORS_IT-CTR0076-OG-MX-00 | C80: IT-CTR0076-OG-MX-00 | D80: None | E80: 6000 | F80: 6000 | L80: 0 | M80: 0 | N80: 0 | Q80: 6000 | R80: 0 | S80: 0 | T80: 0 | U80: 6000 | V80: 0
B81: Ganesan, Srinivasan_CONTRACTORS_IT-CTR0077-OG-MX-00 | C81: IT-CTR0077-OG-MX-00 | D81: None | E81: 45000 | F81: 45000 | L81: 0 | M81: 0 | N81: 0 | Q81: 45000 | R81: 0 | S81: 0 | T81: 0 | U81: 45000 | V81: 0
B82: Ganesan, Srinivasan_CONTRACTORS_IT-CTR0149-OG-US-00 | C82: IT-CTR0149-OG-US-00 | D82: None | E82: 515000 | F82: 335362.38 | J82: 66916.99 | K82: 75010.39 | L82: 45158.71 | M82: 45158.71 | N82: 56448.39 | O82: 25000 | P82: 22236 | Q82: 0 | R82: 0 | S82: 0 | T82: 0 | U82: 335929.19 | V82: 566.81
B83: Ganesan, Srinivasan_CONTRACTORS_IT-CTR0153-OG-US-00 | C83: IT-CTR0153-OG-US-00 | D83: None | E83: 0 | F83: 0 | L83: 0 | M83: 0 | N83: 0 | O83: 0 | P83: 0 | Q83: 0 | R83: 0 | S83: 0 | T83: 0 | U83: 0 | V83: 0
B84: Ganesan, Srinivasan_CONTRACTORS_IT-FBT0544-OG-US-00 | C84: IT-FBT0544-OG-US-00 | D84: None | E84: 1452300 | F84: 963567.79 | I84: 48462.57 | J84: 207334.66 | K84: 98620.56 | L84: 116861 | M84: 28181.63 | N84: 293546.2 | O84: 70000 | P84: 70000 | Q84: 70000 | R84: 70000 | S84: 70000 | T84: 54107 | U84: 1197113.6 | V84: 233545.83
B85: Ganesan, Srinivasan_CONTRACTORS_IT-FBT0545-OG-US-00 | C85: IT-FBT0545-OG-US-00 | D85: None | E85: 486372.24 | F85: 426376.62 | I85: 58570.53 | J85: 65599.81 | K85: 81999.28 | L85: 65599.43 | M85: 65599.42 | N85: 66848.25 | O85: 11682 | P85: 0 | Q85: 0 | R85: 0 | S85: 0 | T85: 0 | U85: 415898.72 | V85: -10477.9
B86: Ganesan, Srinivasan_CONTRACTORS_IT-FBT0546-OG-US-00 | C86: IT-FBT0546-OG-US-00 | D86: MuleSoft | E86: 50000 | F86: 50000 | L86: 0 | M86: 0 | N86: 0 | P86: 50000 | Q86: 0 | R86: 0 | S86: 0 | T86: 0 | U86: 50000 | V86: 0
B87: Ganesan, Srinivasan_CONTRACTORS_IT-FBT0657-OG-US-00 | C87: IT-FBT0657-OG-US-00 | D87: MuleSoft | E87: 25000 | F87: 25000 | L87: 0 | M87: 0 | N87: 0 | P87: 25000 | Q87: 0 | R87: 0 | S87: 0 | T87: 0 | U87: 25000 | V87: 0
B88: Ganesan, Srinivasan_CONTRACTORS_IT-FBT0661-OG-US-00 | C88: IT-FBT0661-OG-US-00 | D88: None | E88: 47697 | F88: 53620 | L88: 0 | M88: 5850 | N88: 0 | O88: 20000 | P88: 11847 | R88: 0 | S88: 0 | T88: 0 | U88: 37697 | V88: -15923
B89: Ganesan, Srinivasan_CONTRACTORS_IT-FBT0778-OT-US-00 | C89: IT-FBT0778-OT-US-00 | D89: Metastorm | E89: 25200 | F89: 0 | L89: 0 | M89: 0 | N89: 0 | O89: 0 | P89: 0 | Q89: 0 | R89: 0 | S89: 0 | T89: 0 | U89: 0 | V89: 0
B90: Ganesan, Srinivasan_CONTRACTORS_IT-FBT0784-OG-US-00 | C90: IT-FBT0784-OG-US-00 | D90: None | E90: 1129982.6 | F90: 874707.09 | I90: 77285 | J90: 177053.54 | K90: -2920.45 | L90: 86558.85 | M90: 86558.85 | N90: 98924.39 | O90: 62406 | P90: 62406 | Q90: 62406 | R90: 55438 | S90: 55438 | T90: 55438 | U90: 876992.18 | V90: 2285.09
B91: Ganesan, Srinivasan_CONTRACTORS_IT-FBT0790-OG-US-00 | C91: IT-FBT0790-OG-US-00 | D91: None | E91: 513000 | F91: 384928.75 | I91: 98474.5 | J91: -21757.25 | K91: -81628.5 | L91: -18382.5 | M91: 0 | N91: 0 | O91: 69140 | P91: 69140 | Q91: 69140 | R91: 69140 | S91: 69140 | T91: 62523 | U91: 384929.25 | V91: 0.5
B92: Ganesan, Srinivasan_CONTRACTORS_IT-SFT1205-86-OG-US | C92: IT-SFT1205-86-OG-US | D92: None | E92: 0 | F92: 3710 | J92: 3710 | K92: 0 | L92: 0 | M92: 0 | N92: 0 | O92: 0 | P92: 0 | Q92: 0 | R92: 0 | S92: 0 | T92: 0 | U92: 3710 | V92: 0
B93: Ganesan, Srinivasan_CONTRACTORS_MISC001 | C93: MISC001 | D93: None | E93: 0 | F93: -0.47 | I93: -0.29 | J93: 0.43 | K93: -0.61 | L93: 0.34 | M93: 0.22 | N93: 0.05 | O93: 0 | P93: 0 | Q93: 0 | R93: 0 | S93: 0 | T93: 0 | U93: 0.14 | V93: 0.61
B94: Ganesan, Srinivasan_CONTRACTORS_POClosure001 | C94: POClosure001 | D94: None | E94: 0 | F94: -8178.72 | I94: -879.72 | J94: -0.18 | K94: -7298.82 | L94: 0 | M94: 0 | N94: 0 | O94: 0 | P94: 0 | Q94: 0 | R94: 0 | S94: 0 | T94: 0 | U94: -8178.72 | V94: 0
B95: Hase, Raj_CONTRACTORS_ColleagueSolutions001 | C95: ColleagueSolutions001 | D95: None | E95: 437.38 | F95: 0 | L95: 0 | M95: 0 | N95: 0 | O95: 0 | P95: 0 | Q95: 0 | R95: 0 | S95: 0 | T95: 0 | U95: 0 | V95: 0
B96: Hase, Raj_CONTRACTORS_EnhanceChargeout001 | C96: EnhanceChargeout001 | D96: None | E96: 0 | F96: 0 | I96: 579568 | J96: -598991 | K96: -317436 | L96: 577046 | M96: -397395 | N96: 179883 | U96: 22675 | V96: 22675
B97: Hase, Raj_CONTRACTORS_EP&SCharges001 | C97: EP&SCharges001 | D97: EP&S | E97: 24000 | F97: 18457.8 | I97: 366.24 | J97: 0 | K97: 91.56 | L97: 0 | M97: 0 | N97: 0 | O97: 2000 | P97: 2000 | Q97: 2000 | R97: 2000 | S97: 2000 | T97: 2000 | U97: 12457.8 | V97: -6000
B98: Hase, Raj_CONTRACTORS_IT-FBT0450-OG-US-00 | C98: IT-FBT0450-OG-US-00 | D98: (blank) | M98: 50000 | N98: 0 | P98: 50000 | R98: 50000 | U98: 150000 | V98: 150000
B99: Hase, Raj_CONTRACTORS_MISC001 | C99: MISC001 | D99: None | E99: 0 | F99: 0.34 | I99: -0.1 | J99: 0 | K99: 0.44 | L99: 0 | M99: 0 | N99: 0 | O99: 0 | P99: 0 | Q99: 0 | R99: 0 | S99: 0 | T99: 0 | U99: 0.34 | V99: 0
D100: (blank) | M100: 0 | N100: 0 | U100: 0 | V100: 0
B101: Hase, Raj_CONTRACTORS_POClosure001 | C101: POClosure001 | D101: None | E101: 0 | F101: -4133.14 | I101: -4133.14 | J101: 0 | K101: 0 | L101: 0 | M101: 0 | N101: 0 | O101: 0 | P101: 0 | Q101: 0 | R101: 0 | S101: 0 | T101: 0 | U101: -4133.14 | V101: 0
...

Sheet ERP
V2: =V3-AL3 -> 57848.84
U3: =V3-554586-35645 -> 554347.86 | V3: =SUBTOTAL(9,ERP_8[2026 LE0]) -> 1144578.9 | W3: =SUBTOTAL(9,ERP_8[LE2 Final Submission]) -> 1232202.9 | X3: =SUBTOTAL(9,ERP_8[LE3 Final Submission]) -> 0 | Y3: =SUBTOTAL(9,ERP_8[LE4 Final Submission]) -> 0 | Z3: =SUBTOTAL(9,ERP_8[AP01]) -> 124106 | AA3: =SUBTOTAL(9,ERP_8[AP02]) -> 279597 | AB3: =SUBTOTAL(9,ERP_8[AP03]) -> 270738 | AC3: =SUBTOTAL(9,ERP_8[AP04]) -> 224079 | AD3: =SUBTOTAL(9,ERP_8[AP05]) -> -87798 | AE3: =SUBTOTAL(9,ERP_8[AP06]) -> -72135 | AF3: =SUBTOTAL(9,ERP_8[AP07]) -> 239901.02 | AG3: =SUBTOTAL(9,ERP_8[AP08]) -> -47778 | AH3: =SUBTOTAL(9,ERP_8[AP09]) -> 118477 | AI3: =SUBTOTAL(9,ERP_8[AP10]) -> 175123 | AJ3: =SUBTOTAL(9,ERP_8[AP11]) -> -26320 | AK3: =SUBTOTAL(9,ERP_8[AP12]) -> -111260 | AL3: =SUBTOTAL(9,ERP_8[2026 Working Total]) -> 1086730 | AM3: =SUBTOTAL(9,ERP_8[2026 Working Total to Budget/LE]) -> -145472.85 | AN3: =SUBTOTAL(9,ERP_8[Latest AP Snapshot]) -> 16400 | AO3: =SUBTOTAL(9,ERP_8[Latest AP Variance to Snapshot]) -> -88535 | AP3: =SUBTOTAL(9,ERP_8[YTD Act to Bud/LE]) -> 12780.1 | AQ3: =SUBTOTAL(9,ERP_8[Giveback]) -> 0 | AR3: =SUBTOTAL(9,ERP_8[Other Allocation]) -> -145472.85 | AT3: =SUBTOTAL(9,ERP_8[AP01 LE2]) -> 124106 | AU3: =SUBTOTAL(9,ERP_8[AP02 LE2]) -> 279597 | AV3: =SUBTOTAL(9,ERP_8[AP03 LE2]) -> 270738 | AW3: =SUBTOTAL(9,ERP_8[AP04 LE2]) -> 97715 | AX3: =SUBTOTAL(9,ERP_8[AP05 LE2]) -> 81860 | AY3: =SUBTOTAL(9,ERP_8[AP06 LE2]) -> 59831.92 | AZ3: =SUBTOTAL(9,ERP_8[AP07 LE2]) -> 51860 | BA3: =SUBTOTAL(9,ERP_8[AP08 LE2]) -> 51144 | BB3: =SUBTOTAL(9,ERP_8[AP09 LE2]) -> 64076.95 | BC3: =SUBTOTAL(9,ERP_8[AP10 LE2]) -> 47974 | BD3: =SUBTOTAL(9,ERP_8[AP11 LE2]) -> 47974 | BE3: =SUBTOTAL(9,ERP_8[AP12 LE2]) -> 55326 | BF3: =SUBTOTAL(9,ERP_8[2026 LE2 Working Total]) -> 1232202.9 | BG3: =SUBTOTAL(9,ERP_8[2026 AP01]) -> 124106 | BH3: =SUBTOTAL(9,ERP_8[2026 AP02]) -> 279597 | BI3: =SUBTOTAL(9,ERP_8[2026 AP03]) -> 270738 | BJ3: =SUBTOTAL(9,ERP_8[2026 AP04]) -> 116163 | BK3: =SUBTOTAL(9,ERP_8[2026 AP05]) -> 51100 | BL3: =SUBTOTAL(9,ERP_8[2026 AP06]) -> 69791.92 | BM3: =SUBTOTAL(9,ERP_8[2026 AP07]) -> 69563 | BN3: =SUBTOTAL(9,ERP_8[2026 AP08]) -> 68847 | BO3: =SUBTOTAL(9,ERP_8[2026 AP09]) -> 84949.95 | BP3: =SUBTOTAL(9,ERP_8[2026 AP10]) -> 68847 | BQ3: =SUBTOTAL(9,ERP_8[2026 AP11]) -> 68847 | BR3: =SUBTOTAL(9,ERP_8[2026 AP12]) -> 81097 | BS3: =SUBTOTAL(9,ERP_8[2026 LE0 Submission]) -> 1353646.9
O5: Digital Funded Projects | U5: Submissions | V5: Pre LE2 from Planful | Z5: Working Forecast | AP5: Variance & Giveback Analysis | AT5: Prior Submission | BG5: Pre LE2 from Planful
V6: 0223 Extract | W6: 518 | X6: 821 | Y6: 1023 | Z6: Actual | AA6: Actual | AB6: Actual | AC6: Actual | AD6: Actual | AE6: Actual | AF6: Actual | AG6: Forecast | AH6: Forecast | AI6: Forecast | AJ6: Forecast | AK6: Forecast | AN6: AP07 | AP6: YTD Variance | AQ6: (Input) | AR6: (Calculated) | AT6: LE2 | AU6: LE2 | AV6: LE2 | AW6: LE2 | AX6: LE2 | AY6: LE2 | AZ6: LE2 | BA6: LE2 | BB6: LE2 | BC6: LE2 | BD6: LE2 | BE6: LE2 | BF6: LE2 | BG6: 0223 Planful | BH6: 0223 Planful | BI6: 0223 Planful | BJ6: 0223 Planful | BK6: 0223 Planful | BL6: 0223 Planful | BM6: 0223 Planful | BN6: 0223 Planful | BO6: 0223 Planful | BP6: 0223 Planful | BQ6: 0223 Planful | BR6: 0223 Planful | BS6: 0223 Planful
A7: UID | B7: Match | C7: UID2 | D7: NM | E7: NLT | F7: NPOC | G7: CCL3 | H7: LT Member* | I7: LT Member -1* | J7: Point of Contact | K7: Expense Category | L7: Description* | M7: Vendor* | N7: Cost Center* | O7: Project Code* | P7: Prior Year PO | Q7: 2026 Purchase Order | R7: Pullforward | S7: Grouping | T7: 2026 Budget Comment | U7: 2026 Transfers | V7: 2026 LE0 | W7: LE2 Final Submission | X7: LE3 Final Submission | Y7: LE4 Final Submission | Z7: AP01 | AA7: AP02 | AB7: AP03 | AC7: AP04 | AD7: AP05 | AE7: AP06 | AF7: AP07 | AG7: AP08 | AH7: AP09 | AI7: AP10 | AJ7: AP11 | AK7: AP12 | AL7: 2026 Working Total | AM7: 2026 Working Total to Budget/LE | AN7: Latest AP Snapshot | AO7: Latest AP Variance to Snapshot | AP7: YTD Act to Bud/LE | AQ7: Giveback | AR7: Other Allocation | AS7: Giveback Comments | AT7: AP01 LE2 | AU7: AP02 LE2 | AV7: AP03 LE2 | AW7: AP04 LE2 | AX7: AP05 LE2 | AY7: AP06 LE2 | AZ7: AP07 LE2 | BA7: AP08 LE2 | BB7: AP09 LE2 | BC7: AP10 LE2 | BD7: AP11 LE2 | BE7: AP12 LE2 | BF7: 2026 LE2 Working Total | BG7: 2026 AP01 | BH7: 2026 AP02 | BI7: 2026 AP03 | BJ7: 2026 AP04 | BK7: 2026 AP05 | BL7: 2026 AP06 | BM7: 2026 AP07 | BN7: 2026 AP08 | BO7: 2026 AP09 | BP7: 2026 AP10 | BQ7: 2026 AP11 | BR7: 2026 AP12 | BS7: 2026 LE0 Submission
A8: L-ERP-324 | B8: Maguire, Karla_CONTRACTORS_ColleagueSolutions001 | D8: =_xlfn.TEXTJOIN("_",FALSE,E8,ERP_8[[#This Row],[Expense Category]],ERP_8[[#This Row],[Project Code*]]) -> Dougherty, Chris_CONTRACTORS_ColleagueSolutions001 | E8: Dougherty, Chris | G8: ERP | H8: Dougherty, Chris | I8: Maguire, Karla | J8: Maguire, Karla | K8: CONTRACTORS | L8: Colleague Solutions Delivery Chargebacks | O8: ColleagueSolutions001 | P8: CHW - Ok | Q8: N/A | S8: None | T8: KP- Could you confirm who this line was transferred to? | V8: 1214.4 | W8: 910.8 | AD8: 0 | AE8: 0 | AG8: 101.2 | AH8: 101.2 | AI8: 101.2 | AJ8: 101.2 | AK8: 101.2 | AL8: =SUM(Z8:AK8) -> 506 | AM8: =ERP_8[[#This Row],[2026 Working Total]]-ERP_8[[#This Row],[LE2 Final Submission]] -> -404.8 | AN8: 0 | AO8: =$AE8 - $AN8 -> 0 | AP8: =SUM(ERP_8[[#This Row],[AP01]:[AP07]])-SUM(ERP_8[[#This Row],[AP01 LE2]:[AP07 LE2]]) -> -404.8 | AR8: =ERP_8[[#This Row],[2026 Working Total to Budget/LE]]-ERP_8[[#This Row],[Giveback]] -> -404.8 | AW8: 101.2 | AX8: 101.2 | AY8: 101.2 | AZ8: 101.2 | BA8: 101.2 | BB8: 101.2 | BC8: 101.2 | BD8: 101.2 | BE8: 101.2 | BF8: 910.8 | BJ8: 101.2 | BK8: 101.2 | BL8: 101.2 | BM8: 101.2 | BN8: 101.2 | BO8: 101.2 | BP8: 101.2 | BQ8: 101.2 | BR8: 101.2 | BS8: 910.8
A9: L-ERP-369 | B9: McCormick, Pete_CONTRACTORS_ColleagueSolutions001 | D9: =_xlfn.TEXTJOIN("_",FALSE,E9,ERP_8[[#This Row],[Expense Category]],ERP_8[[#This Row],[Project Code*]]) -> Dougherty, Chris_CONTRACTORS_ColleagueSolutions001 | E9: Dougherty, Chris | G9: ERP | H9: Dougherty, Chris | I9: McCormick, Pete | J9: Maguire, Karla | K9: CONTRACTORS | L9: Colleague Solutions Delivery Chargebacks | O9: ColleagueSolutions001 | P9: CHW - Ok | Q9: N/A | S9: None | V9: 1800 | W9: 3600 | AD9: 0 | AE9: 0 | AG9: 0 | AH9: 0 | AI9: 1800 | AJ9: 0 | AK9: 0 | AL9: =SUM(Z9:AK9) -> 1800 | AM9: =ERP_8[[#This Row],[2026 Working Total]]-ERP_8[[#This Row],[LE2 Final Submission]] -> -1800 | AN9: 0 | AO9: =$AE9 - $AN9 -> 0 | AP9: =SUM(ERP_8[[#This Row],[AP01]:[AP07]])-SUM(ERP_8[[#This Row],[AP01 LE2]:[AP07 LE2]]) -> -3600 | AR9: =ERP_8[[#This Row],[2026 Working Total to Budget/LE]]-ERP_8[[#This Row],[Giveback]] -> -1800 | AW9: 1800 | AX9: 0 | AY9: 1800 | AZ9: 0 | BA9: 0 | BB9: 0 | BC9: 0 | BD9: 0 | BE9: 0 | BF9: 3600 | BJ9: 1800 | BK9: 0 | BL9: 1800 | BM9: 0 | BN9: 0 | BO9: 0 | BP9: 0 | BQ9: 0 | BR9: 0 | BS9: 3600
A10: L-ERP-092 | B10: Dougherty, Chris_CONTRACTORS_EnhanceChargeout001 | D10: =_xlfn.TEXTJOIN("_",FALSE,E10,ERP_8[[#This Row],[Expense Category]],ERP_8[[#This Row],[Project Code*]]) -> Dougherty, Chris_CONTRACTORS_EnhanceChargeout001 | E10: Dougherty, Chris | G10: ERP | H10: Dougherty, Chris | I10: Dougherty, Chris | J10: Maguire, Karla | K10: CONTRACTORS | L10: Enhance Chargeout Cost Centers | N10: 2329946; 2329949 | O10: EnhanceChargeout001 | P10: CHW - Ok ~9500 | S10: None | V10: 0 | W10: -51577 | Z10: 44340 | AA10: -23011 | AB10: -72906 | AC10: 9489 | AD10: -2647 | AE10: 5440 | AF10: 10218.97 | AG10: 0 | AH10: 0 | AI10: 0 | AJ10: 0 | AK10: 0 | AL10: =SUM(Z10:AK10) -> -29076.03 | AM10: =ERP_8[[#This Row],[2026 Working Total]]-ERP_8[[#This Row],[LE2 Final Submission]] -> 22500.97 | AN10: 0 | AO10: =$AE10 - $AN10 -> 5440 | AP10: =SUM(ERP_8[[#This Row],[AP01]:[AP07]])-SUM(ERP_8[[#This Row],[AP01 LE2]:[AP07 LE2]]) -> 22500.97 | AR10: =ERP_8[[#This Row],[2026 Working Total to Budget/LE]]-ERP_8[[#This Row],[Giveback]] -> 22500.97 | AT10: 44340 | AU10: -23011 | AV10: -72906 | AW10: 0 | AX10: 0 | AY10: 0 | AZ10: 0 | BA10: 0 | BB10: 0 | BC10: 0 | BD10: 0 | BE10: 0 | BF10: -51577 | BG10: 44340 | BH10: -23011 | BI10: -72906 | BJ10: 0 | BK10: 0 | BL10: 0 | BM10: 0 | BN10: 0 | BO10: 0 | BP10: 0 | BQ10: 0 | BR10: 0 | BS10: -51577
A11: L-ERP-370 | B11: McCormick, Pete_CONTRACTORS_EnhanceChargeout001 | D11: =_xlfn.TEXTJOIN("_",FALSE,E11,ERP_8[[#This Row],[Expense Category]],ERP_8[[#This Row],[Project Code*]]) -> Dougherty, Chris_CONTRACTORS_EnhanceChargeout001 | E11: Dougherty, Chris | G11: ERP | H11: Dougherty, Chris | I11: McCormick, Pete | J11: Maguire, Karla | K11: CONTRACTORS | L11: Enhance Chargeout Cost Centers | N11: 2329947 | O11: EnhanceChargeout001 | P11: CHW - F/U | S11: None | V11: -694940 | W11: -587120.73 | AA11: -20640.86 | AB11: -10639.87 | AC11: 0.74 | AD11: -75810.34 | AE11: -172301.13 | AF11: 0.43 | AG11: -152040 | AH11: -65840 | AI11: -6640 | AJ11: -72992 | AK11: -146147 | AL11: =SUM(Z11:AK11) -> -723050.03 | AM11: =ERP_8[[#This Row],[2026 Working Total]]-ERP_8[[#This Row],[LE2 Final Submission]] -> -135929.3 | AN11: 0 | AO11: =$AE11 - $AN11 -> -172301.13 | AP11: =SUM(ERP_8[[#This Row],[AP01]:[AP07]])-SUM(ERP_8[[#This Row],[AP01 LE2]:[AP07 LE2]]) -> -67270.3 | AR11: =ERP_8[[#This Row],[2026 Working Total to Budget/LE]]-ERP_8[[#This Row],[Giveback]] -> -135929.3 | AU11: -20640.86 | AV11: -10639.87 | AW11: -55600 | AX11: -6440 | AY11: -43800 | AZ11: -75000 | BA11: -75000 | BB11: -75000 | BC11: -75000 | BD11: -75000 | BE11: -75000 | BF11: -587120.73 | BH11: -20640.86 | BI11: -10639.87 | BJ11: -54600 | BK11: -50000 | BL11: -33840 | BM11: -75000 | BN11: -75000 | BO11: -75000 | BP11: -75000 | BQ11: -75000 | BR11: -75000 | BS11: -619720.73
A12: L-ERP-444 | B12: Meadows, Leslie_CONTRACTORS_EnhanceChargeout001 | D12: =_xlfn.TEXTJOIN("_",FALSE,E12,ERP_8[[#This Row],[Expense Category]],ERP_8[[#This Row],[Project Code*]]) -> Dougherty, Chris_CONTRACTORS_EnhanceChargeout001 | E12: Dougherty, Chris | G12: ERP | H12: Dougherty, Chris | I12: Meadows, Leslie | J12: Maguire, Karla | K12: CONTRACTORS | L12: Enhance Chargeout Cost Centers | N12: 2329948 | O12: EnhanceChargeout001 | P12: CHW - F/U | S12: None | T12: KP - ER #'s in Project Code comments | V12: 0 | W12: -1440 | AA12: -1440 | AB12: 0 | AC12: 0 | AD12: 0 | AE12: -18000 | AF12: 0 | AG12: 0 | AH12: 0 | AI12: 0 | AJ12: 0 | AK12: 0 | AL12: =SUM(Z12:AK12) -> -19440 | AM12: =ERP_8[[#This Row],[2026 Working Total]]-ERP_8[[#This Row],[LE2 Final Submission]] -> -18000 | AN12: 0 | AO12: =$AE12 - $AN12 -> -18000 | AP12: =SUM(ERP_8[[#This Row],[AP01]:[AP07]])-SUM(ERP_8[[#This Row],[AP01 LE2]:[AP07 LE2]]) -> -18000 | AR12: =ERP_8[[#This Row],[2026 Working Total to Budget/LE]]-ERP_8[[#This Row],[Giveback]] -> -18000 | AU12: -1440 | AV12: 0 | AW12: 0 | AX12: 0 | AY12: 0 | AZ12: 0 | BA12: 0 | BB12: 0 | BC12: 0 | BD12: 0 | BE12: 0 | BF12: -1440 | BH12: -1440 | BI12: 0 | BJ12: 0 | BK12: 0 | BL12: 0 | BM12: 0 | BN12: 0 | BO12: 0 | BP12: 0 | BQ12: 0 | BR12: 0 | BS12: -1440
A13: L-ERP-473 | B13: Patel, Nikunj Rohitkumar_CONTRACTORS_EnhanceChargeout001 | D13: =_xlfn.TEXTJOIN("_",FALSE,E13,ERP_8[[#This Row],[Expense Category]],ERP_8[[#This Row],[Project Code*]]) -> Dougherty, Chris_CONTRACTORS_EnhanceChargeout001 | E13: Dougherty, Chris | G13: ERP | H13: Dougherty, Chris | I13: Patel, Nikunj Rohitkumar | J13: Maguire, Karla | K13: CONTRACTORS | L13: Enhance Chargeout Cost Centers | O13: EnhanceChargeout001 | P13: CHW - F/U | S13: None | T13: KP - Where would i be able to get more details on this? Please advise. thank you | V13: 0 | W13: -68766 | AA13: -57216 | AB13: -11550 | AD13: 0 | AE13: 0 | AG13: 0 | AH13: 0 | AI13: 0 | AJ13: 0 | AK13: 0 | AL13: =SUM(Z13:AK13) -> -68766 | AM13: =ERP_8[[#This Row],[2026 Working Total]]-ERP_8[[#This Row],[LE2 Final Submission]] -> 0 | AN13: 0 | AO13: =$AE13 - $AN13 -> 0 | AP13: =SUM(ERP_8[[#This Row],[AP01]:[AP07]])-SUM(ERP_8[[#This Row],[AP01 LE2]:[AP07 LE2]]) -> 0 | AR13: =ERP_8[[#This Row],[2026 Working Total to Budget/LE]]-ERP_8[[#This Row],[Giveback]] -> 0 | AU13: -57216 | AV13: -11550 | AW13: 0 | AX13: 0 | AY13: 0 | AZ13: 0 | BA13: 0 | BB13: 0 | BC13: 0 | BD13: 0 | BE13: 0 | BF13: -68766 | BH13: -57216 | BI13: -11550 | BJ13: 0 | BK13: 0 | BL13: 0 | BM13: 0 | BN13: 0 | BO13: 0 | BP13: 0 | BQ13: 0 | BR13: 0 | BS13: -68766
A14: ERP-026 | B14: Tamavada, Ram_CONTRACTORS_EnhanceChargeout001 | D14: =_xlfn.TEXTJOIN("_",FALSE,E14,ERP_8[[#This Row],[Expense Category]],ERP_8[[#This Row],[Project Code*]]) -> Dougherty, Chris_CONTRACTORS_EnhanceChargeout001 | E14: Dougherty, Chris | G14: ERP | H14: Dougherty, Chris | I14: Tamavada, Ram | J14: Tamavada, Ram | K14: CONTRACTORS | L14: SAP SECURITY CLIENT PROJECTS-IBM | M14: IBM | N14: 2339537 | O14: EnhanceChargeout001 | AC14: 24147 | AD14: -46130 | AE14: -215360 | AF14: 30735.05 | AL14: =SUM(Z14:AK14) -> -206607.95 | AM14: =ERP_8[[#This Row],[2026 Working Total]]-ERP_8[[#This Row],[LE2 Final Submission]] -> -206607.95 | AN14: 0 | AO14: =$AE14 - $AN14 -> -215360 | AP14: =SUM(ERP_8[[#This Row],[AP01]:[AP07]])-SUM(ERP_8[[#This Row],[AP01 LE2]:[AP07 LE2]]) -> -206607.95 | AR14: =ERP_8[[#This Row],[2026 Working Total to Budget/LE]]-ERP_8[[#This Row],[Giveback]] -> -206607.95
A15: ERP-037 | B15: Dougherty, Chris_CONTRACTORS_EP&SCharges001 | D15: =_xlfn.TEXTJOIN("_",FALSE,E15,ERP_8[[#This Row],[Expense Category]],ERP_8[[#This Row],[Project Code*]]) -> Dougherty, Chris_CONTRACTORS_EP&SCharges001 | E15: Dougherty, Chris | G15: ERP | H15: Dougherty, Chris | I15: Dougherty, Chris | J15: Dougherty, Chris | K15: CONTRACTORS | L15: DIGITAL-CITRIX-APPSTREAMING | N15: 2321402 | O15: EP&SCharges001 | AD15: 550 | AE15: 0 | AF15: 0 | AL15: =SUM(Z15:AK15) -> 550 | AM15: =ERP_8[[#This Row],[2026 Working Total]]-ERP_8[[#This Row],[LE2 Final Submission]] -> 550 | AN15: 0 | AO15: =$AE15 - $AN15 -> 0 | AP15: =SUM(ERP_8[[#This Row],[AP01]:[AP07]])-SUM(ERP_8[[#This Row],[AP01 LE2]:[AP07 LE2]]) -> 550 | AR15: =ERP_8[[#This Row],[2026 Working Total to Budget/LE]]-ERP_8[[#This Row],[Giveback]] -> 550
A16: L-ERP-518 | B16: Tamavada, Ram_CONTRACTORS_EP&SCharges001 | D16: =_xlfn.TEXTJOIN("_",FALSE,E16,ERP_8[[#This Row],[Expense Category]],ERP_8[[#This Row],[Project Code*]]) -> Dougherty, Chris_CONTRACTORS_EP&SCharges001 | E16: Dougherty, Chris | G16: ERP | H16: Dougherty, Chris | I16: Tamavada, Ram | J16: Maguire, Karla | K16: CONTRACTORS | L16: Infrastructure Billing Charges | N16: 2320843;2321403 | O16: EP&SCharges001 | P16: CHW - Ok | Q16: N/A | S16: EP&S | V16: 0 | W16: 1080 | Z16: 360 | AA16: 360 | AB16: 360 | AC16: 0 | AD16: 0 | AE16: 0 | AF16: 0 | AG16: 0 | AH16: 0 | AI16: 0 | AJ16: 0 | AK16: 0 | AL16: =SUM(Z16:AK16) -> 1080 | AM16: =ERP_8[[#This Row],[2026 Working Total]]-ERP_8[[#This Row],[LE2 Final Submission]] -> 0 | AN16: 0 | AO16: =$AE16 - $AN16 -> 0 | AP16: =SUM(ERP_8[[#This Row],[AP01]:[AP07]])-SUM(ERP_8[[#This Row],[AP01 LE2]:[AP07 LE2]]) -> 0 | AR16: =ERP_8[[#This Row],[2026 Working Total to Budget/LE]]-ERP_8[[#This Row],[Giveback]] -> 0 | AT16: 360 | AU16: 360 | AV16: 360 | AW16: 0 | AX16: 0 | AY16: 0 | AZ16: 0 | BA16: 0 | BB16: 0 | BC16: 0 | BD16: 0 | BE16: 0 | BF16: 1080 | BG16: 360 | BH16: 360 | BI16: 360 | BJ16: 0 | BK16: 0 | BL16: 0 | BM16: 0 | BN16: 0 | BO16: 0 | BP16: 0 | BQ16: 0 | BR16: 0 | BS16: 1080
A17: L-ERP-439 | B17: Meadows, Leslie_CONTRACTORS_IT-CTR0044-OG-US-00 | D17: =_xlfn.TEXTJOIN("_",FALSE,E17,ERP_8[[#This Row],[Expense Category]],ERP_8[[#This Row],[Project Code*]]) -> Dougherty, Chris_CONTRACTORS_IT-CTR0044-OG-US-00 | E17: Dougherty, Chris | G17: ERP | H17: Dougherty, Chris | I17: Meadows, Leslie | J17: Maguire, Karla | K17: CONTRACTORS | L17: SSCS Services (Karla)_XFR0954 & XFR0934 & XFR0932 & XFR0913 & XFR0940 & XFR0941 | N17: 2321511 | O17: IT-CTR0044-OG-US-00 | S17: None | V17: 551723.04 | W17: 460642 | AC17: 0 | AD17: 29102.65 | AE17: 67355.9 | AF17: 34698.83 | AG17: 81341 | AH17: =42525+20000 -> 62525 | AI17: 48020 | AJ17: 42525 | AK17: 39926 | AL17: =SUM(Z17:AK17) -> 405494.38 | AM17: =ERP_8[[#This Row],[2026 Working Total]]-ERP_8[[#This Row],[LE2 Final Submission]] -> -55147.62 | AN17: 0 | AO17: =$AE17 - $AN17 -> 67355.9 | AP17: =SUM(ERP_8[[#This Row],[AP01]:[AP07]])-SUM(ERP_8[[#This Row],[AP01 LE2]:[AP07 LE2]]) -> -138125.62 | AQ17: -91081 | AR17: =ERP_8[[#This Row],[2026 Working Total to Budget/LE]]-ERP_8[[#This Row],[Giveback]] -> 35933.38 | AS17: testing factory adjustment | AW17: 36666 | AX17: 141912 | AY17: 49848 | AZ17: 40857 | BA17: 40681 | BB17: 37645 | BC17: 37694 | BD17: 37645 | BE17: 37694 | BF17: 460642 | BJ17: 61303 | BK17: 61303 | BL17: 61303 | BM17: 61303 | BN17: 61303 | BO17: 61303 | BP17: 61303 | BQ17: 61303 | BR17: 61303 | BS17: 551727
A18: L-ERP-323 | B18: Maguire, Karla_CONTRACTORS_IT-CTR0067-OG-CR-00 | D18: =_xlfn.TEXTJOIN("_",FALSE,E18,ERP_8[[#This Row],[Expense Category]],ERP_8[[#This Row],[Project Code*]]) -> Dougherty, Chris_CONTRACTORS_IT-CTR0067-OG-CR-00 | E18: Dougherty, Chris | G18: ERP | H18: Dougherty, Chris | I18: Maguire, Karla | J18: Maguire, Karla | K18: CONTRACTORS | L18: *RonMendler*_EPS203076 - Edicom CR Recepcion Enero-Diciembre 2025 | O18: IT-CTR0067-OG-CR-00 | S18: None | V18: 0 | W18: 214.49 | Z18: 215.71 | AA18: -1.22 | AB18: 0 | AD18: 0 | AE18: 0 | AG18: 0 | AH18: 0 | AI18: 0 | AJ18: 0 | AK18: 0 | AL18: =SUM(Z18:AK18) -> 214.49 | AM18: =ERP_8[[#This Row],[2026 Working Total]]-ERP_8[[#This Row],[LE2 Final Submission]] -> 0 | AN18: 0 | AO18: =$AE18 - $AN18 -> 0 | AP18: =SUM(ERP_8[[#This Row],[AP01]:[AP07]])-SUM(ERP_8[[#This Row],[AP01 LE2]:[AP07 LE2]]) -> 0 | AR18: =ERP_8[[#This Row],[2026 Working Total to Budget/LE]]-ERP_8[[#This Row],[Giveback]] -> 0 | AT18: 215.71 | AU18: -1.22 | AV18: 0 | AW18: 0 | AX18: 0 | AY18: 0 | AZ18: 0 | BA18: 0 | BB18: 0 | BC18: 0 | BD18: 0 | BE18: 0 | BF18: 214.49 | BG18: 215.71 | BH18: -1.22 | BI18: 0 | BJ18: 0 | BK18: 0 | BL18: 0 | BM18: 0 | BN18: 0 | BO18: 0 | BP18: 0 | BQ18: 0 | BR18: 0 | BS18: 214.49
A19: L-ERP-348 | B19: McCormick, Pete_CONTRACTORS_IT-CTR0093-OG-US-00 | D19: =_xlfn.TEXTJOIN("_",FALSE,E19,ERP_8[[#This Row],[Expense Category]],ERP_8[[#This Row],[Project Code*]]) -> Dougherty, Chris_CONTRACTORS_IT-CTR0093-OG-US-00 | E19: Dougherty, Chris | G19: ERP | H19: Dougherty, Chris | I19: McCormick, Pete | J19: Maguire, Karla | K19: CONTRACTORS | L19: SAP Platform Engineers (Judge) | N19: 2329614 | O19: IT-CTR0093-OG-US-00 | Q19: Multiple | S19: 2024 Transfer | V19: 345518.86 | W19: 345670.24 | Z19: 35812 | AA19: 40109.44 | AB19: 50136.8 | AC19: 40109.45 | AD19: 40109.45 | AE19: 29136.78 | AF19: 40109.45 | AG19: 14015 | AH19: 14015 | AI19: 14015 | AJ19: 14015 | AK19: 14015 | AL19: =SUM(Z19:AK19) -> 345598.37 | AM19: =ERP_8[[#This Row],[2026 Working Total]]-ERP_8[[#This Row],[LE2 Final Submission]] -> -71.87 | AN19: 0 | AO19: =$AE19 - $AN19 -> 29136.78 | AP19: =SUM(ERP_8[[#This Row],[AP01]:[AP07]])-SUM(ERP_8[[#This Row],[AP01 LE2]:[AP07 LE2]]) -> 28658.13 | AR19: =ERP_8[[#This Row],[2026 Working Total to Budget/LE]]-ERP_8[[#This Row],[Giveback]] -> -71.87 | AT19: 35812 | AU19: 40109.44 | AV19: 50136.8 | AW19: 40000 | AX19: 28897 | AY19: 28897 | AZ19: 23013 | BA19: 22297 | BB19: 19127 | BC19: 19127 | BD19: 19127 | BE19: 19127 | BF19: 345670.24 | BG19: 35812 | BH19: 40109.44 | BI19: 50136.8 | BJ19: 40000 | BK19: 28897 | BL19: 28897 | BM19: 23013 | BN19: 22297 | BO19: 22297 | BP19: 22297 | BQ19: 22297 | BR19: 22297 | BS19: 358350.24
A20: L-ERP-108 | B20: Dougherty, Chris_CONTRACTORS_IT-CTR0094-OG-US-00 | D20: =_xlfn.TEXTJOIN("_",FALSE,E20,ERP_8[[#This Row],[Expense Category]],ERP_8[[#This Row],[Project Code*]]) -> Dougherty, Chris_CONTRACTORS_IT-CTR0094-OG-US-00 | E20: Dougherty, Chris | G20: ERP | H20: Dougherty, Chris | I20: Dougherty, Chris | J20: Maguire, Karla | K20: CONTRACTORS | L20: BPAI Axway B2Bi - L4 Engineer (ML-0024) | M20: JUDGE TECHNICAL STAFFING | N20: 2137469 | O20: IT-CTR0094-OG-US-00 | Q20: 9501146792 | S20: SAP | V20: 216000 | W20: 197423.06 | Z20: 14166 | AA20: 18835.37 | AB20: 16863.69 | AC20: 15866.15 | AD20: 15866.16 | AE20: 19832.69 | AF20: 15866.15 | AG20: 17000 | AH20: 18134 | AI20: 17000 | AJ20: 17000 | AK20: 17000 | AL20: =SUM(Z20:AK20) -> 203430.21 | AM20: =ERP_8[[#This Row],[2026 Working Total]]-ERP_8[[#This Row],[LE2 Final Submission]] -> 6007.15 | AN20: 0 | AO20: =$AE20 - $AN20 -> 19832.69 | AP20: =SUM(ERP_8[[#This Row],[AP01]:[AP07]])-SUM(ERP_8[[#This Row],[AP01 LE2]:[AP07 LE2]]) -> 4873.15 | AR20: =ERP_8[[#This Row],[2026 Working Total to Budget/LE]]-ERP_8[[#This Row],[Giveback]] -> 6007.15 | AT20: 14166 | AU20: 18835.37 | AV20: 16863.69 | AW20: 11558 | AX20: 17000 | AY20: 17000 | AZ20: 17000 | BA20: 17000 | BB20: 17000 | BC20: 17000 | BD20: 17000 | BE20: 17000 | BF20: 197423.06 | BG20: 14166 | BH20: 18835.37 | BI20: 16863.69 | BJ20: 18000 | BK20: 18000 | BL20: 18000 | BM20: 18000 | BN20: 18000 | BO20: 18000 | BP20: 18000 | BQ20: 18000 | BR20: 18000 | BS20: 211865.06
A21: L-ERP-109 | B21: Dougherty, Chris_CONTRACTORS_IT-CTR0096-OG-US-00 | D21: =_xlfn.TEXTJOIN("_",FALSE,E21,ERP_8[[#This Row],[Expense Category]],ERP_8[[#This Row],[Project Code*]]) -> Dougherty, Chris_CONTRACTORS_IT-CTR0096-OG-US-00 | E21: Dougherty, Chris | G21: ERP | H21: Dougherty, Chris | I21: Dougherty, Chris | J21: Maguire, Karla | K21: CONTRACTORS | L21: SAP PI L4 Engineer | M21: MPHASIS CORPORATION | N21: 2321402 | O21: IT-CTR0096-OG-US-00 | Q21: 9501172399 | S21: SAP | V21: 237888 | W21: 236045.4 | Z21: 16372 | AA21: 18336.62 | AB21: 22920.78 | AC21: 18336.63 | AD21: 18336.63 | AE21: 22920.78 | AF21: 18336.63 | AG21: =19824+1487 -> 21311 | AH21: 19824 | AI21: 19824 | AJ21: 19824 | AK21: 19824 | AL21: =SUM(Z21:AK21) -> 236167.07 | AM21: =ERP_8[[#This Row],[2026 Working Total]]-ERP_8[[#This Row],[LE2 Final Submission]] -> 121.67 | AN21: 0 | AO21: =$AE21 - $AN21 -> 22920.78 | AP21: =SUM(ERP_8[[#This Row],[AP01]:[AP07]])-SUM(ERP_8[[#This Row],[AP01 LE2]:[AP07 LE2]]) -> -1365.33 | AR21: =ERP_8[[#This Row],[2026 Working Total to Budget/LE]]-ERP_8[[#This Row],[Giveback]] -> 121.67 | AT21: 16372 | AU21: 18336.62 | AV21: 22920.78 | AW21: 19824 | AX21: 19824 | AY21: 19824 | AZ21: 19824 | BA21: 19824 | BB21: 19824 | BC21: 19824 | BD21: 19824 | BE21: 19824 | BF21: 236045.4 | BG21: 16372 | BH21: 18336.62 | BI21: 22920.78 | BJ21: 19824 | BK21: 19824 | BL21: 19824 | BM21: 19824 | BN21: 19824 | BO21: 19824 | BP21: 19824 | BQ21: 19824 | BR21: 19824 | BS21: 236045.4
A22: L-ERP-050 | B22: Dougherty, Chris_CONTRACTORS_IT-CTR0097-OG-US-00 | D22: =_xlfn.TEXTJOIN("_",FALSE,E22,ERP_8[[#This Row],[Expense Category]],ERP_8[[#This Row],[Project Code*]]) -> Dougherty, Chris_CONTRACTORS_IT-CTR0097-OG-US-00 | E22: Dougherty, Chris | G22: ERP | H22: Dougherty, Chris | I22: Dougherty, Chris | J22: Maguire, Karla | K22: CONTRACTORS | L22: BPAI IBM B2Bi - GMFT L4 Engineer (ML-0738) | M22: JUDGE TECHNICAL STAFFING | N22: 2321402 | O22: IT-CTR0097-OG-US-00 | Q22: 9501146194 | S22: 2024 Transfer | V22: 230004 | W22: 211390.3 | Z22: 14973 | AA22: 18162.76 | AB22: 19567.54 | AC22: 16769.23 | AD22: 16769.23 | AE22: -21713.76 | AF22: 0 | AG22: 20928 | AH22: 20928 | AI22: 20928 | AJ22: 20928 | AK22: 20928 | AL22: =SUM(Z22:AK22) -> 169168 | AM22: =ERP_8[[#This Row],[2026 Working Total]]-ERP_8[[#This Row],[LE2 Final Submission]] -> -42222.3 | AN22: 0 | AO22: =$AE22 - $AN22 -> -21713.76 | AP22: =SUM(ERP_8[[#This Row],[AP01]:[AP07]])-SUM(ERP_8[[#This Row],[AP01 LE2]:[AP07 LE2]]) -> -59662.3 | AR22: =ERP_8[[#This Row],[2026 Working Total to Budget/LE]]-ERP_8[[#This Row],[Giveback]] -> -42222.3 | AT22: 14973 | AU22: 18162.76 | AV22: 19567.54 | AW22: 19167 | AX22: 17440 | AY22: 17440 | AZ22: 17440 | BA22: 17440 | BB22: 17440 | BC22: 17440 | BD22: 17440 | BE22: 17440 | BF22: 211390.3 | BG22: 14973 | BH22: 18162.76 | BI22: 19567.54 | BJ22: 19167 | BK22: 19167 | BL22: 19167 | BM22: 19167 | BN22: 19167 | BO22: 19167 | BP22: 19167 | BQ22: 19167 | BR22: 19167 | BS22: 225206.3
A23: L-ERP-051 | B23: Dougherty, Chris_CONTRACTORS_IT-CTR0098-OG-US-00 | D23: =_xlfn.TEXTJOIN("_",FALSE,E23,ERP_8[[#This Row],[Expense Category]],ERP_8[[#This Row],[Project Code*]]) -> Dougherty, Chris_CONTRACTORS_IT-CTR0098-OG-US-00 | E23: Dougherty, Chris | G23: ERP | H23: Dougherty, Chris | I23: Dougherty, Chris | J23: Maguire, Karla | K23: CONTRACTORS | L23: BPAI IBM B2Bi - EDI L4 Engineer (ML-0728) | M23: COMBINED COMPUTER RESOURCES INC | N23: 2321402 | O23: IT-CTR0098-OG-US-00 | Q23: 9501146188 | S23: 2024 Transfer | V23: 187200 | W23: 185657.15 | Z23: 12857 | AA23: 18823.15 | AB23: 13577 | AC23: 14400 | AD23: 17263 | AE23: 36956.74 | AF23: -1531.12 | AG23: 19743 | AH23: 19743 | AI23: 19743 | AJ23: 19743 | AK23: 19743 | AL23: =SUM(Z23:AK23) -> 211060.77 | AM23: =ERP_8[[#This Row],[2026 Working Total]]-ERP_8[[#This Row],[LE2 Final Submission]] -> 25403.62 | AN23: 0 | AO23: =$AE23 - $AN23 -> 36956.74 | AP23: =SUM(ERP_8[[#This Row],[AP01]:[AP07]])-SUM(ERP_8[[#This Row],[AP01 LE2]:[AP07 LE2]]) -> 4688.62 | AR23: =ERP_8[[#This Row],[2026 Working Total to Budget/LE]]-ERP_8[[#This Row],[Giveback]] -> 25403.62 | AT23: 12857 | AU23: 18823.15 | AV23: 13577 | AW23: 15600 | AX23: 15600 | AY23: 15600 | AZ23: 15600 | BA23: 15600 | BB23: 15600 | BC23: 15600 | BD23: 15600 | BE23: 15600 | BF23: 185657.15 | BG23: 12857 | BH23: 18823.15 | BI23: 13577 | BJ23: 15600 | BK23: 15600 | BL23: 15600 | BM23: 15600 | BN23: 15600 | BO23: 15600 | BP23: 15600 | BQ23: 15600 | BR23: 15600 | BS23: 185657.15
A24: L-ERP-052 | B24: Dougherty, Chris_CONTRACTORS_IT-CTR0099-OG-US-00 | D24: =_xlfn.TEXTJOIN("_",FALSE,E24,ERP_8[[#This Row],[Expense Category]],ERP_8[[#This Row],[Project Code*]]) -> Dougherty, Chris_CONTRACTORS_IT-CTR0099-OG-US-00 | E24: Dougherty, Chris | G24: ERP | H24: Dougherty, Chris | I24: Dougherty, Chris | J24: Maguire, Karla | K24: CONTRACTORS | L24: BPAI MQ/MB - L4 Engineer (ML-0730) | M24: ACCENTURE LLP | N24: 2321402 | O24: IT-CTR0099-OG-US-00 | Q24: 9501155447 | S24: 2024 Transfer | V24: 141310.95 | W24: 132735.51 | Z24: 9654 | AA24: 14825.74 | AB24: 12851.77 | AC24: 7463.62 | AD24: 16343.61 | AE24: 13997.28 | AF24: 16825.13 | AG24: 6534 | AH24: 6534 | AI24: 6534 | AJ24: 6534 | AK24: 6534 | AL24: =SUM(Z24:AK24) -> 124631.15 | AM24: =ERP_8[[#This Row],[2026 Working Total]]-ERP_8[[#This Row],[LE2 Final Submission]] -> -8104.36 | AN24: 0 | AO24: =$AE24 - $AN24 -> 13997.28 | AP24: =SUM(ERP_8[[#This Row],[AP01]:[AP07]])-SUM(ERP_8[[#This Row],[AP01 LE2]:[AP07 LE2]]) -> 12789.64 | AR24: =ERP_8[[#This Row],[2026 Working Total to Budget/LE]]-ERP_8[[#This Row],[Giveback]] -> -8104.36 | AT24: 9654 | AU24: 14825.74 | AV24: 12851.77 | AW24: 11942 | AX24: 10718 | AY24: 9590 | AZ24: 9590 | BA24: 10718 | BB24: 11090 | BC24: 11090 | BD24: 9590 | BE24: 11076 | BF24: 132735.51 | BG24: 9654 | BH24: 14825.74 | BI24: 12851.77 | BJ24: 10870.45 | BK24: 11986 | BL24: 11986 | BM24: 11986 | BN24: 11986 | BO24: 11986 | BP24: 11986 | BQ24: 11986 | BR24: 11986 | BS24: 144089.96
A25: L-ERP-081 | B25: Dougherty, Chris_CONTRACTORS_IT-CTR0101-OG-US-00 | D25: =_xlfn.TEXTJOIN("_",FALSE,E25,ERP_8[[#This Row],[Expense Category]],ERP_8[[#This Row],[Project Code*]]) -> Dougherty, Chris_CONTRACTORS_IT-CTR0101-OG-US-00 | E25: Dougherty, Chris | G25: ERP | H25: Dougherty, Chris | I25: Dougherty, Chris | J25: Maguire, Karla | K25: CONTRACTORS | L25: BPAI IBM B2Bi - GMFT L4 Engineer (ML-0732) | M25: INFOSYS LIMITED | N25: 2321402 | O25: IT-CTR0101-OG-US-00 | Q25: 9501140303 | S25: None | V25: 97500 | W25: 90751.67 | Z25: 10704.42 | AA25: 11988.8 | AB25: 9558.45 | AC25: 6923.07 | AD25: 8819.08 | AE25: 6012.11 | AF25: 6012.51 | AG25: 6000 | AH25: 6000 | AI25: 7500 | AJ25: 7500 | AK25: 7500 | AL25: =SUM(Z25:AK25) -> 94518.44 | AM25: =ERP_8[[#This Row],[2026 Working Total]]-ERP_8[[#This Row],[LE2 Final Submission]] -> 3766.77 | AN25: 0 | AO25: =$AE25 - $AN25 -> 6012.11 | AP25: =SUM(ERP_8[[#This Row],[AP01]:[AP07]])-SUM(ERP_8[[#This Row],[AP01 LE2]:[AP07 LE2]]) -> 3766.77 | AR25: =ERP_8[[#This Row],[2026 Working Total to Budget/LE]]-ERP_8[[#This Row],[Giveback]] -> 3766.77 | AT25: 10704.42 | AU25: 11988.8 | AV25: 9558.45 | AW25: 6000 | AX25: 6000 | AY25: 6000 | AZ25: 6000 | BA25: 6000 | BB25: 6000 | BC25: 7500 | BD25: 7500 | BE25: 7500 | BF25: 90751.67 | BG25: 10704.42 | BH25: 11988.8 | BI25: 9558.45 | BJ25: 8125 | BK25: 8125 | BL25: 8125 | BM25: 8125 | BN25: 8125 | BO25: 8125 | BP25: 8125 | BQ25: 8125 | BR25: 8125 | BS25: 105376.67
A26: L-ERP-082 | B26: Dougherty, Chris_CONTRACTORS_IT-CTR0102-OG-US-00 | D26: =_xlfn.TEXTJOIN("_",FALSE,E26,ERP_8[[#This Row],[Expense Category]],ERP_8[[#This Row],[Project Code*]]) -> Dougherty, Chris_CONTRACTORS_IT-CTR0102-OG-US-00 | E26: Dougherty, Chris | G26: ERP | H26: Dougherty, Chris | I26: Dougherty, Chris | J26: Maguire, Karla | K26: CONTRACTORS | L26: BPAI AutoSys/UC4 - L4 Engineer (ML-0733) | M26: INFOSYS LIMITED | N26: 2321402 | O26: IT-CTR0102-OG-US-00 | Q26: 9501145077 | S26: None | V26: 107910 | W26: 99679.13 | Z26: 6841 | AA26: 9759.2 | AB26: 7478.93 | AC26: 7661.53 | AD26: 9759.54 | AE26: 8299.79 | AF26: 6840.67 | AG26: 9300 | AH26: 8300 | AI26: 8300 | AJ26: 8300 | AK26: 8300 | AL26: =SUM(Z26:AK26) -> 99140.66 | AM26: =ERP_8[[#This Row],[2026 Working Total]]-ERP_8[[#This Row],[LE2 Final Submission]] -> -538.47 | AN26: 0 | AO26: =$AE26 - $AN26 -> 8299.79 | AP26: =SUM(ERP_8[[#This Row],[AP01]:[AP07]])-SUM(ERP_8[[#This Row],[AP01 LE2]:[AP07 LE2]]) -> -1038.47 | AR26: =ERP_8[[#This Row],[2026 Working Total to Budget/LE]]-ERP_8[[#This Row],[Giveback]] -> -538.47 | AT26: 6841 | AU26: 9759.2 | AV26: 7478.93 | AW26: 8400 | AX26: 8400 | AY26: 8400 | AZ26: 8400 | BA26: 8400 | BB26: 8400 | BC26: 8400 | BD26: 8400 | BE26: 8400 | BF26: 99679.13 | BG26: 6841 | BH26: 9759.2 | BI26: 7478.93 | BJ26: 8992.5 | BK26: 8992.5 | BL26: 8992.5 | BM26: 8992.5 | BN26: 8992.5 | BO26: 8992.5 | BP26: 8992.5 | BQ26: 8992.5 | BR26: 8992.5 | BS26: 105011.63
A27: L-ERP-083 | B27: Dougherty, Chris_CONTRACTORS_IT-CTR0103-OG-US-00 | D27: =_xlfn.TEXTJOIN("_",FALSE,E27,ERP_8[[#This Row],[Expense Category]],ERP_8[[#This Row],[Project Code*]]) -> Dougherty, Chris_CONTRACTORS_IT-CTR0103-OG-US-00 | E27: Dougherty, Chris | G27: ERP | H27: Dougherty, Chris | I27: Dougherty, Chris | J27: Maguire, Karla | K27: CONTRACTORS | L27: BPAI Cross-Functional Audit Specialist (ML-0735) | M27: JUDGE TECHNICAL STAFFING | N27: 2321402 | O27: IT-CTR0103-OG-US-00 | Q27: 9501145076 | S27: None | V27: 87360 | W27: 83873.7 | Z27: 11538 | AA27: 8258.77 | AB27: 1796.93 | AC27: 5175.54 | AD27: 10565.53 | AE27: 3972.93 | AF27: 8113.89 | AG27: 13000 | AH27: 7000 | AI27: 7000 | AJ27: 7000 | AK27: 7000 | AL27: =SUM(Z27:AK27) -> 90421.59 | AM27: =ERP_8[[#This Row],[2026 Working Total]]-ERP_8[[#This Row],[LE2 Final Submission]] -> 6547.89 | AN27: 0 | AO27: =$AE27 - $AN27 -> 3972.93 | AP27: =SUM(ERP_8[[#This Row],[AP01]:[AP07]])-SUM(ERP_8[[#This Row],[AP01 LE2]:[AP07 LE2]]) -> 827.89 | AR27: =ERP_8[[#This Row],[2026 Working Total to Budget/LE]]-ERP_8[[#This Row],[Giveback]] -> 6547.89 | AT27: 11538 | AU27: 8258.77 | AV27: 1796.93 | AW27: 6000 | AX27: 7000 | AY27: 7000 | AZ27: 7000 | BA27: 7000 | BB27: 7000 | BC27: 7000 | BD27: 7000 | BE27: 7280 | BF27: 83873.7 | BG27: 11538 | BH27: 8258.77 | BI27: 1796.93 | BJ27: 7280 | BK27: 7280 | BL27: 7280 | BM27: 7280 | BN27: 7280 | BO27: 7280 | BP27: 7280 | BQ27: 7280 | BR27: 7280 | BS27: 87113.7
A28: L-ERP-440 | B28: Meadows, Leslie_CONTRACTORS_IT-CTR0105-OG-US-00 | D28: =_xlfn.TEXTJOIN("_",FALSE,E28,ERP_8[[#This Row],[Expense Category]],ERP_8[[#This Row],[Project Code*]]) -> Dougherty, Chris_CONTRACTORS_IT-CTR0105-OG-US-00 | E28: Dougherty, Chris | G28: ERP | H28: Dougherty, Chris | I28: Meadows, Leslie | J28: Maguire, Karla | K28: CONTRACTORS | L28: Chargeback / ERP Change Management Solution PA APP | O28: IT-CTR0105-OG-US-00 | Q28: N | S28: None | T28: KP - 'Services Discontinued as per Leslie. | V28: 750 | W28: 0 | AD28: 0 | AE28: 0 | AG28: 0 | AH28: 0 | AI28: 0 | AJ28: 0 | AK28: 0 | AL28: =SUM(Z28:AK28) -> 0 | AM28: =ERP_8[[#This Row],[2026 Working Total]]-ERP_8[[#This Row],[LE2 Final Submission]] -> 0 | AN28: 0 | AO28: =$AE28 - $AN28 -> 0 | AP28: =SUM(ERP_8[[#This Row],[AP01]:[AP07]])-SUM(ERP_8[[#This Row],[AP01 LE2]:[AP07 LE2]]) -> 0 | AQ28: -750 | AR28: =ERP_8[[#This Row],[2026 Working Total to Budget/LE]]-ERP_8[[#This Row],[Giveback]] -> 750 | AS28: Services Discontinued as per Leslie - Kinjal | BF28: 0 | BJ28: 62.5 | BK28: 62.5 | BL28: 62.5 | BM28: 62.5 | BN28: 62.5 | BO28: 62.5 | BP28: 62.5 | BQ28: 62.5 | BR28: 62.5 | BS28: 562.5
A29: L-ERP-366 | B29: McCormick, Pete_CONTRACTORS_IT-CTR0130-OG-US-00 | D29: =_xlfn.TEXTJOIN("_",FALSE,E29,ERP_8[[#This Row],[Expense Category]],ERP_8[[#This Row],[Project Code*]]) -> Dougherty, Chris_CONTRACTORS_IT-CTR0130-OG-US-00 | E29: Dougherty, Chris | G29: ERP | H29: Dougherty, Chris | I29: McCormick, Pete | J29: Maguire, Karla | K29: CONTRACTORS | L29: SAP Basis Engineering Projects (IBM) | N29: 2329614 | O29: IT-CTR0130-OG-US-00 | Q29: 9501143253 | S29: None | T29: PO 9501143253 ($357k) | V29: 357000 | W29: 356999.8 | Z29: 24570 | AA29: 27517.44 | AB29: 34397.36 | AC29: 27517.89 | AD29: 27517.89 | AE29: 34397.36 | AF29: 27517.89 | AG29: 29750 | AH29: 34565 | AI29: 29750 | AJ29: 29750 | AK29: 29750 | AL29: =SUM(Z29:AK29) -> 357000.83 | AM29: =ERP_8[[#This Row],[2026 Working Total]]-ERP_8[[#This Row],[LE2 Final Submission]] -> 1.03 | AN29: 0 | AO29: =$AE29 - $AN29 -> 34397.36 | AP29: =SUM(ERP_8[[#This Row],[AP01]:[AP07]])-SUM(ERP_8[[#This Row],[AP01 LE2]:[AP07 LE2]]) -> -4813.97 | AR29: =ERP_8[[#This Row],[2026 Working Total to Budget/LE]]-ERP_8[[#This Row],[Giveback]] -> 1.03 | AT29: 24570 | AU29: 27517.44 | AV29: 34397.36 | AW29: 32515 | AX29: 29750 | AY29: 29750 | AZ29: 29750 | BA29: 29750 | BB29: 29750 | BC29: 29750 | BD29: 29750 | BE29: 29750 | BF29: 356999.8 | BG29: 24570 | BH29: 27517.44 | BI29: 34397.36 | BJ29: 37163 | BK29: 29750 | BL29: 29750 | BM29: 29750 | BN29: 29750 | BO29: 29750 | BP29: 29750 | BQ29: 29750 | BR29: 29750 | BS29: 361647.8
A30: L-ERP-084 | B30: Dougherty, Chris_CONTRACTORS_IT-CTR0132-OT-US-00 | D30: =_xlfn.TEXTJOIN("_",FALSE,E30,ERP_8[[#This Row],[Expense Category]],ERP_8[[#This Row],[Project Code*]]) -> Dougherty, Chris_CONTRACTORS_IT-CTR0132-OT-US-00 | E30: Dougherty, Chris | G30: ERP | H30: Dougherty, Chris | I30: Dougherty, Chris | J30: Maguire, Karla | K30: CONTRACTORS | L30: 2026 SAP Max Attention Days | M30: Prepaid - SAP AMERICA INC | N30: 2321402 | O30: IT-CTR0132-OT-US-00 | Q30: 9501158603 | S30: None | T30: 5/7 CHW - Updated for soft close on prepaid at 137,279 monthly or AP03 1,647,350 Invoice | V30: 1678341.6 | W30: 1647348.4 | Z30: 113142.14 | AA30: 160853.86 | AB30: 137841.36 | AC30: 0 | AD30: 274558.24 | AE30: 137279.12 | AF30: 0 | AG30: =136998-136998+137279+137279 -> 274558 | AH30: =136998-136998+137279 -> 137279 | AI30: =136998-136998 -> 0 | AJ30: =136998-136998+137279+137279 -> 274558 | AK30: =136998-136998+137279 -> 137279 | AL30: =SUM(Z30:AK30) -> 1647348.7 | AM30: =ERP_8[[#This Row],[2026 Working Total]]-ERP_8[[#This Row],[LE2 Final Submission]] -> 0.36 | AN30: 0 | AO30: =$AE30 - $AN30 -> 137279.12 | AP30: =SUM(ERP_8[[#This Row],[AP01]:[AP07]])-SUM(ERP_8[[#This Row],[AP01 LE2]:[AP07 LE2]]) -> 0.36 | AR30: =ERP_8[[#This Row],[2026 Working Total to Budget/LE]]-ERP_8[[#This Row],[Giveback]] -> 0.36 | AS30: 5/7 CHW - Diff is prepaid amort on invoiced amt | AT30: 113142.14 | AU30: 160853.86 | AV30: 137841.36 | AW30: 0 | AX30: 274558 | AY30: 137279 | AZ30: 0 | BA30: 274558 | BB30: 137279 | BC30: 0 | BD30: 274558 | BE30: 137279 | BF30: 1647348.4 | BG30: 113142.14 | BH30: 160853.86 | BI30: 137841.36 | BJ30: 136998 | BK30: 136998 | BL30: 136998 | BM30: 136998 | BN30: 136998 | BO30: 136998 | BP30: 136998 | BQ30: 136998 | BR30: 136998 | BS30: 1644819.4
A31: N-ERP-503 | B31: Dougherty, Chris_CONTRACTORS_IT-CTR0132-OT-US-00/BDC | D31: =_xlfn.TEXTJOIN("_",FALSE,E31,ERP_8[[#This Row],[Expense Category]],ERP_8[[#This Row],[Project Code*]]) -> Dougherty, Chris_CONTRACTORS_IT-CTR0132-OT-US-00/BDC | E31: Dougherty, Chris | G31: ERP | H31: Dougherty, Chris | I31: Dougherty, Chris | J31: Maguire, Karla | K31: CONTRACTORS | L31: BDC Reclass - 2026 SAP Max Attention Days | O31: IT-CTR0132-OT-US-00/BDC | Q31: 9501158603 | S31: None | V31: =-213108+213108 -> 0 | W31: 0 | AD31: 0 | AE31: 0 | AG31: 0 | AH31: 0 | AI31: 0 | AJ31: 0 | AL31: =SUM(Z31:AK31) -> 0 | AM31: =ERP_8[[#This Row],[2026 Working Total]]-ERP_8[[#This Row],[LE2 Final Submission]] -> 0 | AN31: 0 | AO31: =$AE31 - $AN31 -> 0 | AP31: =SUM(ERP_8[[#This Row],[AP01]:[AP07]])-SUM(ERP_8[[#This Row],[AP01 LE2]:[AP07 LE2]]) -> 0 | AR31: =ERP_8[[#This Row],[2026 Working Total to Budget/LE]]-ERP_8[[#This Row],[Giveback]] -> 0 | AW31: 0 | AX31: 0 | AY31: 0 | AZ31: 0 | BA31: 0 | BB31: 0 | BC31: 0 | BD31: 0 | BF31: 0 | BG31: 0 | BH31: 0 | BI31: 0 | BJ31: 0 | BK31: 0 | BL31: -213108 | BM31: 0 | BN31: 0 | BO31: 0 | BP31: 0 | BQ31: 0 | BR31: 0 | BS31: =SUM(ERP_8[[#This Row],[2026 AP01]:[2026 AP12]]) -> -213108
A32: N-ERP-504 | B32: Dougherty, Chris_CONTRACTORS_IT-CTR0132-OT-US-00/Colalborate 360 | D32: =_xlfn.TEXTJOIN("_",FALSE,E32,ERP_8[[#This Row],[Expense Category]],ERP_8[[#This Row],[Project Code*]]) -> Dougherty, Chris_CONTRACTORS_IT-CTR0132-OT-US-00/Colalborate 360 | E32: Dougherty, Chris | G32: ERP | H32: Dougherty, Chris | I32: Dougherty, Chris | J32: Maguire, Karla | K32: CONTRACTORS | L32: Colalborate 360 Reclass - 2026 SAP Max Attention Days | O32: IT-CTR0132-OT-US-00/Colalborate 360 | Q32: 9501158603 | S32: None | V32: =76110+-76110 -> 0 | W32: 0 | AD32: 0 | AE32: 0 | AG32: 0 | AH32: 0 | AI32: 0 | AJ32: 0 | AL32: =SUM(Z32:AK32) -> 0 | AM32: =ERP_8[[#This Row],[2026 Working Total]]-ERP_8[[#This Row],[LE2 Final Submission]] -> 0 | AN32: 0 | AO32: =$AE32 - $AN32 -> 0 | AP32: =SUM(ERP_8[[#This Row],[AP01]:[AP07]])-SUM(ERP_8[[#This Row],[AP01 LE2]:[AP07 LE2]]) -> 0 | AR32: =ERP_8[[#This Row],[2026 Working Total to Budget/LE]]-ERP_8[[#This Row],[Giveback]] -> 0 | AW32: 0 | AX32: 0 | AY32: 0 | AZ32: 0 | BA32: 0 | BB32: 0 | BC32: 0 | BD32: 0 | BF32: 0 | BG32: 0 | BH32: 0 | BI32: 0 | BJ32: 0 | BK32: 0 | BL32: -76110 | BM32: 0 | BN32: 0 | BO32: 0 | BP32: 0 | BQ32: 0 | BR32: 0 | BS32: =SUM(ERP_8[[#This Row],[2026 AP01]:[2026 AP12]]) -> -76110
A33: N-ERP-505 | B33: Dougherty, Chris_CONTRACTORS_IT-CTR0132-OT-US-00/iERP | D33: =_xlfn.TEXTJOIN("_",FALSE,E33,ERP_8[[#This Row],[Expense Category]],ERP_8[[#This Row],[Project Code*]]) -> Dougherty, Chris_CONTRACTORS_IT-CTR0132-OT-US-00/iERP | E33: Dougherty, Chris | G33: ERP | H33: Dougherty, Chris | I33: Dougherty, Chris | J33: Maguire, Karla | K33: CONTRACTORS | L33: iERP Reclass - 2026 SAP Max Attention Days | O33: IT-CTR0132-OT-US-00/iERP | Q33: 9501158603 | S33: None | V33: =-91332+91332 -> 0 | W33: 0 | AD33: 0 | AE33: 0 | AG33: 0 | AH33: 0 | AI33: 0 | AJ33: 0 | AL33: =SUM(Z33:AK33) -> 0 | AM33: =ERP_8[[#This Row],[2026 Working Total]]-ERP_8[[#This Row],[LE2 Final Submission]] -> 0 | AN33: 0 | AO33: =$AE33 - $AN33 -> 0 | AP33: =SUM(ERP_8[[#This Row],[AP01]:[AP07]])-SUM(ERP_8[[#This Row],[AP01 LE2]:[AP07 LE2]]) -> 0 | AR33: =ERP_8[[#This Row],[2026 Working Total to Budget/LE]]-ERP_8[[#This Row],[Giveback]] -> 0 | AW33: 0 | AX33: 0 | AY33: 0 | AZ33: 0 | BA33: 0 | BB33: 0 | BC33: 0 | BD33: 0 | BF33: 0 | BG33: 0 | BH33: 0 | BI33: 0 | BJ33: 0 | BK33: 0 | BL33: -91332 | BM33: 0 | BN33: 0 | BO33: 0 | BP33: 0 | BQ33: 0 | BR33: 0 | BS33: =SUM(ERP_8[[#This Row],[2026 AP01]:[2026 AP12]]) -> -91332
A34: N-ERP-506 | B34: Dougherty, Chris_CONTRACTORS_IT-CTR0132-OT-US-00/S4 Innovation | D34: =_xlfn.TEXTJOIN("_",FALSE,E34,ERP_8[[#This Row],[Expense Category]],ERP_8[[#This Row],[Project Code*]]) -> Dougherty, Chris_CONTRACTORS_IT-CTR0132-OT-US-00/S4 Innovation | E34: Dougherty, Chris | G34: ERP | H34: Dougherty, Chris | I34: Dougherty, Chris | J34: Maguire, Karla | K34: CONTRACTORS | L34: S4 Innovation Reclass - 2026 SAP Max Attention Days | O34: IT-CTR0132-OT-US-00/S4 Innovation | Q34: 9501158603 | S34: None | V34: =-76110+76110 -> 0 | W34: 0 | AD34: 0 | AE34: 0 | AG34: 0 | AH34: 0 | AI34: 0 | AJ34: 0 | AL34: =SUM(Z34:AK34) -> 0 | AM34: =ERP_8[[#This Row],[2026 Working Total]]-ERP_8[[#This Row],[LE2 Final Submission]] -> 0 | AN34: 0 | AO34: =$AE34 - $AN34 -> 0 | AP34: =SUM(ERP_8[[#This Row],[AP01]:[AP07]])-SUM(ERP_8[[#This Row],[AP01 LE2]:[AP07 LE2]]) -> 0 | AR34: =ERP_8[[#This Row],[2026 Working Total to Budget/LE]]-ERP_8[[#This Row],[Giveback]] -> 0 | AW34: 0 | AX34: 0 | AY34: 0 | AZ34: 0 | BA34: 0 | BB34: 0 | BC34: 0 | BD34: 0 | BF34: 0 | BG34: 0 | BH34: 0 | BI34: 0 | BJ34: 0 | BK34: 0 | BL34: -76110 | BM34: 0 | BN34: 0 | BO34: 0 | BP34: 0 | BQ34: 0 | BR34: 0 | BS34: =SUM(ERP_8[[#This Row],[2026 AP01]:[2026 AP12]]) -> -76110
A35: L-ERP-085 | B35: Dougherty, Chris_CONTRACTORS_IT-CTR0132-OT-US-01 | D35: =_xlfn.TEXTJOIN("_",FALSE,E35,ERP_8[[#This Row],[Expense Category]],ERP_8[[#This Row],[Project Code*]]) -> Dougherty, Chris_CONTRACTORS_IT-CTR0132-OT-US-01 | E35: Dougherty, Chris | G35: ERP | H35: Dougherty, Chris | I35: Dougherty, Chris | J35: Maguire, Karla | K35: CONTRACTORS | L35: Colalborate 360 Reclass - 2026 SAP Max Attention Days | N35: 2321402 | O35: IT-CTR0132-OT-US-01 | Q35: 9501158603 | S35: None | T35: 6/4 CHW - Removed AP06 Forecast as items hit in AP05 | V35: 0 | W35: -76110 | AD35: -76110 | AE35: 0 | AF35: 0 | AG35: 0 | AH35: 0 | AI35: 0 | AJ35: 0 | AK35: 0 | AL35: =SUM(Z35:AK35) -> -76110 | AM35: =ERP_8[[#This Row],[2026 Working Total]]-ERP_8[[#This Row],[LE2 Final Submission]] -> 0 | AN35: 0 | AO35: =$AE35 - $AN35 -> 0 | AP35: =SUM(ERP_8[[#This Row],[AP01]:[AP07]])-SUM(ERP_8[[#This Row],[AP01 LE2]:[AP07 LE2]]) -> 0 | AR35: =ERP_8[[#This Row],[2026 Working Total to Budget/LE]]-ERP_8[[#This Row],[Giveback]] -> 0 | AY35: -76110 | AZ35: 0 | BA35: 0 | BB35: 0 | BC35: 0 | BD35: 0 | BE35: 0 | BF35: -76110 | BL35: -76110 | BM35: 0 | BN35: 0 | BO35: 0 | BP35: 0 | BQ35: 0 | BR35: 0 | BS35: -76110
A36: L-ERP-086 | B36: Dougherty, Chris_CONTRACTORS_IT-CTR0132-OT-US-02 | D36: =_xlfn.TEXTJOIN("_",FALSE,E36,ERP_8[[#This Row],[Expense Category]],ERP_8[[#This Row],[Project Code*]]) -> Dougherty, Chris_CONTRACTORS_IT-CTR0132-OT-US-02 | E36: Dougherty, Chris | G36: ERP | H36: Dougherty, Chris | I36: Dougherty, Chris | J36: Maguire, Karla | K36: CONTRACTORS | L36: S4 Innovation Reclass - 2026 SAP Max Attention Days | N36: 2321402 | O36: IT-CTR0132-OT-US-02 | Q36: 9501158603 | S36: None | T36: 6/4 CHW - Removed AP06 Forecast as items hit in AP05 | V36: 0 | W36: -136110 | AB36: -60000 | AC36: 0 | AD36: -76110 | AE36: 0 | AF36: 0 | AG36: 0 | AH36: 0 | AI36: 0 | AJ36: 0 | AK36: 0 | AL36: =SUM(Z36:AK36) -> -136110 | AM36: =ERP_8[[#This Row],[2026 Working Total]]-ERP_8[[#This Row],[LE2 Final Submission]] -> 0 | AN36: 0 | AO36: =$AE36 - $AN36 -> 0 | AP36: =SUM(ERP_8[[#This Row],[AP01]:[AP07]])-SUM(ERP_8[[#This Row],[AP01 LE2]:[AP07 LE2]]) -> 0 | AR36: =ERP_8[[#This Row],[2026 Working Total to Budget/LE]]-ERP_8[[#This Row],[Giveback]] -> 0 | AV36: -60000 | AW36: 0 | AX36: 0 | AY36: -76110 | AZ36: 0 | BA36: 0 | BB36: 0 | BC36: 0 | BD36: 0 | BE36: 0 | BF36: -136110 | BI36: -60000 | BJ36: 0 | BK36: 0 | BL36: -76110 | BM36: 0 | BN36: 0 | BO36: 0 | BP36: 0 | BQ36: 0 | BR36: 0 | BS36: -136110
A37: L-ERP-087 | B37: Dougherty, Chris_CONTRACTORS_IT-CTR0132-OT-US-03 | D37: =_xlfn.TEXTJOIN("_",FALSE,E37,ERP_8[[#This Row],[Expense Category]],ERP_8[[#This Row],[Project Code*]]) -> Dougherty, Chris_CONTRACTORS_IT-CTR0132-OT-US-03 | E37: Dougherty, Chris | G37: ERP | H37: Dougherty, Chris | I37: Dougherty, Chris | J37: Maguire, Karla | K37: CONTRACTORS | L37: iERP Reclass - 2026 SAP Max Attention Days | N37: 2321402 | O37: IT-CTR0132-OT-US-03 | Q37: 9501158603 | S37: None | T37: 6/4 CHW - Removed AP06 Forecast as items hit in AP05 | V37: 0 | W37: -91332 | AD37: -91332 | AE37: 0 | AF37: 0 | AG37: 0 | AH37: 0 | AI37: 0 | AJ37: 0 | AK37: 0 | AL37: =SUM(Z37:AK37) -> -91332 | AM37: =ERP_8[[#This Row],[2026 Working Total]]-ERP_8[[#This Row],[LE2 Final Submission]] -> 0 | AN37: 0 | AO37: =$AE37 - $AN37 -> 0 | AP37: =SUM(ERP_8[[#This Row],[AP01]:[AP07]])-SUM(ERP_8[[#This Row],[AP01 LE2]:[AP07 LE2]]) -> 0 | AR37: =ERP_8[[#This Row],[2026 Working Total to Budget/LE]]-ERP_8[[#This Row],[Giveback]] -> 0 | AY37: -91332 | AZ37: 0 | BA37: 0 | BB37: 0 | BC37: 0 | BD37: 0 | BE37: 0 | BF37: -91332 | BL37: -91332 | BM37: 0 | BN37: 0 | BO37: 0 | BP37: 0 | BQ37: 0 | BR37: 0 | BS37: -91332
A38: L-ERP-088 | B38: Dougherty, Chris_CONTRACTORS_IT-CTR0132-OT-US-04 | D38: =_xlfn.TEXTJOIN("_",FALSE,E38,ERP_8[[#This Row],[Expense Category]],ERP_8[[#This Row],[Project Code*]]) -> Dougherty, Chris_CONTRACTORS_IT-CTR0132-OT-US-04 | E38: Dougherty, Chris | G38: ERP | H38: Dougherty, Chris | I38: Dougherty, Chris | J38: Maguire, Karla | K38: CONTRACTORS | L38: BDC Reclass - 2026 SAP Max Attention Days | N38: 2321402 | O38: IT-CTR0132-OT-US-04 | Q38: 9501158603 | S38: None | T38: 6/4 CHW - Removed AP06 Forecast as items hit in AP05 | V38: 0 | W38: -213108 | AD38: -213108 | AE38: 0 | AF38: 0 | AG38: 0 | AH38: 0 | AI38: 0 | AJ38: 0 | AK38: 0 | AL38: =SUM(Z38:AK38) -> -213108 | AM38: =ERP_8[[#This Row],[2026 Working Total]]-ERP_8[[#This Row],[LE2 Final Submission]] -> 0 | AN38: 0 | AO38: =$AE38 - $AN38 -> 0 | AP38: =SUM(ERP_8[[#This Row],[AP01]:[AP07]])-SUM(ERP_8[[#This Row],[AP01 LE2]:[AP07 LE2]]) -> 0 | AR38: =ERP_8[[#This Row],[2026 Working Total to Budget/LE]]-ERP_8[[#This Row],[Giveback]] -> 0 | AY38: -213108 | AZ38: 0 | BA38: 0 | BB38: 0 | BC38: 0 | BD38: 0 | BE38: 0 | BF38: -213108 | BL38: -213108 | BM38: 0 | BN38: 0 | BO38: 0 | BP38: 0 | BQ38: 0 | BR38: 0 | BS38: -213108
A39: N-ERP-606 | B39: Meadows, Leslie_CONTRACTORS_IT-CTR0140-OT-US-00 | D39: =_xlfn.TEXTJOIN("_",FALSE,E39,ERP_8[[#This Row],[Expense Category]],ERP_8[[#This Row],[Project Code*]]) -> Dougherty, Chris_CONTRACTORS_IT-CTR0140-OT-US-00 | E39: Dougherty, Chris | G39: ERP | H39: Dougherty, Chris | I39: Meadows, Leslie | J39: Maguire, Karla | K39: CONTRACTORS | L39: Tricentis Tosca Professional Services | M39: TRICENTIS USA CORP | N39: 2321403 | O39: IT-CTR0140-OT-US-00 | Q39: 9501021870 | S39: None | T39: 4/28/26 CHW New add to tie-out 0223 to 0317 Planful Extracts 2026 Tricentis Tosca Professional Services has been reduced from $8,000 to $0 by deferring upgrade/optimization work and will be revisited in 2027 | V39: 1 | W39: 0 | AD39: 0 | AE39: 0 | AG39: 0 | AH39: 0 | AI39: 0 | AJ39: 0 | AK39: 0 | AL39: =SUM(Z39:AK39) -> 0 | AM39: =ERP_8[[#This Row],[2026 Working Total]]-ERP_8[[#This Row],[LE2 Final Submission]] -> 0 | AN39: 0 | AO39: =$AE39 - $AN39 -> 0 | AP39: =SUM(ERP_8[[#This Row],[AP01]:[AP07]])-SUM(ERP_8[[#This Row],[AP01 LE2]:[AP07 LE2]]) -> 0 | AR39: =ERP_8[[#This Row],[2026 Working Total to Budget/LE]]-ERP_8[[#This Row],[Giveback]] -> 0 | AW39: 0 | AX39: 0 | AY39: 0 | AZ39: 0 | BA39: 0 | BB39: 0 | BC39: 0 | BD39: 0 | BE39: 0 | BF39: 0 | BG39: 0 | BH39: 0 | BI39: 0 | BJ39: 0 | BK39: 0 | BL39: 0 | BM39: 0 | BN39: 0 | BO39: 0 | BP39: 0 | BQ39: 0 | BR39: 1 | BS39: =SUM(ERP_8[[#This Row],[2026 AP01]:[2026 AP12]]) -> 1
A40: L-ERP-089 | B40: Dougherty, Chris_CONTRACTORS_IT-CTR0147-OG-US-00 | D40: =_xlfn.TEXTJOIN("_",FALSE,E40,ERP_8[[#This Row],[Expense Category]],ERP_8[[#This Row],[Project Code*]]) -> Dougherty, Chris_CONTRACTORS_IT-CTR0147-OG-US-00 | E40: Dougherty, Chris | G40: ERP | H40: Dougherty, Chris | I40: Dougherty, Chris | J40: Maguire, Karla | K40: CONTRACTORS | L40: Accenture: eWM Integration | M40: ACCENTURE LLP | N40: 2321402 | O40: IT-CTR0147-OG-US-00 | Q40: 9501182158 | S40: None | V40: 178000 | W40: 136206.92 | AA40: 53852.77 | AB40: 35563.15 | AC40: 1016.08 | AD40: -9701 | AE40: 0 | AF40: 0 | AG40: 0 | AH40: 0 | AI40: 0 | AJ40: 0 | AK40: 0 | AL40: =SUM(Z40:AK40) -> 80731 | AM40: =ERP_8[[#This Row],[2026 Working Total]]-ERP_8[[#This Row],[LE2 Final Submission]] -> -55475.92 | AN40: 0 | AO40: =$AE40 - $AN40 -> 0 | AP40: =SUM(ERP_8[[#This Row],[AP01]:[AP07]])-SUM(ERP_8[[#This Row],[AP01 LE2]:[AP07 LE2]]) -> -55475.92 | AR40: =ERP_8[[#This Row],[2026 Working Total to Budget/LE]]-ERP_8[[#This Row],[Giveback]] -> -55475.92 | AU40: 53852.77 | AV40: 35563.15 | AW40: 19053 | AX40: 27738 | AZ40: 0 | BA40: 0 | BB40: 0 | BC40: 0 | BD40: 0 | BE40: 0 | BF40: 136206.92 | BH40: 53852.77 | BI40: 35563.15 | BJ40: 29666.67 | BK40: 29666.67 | BL40: 29666.67 | BM40: 0 | BN40: 0 | BO40: 0 | BP40: 0 | BQ40: 0 | BR40: 0 | BS40: 178415.93
A41: L-ERP-090 | B41: Dougherty, Chris_CONTRACTORS_IT-CTR0148-OG-US-00 | D41: =_xlfn.TEXTJOIN("_",FALSE,E41,ERP_8[[#This Row],[Expense Category]],ERP_8[[#This Row],[Project Code*]]) -> Dougherty, Chris_CONTRACTORS_IT-CTR0148-OG-US-00 | E41: Dougherty, Chris | G41: ERP | H41: Dougherty, Chris | I41: Dougherty, Chris | J41: Maguire, Karla | K41: CONTRACTORS | L41: Accenture: Technical Development Support | M41: ACCENTURE LLP | N41: 2321402 | O41: IT-CTR0148-OG-US-00 | Q41: 9501235860 | S41: None | V41: 222000 | W41: 134302.4 | AA41: 72114.23 | AB41: 40652.34 | AC41: 64472.48 | AD41: -4813.73 | AE41: -14788.65 | AF41: 0 | AG41: 0 | AH41: 0 | AI41: 0 | AJ41: 0 | AK41: 0 | AL41: =SUM(Z41:AK41) -> 157636.67 | AM41: =ERP_8[[#This Row],[2026 Working Total]]-ERP_8[[#This Row],[LE2 Final Submission]] -> 23334.27 | AN41: 0 | AO41: =$AE41 - $AN41 -> -14788.65 | AP41: =SUM(ERP_8[[#This Row],[AP01]:[AP07]])-SUM(ERP_8[[#This Row],[AP01 LE2]:[AP07 LE2]]) -> 23334.27 | AR41: =ERP_8[[#This Row],[2026 Working Total to Budget/LE]]-ERP_8[[#This Row],[Giveback]] -> 23334.27 | AU41: 72114.23 | AV41: 40652.34 | AW41: -11823.57 | AX41: 33359.4 | AZ41: 0 | BA41: 0 | BB41: 0 | BC41: 0 | BD41: 0 | BE41: 0 | BF41: 134302.4 | BH41: 72114.23 | BI41: 40652.34 | BJ41: 37000 | BK41: 37000 | BL41: 37000 | BM41: 0 | BN41: 0 | BO41: 0 | BP41: 0 | BQ41: 0 | BR41: 0 | BS41: 223766.57
A42: L-ERP-091 | B42: Dougherty, Chris_CONTRACTORS_IT-CTR0150-OG-US-00 | D42: =_xlfn.TEXTJOIN("_",FALSE,E42,ERP_8[[#This Row],[Expense Category]],ERP_8[[#This Row],[Project Code*]]) -> Dougherty, Chris_CONTRACTORS_IT-CTR0150-OG-US-00 | E42: Dougherty, Chris | G42: ERP | H42: Dougherty, Chris | I42: Dougherty, Chris | J42: Maguire, Karla | K42: CONTRACTORS | L42: Syniti Knowledge Platform Support | M42: BACKOFFICE ASSOCIATES LLC | N42: 2329946 | O42: IT-CTR0150-OG-US-00 | Q42: 9501234927 | S42: None | V42: 100000 | W42: 100000 | AD42: 0 | AE42: 0 | AG42: 20000 | AH42: 20000 | AI42: 20000 | AJ42: 20000 | AK42: 20000 | AL42: =SUM(Z42:AK42) -> 100000 | AM42: =ERP_8[[#This Row],[2026 Working Total]]-ERP_8[[#This Row],[LE2 Final Submission]] -> 0 | AN42: 0 | AO42: =$AE42 - $AN42 -> 0 | AP42: =SUM(ERP_8[[#This Row],[AP01]:[AP07]])-SUM(ERP_8[[#This Row],[AP01 LE2]:[AP07 LE2]]) -> -44444 | AR42: =ERP_8[[#This Row],[2026 Working Total to Budget/LE]]-ERP_8[[#This Row],[Giveback]] -> 0 | AW42: 11111 | AX42: 11111 | AY42: 11111 | AZ42: 11111 | BA42: 11111 | BB42: 11111 | BC42: 11111 | BD42: 11111 | BE42: 11112 | BF42: 100000 | BJ42: 11111 | BK42: 11111 | BL42: 11111 | BM42: 11111 | BN42: 11111 | BO42: 11111 | BP42: 11111 | BQ42: 11111 | BR42: 11112 | BS42: 100000
A43: L-ERP-535 | B43: Tamavada, Ram_CONTRACTORS_IT-FBT0066-OG-IN-00 | D43: =_xlfn.TEXTJOIN("_",FALSE,E43,ERP_8[[#This Row],[Expense Category]],ERP_8[[#This Row],[Project Code*]]) -> Dougherty, Chris_CONTRACTORS_IT-FBT0066-OG-IN-00 | E43: Dougherty, Chris | G43: ERP | H43: Dougherty, Chris | I43: Tamavada, Ram | J43: Maguire, Karla | K43: CONTRACTORS | L43: India Sales Order Management Support (SAP SME Support) | N43: 2662855 | O43: IT-FBT0066-OG-IN-00 | S43: India | V43: 39781 | W43: 37314.43 | Z43: 3217.02 | AA43: 2578.49 | AB43: 2874.84 | AC43: 3540.9 | AD43: 2797.94 | AE43: 2743.02 | AF43: 3439.23 | AG43: 2909.77 | AH43: 3150 | AI43: 3150 | AJ43: 3150 | AK43: 3150 | AL43: =SUM(Z43:AK43) -> 36701.21 | AM43: =ERP_8[[#This Row],[2026 Working Total]]-ERP_8[[#This Row],[LE2 Final Submission]] -> -613.22 | AN43: 0 | AO43: =$AE43 - $AN43 -> 2743.02 | AP43: =SUM(ERP_8[[#This Row],[AP01]:[AP07]])-SUM(ERP_8[[#This Row],[AP01 LE2]:[AP07 LE2]]) -> -332.99 | AR43: =ERP_8[[#This Row],[2026 Working Total to Budget/LE]]-ERP_8[[#This Row],[Giveback]] -> -613.22 | AT43: 3217.02 | AU43: 2578.49 | AV43: 2874.84 | AW43: 3315.08 | AX43: 3190 | AY43: 3190 | AZ43: 3159 | BA43: 3190 | BB43: 3150 | BC43: 3150 | BD43: 3150 | BE43: 3150 | BF43: 37314.43 | BG43: 3217.02 | BH43: 2578.49 | BI43: 2874.84 | BJ43: 3315.08 | BK43: 3315.08 | BL43: 3315.08 | BM43: 3315.08 | BN43: 3315.08 | BO43: 3315.08 | BP43: 3315.08 | BQ43: 3315.08 | BR43: 3315.12 | BS43: 38506.11
A44: ERP-071 | B44: McCormick, Pete | D44: =_xlfn.TEXTJOIN("_",FALSE,E44,ERP_8[[#This Row],[Expense Category]],ERP_8[[#This Row],[Project Code*]]) -> Dougherty, Chris_CONTRACTORS_IT-FBT0213-OG-US-00 | E44: Dougherty, Chris | G44: ERP | H44: Dougherty, Chris | I44: McCormick, Pete | J44: McCormick, Pete | K44: CONTRACTORS | L44: 2026 IBM SAP SVO Basis Staff Augmentation | M44: IBM | N44: 2329614 | O44: IT-FBT0213-OG-US-00 | P44: ForD | Q44: 9501276544 | T44: 8/3: actuals on line with WBS code FBT0213 | AH44: 75240 | AI44: 75240 | AJ44: -75240 | AK44: -75240 | AL44: =SUM(Z44:AK44) -> 0 | AM44: =ERP_8[[#This Row],[2026 Working Total]]-ERP_8[[#This Row],[LE2 Final Submission]] -> 0 | AO44: =$AE44 - $AN44 -> 0 | AP44: =SUM(ERP_8[[#This Row],[AP01]:[AP07]])-SUM(ERP_8[[#This Row],[AP01 LE2]:[AP07 LE2]]) -> 0 | AR44: =ERP_8[[#This Row],[2026 Working Total to Budget/LE]]-ERP_8[[#This Row],[Giveback]] -> 0
A45: L-ERP-381 | B45: McCormick, Pete_CONTRACTORS_IT-FBT0213-OG-US-00 | D45: =_xlfn.TEXTJOIN("_",FALSE,E45,ERP_8[[#This Row],[Expense Category]],ERP_8[[#This Row],[Project Code*]]) -> Dougherty, Chris_CONTRACTORS_IT-FBT0213-OG-US-00 | E45: Dougherty, Chris | G45: ERP | H45: Dougherty, Chris | I45: McCormick, Pete | J45: Maguire, Karla | K45: CONTRACTORS | L45: SAP Basis Engineering Projects (Compucom) | N45: 2329947 | O45: IT-FBT0213-OG-US-00 | P45: ForD | Q45: Multiple | S45: SAP | T45: PO 9501164195, 9501158807, 9501164196 ($948k) | V45: 948000 | W45: 948000.73 | Z45: 59013 | AA45: 227334.86 | AB45: 185217.87 | AC45: 148174.26 | AD45: -79812.66 | AE45: 30037.13 | AF45: 156085.57 | AG45: 44097 | AH45: 44097 | AI45: 44097 | AJ45: 44097 | AK45: 45562 | AL45: =SUM(Z45:AK45) -> 948000.03 | AM45: =ERP_8[[#This Row],[2026 Working Total]]-ERP_8[[#This Row],[LE2 Final Submission]] -> -0.7 | AN45: 0 | AO45: =$AE45 - $AN45 -> 30037.13 | AP45: =SUM(ERP_8[[#This Row],[AP01]:[AP07]])-SUM(ERP_8[[#This Row],[AP01 LE2]:[AP07 LE2]]) -> 84534.3 | AR45: =ERP_8[[#This Row],[2026 Working Total to Budget/LE]]-ERP_8[[#This Row],[Giveback]] -> -0.7 | AT45: 59013 | AU45: 227334.86 | AV45: 185217.87 | AW45: 79000 | AX45: 29653 | AY45: 0 | AZ45: 61297 | BA45: 61297 | BB45: 61297 | BC45: 61297 | BD45: 61297 | BE45: 61297 | BF45: 948000.73 | BG45: 59013 | BH45: 227334.86 | BI45: 185217.87 | BJ45: 79000 | BK45: 29653 | BL45: 0 | BM45: 79000 | BN45: 79000 | BO45: 79000 | BP45: 79000 | BQ45: 79000 | BR45: 79000 | BS45: 1054218.7
A46: L-ERP-080 | B46: Dougherty, Chris_CONTRACTORS_IT-FBT0219-OG-US-00 | D46: =_xlfn.TEXTJOIN("_",FALSE,E46,ERP_8[[#This Row],[Expense Category]],ERP_8[[#This Row],[Project Code*]]) -> Dougherty, Chris_CONTRACTORS_IT-FBT0219-OG-US-00 | E46: Dougherty, Chris | G46: ERP | H46: Dougherty, Chris | I46: Dougherty, Chris | J46: Maguire, Karla | K46: CONTRACTORS | L46: ESC/AIS APP & Platform Support: ESC/AIS Mulesoft M | O46: IT-FBT0219-OG-US-00 | Q46: N | S46: MuleSoft | V46: 71440 | W46: 71440 | AD46: 0 | AE46: 0 | AG46: 71440 | AH46: 0 | AI46: 0 | AJ46: 0 | AK46: 0 | AL46: =SUM(Z46:AK46) -> 71440 | AM46: =ERP_8[[#This Row],[2026 Working Total]]-ERP_8[[#This Row],[LE2 Final Submission]] -> 0 | AN46: 0 | AO46: =$AE46 - $AN46 -> 0 | AP46: =SUM(ERP_8[[#This Row],[AP01]:[AP07]])-SUM(ERP_8[[#This Row],[AP01 LE2]:[AP07 LE2]]) -> 0 | AR46: =ERP_8[[#This Row],[2026 Working Total to Budget/LE]]-ERP_8[[#This Row],[Giveback]] -> 0 | BA46: 71440 | BB46: 0 | BC46: 0 | BD46: 0 | BE46: 0 | BF46: 71440 | BN46: 71440 | BO46: 0 | BP46: 0 | BQ46: 0 | BR46: 0 | BS46: 71440
A47: L-ERP-315 | B47: Maguire, Karla_CONTRACTORS_IT-FBT0245-OG-US-00 | D47: =_xlfn.TEXTJOIN("_",FALSE,E47,ERP_8[[#This Row],[Expense Category]],ERP_8[[#This Row],[Project Code*]]) -> Dougherty, Chris_CONTRACTORS_IT-FBT0245-OG-US-00 | E47: Dougherty, Chris | G47: ERP | H47: Dougherty, Chris | I47: Maguire, Karla | J47: Maguire, Karla | K47: CONTRACTORS | L47: Enterprise Integration Hub (EIH) - Code repository, DevOps and API | N47: 2320494 | O47: IT-FBT0245-OG-US-00 | S47: EIH | V47: 0 | W47: 0 | Z47: 10113 | AA47: 11863.11 | AB47: -21976.11 | AC47: 0 | AD47: 0 | AE47: 0 | AF47: 0 | AL47: =SUM(Z47:AK47) -> 0 | AM47: =ERP_8[[#This Row],[2026 Working Total]]-ERP_8[[#This Row],[LE2 Final Submission]] -> 0 | AN47: 0 | AO47: =$AE47 - $AN47 -> 0 | AP47: =SUM(ERP_8[[#This Row],[AP01]:[AP07]])-SUM(ERP_8[[#This Row],[AP01 LE2]:[AP07 LE2]]) -> 0 | AR47: =ERP_8[[#This Row],[2026 Working Total to Budget/LE]]-ERP_8[[#This Row],[Giveback]] -> 0 | AT47: 10113 | AU47: 11863.11 | AV47: -21976.11 | BF47: 0 | BG47: 10113 | BH47: 11863.11 | BI47: -21976.11 | BS47: 0
A48: L-ERP-517 | B48: Tamavada, Ram_CONTRACTORS_IT-FBT0245-OG-US-00 | D48: =_xlfn.TEXTJOIN("_",FALSE,E48,ERP_8[[#This Row],[Expense Category]],ERP_8[[#This Row],[Project Code*]]) -> Dougherty, Chris_CONTRACTORS_IT-FBT0245-OG-US-00 | E48: Dougherty, Chris | G48: ERP | H48: Dougherty, Chris | I48: Tamavada, Ram | J48: Maguire, Karla | K48: CONTRACTORS | L48: Enterprise Integration Hub (EIH) - Code repository, DevOps and API | N48: 2320843 | O48: IT-FBT0245-OG-US-00 | S48: EIH | V48: 150000 | W48: 149999.65 | AB48: 36597.65 | AC48: 17284.68 | AD48: 12179.44 | AE48: 11999.99 | AF48: 7772.7 | AG48: 16227 | AH48: 12000 | AI48: 12000 | AJ48: 12000 | AK48: 12000 | AL48: =SUM(Z48:AK48) -> 150061.46 | AM48: =ERP_8[[#This Row],[2026 Working Total]]-ERP_8[[#This Row],[LE2 Final Submission]] -> 61.81 | AN48: 0 | AO48: =$AE48 - $AN48 -> 11999.99 | AP48: =SUM(ERP_8[[#This Row],[AP01]:[AP07]])-SUM(ERP_8[[#This Row],[AP01 LE2]:[AP07 LE2]]) -> -1665.19 | AR48: =ERP_8[[#This Row],[2026 Working Total to Budget/LE]]-ERP_8[[#This Row],[Giveback]] -> 61.81 | AV48: 36597.65 | AW48: 12900 | AX48: 12900 | AY48: 12602 | AZ48: 12500 | BA48: 12500 | BB48: 12500 | BC48: 12500 | BD48: 12500 | BE48: 12500 | BF48: 149999.65 | BI48: 36597.65 | BJ48: 12500 | BK48: 12500 | BL48: 12500 | BM48: 12500 | BN48: 12500 | BO48: 12500 | BP48: 12500 | BQ48: 12500 | BR48: 12500 | BS48: 149097.65
A49: L-ERP-355 | B49: McCormick, Pete_CONTRACTORS_IT-FBT0509-OG-US-00 | D49: =_xlfn.TEXTJOIN("_",FALSE,E49,ERP_8[[#This Row],[Expense Category]],ERP_8[[#This Row],[Project Code*]]) -> Dougherty, Chris_CONTRACTORS_IT-FBT0509-OG-US-00 | E49: Dougherty, Chris | G49: ERP | H49: Dougherty, Chris | I49: McCormick, Pete | J49: Maguire, Karla | K49: CONTRACTORS | L49: SAP BTP Level 4 Engineer | N49: 2329614 | O49: IT-FBT0509-OG-US-00 | S49: BlueBoot | V49: 115200 | W49: 89600 | AC49: 0 | AD49: 0 | AE49: 0 | AF49: 10911.48 | AG49: =12800+3600 -> 16400 | AH49: =12800+3600 -> 16400 | AI49: 12800 | AJ49: 12800 | AK49: 12800 | AL49: =SUM(Z49:AK49) -> 82111.48 | AM49: =ERP_8[[#This Row],[2026 Working Total]]-ERP_8[[#This Row],[LE2 Final Submission]] -> -7488.52 | AN49: 16400 | AO49: =$AE49 - $AN49 -> -16400 | AP49: =SUM(ERP_8[[#This Row],[AP01]:[AP07]])-SUM(ERP_8[[#This Row],[AP01 LE2]:[AP07 LE2]]) -> -14688.52 | AR49: =ERP_8[[#This Row],[2026 Working Total to Budget/LE]]-ERP_8[[#This Row],[Giveback]] -> -7488.52 | AW49: 0 | AX49: 0 | AY49: 12800 | AZ49: 12800 | BA49: 12800 | BB49: 12800 | BC49: 12800 | BD49: 12800 | BE49: 12800 | BF49: 89600 | BJ49: 12800 | BK49: 12800 | BL49: 12800 | BM49: 12800 | BN49: 12800 | BO49: 12800 | BP49: 12800 | BQ49: 12800 | BR49: 12800 | BS49: 115200
A50: L-ERP-536 | B50: Tamavada, Ram_CONTRACTORS_IT-FBT0636-OG-IN-00 | D50: =_xlfn.TEXTJOIN("_",FALSE,E50,ERP_8[[#This Row],[Expense Category]],ERP_8[[#This Row],[Project Code*]]) -> Dougherty, Chris_CONTRACTORS_IT-FBT0636-OG-IN-00 | E50: Dougherty, Chris | G50: ERP | H50: Dougherty, Chris | I50: Tamavada, Ram | J50: Maguire, Karla | K50: CONTRACTORS | L50: India SAP Helpdesk Support / Team Computers L1/L1.5 | N50: 2662855 | O50: IT-FBT0636-OG-IN-00 | S50: India | V50: 73711 | W50: 70191.98 | Z50: 5439.05 | AA50: 4406.87 | AB50: 5062.8 | AC50: 6561.09 | AD50: 5184.41 | AE50: 5082.65 | AF50: 6372.69 | AG50: 5969.89 | AH50: 6200 | AI50: 6200 | AJ50: 6200 | AK50: 6200 | AL50: =SUM(Z50:AK50) -> 68879.45 | AM50: =ERP_8[[#This Row],[2026 Working Total]]-ERP_8[[#This Row],[LE2 Final Submission]] -> -1312.53 | AN50: 6142.58 | AO50: =$AE50 - $AN50 -> -1059.93 | AP50: =SUM(ERP_8[[#This Row],[AP01]:[AP07]])-SUM(ERP_8[[#This Row],[AP01 LE2]:[AP07 LE2]]) -> -1369.48 | AR50: =ERP_8[[#This Row],[2026 Working Total to Budget/LE]]-ERP_8[[#This Row],[Giveback]] -> -1312.53 | AT50: 5439.05 | AU50: 4406.87 | AV50: 5062.8 | AW50: 6142.58 | AX50: 6142.58 | AY50: 6142.58 | AZ50: 6142.58 | BA50: 6142.58 | BB50: 6142.58 | BC50: 6142.58 | BD50: 6142.58 | BE50: 6142.62 | BF50: 70191.98 | BG50: 5439.05 | BH50: 4406.87 | BI50: 5062.8 | BJ50: 6142.58 | BK50: 6142.58 | BL50: 6142.58 | BM50: 6142.58 | BN50: 6142.58 | BO50: 6142.58 | BP50: 6142.58 | BQ50: 6142.58 | BR50: 6142.62 | BS50: 70191.98
A51: L-ERP-537 | B51: Tamavada, Ram_CONTRACTORS_IT-FBT0637-OG-IN-00 | D51: =_xlfn.TEXTJOIN("_",FALSE,E51,ERP_8[[#This Row],[Expense Category]],ERP_8[[#This Row],[Project Code*]]) -> Dougherty, Chris_CONTRACTORS_IT-FBT0637-OG-IN-00 | E51: Dougherty, Chris | G51: ERP | H51: Dougherty, Chris | I51: Tamavada, Ram | J51: Maguire, Karla | K51: CONTRACTORS | L51: India Prime Solution Maintenance | N51: 2662855 | O51: IT-FBT0637-OG-IN-00 | S51: India | V51: 9592 | W51: 9470.88 | Z51: 844.81 | AA51: 677.12 | AB51: 754.94 | AC51: 991.85 | AD51: 673.53 | AE51: 720.34 | AF51: 903.16 | AG51: 695.16 | AH51: 799.33 | AI51: 799.33 | AJ51: 799.33 | AK51: 799.37 | AL51: =SUM(Z51:AK51) -> 9458.27 | AM51: =ERP_8[[#This Row],[2026 Working Total]]-ERP_8[[#This Row],[LE2 Final Submission]] -> -12.61 | AN51: 799.33 | AO51: =$AE51 - $AN51 -> -78.99 | AP51: =SUM(ERP_8[[#This Row],[AP01]:[AP07]])-SUM(ERP_8[[#This Row],[AP01 LE2]:[AP07 LE2]]) -> 91.56 | AR51: =ERP_8[[#This Row],[2026 Working Total to Budget/LE]]-ERP_8[[#This Row],[Giveback]] -> -12.61 | AT51: 844.81 | AU51: 677.12 | AV51: 754.94 | AW51: 799.33 | AX51: 799.33 | AY51: 799.33 | AZ51: 799.33 | BA51: 799.33 | BB51: 799.33 | BC51: 799.33 | BD51: 799.33 | BE51: 799.37 | BF51: 9470.88 | BG51: 844.81 | BH51: 677.12 | BI51: 754.94 | BJ51: 799.33 | BK51: 799.33 | BL51: 799.33 | BM51: 799.33 | BN51: 799.33 | BO51: 799.33 | BP51: 799.33 | BQ51: 799.33 | BR51: 799.37 | BS51: 9470.88
A52: ERP-051 | B52: Tamavada, Ram_CONTRACTORS_IT-FBT0770-OT-US-00 | D52: =_xlfn.TEXTJOIN("_",FALSE,E52,ERP_8[[#This Row],[Expense Category]],ERP_8[[#This Row],[Project Code*]]) -> Dougherty, Chris_CONTRACTORS_IT-FBT0770-OT-US-00 | E52: Dougherty, Chris | G52: ERP | H52: Dougherty, Chris | I52: Tamavada, Ram | J52: Tamavada, Ram | K52: CONTRACTORS | L52: DIGITAL-APPHOSTING-DATABASE-PROJECT | N52: 2320843 | O52: IT-FBT0770-OT-US-00 | AD52: 28.36 | AE52: 0 | AF52: 0 | AL52: =SUM(Z52:AK52) -> 28.36 | AM52: =ERP_8[[#This Row],[2026 Working Total]]-ERP_8[[#This Row],[LE2 Final Submission]] -> 28.36 | AO52: =$AE52 - $AN52 -> 0 | AP52: =SUM(ERP_8[[#This Row],[AP01]:[AP07]])-SUM(ERP_8[[#This Row],[AP01 LE2]:[AP07 LE2]]) -> 28.36 | AR52: =ERP_8[[#This Row],[2026 Working Total to Budget/LE]]-ERP_8[[#This Row],[Giveback]] -> 28.36
A53: L-ERP-441 | B53: Meadows, Leslie_CONTRACTORS_IT-FBT0780-OT-US-00 | D53: =_xlfn.TEXTJOIN("_",FALSE,E53,ERP_8[[#This Row],[Expense Category]],ERP_8[[#This Row],[Project Code*]]) -> Dougherty, Chris_CONTRACTORS_IT-FBT0780-OT-US-00 | E53: Dougherty, Chris | G53: ERP | H53: Dougherty, Chris | I53: Meadows, Leslie | J53: Maguire, Karla | K53: CONTRACTORS | L53: SSCS Operational Support | N53: 2321511 | O53: IT-FBT0780-OT-US-00 | Q53: 9501157382 9501158432 9501157088 | S53: None | T53: AP06 - Accrual Reversal for PO 9500800241(44,938) | V53: 499304.04 | W53: 502636.17 | Z53: 30113.96 | AA53: 19240.66 | AB53: 44681.55 | AC53: 28059.24 | AD53: 37177.21 | AE53: -26229.88 | AF53: 22486.16 | AG53: 14000 | AH53: 41000 | AI53: 42500 | AJ53: 42500 | AK53: 43500 | AL53: =SUM(Z53:AK53) -> 339028.9 | AM53: =ERP_8[[#This Row],[2026 Working Total]]-ERP_8[[#This Row],[LE2 Final Submission]] -> -163607.27 | AN53: 11200 | AO53: =$AE53 - $AN53 -> -37429.88 | AP53: =SUM(ERP_8[[#This Row],[AP01]:[AP07]])-SUM(ERP_8[[#This Row],[AP01 LE2]:[AP07 LE2]]) -> -148107.27 | AR53: =ERP_8[[#This Row],[2026 Working Total to Budget/LE]]-ERP_8[[#This Row],[Giveback]] -> -163607.27 | AT53: 30113.96 | AU53: 19240.66 | AV53: 44681.55 | AW53: 40000 | AX53: 90000 | AY53: 44000 | AZ53: 35600 | BA53: 44000 | BB53: 36000 | BC53: 40000 | BD53: 36000 | BE53: 43000 | BF53: 502636.17 | BG53: 30113.96 | BH53: 19240.66 | BI53: 44681.55 | BJ53: 44995 | BK53: 44995 | BL53: 44995 | BM53: 44995 | BN53: 44995 | BO53: 44995 | BP53: 44995 | BQ53: 44995 | BR53: 44995 | BS53: 498991.17
A54: L-ERP-442 | B54: Meadows, Leslie_CONTRACTORS_IT-FBT0801-OG-US-00 | D54: =_xlfn.TEXTJOIN("_",FALSE,E54,ERP_8[[#This Row],[Expense Category]],ERP_8[[#This Row],[Project Code*]]) -> Dougherty, Chris_CONTRACTORS_IT-FBT0801-OG-US-00 | E54: Dougherty, Chris | G54: ERP | H54: Dougherty, Chris | I54: Meadows, Leslie | J54: Maguire, Karla | K54: CONTRACTORS | L54: SSCS - Functional Support (ACN Testing, IBM testing) | N54: 2321511 | O54: IT-FBT0801-OG-US-00 | S54: None | T54: AP07 have extra auto accrual for $54,481.00 will be reversed in AP08 | V54: 216000 | W54: 178669.02 | Z54: 13712.98 | AA54: 15359.13 | AB54: 67493.54 | AC54: 42271.62 | AD54: 42271.62 | AE54: -40929.35 | AF54: 68752.76 | AG54: 44320 | AL54: =SUM(Z54:AK54) -> 253252.3 | AM54: =ERP_8[[#This Row],[2026 Working Total]]-ERP_8[[#This Row],[LE2 Final Submission]] -> 74583.28 | AO54: =$AE54 - $AN54 -> -40929.35 | AP54: =SUM(ERP_8[[#This Row],[AP01]:[AP07]])-SUM(ERP_8[[#This Row],[AP01 LE2]:[AP07 LE2]]) -> 60263.28 | AQ54: -32339 | AR54: =ERP_8[[#This Row],[2026 Working Total to Budget/LE]]-ERP_8[[#This Row],[Giveback]] -> 106922.28 | AS54: testing factory adjustment | AT54: 13712.98 | AU54: 15359.13 | AV54: 67493.54 | AW54: 4300 | AX54: 35803.37 | AY54: 6000 | AZ54: 6000 | BA54: 6000 | BB54: 6000 | BC54: 6000 | BD54: 6000 | BE54: 6000 | BF54: 178669.02 | BG54: 13712.98 | BH54: 15359.13 | BI54: 67493.54 | BJ54: 18693 | BK54: 18693 | BL54: 18693 | BM54: 18693 | BN54: 18693 | BO54: 18693 | BP54: 18693 | BQ54: 18693 | BR54: 18693 | BS54: 264802.65
A55: L-ERP-443 | B55: Meadows, Leslie_CONTRACTORS_IT-FBT0826-OG-US-00 | D55: =_xlfn.TEXTJOIN("_",FALSE,E55,ERP_8[[#This Row],[Expense Category]],ERP_8[[#This Row],[Project Code*]]) -> Dougherty, Chris_CONTRACTORS_IT-FBT0826-OG-US-00 | E55: Dougherty, Chris | G55: ERP | H55: Dougherty, Chris | I55: Meadows, Leslie | J55: Maguire, Karla | K55: CONTRACTORS | L55: Insight GlobaL: SAP Support Services | N55: 2321511 | O55: IT-FBT0826-OG-US-00 | Q55: KP - 9501160146 | S55: None | V55: 96720 | W55: 96720.44 | Z55: 6643.44 | AA55: 5644 | AB55: 8304 | AC55: 6762 | AD55: 9499 | AE55: 8310.96 | AF55: 6370.04 | AG55: 10130 | AH55: 8600 | AI55: 8600 | AJ55: 8687 | AK55: 8968 | AL55: =SUM(Z55:AK55) -> 96518.44 | AM55: =ERP_8[[#This Row],[2026 Working Total]]-ERP_8[[#This Row],[LE2 Final Submission]] -> -202 | AN55: 8600 | AO55: =$AE55 - $AN55 -> -289.04 | AP55: =SUM(ERP_8[[#This Row],[AP01]:[AP07]])-SUM(ERP_8[[#This Row],[AP01 LE2]:[AP07 LE2]]) -> -4639 | AR55: =ERP_8[[#This Row],[2026 Working Total to Budget/LE]]-ERP_8[[#This Row],[Giveback]] -> -202 | AT55: 6643.44 | AU55: 5644 | AV55: 8304 | AW55: 11029 | AX55: 7812 | AY55: 8184 | AZ55: 8556 | BA55: 7812 | BB55: 8184 | BC55: 8184 | BD55: 7812 | BE55: 8556 | BF55: 96720.44 | BG55: 6643.44 | BH55: 5644 | BI55: 8304 | BJ55: 8184 | BK55: 7812 | BL55: 8184 | BM55: 8556 | BN55: 7812 | BO55: 8184 | BP55: 8184 | BQ55: 7812 | BR55: 8556 | BS55: 93875.44
A56: L-ERP-367 | B56: McCormick, Pete_CONTRACTORS_IT-FBT0831-OT-US-00 | D56: =_xlfn.TEXTJOIN("_",FALSE,E56,ERP_8[[#This Row],[Expense Category]],ERP_8[[#This Row],[Project Code*]]) -> Dougherty, Chris_CONTRACTORS_IT-FBT0831-OT-US-00 | E56: Dougherty, Chris | G56: ERP | H56: Dougherty, Chris | I56: McCormick, Pete | J56: Maguire, Karla | K56: CONTRACTORS | L56: SAP Platform- IBM Power Lab Consulting | N56: 2329614 | O56: IT-FBT0831-OT-US-00 | Q56: 9501155336 | S56: None | V56: 49000 | W56: 48800.63 | Z56: 3356.36 | AA56: 3758.72 | AB56: 4698.63 | AC56: 3758.9 | AD56: 659.46 | AE56: 4698.63 | AF56: 3758.9 | AG56: 0 | AI56: 4061 | AJ56: 12250 | AK56: 8000 | AL56: =SUM(Z56:AK56) -> 49000.6 | AM56: =ERP_8[[#This Row],[2026 Working Total]]-ERP_8[[#This Row],[LE2 Final Submission]] -> 199.97 | AN56: 0 | AO56: =$AE56 - $AN56 -> 4698.63 | AP56: =SUM(ERP_8[[#This Row],[AP01]:[AP07]])-SUM(ERP_8[[#This Row],[AP01 LE2]:[AP07 LE2]]) -> -4509.03 | AR56: =ERP_8[[#This Row],[2026 Working Total to Budget/LE]]-ERP_8[[#This Row],[Giveback]] -> 199.97 | AT56: 3356.36 | AU56: 3758.72 | AV56: 4698.63 | AW56: 0 | AX56: 0 | AY56: 17384.92 | AZ56: 0 | BA56: 0 | BB56: 12250 | BC56: 0 | BD56: 0 | BE56: 7352 | BF56: 48800.63 | BG56: 3356.36 | BH56: 3758.72 | BI56: 4698.63 | BJ56: 0 | BK56: 0 | BL56: 17384.92 | BM56: 0 | BN56: 0 | BO56: 12250 | BP56: 0 | BQ56: 0 | BR56: 12250 | BS56: 53698.63
A57: L-ERP-368 | B57: McCormick, Pete_CONTRACTORS_IT-FBT0832-OT-US-00 | D57: =_xlfn.TEXTJOIN("_",FALSE,E57,ERP_8[[#This Row],[Expense Category]],ERP_8[[#This Row],[Project Code*]]) -> Dougherty, Chris_CONTRACTORS_IT-FBT0832-OT-US-00 | E57: Dougherty, Chris | G57: ERP | H57: Dougherty, Chris | I57: McCormick, Pete | J57: Maguire, Karla | K57: CONTRACTORS | L57: SAP Platform- IBM Power Breakfix Consulting | N57: 2329614 | O57: IT-FBT0832-OT-US-00 | Q57: 9501153160 | S57: None | V57: 23000 | W57: 21621.64 | Z57: 1355 | AA57: 1517.05 | AB57: 1896.64 | AC57: 4517.3 | AD57: -462.14 | AE57: 1896.64 | AF57: 1517.3 | AG57: 0 | AJ57: 9000 | AK57: 0 | AL57: =SUM(Z57:AK57) -> 21237.79 | AM57: =ERP_8[[#This Row],[2026 Working Total]]-ERP_8[[#This Row],[LE2 Final Submission]] -> -383.85 | AN57: 0 | AO57: =$AE57 - $AN57 -> 1896.64 | AP57: =SUM(ERP_8[[#This Row],[AP01]:[AP07]])-SUM(ERP_8[[#This Row],[AP01 LE2]:[AP07 LE2]]) -> -5530.9 | AR57: =ERP_8[[#This Row],[2026 Working Total to Budget/LE]]-ERP_8[[#This Row],[Giveback]] -> -383.85 | AT57: 1355 | AU57: 1517.05 | AV57: 1896.64 | AW57: 0 | AX57: 0 | AY57: 13000 | AZ57: 0 | BA57: 0 | BB57: 3852.95 | BC57: 0 | BD57: 0 | BE57: 0 | BF57: 21621.64 | BG57: 1355 | BH57: 1517.05 | BI57: 1896.64 | BJ57: 0 | BK57: 0 | BL57: 13000 | BM57: 0 | BN57: 0 | BO57: 3852.95 | BP57: 0 | BQ57: 0 | BR57: 0 | BS57: 21621.64
A58: N-ERP-507 | B58: Dougherty, Chris_CONTRACTORS_IT-MGS0168-OG-US-00 | D58: =_xlfn.TEXTJOIN("_",FALSE,E58,ERP_8[[#This Row],[Expense Category]],ERP_8[[#This Row],[Project Code*]]) -> Dougherty, Chris_CONTRACTORS_IT-MGS0168-OG-US-00 | E58: Dougherty, Chris | G58: ERP | H58: Dougherty, Chris | I58: Dougherty, Chris | J58: Maguire, Karla | K58: CONTRACTORS | L58: IBM BPAI AMS (ML-0726) | O58: IT-MGS0168-OG-US-00 | P58: CHW - Ok | S58: None | T58: 4/28/26 CHW New add to tie-out 0223 to 0317 Planful Extracts Account Movement - IBM AMS forecast is recorded under Contractors, while actuals are posted to Managed Services. Zeroed remaining forecast as forecasted under Managed Services | V58: 1472196 | W58: 0 | AD58: 0 | AE58: 0 | AG58: =122683-122683 -> 0 | AH58: =122683-122683 -> 0 | AI58: =122683-122683 -> 0 | AJ58: =122683-122683 -> 0 | AK58: =122683-122683 -> 0 | AL58: =SUM(Z58:AK58) -> 0 | AM58: =ERP_8[[#This Row],[2026 Working Total]]-ERP_8[[#This Row],[LE2 Final Submission]] -> 0 | AN58: 0 | AO58: =$AE58 - $AN58 -> 0 | AP58: =SUM(ERP_8[[#This Row],[AP01]:[AP07]])-SUM(ERP_8[[#This Row],[AP01 LE2]:[AP07 LE2]]) -> 0 | AR58: =ERP_8[[#This Row],[2026 Working Total to Budget/LE]]-ERP_8[[#This Row],[Giveback]] -> 0 | AW58: 0 | AX58: 0 | AY58: 0 | AZ58: 0 | BA58: 0 | BB58: 0 | BC58: 0 | BD58: 0 | BE58: 0 | BF58: 0 | BG58: 122683 | BH58: 122683 | BI58: 122683 | BJ58: 122683 | BK58: 122683 | BL58: 122683 | BM58: 122683 | BN58: 122683 | BO58: 122683 | BP58: 122683 | BQ58: 122683 | BR58: 122683 | BS58: =SUM(ERP_8[[#This Row],[2026 AP01]:[2026 AP12]]) -> 1472196
A59: ERP-061 | B59: Tamavada, Ram_CONTRACTORS_IT-FBT0393-OG-JP-00 | D59: =_xlfn.TEXTJOIN("_",FALSE,E59,ERP_8[[#This Row],[Expense Category]],ERP_8[[#This Row],[Project Code*]]) -> Dougherty, Chris_CONTRACTORS_IT-PGS0057-OG-US-00 | E59: Dougherty, Chris | G59: ERP | H59: Dougherty, Chris | I59: Tamavada, Ram | J59: Tamavada, Ram | K59: CONTRACTORS | L59: SAP Finance (FI) Level 2 application support / IT-FBT0393-OG-JP-00 / June 01, 2026 - December 31, 2 | M59: IBM Corp | N59: 2321403 | O59: IT-PGS0057-OG-US-00 | Q59: 9501275938 | AG59: 18305 | AH59: 16120 | AI59: 16120 | AJ59: 16120 | AK59: 16120 | AL59: =SUM(Z59:AK59) -> 82785 | AM59: =ERP_8[[#This Row],[2026 Working Total]]-ERP_8[[#This Row],[LE2 Final Submission]] -> 82785 | AN59: 9500 | AO59: =$AE59 - $AN59 -> -9500 | AP59: =SUM(ERP_8[[#This Row],[AP01]:[AP07]])-SUM(ERP_8[[#This Row],[AP01 LE2]:[AP07 LE2]]) -> 0 | AR59: =ERP_8[[#This Row],[2026 Working Total to Budget/LE]]-ERP_8[[#This Row],[Giveback]] -> 82785
A60: L-ERP-093 | B60: Dougherty, Chris_CONTRACTORS_MISC001 | D60: =_xlfn.TEXTJOIN("_",FALSE,E60,ERP_8[[#This Row],[Expense Category]],ERP_8[[#This Row],[Project Code*]]) -> Dougherty, Chris_CONTRACTORS_MISC001 | E60: Dougherty, Chris | G60: ERP | H60: Dougherty, Chris | I60: Dougherty, Chris | J60: Maguire, Karla | K60: CONTRACTORS | L60: Miscellaneous Charges | N60: 2321402 | O60: MISC001 | S60: None | V60: 0 | W60: -0.11 | Z60: 20093.1 | AA60: 22504.89 | AB60: -42598.1 | AC60: -0.33 | AD60: 0.71 | AE60: -0.03 | AF60: 0 | AG60: 0 | AH60: 0 | AI60: 0 | AJ60: 0 | AK60: 0 | AL60: =SUM(Z60:AK60) -> 0.24 | AM60: =ERP_8[[#This Row],[2026 Working Total]]-ERP_8[[#This Row],[LE2 Final Submission]] -> 0.35 | AN60: 0 | AO60: =$AE60 - $AN60 -> -0.03 | AP60: =SUM(ERP_8[[#This Row],[AP01]:[AP07]])-SUM(ERP_8[[#This Row],[AP01 LE2]:[AP07 LE2]]) -> 0.35 | AR60: =ERP_8[[#This Row],[2026 Working Total to Budget/LE]]-ERP_8[[#This Row],[Giveback]] -> 0.35 | AT60: 20093.1 | AU60: 22504.89 | AV60: -42598.1 | AW60: 0 | AX60: 0 | AY60: 0 | AZ60: 0 | BA60: 0 | BB60: 0 | BC60: 0 | BD60: 0 | BE60: 0 | BF60: -0.11 | BG60: 20093.1 | BH60: 22504.89 | BI60: -42598.1 | BJ60: 0 | BK60: 0 | BL60: 0 | BM60: 0 | BN60: 0 | BO60: 0 | BP60: 0 | BQ60: 0 | BR60: 0 | BS60: -0.11
A61: L-ERP-325 | B61: Maguire, Karla_CONTRACTORS_MISC001 | D61: =_xlfn.TEXTJOIN("_",FALSE,E61,ERP_8[[#This Row],[Expense Category]],ERP_8[[#This Row],[Project Code*]]) -> Dougherty, Chris_CONTRACTORS_MISC001 | E61: Dougherty, Chris | G61: ERP | H61: Dougherty, Chris | I61: Maguire, Karla | J61: Maguire, Karla | K61: CONTRACTORS | L61: Miscellaneous Charges | O61: MISC001 | S61: None | T61: KP- Could you confirm who this line was transferred to? | V61: 0 | W61: 1220.75 | Z61: 669.53 | AA61: 7.26 | AB61: 543.96 | AC61: 129.35 | AD61: 286.96 | AE61: 206.13 | AF61: 258.93 | AG61: 0 | AH61: 0 | AI61: 0 | AJ61: 0 | AK61: 0 | AL61: =SUM(Z61:AK61) -> 2102.12 | AM61: =ERP_8[[#This Row],[2026 Working Total]]-ERP_8[[#This Row],[LE2 Final Submission]] -> 881.37 | AN61: 0 | AO61: =$AE61 - $AN61 -> 206.13 | AP61: =SUM(ERP_8[[#This Row],[AP01]:[AP07]])-SUM(ERP_8[[#This Row],[AP01 LE2]:[AP07 LE2]]) -> 881.37 | AR61: =ERP_8[[#This Row],[2026 Working Total to Budget/LE]]-ERP_8[[#This Row],[Giveback]] -> 881.37 | AT61: 669.53 | AU61: 7.26 | AV61: 543.96 | AW61: 0 | AX61: 0 | AY61: 0 | AZ61: 0 | BA61: 0 | BB61: 0 | BC61: 0 | BD61: 0 | BE61: 0 | BF61: 1220.75 | BG61: 669.53 | BH61: 7.26 | BI61: 543.96 | BJ61: 0 | BK61: 0 | BL61: 0 | BM61: 0 | BN61: 0 | BO61: 0 | BP61: 0 | BQ61: 0 | BR61: 0 | BS61: 1220.75
A62: L-ERP-371 | B62: McCormick, Pete_CONTRACTORS_MISC001 | D62: =_xlfn.TEXTJOIN("_",FALSE,E62,ERP_8[[#This Row],[Expense Category]],ERP_8[[#This Row],[Project Code*]]) -> Dougherty, Chris_CONTRACTORS_MISC001 | E62: Dougherty, Chris | G62: ERP | H62: Dougherty, Chris | I62: McCormick, Pete | J62: Maguire, Karla | K62: CONTRACTORS | L62: Miscellaneous Charges | N62: 2329614 | O62: MISC001 | S62: None | V62: 0 | W62: 5030.56 | Z62: -0.36 | AA62: 0.35 | AB62: 5030.57 | AC62: 0.46 | AD62: 0.34 | AE62: -0.41 | AF62: 0 | AG62: 0 | AH62: 0 | AI62: 0 | AJ62: 0 | AK62: 0 | AL62: =SUM(Z62:AK62) -> 5030.95 | AM62: =ERP_8[[#This Row],[2026 Working Total]]-ERP_8[[#This Row],[LE2 Final Submission]] -> 0.39 | AN62: 0 | AO62: =$AE62 - $AN62 -> -0.41 | AP62: =SUM(ERP_8[[#This Row],[AP01]:[AP07]])-SUM(ERP_8[[#This Row],[AP01 LE2]:[AP07 LE2]]) -> 0.39 | AR62: =ERP_8[[#This Row],[2026 Working Total to Budget/LE]]-ERP_8[[#This Row],[Giveback]] -> 0.39 | AT62: -0.36 | AU62: 0.35 | AV62: 5030.57 | AW62: 0 | AX62: 0 | AY62: 0 | AZ62: 0 | BA62: 0 | BB62: 0 | BC62: 0 | BD62: 0 | BE62: 0 | BF62: 5030.56 | BG62: -0.36 | BH62: 0.35 | BI62: 5030.57 | BJ62: 0 | BK62: 0 | BL62: 0 | BM62: 0 | BN62: 0 | BO62: 0 | BP62: 0 | BQ62: 0 | BR62: 0 | BS62: 5030.56
A63: L-ERP-445 | B63: Meadows, Leslie_CONTRACTORS_MISC001 | D63: =_xlfn.TEXTJOIN("_",FALSE,E63,ERP_8[[#This Row],[Expense Category]],ERP_8[[#This Row],[Project Code*]]) -> Dougherty, Chris_CONTRACTORS_MISC001 | E63: Dougherty, Chris | G63: ERP | H63: Dougherty, Chris | I63: Meadows, Leslie | J63: Maguire, Karla | K63: CONTRACTORS | L63: Miscellaneous Charges | N63: 2321511 | O63: MISC001 | S63: None | T63: KP - Not sure what this are. Please advise. | V63: 0 | W63: -0.26 | Z63: -0.38 | AA63: 0.21 | AB63: -0.09 | AC63: 0.14 | AD63: 0.52 | AE63: -0.63 | AF63: 0 | AG63: 0 | AH63: 0 | AI63: 0 | AJ63: 0 | AK63: 0 | AL63: =SUM(Z63:AK63) -> -0.23 | AM63: =ERP_8[[#This Row],[2026 Working Total]]-ERP_8[[#This Row],[LE2 Final Submission]] -> 0.03 | AN63: 0 | AO63: =$AE63 - $AN63 -> -0.63 | AP63: =SUM(ERP_8[[#This Row],[AP01]:[AP07]])-SUM(ERP_8[[#This Row],[AP01 LE2]:[AP07 LE2]]) -> 0.03 | AR63: =ERP_8[[#This Row],[2026 Working Total to Budget/LE]]-ERP_8[[#This Row],[Giveback]] -> 0.03 | AT63: -0.38 | AU63: 0.21 | AV63: -0.09 | AW63: 0 | AX63: 0 | AY63: 0 | AZ63: 0 | BA63: 0 | BB63: 0 | BC63: 0 | BD63: 0 | BE63: 0 | BF63: -0.26 | BG63: -0.38 | BH63: 0.21 | BI63: -0.09 | BJ63: 0 | BK63: 0 | BL63: 0 | BM63: 0 | BN63: 0 | BO63: 0 | BP63: 0 | BQ63: 0 | BR63: 0 | BS63: -0.26
A64: L-ERP-541 | B64: Tamavada, Ram_CONTRACTORS_MISC001 | D64: =_xlfn.TEXTJOIN("_",FALSE,E64,ERP_8[[#This Row],[Expense Category]],ERP_8[[#This Row],[Project Code*]]) -> Dougherty, Chris_CONTRACTORS_MISC001 | E64: Dougherty, Chris | G64: ERP | H64: Dougherty, Chris | I64: Tamavada, Ram | J64: Maguire, Karla | K64: CONTRACTORS | L64: Miscellaneous Charges | N64: 2320843;2321403;2662855 | O64: MISC001 | S64: None | T64: KP - May i please get more details on this actual? Can't find it in the actuals file. | V64: 0 | W64: 0.35 | AA64: 0.01 | AB64: 0.34 | AC64: -0.67 | AD64: 0.2 | AE64: 8111.01 | AF64: 8111.45 | AG64: 0 | AH64: 0 | AI64: 0 | AJ64: 0 | AK64: 0 | AL64: =SUM(Z64:AK64) -> 16222.34 | AM64: =ERP_8[[#This Row],[2026 Working Total]]-ERP_8[[#This Row],[LE2 Final Submission]] -> 16221.99 | AN64: 0 | AO64: =$AE64 - $AN64 -> 8111.01 | AP64: =SUM(ERP_8[[#This Row],[AP01]:[AP07]])-SUM(ERP_8[[#This Row],[AP01 LE2]:[AP07 LE2]]) -> 16221.99 | AR64: =ERP_8[[#This Row],[2026 Working Total to Budget/LE]]-ERP_8[[#This Row],[Giveback]] -> 16221.99 | AU64: 0.01 | AV64: 0.34 | AW64: 0 | AX64: 0 | AY64: 0 | AZ64: 0 | BA64: 0 | BB64: 0 | BC64: 0 | BD64: 0 | BE64: 0 | BF64: 0.35 | BH64: 0.01 | BI64: 0.34 | BJ64: 0 | BK64: 0 | BL64: 0 | BM64: 0 | BN64: 0 | BO64: 0 | BP64: 0 | BQ64: 0 | BR64: 0 | BS64: 0.35
A65: L-ERP-094 | B65: Dougherty, Chris_CONTRACTORS_POClosure001 | D65: =_xlfn.TEXTJOIN("_",FALSE,E65,ERP_8[[#This Row],[Expense Category]],ERP_8[[#This Row],[Project Code*]]) -> Dougherty, Chris_CONTRACTORS_POClosure001 | E65: Dougherty, Chris | G65: ERP | H65: Dougherty, Chris | I65: Dougherty, Chris | J65: Maguire, Karla | K65: CONTRACTORS | L65: PO Closure Credit | N65: 2321402 | O65: POClosure001 | P65: CHW - Ok | S65: None | V65: 0 | W65: -16166.66 | Z65: 0.34 | AA65: -10499.16 | AB65: -5667.84 | AC65: 0 | AD65: 0 | AE65: 0 | AF65: 0 | AG65: 0 | AH65: 0 | AI65: 0 | AJ65: 0 | AK65: 0 | AL65: =SUM(Z65:AK65) -> -16166.66 | AM65: =ERP_8[[#This Row],[2026 Working Total]]-ERP_8[[#This Row],[LE2 Final Submission]] -> 0 | AN65: 0 | AO65: =$AE65 - $AN65 -> 0 | AP65: =SUM(ERP_8[[#This Row],[AP01]:[AP07]])-SUM(ERP_8[[#This Row],[AP01 LE2]:[AP07 LE2]]) -> 0 | AR65: =ERP_8[[#This Row],[2026 Working Total to Budget/LE]]-ERP_8[[#This Row],[Giveback]] -> 0 | AT65: 0.34 | AU65: -10499.16 | AV65: -5667.84 | AW65: 0 | AX65: 0 | AY65: 0 | AZ65: 0 | BA65: 0 | BB65: 0 | BC65: 0 | BD65: 0 | BE65: 0 | BF65: -16166.66 | BG65: 0.34 | BH65: -10499.16 | BI65: -5667.84 | BJ65: 0 | BK65: 0 | BL65: 0 | BM65: 0 | BN65: 0 | BO65: 0 | BP65: 0 | BQ65: 0 | BR65: 0 | BS65: -16166.66
A66: L-ERP-446 | B66: Meadows, Leslie_CONTRACTORS_POClosure001 | D66: =_xlfn.TEXTJOIN("_",FALSE,E66,ERP_8[[#This Row],[Expense Category]],ERP_8[[#This Row],[Project Code*]]) -> Dougherty, Chris_CONTRACTORS_POClosure001 | E66: Dougherty, Chris | G66: ERP | H66: Dougherty, Chris | I66: Meadows, Leslie | J66: Maguire, Karla | K66: CONTRACTORS | L66: PO Closure Credit | N66: 2321511 | O66: POClosure001 | P66: CHW - Ok | S66: None | V66: 0 | W66: -14694 | AB66: -14694 | AC66: 0 | AD66: 0 | AE66: 0 | AF66: 0 | AG66: 0 | AH66: 0 | AI66: 0 | AJ66: 0 | AK66: 0 | AL66: =SUM(Z66:AK66) -> -14694 | AM66: =ERP_8[[#This Row],[2026 Working Total]]-ERP_8[[#This Row],[LE2 Final Submission]] -> 0 | AN66: 0 | AO66: =$AE66 - $AN66 -> 0 | AP66: =SUM(ERP_8[[#This Row],[AP01]:[AP07]])-SUM(ERP_8[[#This Row],[AP01 LE2]:[AP07 LE2]]) -> 0 | AR66: =ERP_8[[#This Row],[2026 Working Total to Budget/LE]]-ERP_8[[#This Row],[Giveback]] -> 0 | AV66: -14694 | AW66: 0 | AX66: 0 | AY66: 0 | AZ66: 0 | BA66: 0 | BB66: 0 | BC66: 0 | BD66: 0 | BE66: 0 | BF66: -14694 | BI66: -14694 | BJ66: 0 | BK66: 0 | BL66: 0 | BM66: 0 | BN66: 0 | BO66: 0 | BP66: 0 | BQ66: 0 | BR66: 0 | BS66: -14694
A67: N-ERP-557 | B67: Ganesan, Srinivasan_CONTRACTORS_2026-XFR-0023-A | D67: =_xlfn.TEXTJOIN("_",FALSE,E67,ERP_8[[#This Row],[Expense Category]],ERP_8[[#This Row],[Project Code*]]) -> Ganesan, Srinivasan_CONTRACTORS_2026-XFR-0023-A | E67: Ganesan, Srinivasan | G67: ERP | H67: Hase, Raj | I67: Ganesan, Srinivasan | J67: DeHart, Lynn | K67: CONTRACTORS | L67: GSC AMER - Last Mile Strategy - Delivery Milestones & Dashboards - 50% One offshore contractor; New Global Capability. Only 0.5FTE requested for support. Eventually, will be transferred to BTAMS | O67: 2026-XFR-0023-A | S67: 2026 Budget Transfer | T67: 4/28/26 CHW New add to tie-out 0223 to 0317 Planful Extracts | V67: 70000 | W67: 0 | AD67: 0 | AE67: 0 | AG67: 0 | AH67: 0 | AI67: 0 | AJ67: 0 | AK67: 0 | AL67: =SUM(Z67:AK67) -> 0 | AM67: =ERP_8[[#This Row],[2026 Working Total]]-ERP_8[[#This Row],[LE2 Final Submission]] -> 0 | AN67: 0 | AO67: =$AE67 - $AN67 -> 0 | AP67: =SUM(ERP_8[[#This Row],[AP01]:[AP07]])-SUM(ERP_8[[#This Row],[AP01 LE2]:[AP07 LE2]]) -> 0 | AQ67: 70000 | AR67: =ERP_8[[#This Row],[2026 Working Total to Budget/LE]]-ERP_8[[#This Row],[Giveback]] -> -70000 | AS67: XFRs not needed in 2026 | AW67: 0 | AX67: 0 | AY67: 0 | AZ67: 0 | BA67: 0 | BB67: 0 | BC67: 0 | BD67: 0 | BE67: 0 | BF67: 0 | BG67: 5833.37 | BH67: 5833.33 | BI67: 5833.33 | BJ67: 5833.33 | BK67: 5833.33 | BL67: 5833.33 | BM67: 5833.33 | BN67: 5833.33 | BO67: 5833.33 | BP67: 5833.33 | BQ67: 5833.33 | BR67: 5833.33 | BS67: =SUM(ERP_8[[#This Row],[2026 AP01]:[2026 AP12]]) -> 70000
A68: N-ERP-558 | B68: Ganesan, Srinivasan_CONTRACTORS_2026-XFR-0024-A | D68: =_xlfn.TEXTJOIN("_",FALSE,E68,ERP_8[[#This Row],[Expense Category]],ERP_8[[#This Row],[Project Code*]]) -> Ganesan, Srinivasan_CONTRACTORS_2026-XFR-0024-A | E68: Ganesan, Srinivasan | G68: ERP | H68: Hase, Raj | I68: Ganesan, Srinivasan | J68: DeHart, Lynn | K68: CONTRACTORS | L68: GSC AMER: MIRT Replacement - Phase II and deploy to other markets - 1 Offshore contractor. New capability for Late repackaging. This is a solution resource. | O68: 2026-XFR-0024-A | S68: 2026 Budget Transfer | T68: 4/28/26 CHW New add to tie-out 0223 to 0317 Planful Extracts 2/20 Updated per RG - able to leverate existing contractors | V68: 120000 | W68: 0 | AD68: 0 | AE68: 0 | AG68: 0 | AH68: 0 | AI68: 0 | AJ68: 0 | AK68: 0 | AL68: =SUM(Z68:AK68) -> 0 | AM68: =ERP_8[[#This Row],[2026 Working Total]]-ERP_8[[#This Row],[LE2 Final Submission]] -> 0 | AN68: 0 | AO68: =$AE68 - $AN68 -> 0 | AP68: =SUM(ERP_8[[#This Row],[AP01]:[AP07]])-SUM(ERP_8[[#This Row],[AP01 LE2]:[AP07 LE2]]) -> 0 | AQ68: 120000 | AR68: =ERP_8[[#This Row],[2026 Working Total to Budget/LE]]-ERP_8[[#This Row],[Giveback]] -> -120000 | AS68: XFRs not needed in 2026 | AW68: 0 | AX68: 0 | AY68: 0 | AZ68: 0 | BA68: 0 | BB68: 0 | BC68: 0 | BD68: 0 | BE68: 0 | BF68: 0 | BG68: 10000 | BH68: 10000 | BI68: 10000 | BJ68: 10000 | BK68: 10000 | BL68: 10000 | BM68: 10000 | BN68: 10000 | BO68: 10000 | BP68: 10000 | BQ68: 10000 | BR68: 10000 | BS68: =SUM(ERP_8[[#This Row],[2026 AP01]:[2026 AP12]]) -> 120000
A69: N-ERP-559 | B69: Ganesan, Srinivasan_CONTRACTORS_2026-XFR-0043-A | D69: =_xlfn.TEXTJOIN("_",FALSE,E69,ERP_8[[#This Row],[Expense Category]],ERP_8[[#This Row],[Project Code*]]) -> Ganesan, Srinivasan_CONTRACTORS_2026-XFR-0043-A | E69: Ganesan, Srinivasan | G69: ERP | H69: Hase, Raj | I69: Ganesan, Srinivasan | J69: DeHart, Lynn | K69: CONTRACTORS | L69: GSC GLNS ALC Redressing - 50% One offshore contractor; New Global Capability. Only 0.5FTE requested for support. Eventually, will be transferred to BTAMS | O69: 2026-XFR-0043-A | S69: 2026 Budget Transfer | T69: 4/28/26 CHW New add to tie-out 0223 to 0317 Planful Extracts | V69: 70000 | W69: 0 | AD69: 0 | AE69: 0 | AG69: 0 | AH69: 0 | AI69: 0 | AJ69: 0 | AK69: 0 | AL69: =SUM(Z69:AK69) -> 0 | AM69: =ERP_8[[#This Row],[2026 Working Total]]-ERP_8[[#This Row],[LE2 Final Submission]] -> 0 | AN69: 0 | AO69: =$AE69 - $AN69 -> 0 | AP69: =SUM(ERP_8[[#This Row],[AP01]:[AP07]])-SUM(ERP_8[[#This Row],[AP01 LE2]:[AP07 LE2]]) -> 0 | AQ69: 70000 | AR69: =ERP_8[[#This Row],[2026 Working Total to Budget/LE]]-ERP_8[[#This Row],[Giveback]] -> -70000 | AS69: XFRs not needed in 2026 | AW69: 0 | AX69: 0 | AY69: 0 | AZ69: 0 | BA69: 0 | BB69: 0 | BC69: 0 | BD69: 0 | BE69: 0 | BF69: 0 | BG69: 5833.37 | BH69: 5833.33 | BI69: 5833.33 | BJ69: 5833.33 | BK69: 5833.33 | BL69: 5833.33 | BM69: 5833.33 | BN69: 5833.33 | BO69: 5833.33 | BP69: 5833.33 | BQ69: 5833.33 | BR69: 5833.33 | BS69: =SUM(ERP_8[[#This Row],[2026 AP01]:[2026 AP12]]) -> 70000
A70: N-ERP-560 | B70: Ganesan, Srinivasan_CONTRACTORS_2026-XFR-0051-A | D70: =_xlfn.TEXTJOIN("_",FALSE,E70,ERP_8[[#This Row],[Expense Category]],ERP_8[[#This Row],[Project Code*]]) -> Ganesan, Srinivasan_CONTRACTORS_2026-XFR-0051-A | E70: Ganesan, Srinivasan | G70: ERP | H70: Hase, Raj | I70: Ganesan, Srinivasan | J70: DeHart, Lynn | K70: CONTRACTORS | L70: GSC Comirnaty Launch 2025 - One offshore contractor to support new capabilities are built as part of this initiative, including new interfaces and Fiori Apps and dashboards | O70: 2026-XFR-0051-A | S70: 2026 Budget Transfer | T70: 4/28/26 CHW New add to tie-out 0223 to 0317 Planful Extracts | V70: 140000 | W70: 0 | AD70: 0 | AE70: 0 | AG70: 0 | AH70: 0 | AI70: 0 | AJ70: 0 | AK70: 0 | AL70: =SUM(Z70:AK70) -> 0 | AM70: =ERP_8[[#This Row],[2026 Working Total]]-ERP_8[[#This Row],[LE2 Final Submission]] -> 0 | AN70: 0 | AO70: =$AE70 - $AN70 -> 0 | AP70: =SUM(ERP_8[[#This Row],[AP01]:[AP07]])-SUM(ERP_8[[#This Row],[AP01 LE2]:[AP07 LE2]]) -> 0 | AQ70: 140000 | AR70: =ERP_8[[#This Row],[2026 Working Total to Budget/LE]]-ERP_8[[#This Row],[Giveback]] -> -140000 | AS70: XFRs not needed in 2026 | AW70: 0 | AX70: 0 | AY70: 0 | AZ70: 0 | BA70: 0 | BB70: 0 | BC70: 0 | BD70: 0 | BE70: 0 | BF70: 0 | BG70: 11666.63 | BH70: 11666.67 | BI70: 11666.67 | BJ70: 11666.67 | BK70: 11666.67 | BL70: 11666.67 | BM70: 11666.67 | BN70: 11666.67 | BO70: 11666.67 | BP70: 11666.67 | BQ70: 11666.67 | BR70: 11666.67 | BS70: =SUM(ERP_8[[#This Row],[2026 AP01]:[2026 AP12]]) -> 140000
A71: L-ERP-154 | B71: Ganesan, Srinivasan_CONTRACTORS_EnhanceChargeout001 | D71: =_xlfn.TEXTJOIN("_",FALSE,E71,ERP_8[[#This Row],[Expense Category]],ERP_8[[#This Row],[Project Code*]]) -> Ganesan, Srinivasan_CONTRACTORS_EnhanceChargeout001 | E71: Ganesan, Srinivasan | G71: ERP | H71: Hase, Raj | I71: Ganesan, Srinivasan | J71: DeHart, Lynn | K71: CONTRACTORS | L71: Enhance Chargeout Cost Centers | N71: 2340697 | O71: EnhanceChargeout001 | P71: CHW - F/U | S71: None | T71: 4/30 - CHW Team to F/U as thinks these should be reclassed elsewhere in AP05 | V71: 0 | W71: 130143 | Z71: 91657 | AA71: -50311 | AB71: 88797 | AC71: 142812 | AD71: -181452 | AE71: 124380 | AF71: -27477.65 | AG71: 0 | AH71: 0 | AI71: 0 | AJ71: 0 | AK71: 0 | AL71: =SUM(Z71:AK71) -> 188405.35 | AM71: =ERP_8[[#This Row],[2026 Working Total]]-ERP_8[[#This Row],[LE2 Final Submission]] -> 58262.35 | AN71: 0 | AO71: =$AE71 - $AN71 -> 124380 | AP71: =SUM(ERP_8[[#This Row],[AP01]:[AP07]])-SUM(ERP_8[[#This Row],[AP01 LE2]:[AP07 LE2]]) -> 58262.35 | AR71: =ERP_8[[#This Row],[2026 Working Total to Budget/LE]]-ERP_8[[#This Row],[Giveback]] -> 58262.35 | AS71: Needs to be investigated. | AT71: 91657 | AU71: -50311 | AV71: 88797 | AW71: 0 | AX71: 0 | AY71: 0 | AZ71: 0 | BA71: 0 | BB71: 0 | BC71: 0 | BD71: 0 | BE71: 0 | BF71: 130143 | BG71: 91657 | BH71: -50311 | BI71: 88797 | BJ71: 0 | BK71: 0 | BL71: 0 | BM71: 0 | BN71: 0 | BO71: 0 | BP71: 0 | BQ71: 0 | BR71: 0 | BS71: 130143
A72: L-ERP-141 | B72: Ganesan, Srinivasan_CONTRACTORS_IT-CTR0040-OG-US-00 | D72: =_xlfn.TEXTJOIN("_",FALSE,E72,ERP_8[[#This Row],[Expense Category]],ERP_8[[#This Row],[Project Code*]]) -> Ganesan, Srinivasan_CONTRACTORS_IT-CTR0040-OG-US-00 | E72: Ganesan, Srinivasan | G72: ERP | H72: Hase, Raj | I72: Ganesan, Srinivasan | J72: DeHart, Lynn | K72: CONTRACTORS | L72: GLNS IERP Budget Tool ABAP_XFR0948 | N72: 2320521 | O72: IT-CTR0040-OG-US-00 | Q72: 9501226983 | S72: None | V72: 0 | W72: 0.15 | AA72: -16768 | AB72: 12756.15 | AC72: 6266.17 | AD72: 6266.17 | AE72: 7832.72 | AF72: 223.79 | AG72: -16577 | AH72: 0 | AI72: 0 | AJ72: 0 | AK72: 0 | AL72: =SUM(Z72:AK72) -> 0 | AM72: =ERP_8[[#This Row],[2026 Working Total]]-ERP_8[[#This Row],[LE2 Final Submission]] -> -0.15 | AN72: 0 | AO72: =$AE72 - $AN72 -> 7832.72 | AP72: =SUM(ERP_8[[#This Row],[AP01]:[AP07]])-SUM(ERP_8[[#This Row],[AP01 LE2]:[AP07 LE2]]) -> 16576.85 | AR72: =ERP_8[[#This Row],[2026 Working Total to Budget/LE]]-ERP_8[[#This Row],[Giveback]] -> -0.15 | AS72: IERP Support costs. Incorrectly transferred to Karla's cost center. This should have been transferred to Jerome. | AU72: -16768 | AV72: 12756.15 | AW72: 0 | AX72: 4012 | AY72: 0 | AZ72: 0 | BA72: 0 | BB72: 0 | BC72: 0 | BD72: 0 | BE72: 0 | BF72: 0.15 | BH72: -16768 | BI72: 12756.15 | BJ72: 0 | BK72: 0 | BL72: 0 | BM72: 0 | BN72: 0 | BO72: 0 | BP72: 0 | BQ72: 0 | BR72: 0 | BS72: -4011.85
A73: L-ERP-142 | B73: Ganesan, Srinivasan_CONTRACTORS_IT-CTR0045-OG-US-00 | D73: =_xlfn.TEXTJOIN("_",FALSE,E73,ERP_8[[#This Row],[Expense Category]],ERP_8[[#This Row],[Project Code*]]) -> Ganesan, Srinivasan_CONTRACTORS_IT-CTR0045-OG-US-00 | E73: Ganesan, Srinivasan | G73: ERP | H73: Hase, Raj | I73: Ganesan, Srinivasan | J73: DeHart, Lynn | K73: CONTRACTORS | L73: Planning Pfizer Connect Specialist Support_XFR0670 & XFR0955 | N73: 2320521 | O73: IT-CTR0045-OG-US-00 | P73: CHW - Ok | S73: None | V73: 0 | W73: 3558.41 | Z73: 3558.41 | AA73: 0 | AB73: 0 | AC73: 0 | AD73: 0 | AE73: 0 | AF73: 0 | AG73: 0 | AH73: 0 | AI73: 0 | AJ73: 0 | AK73: 0 | AL73: =SUM(Z73:AK73) -> 3558.41 | AM73: =ERP_8[[#This Row],[2026 Working Total]]-ERP_8[[#This Row],[LE2 Final Submission]] -> 0 | AN73: 0 | AO73: =$AE73 - $AN73 -> 0 | AP73: =SUM(ERP_8[[#This Row],[AP01]:[AP07]])-SUM(ERP_8[[#This Row],[AP01 LE2]:[AP07 LE2]]) -> 0 | AR73: =ERP_8[[#This Row],[2026 Working Total to Budget/LE]]-ERP_8[[#This Row],[Giveback]] -> 0 | AS73: Don't know what this is. - This is Glenn White's PO 9500912136 | AT73: 3558.41 | AU73: 0 | AV73: 0 | AW73: 0 | AX73: 0 | AY73: 0 | AZ73: 0 | BA73: 0 | BB73: 0 | BC73: 0 | BD73: 0 | BE73: 0 | BF73: 3558.41 | BG73: 3558.41 | BH73: 0 | BI73: 0 | BJ73: 0 | BK73: 0 | BL73: 0 | BM73: 0 | BN73: 0 | BO73: 0 | BP73: 0 | BQ73: 0 | BR73: 0 | BS73: 3558.41
A74: L-ERP-123 | B74: Ganesan, Srinivasan_CONTRACTORS_IT-CTR0049-OG-US-00 | D74: =_xlfn.TEXTJOIN("_",FALSE,E74,ERP_8[[#This Row],[Expense Category]],ERP_8[[#This Row],[Project Code*]]) -> Ganesan, Srinivasan_CONTRACTORS_IT-CTR0049-OG-US-00 | E74: Ganesan, Srinivasan | G74: ERP | H74: Hase, Raj | I74: Ganesan, Srinivasan | J74: DeHart, Lynn | K74: CONTRACTORS | L74: GLNS Ingestion of IOT to UDH-CDM_XFR0962 | N74: 2320521 | O74: IT-CTR0049-OG-US-00 | P74: 9501015433 | S74: 2026 Budget Transfer | V74: 50000 | W74: 50000 | AD74: 0 | AE74: 0 | AF74: 0 | AG74: 0 | AH74: 0 | AI74: 33423 | AJ74: 0 | AK74: 0 | AL74: =SUM(Z74:AK74) -> 33423 | AM74: =ERP_8[[#This Row],[2026 Working Total]]-ERP_8[[#This Row],[LE2 Final Submission]] -> -16577 | AN74: 0 | AO74: =$AE74 - $AN74 -> 0 | AP74: =SUM(ERP_8[[#This Row],[AP01]:[AP07]])-SUM(ERP_8[[#This Row],[AP01 LE2]:[AP07 LE2]]) -> -22500 | AR74: =ERP_8[[#This Row],[2026 Working Total to Budget/LE]]-ERP_8[[#This Row],[Giveback]] -> -16577 | AW74: 0 | AX74: 11100 | AY74: 11400 | AZ74: 0 | BA74: 0 | BB74: 9000 | BC74: 9000 | BD74: 9500 | BE74: 0 | BF74: 50000 | BM74: 10000 | BN74: 10000 | BO74: 10000 | BP74: 10000 | BQ74: 10000 | BR74: 0 | BS74: 50000
A75: L-ERP-143 | B75: Ganesan, Srinivasan_CONTRACTORS_IT-CTR0075-OG-MX-00 | D75: =_xlfn.TEXTJOIN("_",FALSE,E75,ERP_8[[#This Row],[Expense Category]],ERP_8[[#This Row],[Project Code*]]) -> Ganesan, Srinivasan_CONTRACTORS_IT-CTR0075-OG-MX-00 | E75: Ganesan, Srinivasan | G75: ERP | H75: Hase, Raj | I75: Ganesan, Srinivasan | J75: DeHart, Lynn | K75: CONTRACTORS | L75: Logistics Cyclical Counting Calendar Mexico | O75: IT-CTR0075-OG-MX-00 | S75: None | V75: 6000 | W75: 6000 | AD75: 0 | AE75: 0 | AH75: 6000 | AI75: 0 | AJ75: 0 | AK75: 0 | AL75: =SUM(Z75:AK75) -> 6000 | AM75: =ERP_8[[#This Row],[2026 Working Total]]-ERP_8[[#This Row],[LE2 Final Submission]] -> 0 | AN75: 0 | AO75: =$AE75 - $AN75 -> 0 | AP75: =SUM(ERP_8[[#This Row],[AP01]:[AP07]])-SUM(ERP_8[[#This Row],[AP01 LE2]:[AP07 LE2]]) -> 0 | AR75: =ERP_8[[#This Row],[2026 Working Total to Budget/LE]]-ERP_8[[#This Row],[Giveback]] -> 0 | BB75: 6000 | BC75: 0 | BD75: 0 | BE75: 0 | BF75: 6000 | BO75: 6000 | BP75: 0 | BQ75: 0 | BR75: 0 | BS75: 6000
A76: L-ERP-144 | B76: Ganesan, Srinivasan_CONTRACTORS_IT-CTR0076-OG-MX-00 | D76: =_xlfn.TEXTJOIN("_",FALSE,E76,ERP_8[[#This Row],[Expense Category]],ERP_8[[#This Row],[Project Code*]]) -> Ganesan, Srinivasan_CONTRACTORS_IT-CTR0076-OG-MX-00 | E76: Ganesan, Srinivasan | G76: ERP | H76: Hase, Raj | I76: Ganesan, Srinivasan | J76: DeHart, Lynn | K76: CONTRACTORS | L76: Logistics Financial Reserve in Mexico | O76: IT-CTR0076-OG-MX-00 | S76: None | V76: 6000 | W76: 6000 | AD76: 0 | AE76: 0 | AH76: 6000 | AI76: 0 | AJ76: 0 | AK76: 0 | AL76: =SUM(Z76:AK76) -> 6000 | AM76: =ERP_8[[#This Row],[2026 Working Total]]-ERP_8[[#This Row],[LE2 Final Submission]] -> 0 | AN76: 0 | AO76: =$AE76 - $AN76 -> 0 | AP76: =SUM(ERP_8[[#This Row],[AP01]:[AP07]])-SUM(ERP_8[[#This Row],[AP01 LE2]:[AP07 LE2]]) -> 0 | AR76: =ERP_8[[#This Row],[2026 Working Total to Budget/LE]]-ERP_8[[#This Row],[Giveback]] -> 0 | BB76: 6000 | BC76: 0 | BD76: 0 | BE76: 0 | BF76: 6000 | BO76: 6000 | BP76: 0 | BQ76: 0 | BR76: 0 | BS76: 6000
A77: L-ERP-145 | B77: Ganesan, Srinivasan_CONTRACTORS_IT-CTR0077-OG-MX-00 | D77: =_xlfn.TEXTJOIN("_",FALSE,E77,ERP_8[[#This Row],[Expense Category]],ERP_8[[#This Row],[Project Code*]]) -> Ganesan, Srinivasan_CONTRACTORS_IT-CTR0077-OG-MX-00 | E77: Ganesan, Srinivasan | G77: ERP | H77: Hase, Raj | I77: Ganesan, Srinivasan | J77: DeHart, Lynn | K77: CONTRACTORS | L77: Logistics LATAM Support | O77: IT-CTR0077-OG-MX-00 | S77: None | V77: 45000 | W77: 45000 | AD77: 0 | AE77: 0 | AH77: 45000 | AI77: 0 | AJ77: 0 | AK77: 0 | AL77: =SUM(Z77:AK77) -> 45000 | AM77: =ERP_8[[#This Row],[2026 Working Total]]-ERP_8[[#This Row],[LE2 Final Submission]] -> 0 | AN77: 0 | AO77: =$AE77 - $AN77 -> 0 | AP77: =SUM(ERP_8[[#This Row],[AP01]:[AP07]])-SUM(ERP_8[[#This Row],[AP01 LE2]:[AP07 LE2]]) -> 0 | AR77: =ERP_8[[#This Row],[2026 Working Total to Budget/LE]]-ERP_8[[#This Row],[Giveback]] -> 0 | BB77: 45000 | BC77: 0 | BD77: 0 | BE77: 0 | BF77: 45000 | BO77: 45000 | BP77: 0 | BQ77: 0 | BR77: 0 | BS77: 45000
A78: L-ERP-146 | B78: Ganesan, Srinivasan_CONTRACTORS_IT-CTR0149-OG-US-00 | D78: =_xlfn.TEXTJOIN("_",FALSE,E78,ERP_8[[#This Row],[Expense Category]],ERP_8[[#This Row],[Project Code*]]) -> Ganesan, Srinivasan_CONTRACTORS_IT-CTR0149-OG-US-00 | E78: Ganesan, Srinivasan | G78: ERP | H78: Hase, Raj | I78: Ganesan, Srinivasan | J78: DeHart, Lynn | K78: CONTRACTORS | L78: GLNS - E2E Functional Support | N78: 2320521 | O78: IT-CTR0149-OG-US-00 | Q78: 9501178401 | S78: None | V78: 515000 | W78: 335362.38 | AA78: 66916.99 | AB78: 75010.39 | AC78: 45158.71 | AD78: 45158.71 | AE78: 56448.39 | AF78: -106709.88 | AG78: 80704 | AH78: 13224 | AI78: 13224 | AJ78: 16704 | AK78: 29523 | AL78: =SUM(Z78:AK78) -> 335362.31 | AM78: =ERP_8[[#This Row],[2026 Working Total]]-ERP_8[[#This Row],[LE2 Final Submission]] -> -0.07 | AN78: 0 | AO78: =$AE78 - $AN78 -> 56448.39 | AP78: =SUM(ERP_8[[#This Row],[AP01]:[AP07]])-SUM(ERP_8[[#This Row],[AP01 LE2]:[AP07 LE2]]) -> -119379.07 | AQ78: 180000 | AR78: =ERP_8[[#This Row],[2026 Working Total to Budget/LE]]-ERP_8[[#This Row],[Giveback]] -> -180000.07 | AS78: Combination of XFR 0027A, 0038A, 0039A, 0042A. Reduced to $335K | AU78: 66916.99 | AV78: 75010.39 | AW78: 40062 | AX78: 40792 | AY78: 43581 | AZ78: 35000 | BA78: 34000 | BB78: 0 | BC78: 0 | BD78: 0 | BE78: 0 | BF78: 335362.38 | BH78: 66916.99 | BI78: 75010.39 | BJ78: 48286 | BK78: 48386 | BL78: 48286 | BM78: 38449 | BN78: 38449 | BO78: 44462 | BP78: 44462 | BQ78: 44462 | BR78: 44462 | BS78: 541631.38
A79: L-ERP-147 | B79: Ganesan, Srinivasan_CONTRACTORS_IT-CTR0153-OG-US-00 | D79: =_xlfn.TEXTJOIN("_",FALSE,E79,ERP_8[[#This Row],[Expense Category]],ERP_8[[#This Row],[Project Code*]]) -> Ganesan, Srinivasan_CONTRACTORS_IT-CTR0153-OG-US-00 | E79: Ganesan, Srinivasan | G79: ERP | H79: Hase, Raj | I79: Ganesan, Srinivasan | J79: DeHart, Lynn | K79: CONTRACTORS | L79: Global Supply Chain Market Logistics 2026 XFERs-0023,0043,0051 | O79: IT-CTR0153-OG-US-00 | S79: None | V79: 0 | W79: 0 | AD79: 0 | AE79: 0 | AG79: 0 | AH79: 0 | AI79: 0 | AJ79: 0 | AK79: 0 | AL79: =SUM(Z79:AK79) -> 0 | AM79: =ERP_8[[#This Row],[2026 Working Total]]-ERP_8[[#This Row],[LE2 Final Submission]] -> 0 | AN79: 0 | AO79: =$AE79 - $AN79 -> 0 | AP79: =SUM(ERP_8[[#This Row],[AP01]:[AP07]])-SUM(ERP_8[[#This Row],[AP01 LE2]:[AP07 LE2]]) -> 0 | AQ79: 280000 | AR79: =ERP_8[[#This Row],[2026 Working Total to Budget/LE]]-ERP_8[[#This Row],[Giveback]] -> -280000 | AS79: 0043, 0051) | AZ79: 0 | BA79: 0 | BB79: 0 | BC79: 0 | BD79: 0 | BE79: 0 | BF79: 0 | BM79: 46666.667 | BN79: 46666.667 | BO79: 46666.667 | BP79: 46666.667 | BQ79: 46666.667 | BR79: 46666.667 | BS79: 280000
A80: L-ERP-148 | B80: Ganesan, Srinivasan_CONTRACTORS_IT-FBT0544-OG-US-00 | D80: =_xlfn.TEXTJOIN("_",FALSE,E80,ERP_8[[#This Row],[Expense Category]],ERP_8[[#This Row],[Project Code*]]) -> Ganesan, Srinivasan_CONTRACTORS_IT-FBT0544-OG-US-00 | E80: Ganesan, Srinivasan | G80: ERP | H80: Hase, Raj | I80: Ganesan, Srinivasan | J80: DeHart, Lynn | K80: CONTRACTORS | L80: Market Logistics Functional Support | M80: IBM CORP | N80: 2320521 | O80: IT-FBT0544-OG-US-00 | Q80: 9501181803 | S80: None | V80: 1452300 | W80: 963567.79 | Z80: 48462.57 | AA80: 207334.66 | AB80: 98620.56 | AC80: 116861 | AD80: 28181.63 | AE80: 293546.2 | AF80: -271730.29 | AG80: 186468 | AH80: 65052 | AI80: 65052 | AJ80: 65052 | AK80: 65018 | AL80: =SUM(Z80:AK80) -> 967918.33 | AM80: =ERP_8[[#This Row],[2026 Working Total]]-ERP_8[[#This Row],[LE2 Final Submission]] -> 4350.54 | AN80: 70000 | AO80: =$AE80 - $AN80 -> 223546.2 | AP80: =SUM(ERP_8[[#This Row],[AP01]:[AP07]])-SUM(ERP_8[[#This Row],[AP01 LE2]:[AP07 LE2]]) -> -297291.46 | AQ80: 488000 | AR80: =ERP_8[[#This Row],[2026 Working Total to Budget/LE]]-ERP_8[[#This Row],[Giveback]] -> -483649.46 | AS80: Reduce BAU contractors, Move contractors to offshore.Move contractors to Project funding. | AT80: 48462.57 | AU80: 207334.66 | AV80: 98620.56 | AW80: 132050 | AX80: 132050 | AY80: 132050 | AZ80: 68000 | BA80: 29000 | BB80: 29000 | BC80: 29000 | BD80: 29000 | BE80: 29000 | BF80: 963567.79 | BG80: 48462.57 | BH80: 207334.66 | BI80: 98620.56 | BJ80: 132050 | BK80: 132050 | BL80: 132050 | BM80: 108302.77 | BN80: 100000 | BO80: 100000 | BP80: 100000 | BQ80: 100000 | BR80: 100000 | BS80: 1358870.6
A81: L-ERP-149 | B81: Ganesan, Srinivasan_CONTRACTORS_IT-FBT0545-OG-US-00 | D81: =_xlfn.TEXTJOIN("_",FALSE,E81,ERP_8[[#This Row],[Expense Category]],ERP_8[[#This Row],[Project Code*]]) -> Ganesan, Srinivasan_CONTRACTORS_IT-FBT0545-OG-US-00 | E81: Ganesan, Srinivasan | G81: ERP | H81: Hase, Raj | I81: Ganesan, Srinivasan | J81: DeHart, Lynn | K81: CONTRACTORS | L81: GLNS Functional Support | M81: IBM CORP | N81: 2320521 | O81: IT-FBT0545-OG-US-00 | Q81: 9501178403 | S81: None | V81: 486372.24 | W81: 426376.62 | Z81: 58570.53 | AA81: 65599.81 | AB81: 81999.28 | AC81: 65599.43 | AD81: 65599.42 | AE81: 66848.25 | AF81: -216473.81 | AG81: 47304 | AH81: 44000 | AI81: 44000 | AJ81: 44000 | AK81: 59330 | AL81: =SUM(Z81:AK81) -> 426376.91 | AM81: =ERP_8[[#This Row],[2026 Working Total]]-ERP_8[[#This Row],[LE2 Final Submission]] -> 0.29 | AN81: 11682 | AO81: =$AE81 - $AN81 -> 55166.25 | AP81: =SUM(ERP_8[[#This Row],[AP01]:[AP07]])-SUM(ERP_8[[#This Row],[AP01 LE2]:[AP07 LE2]]) -> -238633.71 | AQ81: 60000 | AR81: =ERP_8[[#This Row],[2026 Working Total to Budget/LE]]-ERP_8[[#This Row],[Giveback]] -> -59999.71 | AS81: Leverage existing contractors. | AT81: 58570.53 | AU81: 65599.81 | AV81: 81999.28 | AW81: 70019 | AX81: 70019 | AY81: 70019 | AZ81: 10150 | BA81: 0 | BB81: 0 | BC81: 0 | BD81: 0 | BE81: 0 | BF81: 426376.62 | BG81: 58570.53 | BH81: 65599.81 | BI81: 81999.28 | BJ81: 69224 | BK81: 69224 | BL81: 69224 | BM81: 71025 | BN81: 15160 | BO81: 0 | BP81: 0 | BQ81: 0 | BR81: 0 | BS81: 500026.62
A82: L-ERP-138 | B82: Ganesan, Srinivasan_CONTRACTORS_IT-FBT0546-OG-US-00 | D82: =_xlfn.TEXTJOIN("_",FALSE,E82,ERP_8[[#This Row],[Expense Category]],ERP_8[[#This Row],[Project Code*]]) -> Ganesan, Srinivasan_CONTRACTORS_IT-FBT0546-OG-US-00 | E82: Ganesan, Srinivasan | G82: ERP | H82: Hase, Raj | I82: Ganesan, Srinivasan | J82: DeHart, Lynn | K82: CONTRACTORS | L82: MuleSoft - GLNS (Contractors)_XFR0786 | O82: IT-FBT0546-OG-US-00 | S82: MuleSoft | V82: 50000 | W82: 50000 | AD82: 0 | AE82: 0 | AG82: 50000 | AH82: 0 | AI82: 0 | AJ82: 0 | AK82: 0 | AL82: =SUM(Z82:AK82) -> 50000 | AM82: =ERP_8[[#This Row],[2026 Working Total]]-ERP_8[[#This Row],[LE2 Final Submission]] -> 0 | AO82: =$AE82 - $AN82 -> 0 | AP82: =SUM(ERP_8[[#This Row],[AP01]:[AP07]])-SUM(ERP_8[[#This Row],[AP01 LE2]:[AP07 LE2]]) -> 0 | AR82: =ERP_8[[#This Row],[2026 Working Total to Budget/LE]]-ERP_8[[#This Row],[Giveback]] -> 0 | BA82: 50000 | BB82: 0 | BC82: 0 | BD82: 0 | BE82: 0 | BF82: 50000 | BN82: 50000 | BO82: 0 | BP82: 0 | BQ82: 0 | BR82: 0 | BS82: 50000
A83: L-ERP-139 | B83: Ganesan, Srinivasan_CONTRACTORS_IT-FBT0657-OG-US-00 | D83: =_xlfn.TEXTJOIN("_",FALSE,E83,ERP_8[[#This Row],[Expense Category]],ERP_8[[#This Row],[Project Code*]]) -> Ganesan, Srinivasan_CONTRACTORS_IT-FBT0657-OG-US-00 | E83: Ganesan, Srinivasan | G83: ERP | H83: Hase, Raj | I83: Ganesan, Srinivasan | J83: DeHart, Lynn | K83: CONTRACTORS | L83: Mulesoft - Logistics (Contractors) | O83: IT-FBT0657-OG-US-00 | S83: MuleSoft | V83: 25000 | W83: 25000 | AD83: 0 | AE83: 0 | AG83: 25000 | AH83: 0 | AI83: 0 | AJ83: 0 | AK83: 0 | AL83: =SUM(Z83:AK83) -> 25000 | AM83: =ERP_8[[#This Row],[2026 Working Total]]-ERP_8[[#This Row],[LE2 Final Submission]] -> 0 | AO83: =$AE83 - $AN83 -> 0 | AP83: =SUM(ERP_8[[#This Row],[AP01]:[AP07]])-SUM(ERP_8[[#This Row],[AP01 LE2]:[AP07 LE2]]) -> 0 | AR83: =ERP_8[[#This Row],[2026 Working Total to Budget/LE]]-ERP_8[[#This Row],[Giveback]] -> 0 | BA83: 25000 | BB83: 0 | BC83: 0 | BD83: 0 | BE83: 0 | BF83: 25000 | BN83: 25000 | BO83: 0 | BP83: 0 | BQ83: 0 | BR83: 0 | BS83: 25000
A84: L-ERP-150 | B84: Ganesan, Srinivasan_CONTRACTORS_IT-FBT0661-OG-US-00 | D84: =_xlfn.TEXTJOIN("_",FALSE,E84,ERP_8[[#This Row],[Expense Category]],ERP_8[[#This Row],[Project Code*]]) -> Ganesan, Srinivasan_CONTRACTORS_IT-FBT0661-OG-US-00 | E84: Ganesan, Srinivasan | G84: ERP | H84: Hase, Raj | I84: Ganesan, Srinivasan | J84: DeHart, Lynn | K84: CONTRACTORS | L84: GLNS Process Optimization & Compliance Contractor | N84: 2320521 | O84: IT-FBT0661-OG-US-00 | S84: None | T84: 4/30 - Team to reclass btwn MG & Contractors | V84: 47697 | W84: 53620 | AC84: 0 | AD84: 5850 | AE84: 0 | AF84: 0 | AG84: 10000 | AH84: 10000 | AI84: 0 | AJ84: 21920 | AK84: 0 | AL84: =SUM(Z84:AK84) -> 47770 | AM84: =ERP_8[[#This Row],[2026 Working Total]]-ERP_8[[#This Row],[LE2 Final Submission]] -> -5850 | AN84: 20000 | AO84: =$AE84 - $AN84 -> -20000 | AP84: =SUM(ERP_8[[#This Row],[AP01]:[AP07]])-SUM(ERP_8[[#This Row],[AP01 LE2]:[AP07 LE2]]) -> -38247 | AR84: =ERP_8[[#This Row],[2026 Working Total to Budget/LE]]-ERP_8[[#This Row],[Giveback]] -> -5850 | AW84: 15000 | AX84: 5850 | AY84: 0 | AZ84: 23247 | BA84: 0 | BB84: 9523 | BC84: 0 | BD84: 0 | BE84: 0 | BF84: 53620 | BJ84: 15000 | BK84: 0 | BL84: 0 | BM84: 23247 | BN84: 0 | BO84: 9523 | BP84: 0 | BQ84: 0 | BR84: 0 | BS84: 47770
A85: L-ERP-135 | B85: Ganesan, Srinivasan_CONTRACTORS_IT-FBT0778-OT-US-00 | D85: =_xlfn.TEXTJOIN("_",FALSE,E85,ERP_8[[#This Row],[Expense Category]],ERP_8[[#This Row],[Project Code*]]) -> Ganesan, Srinivasan_CONTRACTORS_IT-FBT0778-OT-US-00 | E85: Ganesan, Srinivasan | G85: ERP | H85: Hase, Raj | I85: Ganesan, Srinivasan | J85: DeHart, Lynn | K85: CONTRACTORS | L85: MetaStorm - Import Manager Contractor Support | O85: IT-FBT0778-OT-US-00 | S85: Metastorm | T85: 4/30 CHW - duplicate lines moved to match actuals | V85: 25200 | W85: 0 | AD85: 0 | AE85: 0 | AG85: =2100-2100 -> 0 | AH85: =2100-2100 -> 0 | AI85: =2100-2100 -> 0 | AJ85: =2100-2100 -> 0 | AK85: =2100-2100 -> 0 | AL85: =SUM(Z85:AK85) -> 0 | AM85: =ERP_8[[#This Row],[2026 Working Total]]-ERP_8[[#This Row],[LE2 Final Submission]] -> 0 | AN85: 0 | AO85: =$AE85 - $AN85 -> 0 | AP85: =SUM(ERP_8[[#This Row],[AP01]:[AP07]])-SUM(ERP_8[[#This Row],[AP01 LE2]:[AP07 LE2]]) -> 0 | AR85: =ERP_8[[#This Row],[2026 Working Total to Budget/LE]]-ERP_8[[#This Row],[Giveback]] -> 0 | AW85: 0 | AX85: 0 | AY85: 0 | AZ85: 0 | BA85: 0 | BB85: 0 | BC85: 0 | BD85: 0 | BE85: 0 | BF85: 0 | BJ85: 2100 | BK85: 2100 | BL85: 2100 | BM85: 2100 | BN85: 2100 | BO85: 2100 | BP85: 2100 | BQ85: 2100 | BR85: 2100 | BS85: 18900
A86: L-ERP-151 | B86: Ganesan, Srinivasan_CONTRACTORS_IT-FBT0784-OG-US-00 | D86: =_xlfn.TEXTJOIN("_",FALSE,E86,ERP_8[[#This Row],[Expense Category]],ERP_8[[#This Row],[Project Code*]]) -> Ganesan, Srinivasan_CONTRACTORS_IT-FBT0784-OG-US-00 | E86: Ganesan, Srinivasan | G86: ERP | H86: Hase, Raj | I86: Ganesan, Srinivasan | J86: DeHart, Lynn | K86: CONTRACTORS | L86: GLNS Analytics Resources | M86: IBM CORP | N86: 2320521 | O86: IT-FBT0784-OG-US-00 | P86: CHW - F/U | Q86: 9501171323 | S86: None | T86: 4/30 - CHW follow-up with Sashi M on XFR and LE2 status | V86: 1129982.6 | W86: 874707.09 | Z86: 77285 | AA86: 177053.54 | AB86: -2920.45 | AC86: 86558.85 | AD86: 86558.85 | AE86: 98924.39 | AF86: 94986.8 | AG86: 102575 | AH86: 79587 | AI86: 79587 | AJ86: 11552 | AK86: 22422 | AL86: =SUM(Z86:AK86) -> 914169.98 | AM86: =ERP_8[[#This Row],[2026 Working Total]]-ERP_8[[#This Row],[LE2 Final Submission]] -> 39462.89 | AN86: 62406 | AO86: =$AE86 - $AN86 -> 36518.39 | AP86: =SUM(ERP_8[[#This Row],[AP01]:[AP07]])-SUM(ERP_8[[#This Row],[AP01 LE2]:[AP07 LE2]]) -> 20429.89 | AQ86: 255000 | AR86: =ERP_8[[#This Row],[2026 Working Total to Budget/LE]]-ERP_8[[#This Row],[Giveback]] -> -215537.11 | AS86: $770K to be transferred to Sashi in 2027 | AT86: 77285 | AU86: 177053.54 | AV86: -2920.45 | AW86: 97087 | AX86: 97087 | AY86: 97087 | AZ86: 55338 | BA86: 55338 | BB86: 55338 | BC86: 55338 | BD86: 55338 | BE86: 55338 | BF86: 874707.09 | BG86: 77285 | BH86: 177053.54 | BI86: -2920.45 | BJ86: 90495 | BK86: 90495 | BL86: 99200 | BM86: 54165 | BN86: 54165 | BO86: 54165 | BP86: 54165 | BQ86: 54165 | BR86: 54165 | BS86: 856598.09
A87: L-ERP-152 | B87: Ganesan, Srinivasan_CONTRACTORS_IT-FBT0790-OG-US-00 | D87: =_xlfn.TEXTJOIN("_",FALSE,E87,ERP_8[[#This Row],[Expense Category]],ERP_8[[#This Row],[Project Code*]]) -> Ganesan, Srinivasan_CONTRACTORS_IT-FBT0790-OG-US-00 | E87: Ganesan, Srinivasan | G87: ERP | H87: Hase, Raj | I87: Ganesan, Srinivasan | J87: DeHart, Lynn | K87: CONTRACTORS | L87: GLNS Functional Support_XFR0974 & XFR0929 & XFR0906 & XFR0959 | N87: 2320521 | O87: IT-FBT0790-OG-US-00 | S87: None | V87: 513000 | W87: 384928.75 | Z87: 98474.5 | AA87: -21757.25 | AB87: -81628.5 | AC87: -18382.5 | AD87: 0 | AE87: 0 | AF87: 153730.32 | AG87: 43860 | AH87: 34723 | AI87: 78017 | AJ87: 43860 | AK87: 36923 | AL87: =SUM(Z87:AK87) -> 367819.57 | AM87: =ERP_8[[#This Row],[2026 Working Total]]-ERP_8[[#This Row],[LE2 Final Submission]] -> -17109.18 | AN87: 69140 | AO87: =$AE87 - $AN87 -> -69140 | AP87: =SUM(ERP_8[[#This Row],[AP01]:[AP07]])-SUM(ERP_8[[#This Row],[AP01 LE2]:[AP07 LE2]]) -> 71207.82 | AQ87: 128000 | AR87: =ERP_8[[#This Row],[2026 Working Total to Budget/LE]]-ERP_8[[#This Row],[Giveback]] -> -145109.18 | AS87: Giveback is the portain earmarked for colleague vacant position that was already accounted for in Compensation. | AT87: 98474.5 | AU87: -21757.25 | AV87: -81628.5 | AW87: 0 | AX87: 0 | AY87: 0 | AZ87: 64140 | BA87: 64140 | BB87: 64140 | BC87: 64140 | BD87: 64140 | BE87: 69140 | BF87: 384928.75 | BG87: 98474.5 | BH87: -21757.25 | BI87: -81628.5 | BJ87: 7667 | BK87: 9667 | BL87: 15667 | BM87: 70892 | BN87: 65000 | BO87: 65000 | BP87: 65000 | BQ87: 65000 | BR87: 65000 | BS87: 423981.75
A88: L-ERP-016 | B88: DeHart, Lynn_CONTRACTORS_IT-PBU0901-OT-US-00 | D88: =_xlfn.TEXTJOIN("_",FALSE,E88,ERP_8[[#This Row],[Expense Category]],ERP_8[[#This Row],[Project Code*]]) -> Ganesan, Srinivasan_CONTRACTORS_IT-PBU0901-OT-US-00 | E88: Ganesan, Srinivasan | G88: ERP | H88: Hase, Raj | I88: DeHart, Lynn | J88: DeHart, Lynn | K88: CONTRACTORS | L88: P324-0013439-GSC EMEA: Dx Sub-cluster – | N88: 2351818 | O88: IT-PBU0901-OT-US-00 | Q88: 9501182061 | S88: None | T88: 8/3 - Move LT Member-1 to Srinivasan Ganesan (RG) | V88: 0 | W88: 0.33 | AA88: 63054.92 | AB88: -63054.59 | AC88: 0 | AD88: 0 | AE88: 0 | AF88: 0 | AG88: 0 | AH88: 0 | AI88: 0 | AJ88: 0 | AK88: 0 | AL88: =SUM(Z88:AK88) -> 0.33 | AM88: =ERP_8[[#This Row],[2026 Working Total]]-ERP_8[[#This Row],[LE2 Final Submission]] -> 0 | AN88: 0 | AO88: =$AE88 - $AN88 -> 0 | AP88: =SUM(ERP_8[[#This Row],[AP01]:[AP07]])-SUM(ERP_8[[#This Row],[AP01 LE2]:[AP07 LE2]]) -> 0 | AR88: =ERP_8[[#This Row],[2026 Working Total to Budget/LE]]-ERP_8[[#This Row],[Giveback]] -> 0 | AU88: 63054.92 | AV88: -63054.59 | AW88: 0 | AX88: 0 | AY88: 0 | AZ88: 0 | BA88: 0 | BB88: 0 | BC88: 0 | BD88: 0 | BE88: 0 | BF88: 0.33 | BH88: 63054.92 | BI88: -63054.59 | BJ88: 0 | BK88: 0 | BL88: 0 | BM88: 0 | BN88: 0 | BO88: 0 | BP88: 0 | BQ88: 0 | BR88: 0 | BS88: 0.33
A89: L-ERP-017 | B89: DeHart, Lynn_CONTRACTORS_IT-PBU1059-OT-US-00 | D89: =_xlfn.TEXTJOIN("_",FALSE,E89,ERP_8[[#This Row],[Expense Category]],ERP_8[[#This Row],[Project Code*]]) -> Ganesan, Srinivasan_CONTRACTORS_IT-PBU1059-OT-US-00 | E89: Ganesan, Srinivasan | G89: ERP | H89: Hase, Raj | I89: DeHart, Lynn | J89: DeHart, Lynn | K89: CONTRACTORS | L89: P325-0016309-2026 GSC Regions: Logistics | N89: 2351818 | O89: IT-PBU1059-OT-US-00 | Q89: Multiple | S89: None | T89: 8/3 - Move LT Member-1 to Srinivasan Ganesan (RG) | V89: 0 | W89: 0 | AA89: 89550.8 | AB89: -89550.8 | AC89: 0 | AD89: 0 | AE89: 0 | AF89: 0 | AL89: =SUM(Z89:AK89) -> 0 | AM89: =ERP_8[[#This Row],[2026 Working Total]]-ERP_8[[#This Row],[LE2 Final Submission]] -> 0 | AO89: =$AE89 - $AN89 -> 0 | AP89: =SUM(ERP_8[[#This Row],[AP01]:[AP07]])-SUM(ERP_8[[#This Row],[AP01 LE2]:[AP07 LE2]]) -> 0 | AR89: =ERP_8[[#This Row],[2026 Working Total to Budget/LE]]-ERP_8[[#This Row],[Giveback]] -> 0 | AU89: 89550.8 | AV89: -89550.8 | BF89: 0 | BH89: 89550.8 | BI89: -89550.8 | BS89: 0
A90: L-ERP-153 | B90: Ganesan, Srinivasan_CONTRACTORS_IT-SFT1205-86-OG-US | D90: =_xlfn.TEXTJOIN("_",FALSE,E90,ERP_8[[#This Row],[Expense Category]],ERP_8[[#This Row],[Project Code*]]) -> Ganesan, Srinivasan_CONTRACTORS_IT-SFT1205-86-OG-US | E90: Ganesan, Srinivasan | G90: ERP | H90: Hase, Raj | I90: Ganesan, Srinivasan | J90: DeHart, Lynn | K90: CONTRACTORS | L90: Logistics E2Open Software Support | N90: 2320521 | O90: IT-SFT1205-86-OG-US | S90: None | V90: 0 | W90: 3710 | AA90: 3710 | AB90: 0 | AC90: 0 | AD90: 0 | AE90: 0 | AF90: 0 | AG90: 0 | AH90: 0 | AI90: 0 | AJ90: 0 | AK90: 0 | AL90: =SUM(Z90:AK90) -> 3710 | AM90: =ERP_8[[#This Row],[2026 Working Total]]-ERP_8[[#This Row],[LE2 Final Submission]] -> 0 | AN90: 0 | AO90: =$AE90 - $AN90 -> 0 | AP90: =SUM(ERP_8[[#This Row],[AP01]:[AP07]])-SUM(ERP_8[[#This Row],[AP01 LE2]:[AP07 LE2]]) -> 0 | AR90: =ERP_8[[#This Row],[2026 Working Total to Budget/LE]]-ERP_8[[#This Row],[Giveback]] -> 0 | AS90: Need to be cross charged to projects. | AU90: 3710 | AV90: 0 | AW90: 0 | AX90: 0 | AY90: 0 | AZ90: 0 | BA90: 0 | BB90: 0 | BC90: 0 | BD90: 0 | BE90: 0 | BF90: 3710 | BH90: 3710 | BI90: 0 | BJ90: 0 | BK90: 0 | BL90: 0 | BM90: 0 | BN90: 0 | BO90: 0 | BP90: 0 | BQ90: 0 | BR90: 0 | BS90: 3710
A91: L-ERP-155 | B91: Ganesan, Srinivasan_CONTRACTORS_MISC001 | D91: =_xlfn.TEXTJOIN("_",FALSE,E91,ERP_8[[#This Row],[Expense Category]],ERP_8[[#This Row],[Project Code*]]) -> Ganesan, Srinivasan_CONTRACTORS_MISC001 | E91: Ganesan, Srinivasan | G91: ERP | H91: Hase, Raj | I91: Ganesan, Srinivasan | J91: DeHart, Lynn | K91: CONTRACTORS | L91: Miscellaneous Charges | N91: 2320521 | O91: MISC001 | S91: None | V91: 0 | W91: -0.47 | Z91: -0.29 | AA91: 0.43 | AB91: -0.61 | AC91: 0.34 | AD91: 0.22 | AE91: 0.05 | AF91: 0 | AG91: 0 | AH91: 0 | AI91: 0 | AJ91: 0 | AK91: 0 | AL91: =SUM(Z91:AK91) -> 0.14 | AM91: =ERP_8[[#This Row],[2026 Working Total]]-ERP_8[[#This Row],[LE2 Final Submission]] -> 0.61 | AN91: 0 | AO91: =$AE91 - $AN91 -> 0.05 | AP91: =SUM(ERP_8[[#This Row],[AP01]:[AP07]])-SUM(ERP_8[[#This Row],[AP01 LE2]:[AP07 LE2]]) -> 0.61 | AR91: =ERP_8[[#This Row],[2026 Working Total to Budget/LE]]-ERP_8[[#This Row],[Giveback]] -> 0.61 | AT91: -0.29 | AU91: 0.43 | AV91: -0.61 | AW91: 0 | AX91: 0 | AY91: 0 | AZ91: 0 | BA91: 0 | BB91: 0 | BC91: 0 | BD91: 0 | BE91: 0 | BF91: -0.47 | BG91: -0.29 | BH91: 0.43 | BI91: -0.61 | BJ91: 0 | BK91: 0 | BL91: 0 | BM91: 0 | BN91: 0 | BO91: 0 | BP91: 0 | BQ91: 0 | BR91: 0 | BS91: -0.47
A92: L-ERP-156 | B92: Ganesan, Srinivasan_CONTRACTORS_POClosure001 | D92: =_xlfn.TEXTJOIN("_",FALSE,E92,ERP_8[[#This Row],[Expense Category]],ERP_8[[#This Row],[Project Code*]]) -> Ganesan, Srinivasan_CONTRACTORS_POClosure001 | E92: Ganesan, Srinivasan | G92: ERP | H92: Hase, Raj | I92: Ganesan, Srinivasan | J92: DeHart, Lynn | K92: CONTRACTORS | L92: PO Closure Credit | N92: 2320521 | O92: POClosure001 | P92: CHW - Ok | S92: None | V92: 0 | W92: -8178.72 | Z92: -879.72 | AA92: -0.18 | AB92: -7298.82 | AC92: 0 | AD92: 0 | AE92: 0 | AF92: 0 | AG92: 0 | AH92: 0 | AI92: 0 | AJ92: 0 | AK92: 0 | AL92: =SUM(Z92:AK92) -> -8178.72 | AM92: =ERP_8[[#This Row],[2026 Working Total]]-ERP_8[[#This Row],[LE2 Final Submission]] -> 0 | AN92: 0 | AO92: =$AE92 - $AN92 -> 0 | AP92: =SUM(ERP_8[[#This Row],[AP01]:[AP07]])-SUM(ERP_8[[#This Row],[AP01 LE2]:[AP07 LE2]]) -> 0 | AR92: =ERP_8[[#This Row],[2026 Working Total to Budget/LE]]-ERP_8[[#This Row],[Giveback]] -> 0 | AT92: -879.72 | AU92: -0.18 | AV92: -7298.82 | AW92: 0 | AX92: 0 | AY92: 0 | AZ92: 0 | BA92: 0 | BB92: 0 | BC92: 0 | BD92: 0 | BE92: 0 | BF92: -8178.72 | BG92: -879.72 | BH92: -0.18 | BI92: -7298.82 | BJ92: 0 | BK92: 0 | BL92: 0 | BM92: 0 | BN92: 0 | BO92: 0 | BP92: 0 | BQ92: 0 | BR92: 0 | BS92: -8178.72
A93: ERP-070 | B93: Hase, Raj_CONTRACTORS | D93: =_xlfn.TEXTJOIN("_",FALSE,E93,ERP_8[[#This Row],[Expense Category]],ERP_8[[#This Row],[Project Code*]]) -> Hase, Raj_CONTRACTORS_ | E93: Hase, Raj | G93: ERP | H93: Hase, Raj | I93: Hase, Raj | J93: Hase, Raj | K93: CONTRACTORS | L93: SAP RISE | S93: Digital Funded Project | T93: P326-0017566 - SAP RISE (pending CPA approval) | AI93: 25000 | AJ93: 25000 | AK93: 48924 | AL93: =SUM(Z93:AK93) -> 98924 | AM93: =ERP_8[[#This Row],[2026 Working Total]]-ERP_8[[#This Row],[LE2 Final Submission]] -> 98924 | AO93: =$AE93 - $AN93 -> 0 | AP93: =SUM(ERP_8[[#This Row],[AP01]:[AP07]])-SUM(ERP_8[[#This Row],[AP01 LE2]:[AP07 LE2]]) -> 0 | AR93: =ERP_8[[#This Row],[2026 Working Total to Budget/LE]]-ERP_8[[#This Row],[Giveback]] -> 98924
A94: N-ERP-567 | B94: Hase, Raj_CONTRACTORS_ColleagueSolutions001 | D94: =_xlfn.TEXTJOIN("_",FALSE,E94,ERP_8[[#This Row],[Expense Category]],ERP_8[[#This Row],[Project Code*]]) -> Hase, Raj_CONTRACTORS_ColleagueSolutions001 | E94: Hase, Raj | G94: ERP | H94: Hase, Raj | I94: Hase, Raj | J94: DeHart, Lynn | K94: CONTRACTORS | L94: Colleague Solutions Delivery Chargebacks | O94: ColleagueSolutions001 | P94: CHW - Ok | Q94: N/A | S94: None | T94: 4/28/26 CHW New add to tie-out 0223 to 0317 Planful Extracts | V94: 437.38 | W94: 0 | AD94: 0 | AE94: 0 | AG94: 0 | AH94: 0 | AI94: 0 | AJ94: 0 | AK94: 0 | AL94: =SUM(Z94:AK94) -> 0 | AM94: =ERP_8[[#This Row],[2026 Working Total]]-ERP_8[[#This Row],[LE2 Final Submission]] -> 0 | AN94: 0 | AO94: =$AE94 - $AN94 -> 0 | AP94: =SUM(ERP_8[[#This Row],[AP01]:[AP07]])-SUM(ERP_8[[#This Row],[AP01 LE2]:[AP07 LE2]]) -> 0 | AR94: =ERP_8[[#This Row],[2026 Working Total to Budget/LE]]-ERP_8[[#This Row],[Giveback]] -> 0 | AW94: 0 | AX94: 0 | AY94: 0 | AZ94: 0 | BA94: 0 | BB94: 0 | BC94: 0 | BD94: 0 | BE94: 0 | BF94: 0 | BG94: 0 | BH94: 437.38 | BI94: 0 | BJ94: 0 | BK94: 0 | BL94: 0 | BM94: 0 | BN94: 0 | BO94: 0 | BP94: 0 | BQ94: 0 | BR94: 0 | BS94: =SUM(ERP_8[[#This Row],[2026 AP01]:[2026 AP12]]) -> 437.38
A95: L-ERP-186 | B95: Hase, Raj_CONTRACTORS_EnhanceChargeout001 | D95: =_xlfn.TEXTJOIN("_",FALSE,E95,ERP_8[[#This Row],[Expense Category]],ERP_8[[#This Row],[Project Code*]]) -> Hase, Raj_CONTRACTORS_EnhanceChargeout001 | E95: Hase, Raj | G95: ERP | H95: Hase, Raj | I95: Hase, Raj | J95: DeHart, Lynn | K95: CONTRACTORS | L95: Enhance Chargeout Cost Centers | N95: 2340693 | O95: EnhanceChargeout001 | P95: CHW - F/U | S95: None | T95: 6/15 - balance to zero | V95: 0 | W95: 0 | Z95: 579568 | AA95: -598991 | AB95: -317436 | AC95: 577046 | AD95: -397395 | AE95: 179883 | AF95: 439613.8 | AG95: =-462289/2 -> -231144.5 | AH95: =-462289/2 -> -231144.5 | AL95: =SUM(Z95:AK95) -> -0.2 | AM95: =ERP_8[[#This Row],[2026 Working Total]]-ERP_8[[#This Row],[LE2 Final Submission]] -> -0.2 | AN95: 0 | AO95: =$AE95 - $AN95 -> 179883 | AP95: =SUM(ERP_8[[#This Row],[AP01]:[AP07]])-SUM(ERP_8[[#This Row],[AP01 LE2]:[AP07 LE2]]) -> 462288.8 | AR95: =ERP_8[[#This Row],[2026 Working Total to Budget/LE]]-ERP_8[[#This Row],[Giveback]] -> -0.2 | AT95: 579568 | AU95: -598991 | AV95: -317436 | AW95: 110000 | AX95: 110000 | AY95: 116859 | BF95: 0 | BG95: 579568 | BH95: -598991 | BI95: -317436 | BJ95: 0 | BK95: 0 | BL95: 0 | BM95: 0 | BN95: 0 | BO95: 0 | BP95: 0 | BQ95: 0 | BR95: 0 | BS95: -336859
A96: L-ERP-570 | B96: Yeluri, Durga_CONTRACTORS_EP&SCharges001 | D96: =_xlfn.TEXTJOIN("_",FALSE,E96,ERP_8[[#This Row],[Expense Category]],ERP_8[[#This Row],[Project Code*]]) -> Hase, Raj_CONTRACTORS_EP&SCharges001 | E96: Hase, Raj | G96: ERP | H96: Hase, Raj | I96: Yeluri, Durga | J96: DeHart, Lynn | K96: CONTRACTORS | L96: Infrastructure Billing Charges | N96: 2329612 | O96: EP&SCharges001 | Q96: N/A | S96: EP&S | V96: 24000 | W96: 18457.8 | Z96: 366.24 | AA96: 0 | AB96: 91.56 | AC96: 0 | AD96: 0 | AE96: 0 | AF96: 0 | AG96: 2000 | AH96: 2000 | AI96: 2000 | AJ96: 2000 | AK96: 2000 | AL96: =SUM(Z96:AK96) -> 10457.8 | AM96: =ERP_8[[#This Row],[2026 Working Total]]-ERP_8[[#This Row],[LE2 Final Submission]] -> -8000 | AN96: 0 | AO96: =$AE96 - $AN96 -> 0 | AP96: =SUM(ERP_8[[#This Row],[AP01]:[AP07]])-SUM(ERP_8[[#This Row],[AP01 LE2]:[AP07 LE2]]) -> -8000 | AR96: =ERP_8[[#This Row],[2026 Working Total to Budget/LE]]-ERP_8[[#This Row],[Giveback]] -> -8000 | AT96: 366.24 | AU96: 0 | AV96: 91.56 | AW96: 2000 | AX96: 2000 | AY96: 2000 | AZ96: 2000 | BA96: 2000 | BB96: 2000 | BC96: 2000 | BD96: 2000 | BE96: 2000 | BF96: 18457.8 | BG96: 366.24 | BH96: 0 | BI96: 91.56 | BJ96: 2000 | BK96: 2000 | BL96: 2000 | BM96: 2000 | BN96: 2000 | BO96: 2000 | BP96: 2000 | BQ96: 2000 | BR96: 2000 | BS96: 18457.8
A97: ERP-038 | B97: Hase, Raj_CONTRACTORS_IT-FBT0450-OG-US-00 | D97: =_xlfn.TEXTJOIN("_",FALSE,E97,ERP_8[[#This Row],[Expense Category]],ERP_8[[#This Row],[Project Code*]]) -> Hase, Raj_CONTRACTORS_IT-FBT0450-OG-US-00 | E97: Hase, Raj | G97: ERP | H97: Hase, Raj | I97: Hase, Raj | J97: Hase, Raj | K97: CONTRACTORS | L97: CLD Retrieval Servic - RC03-RC05--MEDICAID CLAIMS LEVEL DETAIL (CLD) QUA | N97: 2329609 | O97: IT-FBT0450-OG-US-00 | Q97: 9501148914 | T97: 8/11 TW: submitted reclass form 000690 to move charges from contractors to MS. Zeroed out AP10 forecast and in contractors and added to AP10 forecast for MS. '8/5 $50k remaining on this PO. Actuals reported on both lines total to $150k. Total forecast $200k. '6/15 Forecast moved from Managed Services L-ERP-180 to Contractors line ERP-038 to align with PO Actuals Forecast moved from Mike H to Raj H | AD97: 50000 | AE97: 0 | AF97: 0 | AG97: -50000 | AI97: 50000 | AL97: =SUM(Z97:AK97) -> 50000 | AM97: =ERP_8[[#This Row],[2026 Working Total]]-ERP_8[[#This Row],[LE2 Final Submission]] -> 50000 | AN97: 0 | AO97: =$AE97 - $AN97 -> 0 | AP97: =SUM(ERP_8[[#This Row],[AP01]:[AP07]])-SUM(ERP_8[[#This Row],[AP01 LE2]:[AP07 LE2]]) -> 50000 | AR97: =ERP_8[[#This Row],[2026 Working Total to Budget/LE]]-ERP_8[[#This Row],[Giveback]] -> 50000
A98: ERP-039 | B98: Hase, Raj_CONTRACTORS_MISC001 | D98: =_xlfn.TEXTJOIN("_",FALSE,E98,ERP_8[[#This Row],[Expense Category]],ERP_8[[#This Row],[Project Code*]]) -> Hase, Raj_CONTRACTORS_MISC001 | E98: Hase, Raj | G98: ERP | H98: Hase, Raj | I98: Hase, Raj | J98: Hase, Raj | K98: CONTRACTORS | L98: Miscellaneous Charges | N98: 2329609 | O98: MISC001 | AD98: 0 | AE98: 0 | AF98: 0 | AL98: =SUM(Z98:AK98) -> 0 | AM98: =ERP_8[[#This Row],[2026 Working Total]]-ERP_8[[#This Row],[LE2 Final Submission]] -> 0 | AO98: =$AE98 - $AN98 -> 0 | AP98: =SUM(ERP_8[[#This Row],[AP01]:[AP07]])-SUM(ERP_8[[#This Row],[AP01 LE2]:[AP07 LE2]]) -> 0 | AR98: =ERP_8[[#This Row],[2026 Working Total to Budget/LE]]-ERP_8[[#This Row],[Giveback]] -> 0
A99: L-ERP-578 | B99: Yeluri, Durga_CONTRACTORS_MISC001 | D99: =_xlfn.TEXTJOIN("_",FALSE,E99,ERP_8[[#This Row],[Expense Category]],ERP_8[[#This Row],[Project Code*]]) -> Hase, Raj_CONTRACTORS_MISC001 | E99: Hase, Raj | G99: ERP | H99: Hase, Raj | I99: Yeluri, Durga | J99: DeHart, Lynn | K99: CONTRACTORS | L99: Miscellaneous Charges | N99: 2329612 | O99: MISC001 | S99: None | V99: 0 | W99: 0.34 | Z99: -0.1 | AA99: 0 | AB99: 0.44 | AC99: 0 | AD99: 0 | AE99: 0 | AF99: 0 | AG99: 0 | AH99: 0 | AI99: 0 | AJ99: 0 | AK99: 0 | AL99: =SUM(Z99:AK99) -> 0.34 | AM99: =ERP_8[[#This Row],[2026 Working Total]]-ERP_8[[#This Row],[LE2 Final Submission]] -> 0 | AN99: 0 | AO99: =$AE99 - $AN99 -> 0 | AP99: =SUM(ERP_8[[#This Row],[AP01]:[AP07]])-SUM(ERP_8[[#This Row],[AP01 LE2]:[AP07 LE2]]) -> 0 | AR99: =ERP_8[[#This Row],[2026 Working Total to Budget/LE]]-ERP_8[[#This Row],[Giveback]] -> 0 | AT99: -0.1 | AU99: 0 | AV99: 0.44 | AW99: 0 | AX99: 0 | AY99: 0 | AZ99: 0 | BA99: 0 | BB99: 0 | BC99: 0 | BD99: 0 | BE99: 0 | BF99: 0.34 | BG99: -0.1 | BH99: 0 | BI99: 0.44 | BJ99: 0 | BK99: 0 | BL99: 0 | BM99: 0 | BN99: 0 | BO99: 0 | BP99: 0 | BQ99: 0 | BR99: 0 | BS99: 0.34
A100: L-ERP-579 | B100: Yeluri, Durga_CONTRACTORS_POClosure001 | D100: =_xlfn.TEXTJOIN("_",FALSE,E100,ERP_8[[#This Row],[Expense Category]],ERP_8[[#This Row],[Project Code*]]) -> Hase, Raj_CONTRACTORS_POClosure001 | E100: Hase, Raj | G100: ERP | H100: Hase, Raj | I100: Yeluri, Durga | J100: DeHart, Lynn | K100: CONTRACTORS | L100: PO Closure Credit | N100: 2329612 | O100: POClosure001 | P100: CHW - Ok | S100: None | V100: 0 | W100: -4133.14 | Z100: -4133.14 | AA100: 0 | AB100: 0 | AC100: 0 | AD100: 0 | AE100: 0 | AF100: 0 | AG100: 0 | AH100: 0 | AI100: 0 | AJ100: 0 | AK100: 0 | AL100: =SUM(Z100:AK100) -> -4133.14 | AM100: =ERP_8[[#This Row],[2026 Working Total]]-ERP_8[[#This Row],[LE2 Final Submission]] -> 0 | AN100: 0 | AO100: =$AE100 - $AN100 -> 0 | AP100: =SUM(ERP_8[[#This Row],[AP01]:[AP07]])-SUM(ERP_8[[#This Row],[AP01 LE2]:[AP07 LE2]]) -> 0 | AR100: =ERP_8[[#This Row],[2026 Working Total to Budget/LE]]-ERP_8[[#This Row],[Giveback]] -> 0 | AT100: -4133.14 | AU100: 0 | AV100: 0 | AW100: 0 | AX100: 0 | AY100: 0 | AZ100: 0 | BA100: 0 | BB100: 0 | BC100: 0 | BD100: 0 | BE100: 0 | BF100: -4133.14 | BG100: -4133.14 | BH100: 0 | BI100: 0 | BJ100: 0 | BK100: 0 | BL100: 0 | BM100: 0 | BN100: 0 | BO100: 0 | BP100: 0 | BQ100: 0 | BR100: 0 | BS100: -4133.14
A101: L-ERP-197 | B101: Herman, Shaun_CONTRACTORS_EP&SCharges001 | D101: =_xlfn.TEXTJOIN("_",FALSE,E101,ERP_8[[#This Row],[Expense Category]],ERP_8[[#This Row],[Project Code*]]) -> Herman, Shaun_CONTRACTORS_EP&SCharges001 | E101: Herman, Shaun | G101: ERP | H101: Hase, Raj | I101: Herman, Shaun | J101: DeHart, Lynn | K101: CONTRACTORS | L101: Infrastructure Billing Charges | N101: 2329611 | O101: EP&SCharges001 | Q101: N/A | S101: EP&S | V101: 0 | W101: 2893.46 | Z101: 183.12 | AA101: 1029.04 | AB101: 1681.3 | AC101: 1593.8 | AD101: 85.08 | AE101: 0 | AF101: 901.43 | AG101: 0 | AH101: 0 | AI101: 0 | AJ101: 0 | AK101: 0 | AL101: =SUM(Z101:AK101) -> 5473.77 | AM101: =ERP_8[[#This Row],[2026 Working Total]]-ERP_8[[#This Row],[LE2 Final Submission]] -> 2580.31 | AN101: 0 | AO101: =$AE101 - $AN101 -> 0 | AP101: =SUM(ERP_8[[#This Row],[AP01]:[AP07]])-SUM(ERP_8[[#This Row],[AP01 LE2]:[AP07 LE2]]) -> 2580.31 | AR101: =ERP_8[[#This Row],[2026 Working Total to Budget/LE]]-ERP_8[[#This Row],[Giveback]] -> 2580.31 | AT101: 183.12 | AU101: 1029.04 | AV101: 1681.3 | AW101: 0 | AX101: 0 | AY101: 0 | AZ101: 0 | BA101: 0 | BB101: 0 | BC101: 0 | BD101: 0 | BE101: 0 | BF101: 2893.46 | BG101: 183.12 | BH101: 1029.04 | BI101: 1681.3 | BJ101: 0 | BK101: 0 | BL101: 0 | BM101: 0 | BN101: 0 | BO101: 0 | BP101: 0 | BQ101: 0 | BR101: 0 | BS101: 2893.46
A102: L-ERP-204 | B102: Herman, Shaun_CONTRACTORS_IT-CTR0024-OG-US-00 | D102: =_xlfn.TEXTJOIN("_",FALSE,E102,ERP_8[[#This Row],[Expense Category]],ERP_8[[#This Row],[Project Code*]]) -> Herman, Shaun_CONTRACTORS_IT-CTR0024-OG-US-00 | E102: Herman, Shaun | G102: ERP | H102: Hase, Raj | I102: Herman, Shaun | J102: DeHart, Lynn | K102: CONTRACTORS | L102: Master Data BAU support_XFR0672 & XFR0938 & XFR0934 & XFR0932 & XFR0846 & XFR0913 | M102: ACCENTURE LLP | N102: 2329611 | O102: IT-CTR0024-OG-US-00 | Q102: 9501157539 | S102: None | V102: 400000 | W102: 300897.52 | Z102: 123337.5 | AA102: 19442.91 | AB102: 113117.11 | AC102: 5172.15 | AD102: -24184.46 | AE102: -229891 | AF102: 761.56 | AG102: 61248 | AH102: 61248 | AI102: 61248 | AJ102: 61248 | AK102: 61248 | AL102: =SUM(Z102:AK102) -> 313995.77 | AM102: =ERP_8[[#This Row],[2026 Working Total]]-ERP_8[[#This Row],[LE2 Final Submission]] -> 13098.25 | AN102: 0 | AO102: =$AE102 - $AN102 -> -229891 | AP102: =SUM(ERP_8[[#This Row],[AP01]:[AP07]])-SUM(ERP_8[[#This Row],[AP01 LE2]:[AP07 LE2]]) -> -113141.75 | AR102: =ERP_8[[#This Row],[2026 Working Total to Budget/LE]]-ERP_8[[#This Row],[Giveback]] -> 13098.25 | AS102: Onshore/Offshore Mix Adjustment | AT102: 123337.5 | AU102: 19442.91 | AV102: 113117.11 | AW102: 5000 | AX102: -200000 | AY102: 30000 | AZ102: 30000 | BA102: 30000 | BB102: 30000 | BC102: 40000 | BD102: 40000 | BE102: 40000 | BF102: 300897.52 | BG102: 123337.5 | BH102: 19442.91 | BI102: 113117.11 | BJ102: 30000 | BK102: 30000 | BL102: 30000 | BM102: 30000 | BN102: 30000 | BO102: 20000 | BP102: 20000 | BQ102: 20000 | BR102: 20000 | BS102: 485897.52
...

Sheet Sheet1
A2: L-ERP-170 | B2: Ganesan, Srinivasan_COMPENSATION_CompBenefits001 | D2: =_xlfn.TEXTJOIN("_",FALSE,E2,ERP_8[[#This Row],[Expense Category]],ERP_8[[#This Row],[Project Code*]]) -> #VALUE! | E2: Ganesan, Srinivasan | G2: ERP | H2: Hase, Raj | I2: Ganesan, Srinivasan | J2: DeHart, Lynn | K2: COMPENSATION | L2: Benefits | O2: CompBenefits001 | P2: CHW - Ok | Q2: N/A | S2: None | V2: 0 | W2: 0 | AD2: 0 | AE2: 0 | AG2: 0 | AH2: 0 | AI2: 0 | AJ2: 0 | AK2: 0 | AL2: =SUM(Z2:AK2) -> 0 | AM2: =ERP_8[[#This Row],[2026 Working Total]]-ERP_8[[#This Row],[LE2 Final Submission]] -> #VALUE! | AN2: 0 | AO2: =$AE2 - $AN2 -> 0 | AP2: =SUM(ERP_8[[#This Row],[AP01]:[AP07]])-SUM(ERP_8[[#This Row],[AP01 LE2]:[AP07 LE2]]) -> #VALUE! | AR2: =ERP_8[[#This Row],[2026 Working Total to Budget/LE]]-ERP_8[[#This Row],[Giveback]] -> #VALUE! | AW2: 0 | AX2: 0 | AY2: 0 | AZ2: 0 | BA2: 0 | BB2: 0 | BC2: 0 | BD2: 0 | BE2: 0 | BF2: 0 | BG2: 3835.35 | BH2: 2416.25 | BI2: 3735.66 | BJ2: 0 | BK2: 0 | BL2: 0 | BM2: 0 | BN2: 0 | BO2: 0 | BP2: 0 | BQ2: 0 | BR2: 0 | BS2: 9987.26
A3: L-ERP-171 | B3: Ganesan, Srinivasan_COMPENSATION_CompBonus001 | D3: =_xlfn.TEXTJOIN("_",FALSE,E3,ERP_8[[#This Row],[Expense Category]],ERP_8[[#This Row],[Project Code*]]) -> #VALUE! | E3: Ganesan, Srinivasan | G3: ERP | H3: Hase, Raj | I3: Ganesan, Srinivasan | J3: DeHart, Lynn | K3: COMPENSATION | L3: Bonus | O3: CompBonus001 | P3: CHW - Ok | Q3: N/A | S3: None | V3: 0 | W3: 0 | AD3: 0 | AE3: 0 | AG3: 0 | AH3: 0 | AI3: 0 | AJ3: 0 | AK3: 0 | AL3: =SUM(Z3:AK3) -> 0 | AM3: =ERP_8[[#This Row],[2026 Working Total]]-ERP_8[[#This Row],[LE2 Final Submission]] -> #VALUE! | AN3: 0 | AO3: =$AE3 - $AN3 -> 0 | AP3: =SUM(ERP_8[[#This Row],[AP01]:[AP07]])-SUM(ERP_8[[#This Row],[AP01 LE2]:[AP07 LE2]]) -> #VALUE! | AR3: =ERP_8[[#This Row],[2026 Working Total to Budget/LE]]-ERP_8[[#This Row],[Giveback]] -> #VALUE! | AW3: 0 | AX3: 0 | AY3: 0 | AZ3: 0 | BA3: 0 | BB3: 0 | BC3: 0 | BD3: 0 | BE3: 0 | BF3: 0 | BG3: 3779.53 | BH3: 7255.22 | BI3: 5363.84 | BJ3: 0 | BK3: 0 | BL3: 0 | BM3: 0 | BN3: 0 | BO3: 0 | BP3: 0 | BQ3: 0 | BR3: 0 | BS3: 16398.59
A4: L-ERP-172 | B4: Ganesan, Srinivasan_COMPENSATION_CompSalary001 | D4: =_xlfn.TEXTJOIN("_",FALSE,E4,ERP_8[[#This Row],[Expense Category]],ERP_8[[#This Row],[Project Code*]]) -> #VALUE! | E4: Ganesan, Srinivasan | G4: ERP | H4: Hase, Raj | I4: Ganesan, Srinivasan | J4: DeHart, Lynn | K4: COMPENSATION | L4: Salary | O4: CompSalary001 | P4: CHW - Ok | Q4: N/A | S4: None | V4: 0 | W4: 0 | AG4: 0 | AH4: 0 | AI4: 0 | AJ4: 0 | AK4: 0 | AL4: =SUM(Z4:AK4) -> 0 | AM4: =ERP_8[[#This Row],[2026 Working Total]]-ERP_8[[#This Row],[LE2 Final Submission]] -> #VALUE! | AN4: 0 | AO4: =$AE4 - $AN4 -> 0 | AP4: =SUM(ERP_8[[#This Row],[AP01]:[AP07]])-SUM(ERP_8[[#This Row],[AP01 LE2]:[AP07 LE2]]) -> #VALUE! | AR4: =ERP_8[[#This Row],[2026 Working Total to Budget/LE]]-ERP_8[[#This Row],[Giveback]] -> #VALUE! | AW4: 0 | AX4: 0 | AY4: 0 | AZ4: 0 | BA4: 0 | BB4: 0 | BC4: 0 | BD4: 0 | BE4: 0 | BF4: 0 | BG4: 6685.48 | BH4: -19872.71 | BI4: 7440.92 | BJ4: 0 | BK4: 0 | BL4: 0 | BM4: 0 | BN4: 0 | BO4: 0 | BP4: 0 | BQ4: 0 | BR4: 0 | BS4: -5746.31
A5: L-ERP-045 | B5: Hase, Raj_COMPENSATION_CompSalary001 | D5: =_xlfn.TEXTJOIN("_",FALSE,E5,ERP_8[[#This Row],[Expense Category]],ERP_8[[#This Row],[Project Code*]]) -> #VALUE! | E5: Hase, Raj | G5: ERP | H5: Hase, Raj | I5: Hase, Raj | J5: DeHart, Lynn | K5: COMPENSATION | L5: Salary | O5: CompSalary001 | P5: CHW - Ok | Q5: N/A | S5: None | T5: 4/23 SMO: AP05 has severance reversals | V5: 16484281 | W5: 21816550 | Z5: 1733431 | AA5: 2659121.5 | AB5: 1591278.2 | AC5: 2358182.7 | AD5: 54442.76 | AE5: 1931126.6 | AF5: 1528268.4 | AG5: 1781851.7 | AH5: 1807055.8 | AI5: 1862531.5 | AJ5: 1871210 | AK5: 1871210 | AL5: =SUM(Z5:AK5) -> 21049710 | AM5: =ERP_8[[#This Row],[2026 Working Total]]-ERP_8[[#This Row],[LE2 Final Submission]] -> #VALUE! | AN5: 0 | AO5: =$AE5 - $AN5 -> 1931126.6 | AP5: =SUM(ERP_8[[#This Row],[AP01]:[AP07]])-SUM(ERP_8[[#This Row],[AP01 LE2]:[AP07 LE2]]) -> #VALUE! | AR5: =ERP_8[[#This Row],[2026 Working Total to Budget/LE]]-ERP_8[[#This Row],[Giveback]] -> #VALUE! | AT5: 1733431 | AU5: 2659121.5 | AV5: 1591278.2 | AW5: 2405320 | AX5: 657407.65 | AY5: 1790825.9 | AZ5: 1785306.7 | BA5: 1781851.7 | BB5: 1807055.8 | BC5: 1862531.5 | BD5: 1871210 | BE5: 1871210 | BF5: 21816550 | BG5: 1086387.3 | BH5: 1551142.7 | BI5: 857806.14 | BJ5: 1328752.3 | BK5: 1328097.8 | BL5: 1371182.9 | BM5: 1392643.5 | BN5: 1403661.4 | BO5: 1403661.4 | BP5: 1403661.4 | BQ5: 1409426 | BR5: 1409426 | BS5: 15945849
A6: L-ERP-252 | B6: Jajodia, Amit_COMPENSATION_CompBenefits001 | D6: =_xlfn.TEXTJOIN("_",FALSE,E6,ERP_8[[#This Row],[Expense Category]],ERP_8[[#This Row],[Project Code*]]) -> #VALUE! | E6: Jajodia, Amit | G6: ERP | H6: Hase, Raj | I6: Jajodia, Amit | J6: DeHart, Lynn | K6: COMPENSATION | L6: Benefits | O6: CompBenefits001 | P6: CHW - Ok | Q6: N/A | S6: None | V6: 0 | W6: 0 | AD6: 0 | AE6: 0 | AG6: 0 | AH6: 0 | AI6: 0 | AJ6: 0 | AK6: 0 | AL6: =SUM(Z6:AK6) -> 0 | AM6: =ERP_8[[#This Row],[2026 Working Total]]-ERP_8[[#This Row],[LE2 Final Submission]] -> #VALUE! | AN6: 0 | AO6: =$AE6 - $AN6 -> 0 | AP6: =SUM(ERP_8[[#This Row],[AP01]:[AP07]])-SUM(ERP_8[[#This Row],[AP01 LE2]:[AP07 LE2]]) -> #VALUE! | AR6: =ERP_8[[#This Row],[2026 Working Total to Budget/LE]]-ERP_8[[#This Row],[Giveback]] -> #VALUE! | AW6: 0 | AX6: 0 | AY6: 0 | AZ6: 0 | BA6: 0 | BB6: 0 | BC6: 0 | BD6: 0 | BE6: 0 | BF6: 0 | BG6: 1989.38 | BH6: 2792.24 | BI6: 4195.36 | BJ6: 0 | BK6: 0 | BL6: 0 | BM6: 0 | BN6: 0 | BO6: 0 | BP6: 0 | BQ6: 0 | BR6: 0 | BS6: 8976.98
A7: L-ERP-253 | B7: Jajodia, Amit_COMPENSATION_CompBonus001 | D7: =_xlfn.TEXTJOIN("_",FALSE,E7,ERP_8[[#This Row],[Expense Category]],ERP_8[[#This Row],[Project Code*]]) -> #VALUE! | E7: Jajodia, Amit | G7: ERP | H7: Hase, Raj | I7: Jajodia, Amit | J7: DeHart, Lynn | K7: COMPENSATION | L7: Bonus | O7: CompBonus001 | P7: CHW - Ok | Q7: N/A | S7: None | V7: 0 | W7: 0 | AD7: 0 | AE7: 0 | AG7: 0 | AH7: 0 | AI7: 0 | AJ7: 0 | AK7: 0 | AL7: =SUM(Z7:AK7) -> 0 | AM7: =ERP_8[[#This Row],[2026 Working Total]]-ERP_8[[#This Row],[LE2 Final Submission]] -> #VALUE! | AN7: 0 | AO7: =$AE7 - $AN7 -> 0 | AP7: =SUM(ERP_8[[#This Row],[AP01]:[AP07]])-SUM(ERP_8[[#This Row],[AP01 LE2]:[AP07 LE2]]) -> #VALUE! | AR7: =ERP_8[[#This Row],[2026 Working Total to Budget/LE]]-ERP_8[[#This Row],[Giveback]] -> #VALUE! | AW7: 0 | AX7: 0 | AY7: 0 | AZ7: 0 | BA7: 0 | BB7: 0 | BC7: 0 | BD7: 0 | BE7: 0 | BF7: 0 | BG7: 2651.11 | BH7: 1336.03 | BI7: 1800.7 | BJ7: 0 | BK7: 0 | BL7: 0 | BM7: 0 | BN7: 0 | BO7: 0 | BP7: 0 | BQ7: 0 | BR7: 0 | BS7: 5787.84
A8: L-ERP-254 | B8: Jajodia, Amit_COMPENSATION_CompSalary001 | D8: =_xlfn.TEXTJOIN("_",FALSE,E8,ERP_8[[#This Row],[Expense Category]],ERP_8[[#This Row],[Project Code*]]) -> Jajodia, Amit_CONTRACTORS_ColleagueSolutions001 | E8: Jajodia, Amit | G8: ERP | H8: Hase, Raj | I8: Jajodia, Amit | J8: DeHart, Lynn | K8: COMPENSATION | L8: Salary | O8: CompSalary001 | P8: CHW - Ok | Q8: N/A | S8: None | V8: 0 | W8: 0 | AG8: 0 | AH8: 0 | AI8: 0 | AJ8: 0 | AK8: 0 | AL8: =SUM(Z8:AK8) -> 0 | AM8: =ERP_8[[#This Row],[2026 Working Total]]-ERP_8[[#This Row],[LE2 Final Submission]] -> -404.8 | AN8: 0 | AO8: =$AE8 - $AN8 -> 0 | AP8: =SUM(ERP_8[[#This Row],[AP01]:[AP07]])-SUM(ERP_8[[#This Row],[AP01 LE2]:[AP07 LE2]]) -> -404.8 | AR8: =ERP_8[[#This Row],[2026 Working Total to Budget/LE]]-ERP_8[[#This Row],[Giveback]] -> -404.8 | AW8: 0 | AX8: 0 | AY8: 0 | AZ8: 0 | BA8: 0 | BB8: 0 | BC8: 0 | BD8: 0 | BE8: 0 | BF8: 0 | BG8: 9779.9 | BH8: 9779.88 | BI8: 9779.88 | BJ8: 0 | BK8: 0 | BL8: 0 | BM8: 0 | BN8: 0 | BO8: 0 | BP8: 0 | BQ8: 0 | BR8: 0 | BS8: 29339.66
A9: L-ERP-043 | B9: DeHart, Lynn_COMPENSATION_CompBenefits001 | D9: =_xlfn.TEXTJOIN("_",FALSE,E9,ERP_8[[#This Row],[Expense Category]],ERP_8[[#This Row],[Project Code*]]) -> Patel, Apurva_CONTRACTORS_ColleagueSolutions001 | E9: Patel, Apurva | G9: ERP | H9: Hase, Raj | I9: DeHart, Lynn | J9: DeHart, Lynn | K9: COMPENSATION | L9: Benefits | O9: CompBenefits001 | P9: CHW - Ok | Q9: N/A | S9: None | V9: 6952244 | W9: 0 | AD9: 0 | AE9: 0 | AL9: =SUM(Z9:AK9) -> 0 | AM9: =ERP_8[[#This Row],[2026 Working Total]]-ERP_8[[#This Row],[LE2 Final Submission]] -> -1800 | AN9: 0 | AO9: =$AE9 - $AN9 -> 0 | AP9: =SUM(ERP_8[[#This Row],[AP01]:[AP07]])-SUM(ERP_8[[#This Row],[AP01 LE2]:[AP07 LE2]]) -> -3600 | AR9: =ERP_8[[#This Row],[2026 Working Total to Budget/LE]]-ERP_8[[#This Row],[Giveback]] -> -1800 | BF9: 0 | BG9: 423409.35 | BH9: 937161.13 | BI9: 426573.21 | BJ9: 561924.33 | BK9: 560912.64 | BL9: 576476.29 | BM9: 585831.8 | BN9: 590499.77 | BO9: 590499.77 | BP9: 590499.77 | BQ9: 592897.86 | BR9: 592897.86 | BS9: 7029583.8
A10: L-ERP-431 | B10: McGettigan, David_COMPENSATION_CompBenefits001 | D10: =_xlfn.TEXTJOIN("_",FALSE,E10,ERP_8[[#This Row],[Expense Category]],ERP_8[[#This Row],[Project Code*]]) -> Patel, Apurva_CONTRACTORS_EnhanceChargeout001 | E10: Patel, Apurva | G10: ERP | H10: McGettigan, David | I10: McGettigan, David | J10: McGettigan, David | K10: COMPENSATION | L10: Benefits | O10: CompBenefits001 | P10: CHW - Ok | Q10: N/A | S10: None | V10: 330694.31 | W10: 0 | AD10: 0 | AE10: 0 | AL10: =SUM(Z10:AK10) -> 0 | AM10: =ERP_8[[#This Row],[2026 Working Total]]-ERP_8[[#This Row],[LE2 Final Submission]] -> 22500.97 | AN10: 0 | AO10: =$AE10 - $AN10 -> 0 | AP10: =SUM(ERP_8[[#This Row],[AP01]:[AP07]])-SUM(ERP_8[[#This Row],[AP01 LE2]:[AP07 LE2]]) -> 22500.97 | AR10: =ERP_8[[#This Row],[2026 Working Total to Budget/LE]]-ERP_8[[#This Row],[Giveback]] -> 22500.97 | BF10: 0 | BG10: 92230.9 | BH10: -4919.59 | BI10: 59978.67 | BJ10: 20638.45 | BK10: 34028.45 | BL10: 32963.75 | BM10: 22316.67 | BN10: 22316.67 | BO10: 22316.67 | BP10: 22316.67 | BQ10: 22316.67 | BR10: 22316.67 | BS10: 368820.65
A11: L-ERP-426 | B11: McGettigan, David_COMPENSATION_CompBenefitsCar001 | D11: =_xlfn.TEXTJOIN("_",FALSE,E11,ERP_8[[#This Row],[Expense Category]],ERP_8[[#This Row],[Project Code*]]) -> Patel, Apurva_CONTRACTORS_EnhanceChargeout001 | E11: Patel, Apurva | G11: ERP | H11: McGettigan, David | I11: McGettigan, David | J11: McGettigan, David | K11: COMPENSATION | L11: Car Allowance | O11: CompBenefitsCar001 | Q11: N/A | S11: None | V11: 144000 | W11: 108000 | AD11: 0 | AE11: 0 | AG11: 12000 | AH11: 12000 | AI11: 12000 | AJ11: 12000 | AK11: 12000 | AL11: =SUM(Z11:AK11) -> 60000 | AM11: =ERP_8[[#This Row],[2026 Working Total]]-ERP_8[[#This Row],[LE2 Final Submission]] -> -135929.3 | AN11: 0 | AO11: =$AE11 - $AN11 -> 0 | AP11: =SUM(ERP_8[[#This Row],[AP01]:[AP07]])-SUM(ERP_8[[#This Row],[AP01 LE2]:[AP07 LE2]]) -> -67270.3 | AR11: =ERP_8[[#This Row],[2026 Working Total to Budget/LE]]-ERP_8[[#This Row],[Giveback]] -> -135929.3 | AW11: 12000 | AX11: 12000 | AY11: 12000 | AZ11: 12000 | BA11: 12000 | BB11: 12000 | BC11: 12000 | BD11: 12000 | BE11: 12000 | BF11: 108000 | BJ11: 12000 | BK11: 12000 | BL11: 12000 | BM11: 12000 | BN11: 12000 | BO11: 12000 | BP11: 12000 | BQ11: 12000 | BR11: 12000 | BS11: 108000
A12: L-ERP-044 | B12: DeHart, Lynn_COMPENSATION_CompBonus001 | D12: =_xlfn.TEXTJOIN("_",FALSE,E12,ERP_8[[#This Row],[Expense Category]],ERP_8[[#This Row],[Project Code*]]) -> Patel, Apurva_CONTRACTORS_EnhanceChargeout001 | E12: Patel, Apurva | G12: ERP | H12: Hase, Raj | I12: DeHart, Lynn | J12: DeHart, Lynn | K12: COMPENSATION | L12: Bonus | O12: CompBonus001 | P12: CHW - Ok | Q12: N/A | S12: None | V12: 2865793.4 | W12: 0 | AD12: 0 | AE12: 0 | AL12: =SUM(Z12:AK12) -> 0 | AM12: =ERP_8[[#This Row],[2026 Working Total]]-ERP_8[[#This Row],[LE2 Final Submission]] -> -18000 | AN12: 0 | AO12: =$AE12 - $AN12 -> 0 | AP12: =SUM(ERP_8[[#This Row],[AP01]:[AP07]])-SUM(ERP_8[[#This Row],[AP01 LE2]:[AP07 LE2]]) -> -18000 | AR12: =ERP_8[[#This Row],[2026 Working Total to Budget/LE]]-ERP_8[[#This Row],[Giveback]] -> -18000 | BF12: 0 | BG12: 195133.21 | BH12: 214325.71 | BI12: 291685.48 | BJ12: 233173.12 | BK12: 232919.73 | BL12: 238777.23 | BM12: 240555.68 | BN12: 242084.56 | BO12: 242084.56 | BP12: 242084.56 | BQ12: 242516.91 | BR12: 242516.91 | BS12: 2857857.7
A13: L-ERP-428 | B13: McGettigan, David_COMPENSATION_CompBonus001 | D13: =_xlfn.TEXTJOIN("_",FALSE,E13,ERP_8[[#This Row],[Expense Category]],ERP_8[[#This Row],[Project Code*]]) -> Patel, Apurva_CONTRACTORS_EnhanceChargeout001 | E13: Patel, Apurva | G13: ERP | H13: McGettigan, David | I13: McGettigan, David | J13: McGettigan, David | K13: COMPENSATION | L13: Bonus | O13: CompBonus001 | P13: CHW - Ok | Q13: N/A | S13: None | V13: 204823.02 | W13: 0 | AD13: 0 | AE13: 0 | AL13: =SUM(Z13:AK13) -> 0 | AM13: =ERP_8[[#This Row],[2026 Working Total]]-ERP_8[[#This Row],[LE2 Final Submission]] -> 0 | AN13: 0 | AO13: =$AE13 - $AN13 -> 0 | AP13: =SUM(ERP_8[[#This Row],[AP01]:[AP07]])-SUM(ERP_8[[#This Row],[AP01 LE2]:[AP07 LE2]]) -> 0 | AR13: =ERP_8[[#This Row],[2026 Working Total to Budget/LE]]-ERP_8[[#This Row],[Giveback]] -> 0 | BF13: 0 | BG13: 51562.58 | BH13: 27159.83 | BI13: 40975 | BJ13: 11866.46 | BK13: 21522.71 | BL13: 20882.86 | BM13: 14484.38 | BN13: 14484.38 | BO13: 14484.38 | BP13: 14484.38 | BQ13: 14484.38 | BR13: 14484.38 | BS13: 260875.72
A14: ERP-062 | B14: Patel, Apurva_COMPENSATION_CompSalary001 | D14: =_xlfn.TEXTJOIN("_",FALSE,E14,ERP_8[[#This Row],[Expense Category]],ERP_8[[#This Row],[Project Code*]]) -> Patel, Apurva_CONTRACTORS_EnhanceChargeout001 | E14: Patel, Apurva | G14: ERP | H14: Patel, Apurva | I14: Patel, Apurva | J14: Dougherty, Chris | K14: COMPENSATION | L14: CC 2578633 - Remapped to CISO | O14: CompSalary001 | T14: 7/20/26 CHW - Adjusted actuals for this cost center mistakenly labelled as Chris D | Z14: -26238.68 | AA14: -44376.73 | AB14: -25573.77 | AC14: 65766.4 | AD14: -31842.66 | AL14: =SUM(X14:AK14) -> -62265.44 | AM14: =ERP_8[[#This Row],[2026 Working Total]]-ERP_8[[#This Row],[LE2 Final Submission]] -> -206607.95 | AO14: =$Z14 - $AN14 -> -26238.68 | AP14: =SUM(ERP_8[[#This Row],[AP01]:[AP07]])-SUM(ERP_8[[#This Row],[AP01 LE2]:[AP07 LE2]]) -> -206607.95 | AR14: =ERP_8[[#This Row],[2026 Working Total to Budget/LE]]-ERP_8[[#This Row],[Giveback]] -> -206607.95
A15: L-ERP-432 | B15: McGettigan, David_COMPENSATION_CompSalary001 | D15: =_xlfn.TEXTJOIN("_",FALSE,E15,ERP_8[[#This Row],[Expense Category]],ERP_8[[#This Row],[Project Code*]]) -> Patel, Apurva_CONTRACTORS_EP&SCharges001 | E15: Patel, Apurva | G15: ERP | H15: McGettigan, David | I15: McGettigan, David | J15: McGettigan, David | K15: COMPENSATION | L15: Salary | O15: CompSalary001 | P15: CHW - Ok | Q15: N/A | S15: None | T15: 5/3 SMO: AP05 has GPP ex-US credit | V15: 794938.18 | W15: 806177.42 | Z15: 358290.86 | AA15: -25689.76 | AB15: 41090.67 | AC15: 85849.4 | AD15: -59378.36 | AE15: -23605.23 | AF15: -39022.84 | AG15: 55233.75 | AH15: 55233.75 | AI15: 55233.75 | AJ15: 55233.75 | AK15: 55233.75 | AL15: =SUM(Z15:AK15) -> 613703.49 | AM15: =ERP_8[[#This Row],[2026 Working Total]]-ERP_8[[#This Row],[LE2 Final Submission]] -> 550 | AN15: 0 | AO15: =$AE15 - $AN15 -> -23605.23 | AP15: =SUM(ERP_8[[#This Row],[AP01]:[AP07]])-SUM(ERP_8[[#This Row],[AP01 LE2]:[AP07 LE2]]) -> 550 | AR15: =ERP_8[[#This Row],[2026 Working Total to Budget/LE]]-ERP_8[[#This Row],[Giveback]] -> 550 | AT15: 358290.86 | AU15: -25689.76 | AV15: 41090.67 | AW15: 85849.4 | AX15: -40000 | AY15: 55233.75 | AZ15: 55233.75 | BA15: 55233.75 | BB15: 55233.75 | BC15: 55233.75 | BD15: 55233.75 | BE15: 55233.75 | BF15: 806177.42 | BG15: 214497.38 | BH15: -47930 | BI15: -59863 | BJ15: 49611.67 | BK15: 81799.17 | BL15: 79239.77 | BM15: 53645.83 | BN15: 53645.83 | BO15: 53645.83 | BP15: 53645.83 | BQ15: 53645.83 | BR15: 53645.83 | BS15: 639229.97
A16: L-ERP-386 | B16: McGettigan, David_COMPENSATION_VacancyFactor001 | D16: =_xlfn.TEXTJOIN("_",FALSE,E16,ERP_8[[#This Row],[Expense Category]],ERP_8[[#This Row],[Project Code*]]) -> Patel, Apurva_CONTRACTORS_EP&SCharges001 | E16: Patel, Apurva | G16: ERP | H16: McGettigan, David | I16: McGettigan, David | J16: McGettigan, David | K16: COMPENSATION | L16: Vacancy Factor | O16: VacancyFactor001 | Q16: N/A | S16: Reserve | V16: -472222.21 | W16: -160000 | AD16: 0 | AE16: 0 | AG16: -20000 | AH16: -20000 | AI16: -20000 | AJ16: -20000 | AK16: -20000 | AL16: =SUM(Z16:AK16) -> -100000 | AM16: =ERP_8[[#This Row],[2026 Working Total]]-ERP_8[[#This Row],[LE2 Final Submission]] -> 0 | AN16: -20000 | AO16: =$AE16 - $AN16 -> 20000 | AP16: =SUM(ERP_8[[#This Row],[AP01]:[AP07]])-SUM(ERP_8[[#This Row],[AP01 LE2]:[AP07 LE2]]) -> 0 | AR16: =ERP_8[[#This Row],[2026 Working Total to Budget/LE]]-ERP_8[[#This Row],[Giveback]] -> 0 | AX16: -20000 | AY16: -20000 | AZ16: -20000 | BA16: -20000 | BB16: -20000 | BC16: -20000 | BD16: -20000 | BE16: -20000 | BF16: -160000 | BJ16: -47222.221 | BK16: -47222.221 | BL16: -47222.221 | BM16: -47222.221 | BN16: -47222.221 | BO16: -47222.221 | BP16: -47222.221 | BQ16: -47222.221 | BR16: -47222.221 | BS16: -424999.99
A17: L-ERP-494 | B17: Robertson, Jerome_COMPENSATION_CompBenefits001 | D17: =_xlfn.TEXTJOIN("_",FALSE,E17,ERP_8[[#This Row],[Expense Category]],ERP_8[[#This Row],[Project Code*]]) -> Robertson, Jerome_CONTRACTORS_IT-CTR0044-OG-US-00 | E17: Robertson, Jerome | G17: ERP | H17: Robertson, Jerome | I17: Robertson, Jerome | J17: Robertson, Jerome | K17: COMPENSATION | L17: Benefits | O17: CompBenefits001 | P17: CHW - Ok | Q17: N/A | S17: None | V17: 763217.95 | W17: 0 | AD17: 0 | AE17: 0 | AL17: =SUM(Z17:AK17) -> 0 | AM17: =ERP_8[[#This Row],[2026 Working Total]]-ERP_8[[#This Row],[LE2 Final Submission]] -> -55147.62 | AN17: 0 | AO17: =$AE17 - $AN17 -> 0 | AP17: =SUM(ERP_8[[#This Row],[AP01]:[AP07]])-SUM(ERP_8[[#This Row],[AP01 LE2]:[AP07 LE2]]) -> -138125.62 | AR17: =ERP_8[[#This Row],[2026 Working Total to Budget/LE]]-ERP_8[[#This Row],[Giveback]] -> 35933.38 | BF17: 0 | BG17: 60869.22 | BH17: 66348.7 | BI17: 65556.32 | BJ17: 66648.33 | BK17: 58804.22 | BL17: 58804.22 | BM17: 58804.22 | BN17: 66557.96 | BO17: 66703.34 | BP17: 66703.34 | BQ17: 66703.34 | BR17: 66703.34 | BS17: 769206.55
A18: L-ERP-495 | B18: Robertson, Jerome_COMPENSATION_CompBonus001 | D18: =_xlfn.TEXTJOIN("_",FALSE,E18,ERP_8[[#This Row],[Expense Category]],ERP_8[[#This Row],[Project Code*]]) -> Robertson, Jerome_CONTRACTORS_IT-CTR0067-OG-CR-00 | E18: Robertson, Jerome | G18: ERP | H18: Robertson, Jerome | I18: Robertson, Jerome | J18: Robertson, Jerome | K18: COMPENSATION | L18: Bonus | O18: CompBonus001 | P18: CHW - Ok | Q18: N/A | S18: None | V18: 355072.04 | W18: 0 | AD18: 0 | AE18: 0 | AL18: =SUM(Z18:AK18) -> 0 | AM18: =ERP_8[[#This Row],[2026 Working Total]]-ERP_8[[#This Row],[LE2 Final Submission]] -> 0 | AN18: 0 | AO18: =$AE18 - $AN18 -> 0 | AP18: =SUM(ERP_8[[#This Row],[AP01]:[AP07]])-SUM(ERP_8[[#This Row],[AP01 LE2]:[AP07 LE2]]) -> 0 | AR18: =ERP_8[[#This Row],[2026 Working Total to Budget/LE]]-ERP_8[[#This Row],[Giveback]] -> 0 | BF18: 0 | BG18: 27497.84 | BH18: 27805.69 | BI18: 37986.93 | BJ18: 30575.92 | BK18: 26871.2 | BL18: 26871.2 | BM18: 26871.2 | BN18: 31487.49 | BO18: 31751.82 | BP18: 31751.82 | BQ18: 31751.82 | BR18: 31751.82 | BS18: 362974.75
A19: L-ERP-496 | B19: Robertson, Jerome_COMPENSATION_CompSalary001 | D19: =_xlfn.TEXTJOIN("_",FALSE,E19,ERP_8[[#This Row],[Expense Category]],ERP_8[[#This Row],[Project Code*]]) -> Robertson, Jerome_CONTRACTORS_IT-CTR0093-OG-US-00 | E19: Robertson, Jerome | G19: ERP | H19: Robertson, Jerome | I19: Robertson, Jerome | J19: Robertson, Jerome | K19: COMPENSATION | L19: Salary | O19: CompSalary001 | P19: CHW - Ok | Q19: N/A | S19: None | V19: 2029390.9 | W19: 3060870.8 | Z19: 238474.07 | AA19: 255306.3 | AB19: 190399.43 | AC19: 293204.89 | AD19: 312206.58 | AE19: 165290.4 | AF19: 237654.9 | AG19: 265188.33 | AH19: 265188.33 | AI19: 278462.33 | AJ19: 278462.33 | AK19: 278462.33 | AL19: =SUM(Z19:AK19) -> 3058300.2 | AM19: =ERP_8[[#This Row],[2026 Working Total]]-ERP_8[[#This Row],[LE2 Final Submission]] -> -71.87 | AN19: 0 | AO19: =$AE19 - $AN19 -> 165290.4 | AP19: =SUM(ERP_8[[#This Row],[AP01]:[AP07]])-SUM(ERP_8[[#This Row],[AP01 LE2]:[AP07 LE2]]) -> 28658.13 | AR19: =ERP_8[[#This Row],[2026 Working Total to Budget/LE]]-ERP_8[[#This Row],[Giveback]] -> -71.87 | AT19: 238474.07 | AU19: 255306.3 | AV19: 190399.43 | AW19: 293204.89 | AX19: 239240.84 | AY19: 239240.84 | AZ19: 239240.84 | BA19: 265188.33 | BB19: 265188.33 | BC19: 278462.33 | BD19: 278462.33 | BE19: 278462.33 | BF19: 3060870.8 | BG19: 150107.01 | BH19: 161151.91 | BI19: 86856.18 | BJ19: 173603.4 | BK19: 155785.32 | BL19: 155785.32 | BM19: 155785.32 | BN19: 180905.4 | BO19: 182227.08 | BP19: 182227.08 | BQ19: 182227.08 | BR19: 182227.08 | BS19: 1948888.2

Sheet ERP_AP7 Macro Failed
R2: =R3-AH3 -> #N/A
Q3: =R3-554586-35645 -> 1.4326261e+08 | R3: =SUBTOTAL(9,ERP[2026 LE0]) -> 1.4385284e+08 | S3: =SUBTOTAL(9,ERP[LE2 Final Submission]) -> 1.2711657e+08 | T3: =SUBTOTAL(9,ERP[LE3 Final Submission]) -> 0 | U3: =SUBTOTAL(9,ERP[LE4 Final Submission]) -> 0 | V3: =SUBTOTAL(9,ERP[AP01]) -> 23366590 | W3: =SUBTOTAL(9,ERP[AP02]) -> -814833.86 | X3: =SUBTOTAL(9,ERP[AP03]) -> 10595458 | Y3: =SUBTOTAL(9,ERP[AP04]) -> 11367345 | Z3: =SUBTOTAL(9,ERP[AP05]) -> 10053232 | AA3: =SUBTOTAL(9,ERP[AP06]) -> 11179044 | AB3: =SUBTOTAL(9,ERP[AP07]) -> #N/A | AC3: =SUBTOTAL(9,ERP[AP08]) -> 13228554 | AD3: =SUBTOTAL(9,ERP[AP09]) -> 9856073.5 | AE3: =SUBTOTAL(9,ERP[AP10]) -> 9104264.5 | AF3: =SUBTOTAL(9,ERP[AP11]) -> 11021883 | AG3: =SUBTOTAL(9,ERP[AP12]) -> 9531482.1 | AH3: =SUBTOTAL(9,ERP[2026 Working Total]) -> #N/A | AI3: =SUBTOTAL(9,ERP[2026 Working Total to Budget/LE]) -> #N/A | AJ3: =SUBTOTAL(9,ERP[Latest AP Snapshot]) -> #N/A | AK3: =SUBTOTAL(9,ERP[Latest AP Variance to Snapshot]) -> #N/A | AL3: =SUBTOTAL(9,ERP[YTD Act to Bud/LE]) -> -1508422.5 | AM3: =SUBTOTAL(9,ERP[Giveback]) -> 1115265 | AN3: =SUBTOTAL(9,ERP[Other Allocation]) -> #N/A | AP3: =SUBTOTAL(9,ERP[AP01 LE2]) -> 23394262 | AQ3: =SUBTOTAL(9,ERP[AP02 LE2]) -> -766426.92 | AR3: =SUBTOTAL(9,ERP[AP03 LE2]) -> 10624250 | AS3: =SUBTOTAL(9,ERP[AP04 LE2]) -> 10731145 | AT3: =SUBTOTAL(9,ERP[AP05 LE2]) -> 11493575 | AU3: =SUBTOTAL(9,ERP[AP06 LE2]) -> 11778451 | AV3: =SUBTOTAL(9,ERP[AP07 LE2]) -> 8765081.1 | AW3: =SUBTOTAL(9,ERP[AP08 LE2]) -> 13268736 | AX3: =SUBTOTAL(9,ERP[AP09 LE2]) -> 9757694 | AY3: =SUBTOTAL(9,ERP[AP10 LE2]) -> 7868848.1 | AZ3: =SUBTOTAL(9,ERP[AP11 LE2]) -> 10799280 | BA3: =SUBTOTAL(9,ERP[AP12 LE2]) -> 9401671.9 | BB3: =SUBTOTAL(9,ERP[2026 LE2 Working Total]) -> 1.2711657e+08 | BC3: =SUBTOTAL(9,ERP[2026 AP01]) -> 23567753 | BD3: =SUBTOTAL(9,ERP[2026 AP02]) -> -355739.16 | BE3: =SUBTOTAL(9,ERP[2026 AP03]) -> 11418987 | BF3: =SUBTOTAL(9,ERP[2026 AP04]) -> 12341163 | BG3: =SUBTOTAL(9,ERP[2026 AP05]) -> 12420208 | BH3: =SUBTOTAL(9,ERP[2026 AP06]) -> 13447114 | BI3: =SUBTOTAL(9,ERP[2026 AP07]) -> 12251484 | BJ3: =SUBTOTAL(9,ERP[2026 AP08]) -> 12298740 | BK3: =SUBTOTAL(9,ERP[2026 AP09]) -> 12666138 | BL3: =SUBTOTAL(9,ERP[2026 AP10]) -> 12314418 | BM3: =SUBTOTAL(9,ERP[2026 AP11]) -> 11523451 | BN3: =SUBTOTAL(9,ERP[2026 AP12]) -> 11426086 | BO3: =SUBTOTAL(9,ERP[2026 LE0 Submission]) -> 1.453198e+08
K5: Digital Funded Projects | Q5: Submissions | R5: Pre LE2 from Planful | V5: Working Forecast | AL5: Variance & Giveback Analysis | AP5: Prior Submission | BC5: Pre LE2 from Planful
R6: 0223 Extract | S6: 518 | T6: 821 | U6: 1023 | V6: Actual | W6: Actual | X6: Actual | Y6: Actual | Z6: Actual | AA6: Actual | AB6: Actual | AC6: Forecast | AD6: Forecast | AE6: Forecast | AF6: Forecast | AG6: Forecast | AJ6: AP07 | AL6: YTD Variance | AM6: (Input) | AN6: (Calculated) | AP6: LE2 | AQ6: LE2 | AR6: LE2 | AS6: LE2 | AT6: LE2 | AU6: LE2 | AV6: LE2 | AW6: LE2 | AX6: LE2 | AY6: LE2 | AZ6: LE2 | BA6: LE2 | BB6: LE2 | BC6: 0223 Planful | BD6: 0223 Planful | BE6: 0223 Planful | BF6: 0223 Planful | BG6: 0223 Planful | BH6: 0223 Planful | BI6: 0223 Planful | BJ6: 0223 Planful | BK6: 0223 Planful | BL6: 0223 Planful | BM6: 0223 Planful | BN6: 0223 Planful | BO6: 0223 Planful
A7: UID | B7: Match | C7: CCL3 | D7: LT Member* | E7: LT Member -1* | F7: Point of Contact | G7: Expense Category | H7: Description* | I7: Vendor* | J7: Cost Center* | K7: Project Code* | L7: Prior Year PO | M7: 2026 Purchase Order | N7: Pullforward | O7: Grouping | P7: 2026 Budget Comment | Q7: 2026 Transfers | R7: 2026 LE0 | S7: LE2 Final Submission | T7: LE3 Final Submission | U7: LE4 Final Submission | V7: AP01 | W7: AP02 | X7: AP03 | Y7: AP04 | Z7: AP05 | AA7: AP06 | AB7: AP07 | AC7: AP08 | AD7: AP09 | AE7: AP10 | AF7: AP11 | AG7: AP12 | AH7: 2026 Working Total | AI7: 2026 Working Total to Budget/LE | AJ7: Latest AP Snapshot | AK7: Latest AP Variance to Snapshot | AL7: YTD Act to Bud/LE | AM7: Giveback | AN7: Other Allocation | AO7: Giveback Comments | AP7: AP01 LE2 | AQ7: AP02 LE2 | AR7: AP03 LE2 | AS7: AP04 LE2 | AT7: AP05 LE2 | AU7: AP06 LE2 | AV7: AP07 LE2 | AW7: AP08 LE2 | AX7: AP09 LE2 | AY7: AP10 LE2 | AZ7: AP11 LE2 | BA7: AP12 LE2 | BB7: 2026 LE2 Working Total | BC7: 2026 AP01 | BD7: 2026 AP02 | BE7: 2026 AP03 | BF7: 2026 AP04 | BG7: 2026 AP05 | BH7: 2026 AP06 | BI7: 2026 AP07 | BJ7: 2026 AP08 | BK7: 2026 AP09 | BL7: 2026 AP10 | BM7: 2026 AP11 | BN7: 2026 AP12 | BO7: 2026 LE0 Submission
A8: L-ERP-059 | B8: Dougherty, Chris_SOFTWARE_2026-XFR-0007-A | C8: ERP | D8: Dougherty, Chris | E8: Dougherty, Chris | F8: Maguire, Karla | G8: SOFTWARE | H8: Serialization - SAP ATTP License - Software maintenance (on-premise) | K8: 2026-XFR-0007-A | O8: 2026 Budget Transfer | R8: 103465 | S8: 77598.72 | Z8: 0 | AA8: 0 | AC8: 17244 | AD8: 17244 | AE8: 17244 | AF8: 17244 | AG8: 17244 | AH8: =SUM(V8:AG8) -> 86220 | AI8: =ERP[[#This Row],[2026 Working Total]]-ERP[[#This Row],[LE2 Final Submission]] -> 8621.28 | AJ8: #N/A | AK8: =$AB8 - $AJ8 -> #N/A | AL8: =SUM(ERP[[#This Row],[AP01]:[AP06]])-SUM(ERP[[#This Row],[AP01 LE2]:[AP06 LE2]]) -> -25866.24 | AN8: =ERP[[#This Row],[2026 Working Total to Budget/LE]]-ERP[[#This Row],[Giveback]] -> 8621.28 | AS8: 8622.08 | AT8: 8622.08 | AU8: 8622.08 | AV8: 8622.08 | AW8: 8622.08 | AX8: 8622.08 | AY8: 8622.08 | AZ8: 8622.08 | BA8: 8622.08 | BB8: 77598.72 | BF8: 8622.08 | BG8: 8622.08 | BH8: 8622.08 | BI8: 8622.08 | BJ8: 8622.08 | BK8: 8622.08 | BL8: 8622.08 | BM8: 8622.08 | BN8: 8622.08 | BO8: 77598.72
A9: N-ERP-613 | B9: Tamavada, Ram_MANAGED SERVICES_2026-XFR-0008-B | C9: ERP | D9: Dougherty, Chris | E9: Tamavada, Ram | F9: Maguire, Karla | G9: MANAGED SERVICES | H9: SAP Fieldglass Vendor Management System Implementation: - Application/Platform support and maintenance | K9: 2026-XFR-0008-B | O9: 2026 Budget Transfer | P9: 4/28/26 CHW New add to tie-out 0223 to 0317 Planful Extracts DS - Ram already took actions to optimize cost to $200k, doesn't believe there is further opportunity. 2027 goes down to $169k. | R9: 183105 | S9: 0 | Z9: 0 | AA9: 0 | AB9: #N/A | AH9: =SUM(V9:AG9) -> #N/A | AI9: =ERP[[#This Row],[2026 Working Total]]-ERP[[#This Row],[LE2 Final Submission]] -> #N/A | AJ9: #N/A | AK9: =$AA9 - $AJ9 -> #N/A | AL9: =SUM(ERP[[#This Row],[AP01]:[AP06]])-SUM(ERP[[#This Row],[AP01 LE2]:[AP06 LE2]]) -> 0 | AM9: -183105 | AN9: =ERP[[#This Row],[2026 Working Total to Budget/LE]]-ERP[[#This Row],[Giveback]] -> #N/A | AO9: Per Leslie - Fieldglass, no payment is due in 2026 for support under IBM. It will resume in 2027 @ $169,020 | BB9: 0 | BC9: 15258.75 | BD9: 15258.75 | BE9: 15258.75 | BF9: 15258.75 | BG9: 15258.75 | BH9: 15258.75 | BI9: 15258.75 | BJ9: 15258.75 | BK9: 15258.75 | BL9: 15258.75 | BM9: 15258.75 | BN9: 15258.75 | BO9: =SUM(ERP[[#This Row],[2026 AP01]:[2026 AP12]]) -> 183105
A10: L-ERP-060 | B10: Dougherty, Chris_SOFTWARE_2026-XFR-0013-A | C10: ERP | D10: Dougherty, Chris | E10: Dougherty, Chris | F10: Maguire, Karla | G10: SOFTWARE | H10: Serialization - SAP ICH License - SAP ICH regulatory collaboration and Regulatory reporting services | K10: 2026-XFR-0013-A | O10: 2026 Budget Transfer | P10: 5/12 CHW - added back 51K to reflect 204K XFR total & shifted forecast to OTC | R10: 204128 | S10: 204128 | Z10: 0 | AA10: 0 | AB10: #N/A | AC10: =17010.67-17010.67 -> 0 | AD10: =17010.67-17010.67 -> 0 | AE10: =17010.67-17010.67+204128 -> 204128 | AF10: =17010.67-17010.67 -> 0 | AG10: =17010.67-17010.67 -> 0 | AH10: =SUM(V10:AG10) -> #N/A | AI10: =ERP[[#This Row],[2026 Working Total]]-ERP[[#This Row],[LE2 Final Submission]] -> #N/A | AJ10: #N/A | AK10: =$AA10 - $AJ10 -> #N/A | AL10: =SUM(ERP[[#This Row],[AP01]:[AP06]])-SUM(ERP[[#This Row],[AP01 LE2]:[AP06 LE2]]) -> 0 | AN10: =ERP[[#This Row],[2026 Working Total to Budget/LE]]-ERP[[#This Row],[Giveback]] -> #N/A | AS10: 0 | AT10: 0 | AU10: 0 | AV10: 0 | AW10: 0 | AX10: 0 | AY10: 204128 | AZ10: 0 | BA10: 0 | BB10: 204128 | BF10: 17010.67 | BG10: 17010.67 | BH10: 17010.67 | BI10: 17010.67 | BJ10: 17010.67 | BK10: 17010.67 | BL10: 17010.67 | BM10: 17010.67 | BN10: 17010.67 | BO10: 153096.03
A11: L-ERP-565 | B11: Yeluri, Durga_MANAGED SERVICES_2026-XFR-0014-A | C11: ERP | D11: Hase, Raj | E11: Yeluri, Durga | F11: DeHart, Lynn | G11: MANAGED SERVICES | H11: Cash Flow Automation Project - Cash Flow Functionality for: SAP S/4 HANA ($51,120); Celonis ($35,000) | K11: 2026-XFR-0014-A | O11: 2026 Budget Transfer | P11: 5/4 CHW - Giveback | R11: 86120 | Z11: 0 | AA11: 0 | AB11: #N/A | AI11: =ERP[[#This Row],[2026 Working Total]]-ERP[[#This Row],[LE2 Final Submission]] -> 0 | AJ11: #N/A | AK11: =$AA11 - $AJ11 -> #N/A | AL11: =SUM(ERP[[#This Row],[AP01]:[AP06]])-SUM(ERP[[#This Row],[AP01 LE2]:[AP06 LE2]]) -> 0 | AN11: =ERP[[#This Row],[2026 Working Total to Budget/LE]]-ERP[[#This Row],[Giveback]] -> 0 | AO11: We will cover with existing colleagues and AMS contract. | BF11: 8612 | BG11: 8612 | BH11: 8612 | BI11: 8612 | BJ11: 8612 | BK11: 8612 | BL11: 8612 | BM11: 8612 | BN11: 8612 | BO11: 77508
A12: L-ERP-568 | B12: Yeluri, Durga_SOFTWARE_2026-XFR-0014-B | C12: ERP | D12: Hase, Raj | E12: Yeluri, Durga | F12: DeHart, Lynn | G12: SOFTWARE | H12: Cash Flow Automation Project - Software License cost for SAP Analytics on Cloud (included as part of SAP S/4 HANA FSA) | K12: 2026-XFR-0014-B | O12: 2026 Budget Transfer | P12: 5/4 CHW - Giveback | R12: 39999.96 | S12: 0 | Z12: 0 | AA12: 0 | AB12: #N/A | AH12: =SUM(V12:AG12) -> #N/A | AI12: =ERP[[#This Row],[2026 Working Total]]-ERP[[#This Row],[LE2 Final Submission]] -> #N/A | AJ12: #N/A | AK12: =$AA12 - $AJ12 -> #N/A | AL12: =SUM(ERP[[#This Row],[AP01]:[AP06]])-SUM(ERP[[#This Row],[AP01 LE2]:[AP06 LE2]]) -> 0 | AN12: =ERP[[#This Row],[2026 Working Total to Budget/LE]]-ERP[[#This Row],[Giveback]] -> #N/A | AO12: SAC license is not needed. Forecast removed. | BB12: 0 | BF12: 4000 | BG12: 4000 | BH12: 4000 | BI12: 4000 | BJ12: 4000 | BK12: 4000 | BL12: 4000 | BM12: 4000 | BN12: 4000 | BO12: 36000
A13: L-ERP-177 | B13: Hase, Raj_SOFTWARE_2026-XFR-0015-A | C13: ERP | D13: Hase, Raj | E13: Hase, Raj | F13: DeHart, Lynn | G13: SOFTWARE | H13: Brazil Tax Reform and SAP GRC Replacement - SAP Document and Risk Compliance Cloud Subscription | K13: 2026-XFR-0015-A | O13: 2026 Budget Transfer | P13: Reclass to business, SAP annual invoice $81,120 expected 8/15 | R13: 0 | S13: 0 | Z13: 0 | AA13: 0 | AB13: #N/A | AC13: 81120 | AD13: -81120 | AE13: 0 | AF13: 0 | AG13: 0 | AH13: =SUM(V13:AG13) -> #N/A | AI13: =ERP[[#This Row],[2026 Working Total]]-ERP[[#This Row],[LE2 Final Submission]] -> #N/A | AJ13: #N/A | AK13: =$AA13 - $AJ13 -> #N/A | AL13: =SUM(ERP[[#This Row],[AP01]:[AP06]])-SUM(ERP[[#This Row],[AP01 LE2]:[AP06 LE2]]) -> 0 | AN13: =ERP[[#This Row],[2026 Working Total to Budget/LE]]-ERP[[#This Row],[Giveback]] -> #N/A | AS13: 0 | AT13: 0 | AU13: 0 | AV13: 0 | AW13: 81120 | AX13: -81120 | AY13: 0 | AZ13: 0 | BA13: 0 | BB13: 0 | BF13: 3235.5 | BG13: 3235.5 | BH13: 3235.5 | BI13: 3235.5 | BJ13: 3235.5 | BK13: 3235.5 | BL13: 3235.5 | BM13: 3235.5 | BN13: -35590.5 | BO13: -9706.5
A14: L-ERP-061 | B14: Dougherty, Chris_SOFTWARE_2026-XFR-0017-A | C14: ERP | D14: Dougherty, Chris | E14: Dougherty, Chris | F14: Maguire, Karla | G14: SOFTWARE | H14: Dedicated US PRIME Commerce Cloud - SAP Licenses | K14: 2026-XFR-0017-A | O14: 2026 Budget Transfer | R14: 0 | S14: 650000 | Z14: 0 | AA14: 0 | AB14: #N/A | AC14: 0 | AD14: 0 | AE14: 650000 | AF14: 0 | AG14: 0 | AH14: =SUM(V14:AG14) -> #N/A | AI14: =ERP[[#This Row],[2026 Working Total]]-ERP[[#This Row],[LE2 Final Submission]] -> #N/A | AJ14: #N/A | AK14: =$AA14 - $AJ14 -> #N/A | AL14: =SUM(ERP[[#This Row],[AP01]:[AP06]])-SUM(ERP[[#This Row],[AP01 LE2]:[AP06 LE2]]) -> -650000 | AN14: =ERP[[#This Row],[2026 Working Total to Budget/LE]]-ERP[[#This Row],[Giveback]] -> #N/A | AO14: Acct Movement from Mike Hovanyetz to Chris Dougherty | AU14: 650000 | AV14: 0 | AW14: 0 | AX14: 0 | AY14: 0 | AZ14: 0 | BA14: 0 | BB14: 650000 | BH14: 650000 | BI14: 0 | BJ14: 0 | BK14: 0 | BL14: 0 | BM14: 0 | BN14: 0 | BO14: 650000
A15: N-ERP-571 | B15: Hovanyetz, Mike_SOFTWARE_2026-XFR-0017-A | C15: ERP | D15: Hase, Raj | E15: Hovanyetz, Mike | F15: DeHart, Lynn | G15: SOFTWARE | H15: Dedicated US PRIME Commerce Cloud - SAP Licenses | K15: 2026-XFR-0017-A | O15: 2026 Budget Transfer | P15: 4/28/26 CHW New add to tie-out 0223 to 0317 Planful Extracts Cost center change from Mike Hovanyetz to Chris Dougherty & removed forecast | R15: 650000 | S15: 0 | Z15: 0 | AA15: 0 | AB15: #N/A | AC15: 0 | AD15: 0 | AE15: 0 | AF15: 0 | AG15: 0 | AH15: =SUM(V15:AG15) -> #N/A | AI15: =ERP[[#This Row],[2026 Working Total]]-ERP[[#This Row],[LE2 Final Submission]] -> #N/A | AJ15: #N/A | AK15: =$AA15 - $AJ15 -> #N/A | AL15: =SUM(ERP[[#This Row],[AP01]:[AP06]])-SUM(ERP[[#This Row],[AP01 LE2]:[AP06 LE2]]) -> 0 | AN15: =ERP[[#This Row],[2026 Working Total to Budget/LE]]-ERP[[#This Row],[Giveback]] -> #N/A | AO15: Acct Movement from Mike Hovanyetz to Chris Dougherty | AS15: 0 | AT15: 0 | AU15: 0 | AV15: 0 | AW15: 0 | AX15: 0 | AY15: 0 | AZ15: 0 | BA15: 0 | BB15: 0 | BC15: 0 | BD15: 0 | BE15: 0 | BF15: 0 | BG15: 0 | BH15: 650000 | BI15: 0 | BJ15: 0 | BK15: 0 | BL15: 0 | BM15: 0 | BN15: 0 | BO15: =SUM(ERP[[#This Row],[2026 AP01]:[2026 AP12]]) -> 650000
A16: L-ERP-062 | B16: Dougherty, Chris_SOFTWARE_2026-XFR-0017-B | C16: ERP | D16: Dougherty, Chris | E16: Dougherty, Chris | F16: Maguire, Karla | G16: SOFTWARE | H16: Dedicated US PRIME Commerce Cloud - Middleware | K16: 2026-XFR-0017-B | O16: 2026 Budget Transfer | R16: 0 | S16: 300000 | Z16: 0 | AA16: 0 | AB16: #N/A | AC16: 0 | AD16: 0 | AE16: 300000 | AF16: 0 | AG16: 0 | AH16: =SUM(V16:AG16) -> #N/A | AI16: =ERP[[#This Row],[2026 Working Total]]-ERP[[#This Row],[LE2 Final Submission]] -> #N/A | AJ16: #N/A | AK16: =$AA16 - $AJ16 -> #N/A | AL16: =SUM(ERP[[#This Row],[AP01]:[AP06]])-SUM(ERP[[#This Row],[AP01 LE2]:[AP06 LE2]]) -> -300000 | AN16: =ERP[[#This Row],[2026 Working Total to Budget/LE]]-ERP[[#This Row],[Giveback]] -> #N/A | AO16: Acct Movement from Mike Hovanyetz to Chris Dougherty | AU16: 300000 | AV16: 0 | AW16: 0 | AX16: 0 | AY16: 0 | AZ16: 0 | BA16: 0 | BB16: 300000 | BH16: 300000 | BI16: 0 | BJ16: 0 | BK16: 0 | BL16: 0 | BM16: 0 | BN16: 0 | BO16: 300000
A17: N-ERP-572 | B17: Hovanyetz, Mike_SOFTWARE_2026-XFR-0017-B | C17: ERP | D17: Hase, Raj | E17: Hovanyetz, Mike | F17: DeHart, Lynn | G17: SOFTWARE | H17: Dedicated US PRIME Commerce Cloud - Middleware | K17: 2026-XFR-0017-B | O17: 2026 Budget Transfer | P17: 4/28/26 CHW New add to tie-out 0223 to 0317 Planful Extracts Cost center change from Mike Hovanyetz to Chris Dougherty & removed forecast | R17: 300000 | S17: 0 | Z17: 0 | AA17: 0 | AB17: #N/A | AC17: 0 | AD17: 0 | AE17: 0 | AF17: 0 | AG17: 0 | AH17: =SUM(V17:AG17) -> #N/A | AI17: =ERP[[#This Row],[2026 Working Total]]-ERP[[#This Row],[LE2 Final Submission]] -> #N/A | AJ17: #N/A | AK17: =$AA17 - $AJ17 -> #N/A | AL17: =SUM(ERP[[#This Row],[AP01]:[AP06]])-SUM(ERP[[#This Row],[AP01 LE2]:[AP06 LE2]]) -> 0 | AN17: =ERP[[#This Row],[2026 Working Total to Budget/LE]]-ERP[[#This Row],[Giveback]] -> #N/A | AO17: Acct Movement from Mike Hovanyetz to Chris Dougherty | AS17: 0 | AT17: 0 | AU17: 0 | AV17: 0 | AW17: 0 | AX17: 0 | AY17: 0 | AZ17: 0 | BA17: 0 | BB17: 0 | BC17: 0 | BD17: 0 | BE17: 0 | BF17: 0 | BG17: 0 | BH17: 300000 | BI17: 0 | BJ17: 0 | BK17: 0 | BL17: 0 | BM17: 0 | BN17: 0 | BO17: =SUM(ERP[[#This Row],[2026 AP01]:[2026 AP12]]) -> 300000
A18: L-ERP-502 | B18: Tamavada, Ram_MANAGED SERVICES_2026-XFR-0017-C | C18: ERP | D18: Dougherty, Chris | E18: Tamavada, Ram | F18: Maguire, Karla | G18: MANAGED SERVICES | H18: Dedicated US PRIME Commerce Cloud - US Prime Cloud Support | K18: 2026-XFR-0017-C | O18: 2026 Budget Transfer | R18: 0 | S18: 112500 | Z18: 0 | AA18: 0 | AB18: #N/A | AC18: 19000 | AD18: 19000 | AE18: 18500 | AF18: 18500 | AG18: 18500 | AH18: =SUM(V18:AG18) -> #N/A | AI18: =ERP[[#This Row],[2026 Working Total]]-ERP[[#This Row],[LE2 Final Submission]] -> #N/A | AJ18: #N/A | AK18: =$AA18 - $AJ18 -> #N/A | AL18: =SUM(ERP[[#This Row],[AP01]:[AP06]])-SUM(ERP[[#This Row],[AP01 LE2]:[AP06 LE2]]) -> -37500 | AN18: =ERP[[#This Row],[2026 Working Total to Budget/LE]]-ERP[[#This Row],[Giveback]] -> #N/A | AS18: 12500 | AT18: 12500 | AU18: 12500 | AV18: 12500 | AW18: 12500 | AX18: 12500 | AY18: 12500 | AZ18: 12500 | BA18: 12500 | BB18: 112500 | BF18: 12500 | BG18: 12500 | BH18: 12500 | BI18: 12500 | BJ18: 12500 | BK18: 12500 | BL18: 12500 | BM18: 12500 | BN18: 12500 | BO18: 112500
A19: N-ERP-568 | B19: Hovanyetz, Mike_MANAGED SERVICES_2026-XFR-0017-C | C19: ERP | D19: Hase, Raj | E19: Hovanyetz, Mike | F19: DeHart, Lynn | G19: MANAGED SERVICES | H19: Dedicated US PRIME Commerce Cloud - US Prime Cloud Support | K19: 2026-XFR-0017-C | O19: 2026 Budget Transfer | P19: 4/28/26 CHW New add to tie-out 0223 to 0317 Planful Extracts Transferred from Mike H to Chris Dougherty; zero forecast as moved to Chris | R19: 125000 | S19: 0 | Z19: 0 | AA19: 0 | AB19: #N/A | AC19: =12500-12500 -> 0 | AD19: =12500-12500 -> 0 | AE19: =12500-12500 -> 0 | AF19: =12500-12500 -> 0 | AG19: =12500-12500 -> 0 | AH19: =SUM(V19:AG19) -> #N/A | AI19: =ERP[[#This Row],[2026 Working Total]]-ERP[[#This Row],[LE2 Final Submission]] -> #N/A | AJ19: #N/A | AK19: =$AA19 - $AJ19 -> #N/A | AL19: =SUM(ERP[[#This Row],[AP01]:[AP06]])-SUM(ERP[[#This Row],[AP01 LE2]:[AP06 LE2]]) -> 0 | AN19: =ERP[[#This Row],[2026 Working Total to Budget/LE]]-ERP[[#This Row],[Giveback]] -> #N/A | AS19: 0 | AT19: 0 | AU19: 0 | AV19: 0 | AW19: 0 | AX19: 0 | AY19: 0 | AZ19: 0 | BA19: 0 | BB19: 0 | BC19: 0 | BD19: 0 | BE19: 12500 | BF19: 12500 | BG19: 12500 | BH19: 12500 | BI19: 12500 | BJ19: 12500 | BK19: 12500 | BL19: 12500 | BM19: 12500 | BN19: 12500 | BO19: =SUM(ERP[[#This Row],[2026 AP01]:[2026 AP12]]) -> 125000
A20: L-ERP-503 | B20: Tamavada, Ram_MANAGED SERVICES_2026-XFR-0017-D | C20: ERP | D20: Dougherty, Chris | E20: Tamavada, Ram | F20: Maguire, Karla | G20: MANAGED SERVICES | H20: Dedicated US PRIME Commerce Cloud - ACES/Inmar Support | K20: 2026-XFR-0017-D | O20: 2026 Budget Transfer | R20: 0 | S20: 90000 | Z20: 0 | AA20: 0 | AB20: #N/A | AC20: 15000 | AD20: 15000 | AE20: 15000 | AF20: 15000 | AG20: 15000 | AH20: =SUM(V20:AG20) -> #N/A | AI20: =ERP[[#This Row],[2026 Working Total]]-ERP[[#This Row],[LE2 Final Submission]] -> #N/A | AJ20: #N/A | AK20: =$AA20 - $AJ20 -> #N/A | AL20: =SUM(ERP[[#This Row],[AP01]:[AP06]])-SUM(ERP[[#This Row],[AP01 LE2]:[AP06 LE2]]) -> -30000 | AN20: =ERP[[#This Row],[2026 Working Total to Budget/LE]]-ERP[[#This Row],[Giveback]] -> #N/A | AS20: 10000 | AT20: 10000 | AU20: 10000 | AV20: 10000 | AW20: 10000 | AX20: 10000 | AY20: 10000 | AZ20: 10000 | BA20: 10000 | BB20: 90000 | BF20: 10000 | BG20: 10000 | BH20: 10000 | BI20: 10000 | BJ20: 10000 | BK20: 10000 | BL20: 10000 | BM20: 10000 | BN20: 10000 | BO20: 90000
A21: N-ERP-569 | B21: Hovanyetz, Mike_MANAGED SERVICES_2026-XFR-0017-D | C21: ERP | D21: Hase, Raj | E21: Hovanyetz, Mike | F21: DeHart, Lynn | G21: MANAGED SERVICES | H21: Dedicated US PRIME Commerce Cloud - ACES/Inmar Support | K21: 2026-XFR-0017-D | O21: 2026 Budget Transfer | P21: 4/28/26 CHW New add to tie-out 0223 to 0317 Planful Extracts Transferred from Mike H to Chris Dougherty; zero forecast as moved to Chris | R21: 100000 | S21: 0 | Z21: 0 | AA21: 0 | AB21: #N/A | AC21: =10000-10000 -> 0 | AD21: =10000-10000 -> 0 | AE21: =10000-10000 -> 0 | AF21: =10000-10000 -> 0 | AG21: =10000-10000 -> 0 | AH21: =SUM(V21:AG21) -> #N/A | AI21: =ERP[[#This Row],[2026 Working Total]]-ERP[[#This Row],[LE2 Final Submission]] -> #N/A | AJ21: #N/A | AK21: =$AA21 - $AJ21 -> #N/A | AL21: =SUM(ERP[[#This Row],[AP01]:[AP06]])-SUM(ERP[[#This Row],[AP01 LE2]:[AP06 LE2]]) -> 0 | AN21: =ERP[[#This Row],[2026 Working Total to Budget/LE]]-ERP[[#This Row],[Giveback]] -> #N/A | AS21: 0 | AT21: 0 | AU21: 0 | AV21: 0 | AW21: 0 | AX21: 0 | AY21: 0 | AZ21: 0 | BA21: 0 | BB21: 0 | BC21: 0 | BD21: 0 | BE21: 10000 | BF21: 10000 | BG21: 10000 | BH21: 10000 | BI21: 10000 | BJ21: 10000 | BK21: 10000 | BL21: 10000 | BM21: 10000 | BN21: 10000 | BO21: =SUM(ERP[[#This Row],[2026 AP01]:[2026 AP12]]) -> 100000
A22: L-ERP-505 | B22: Tamavada, Ram_MANAGED SERVICES_2026-XFR-0020-A | C22: ERP | D22: Dougherty, Chris | E22: Tamavada, Ram | F22: Maguire, Karla | G22: MANAGED SERVICES | H22: IBM: SAP Prime Global Customer Experience - IBM AMS support costs - SAP Commerce Cloud Prime GCx | K22: 2026-XFR-0020-A | O22: 2026 Budget Transfer; AMS | R22: 0 | S22: 56250 | Z22: 0 | AA22: 0 | AB22: #N/A | AC22: 9250 | AD22: 9500 | AE22: 9250 | AF22: 9500 | AG22: 9250 | AH22: =SUM(V22:AG22) -> #N/A | AI22: =ERP[[#This Row],[2026 Working Total]]-ERP[[#This Row],[LE2 Final Submission]] -> #N/A | AJ22: #N/A | AK22: =$AA22 - $AJ22 -> #N/A | AL22: =SUM(ERP[[#This Row],[AP01]:[AP06]])-SUM(ERP[[#This Row],[AP01 LE2]:[AP06 LE2]]) -> -18750 | AN22: =ERP[[#This Row],[2026 Working Total to Budget/LE]]-ERP[[#This Row],[Giveback]] -> #N/A | AS22: 6250 | AT22: 6250 | AU22: 6250 | AV22: 6250 | AW22: 6250 | AX22: 6250 | AY22: 6250 | AZ22: 6250 | BA22: 6250 | BB22: 56250 | BF22: 6250 | BG22: 6250 | BH22: 6250 | BI22: 6250 | BJ22: 6250 | BK22: 6250 | BL22: 6250 | BM22: 6250 | BN22: 6250 | BO22: 56250
A23: N-ERP-570 | B23: Hovanyetz, Mike_MANAGED SERVICES_2026-XFR-0020-A | C23: ERP | D23: Hase, Raj | E23: Hovanyetz, Mike | F23: DeHart, Lynn | G23: MANAGED SERVICES | H23: SAP Prime Global Customer Experience - IBM BTAMS support costs - SAP Commerce Cloud Prime GCx | K23: 2026-XFR-0020-A | O23: 2026 Budget Transfer | P23: 4/28/26 CHW New add to tie-out 0223 to 0317 Planful Extracts Transferred from Mike H to Chris Dougherty; zero forecast as moved to Chris | R23: 75000 | S23: 0 | Z23: 0 | AA23: 0 | AB23: #N/A | AC23: =6250-6250 -> 0 | AD23: =6250-6250 -> 0 | AE23: =6250-6250 -> 0 | AF23: =6250-6250 -> 0 | AG23: =6250-6250 -> 0 | AH23: =SUM(V23:AG23) -> #N/A | AI23: =ERP[[#This Row],[2026 Working Total]]-ERP[[#This Row],[LE2 Final Submission]] -> #N/A | AJ23: #N/A | AK23: =$AA23 - $AJ23 -> #N/A | AL23: =SUM(ERP[[#This Row],[AP01]:[AP06]])-SUM(ERP[[#This Row],[AP01 LE2]:[AP06 LE2]]) -> 0 | AN23: =ERP[[#This Row],[2026 Working Total to Budget/LE]]-ERP[[#This Row],[Giveback]] -> #N/A | AS23: 0 | AT23: 0 | AU23: 0 | AV23: 0 | AW23: 0 | AX23: 0 | AY23: 0 | AZ23: 0 | BA23: 0 | BB23: 0 | BC23: 6250 | BD23: 6250 | BE23: 6250 | BF23: 6250 | BG23: 6250 | BH23: 6250 | BI23: 6250 | BJ23: 6250 | BK23: 6250 | BL23: 6250 | BM23: 6250 | BN23: 6250 | BO23: =SUM(ERP[[#This Row],[2026 AP01]:[2026 AP12]]) -> 75000
A24: N-ERP-557 | B24: Ganesan, Srinivasan_CONTRACTORS_2026-XFR-0023-A | C24: ERP | D24: Hase, Raj | E24: Ganesan, Srinivasan | F24: DeHart, Lynn | G24: CONTRACTORS | H24: GSC AMER - Last Mile Strategy - Delivery Milestones & Dashboards - 50% One offshore contractor; New Global Capability. Only 0.5FTE requested for support. Eventually, will be transferred to BTAMS | K24: 2026-XFR-0023-A | O24: 2026 Budget Transfer | P24: 4/28/26 CHW New add to tie-out 0223 to 0317 Planful Extracts | R24: 70000 | S24: 0 | Z24: 0 | AA24: 0 | AB24: #N/A | AC24: 0 | AD24: 0 | AE24: 0 | AF24: 0 | AG24: 0 | AH24: =SUM(V24:AG24) -> #N/A | AI24: =ERP[[#This Row],[2026 Working Total]]-ERP[[#This Row],[LE2 Final Submission]] -> #N/A | AJ24: #N/A | AK24: =$AA24 - $AJ24 -> #N/A | AL24: =SUM(ERP[[#This Row],[AP01]:[AP06]])-SUM(ERP[[#This Row],[AP01 LE2]:[AP06 LE2]]) -> 0 | AM24: 70000 | AN24: =ERP[[#This Row],[2026 Working Total to Budget/LE]]-ERP[[#This Row],[Giveback]] -> #N/A | AO24: XFRs not needed in 2026 | AS24: 0 | AT24: 0 | AU24: 0 | AV24: 0 | AW24: 0 | AX24: 0 | AY24: 0 | AZ24: 0 | BA24: 0 | BB24: 0 | BC24: 5833.37 | BD24: 5833.33 | BE24: 5833.33 | BF24: 5833.33 | BG24: 5833.33 | BH24: 5833.33 | BI24: 5833.33 | BJ24: 5833.33 | BK24: 5833.33 | BL24: 5833.33 | BM24: 5833.33 | BN24: 5833.33 | BO24: =SUM(ERP[[#This Row],[2026 AP01]:[2026 AP12]]) -> 70000
A25: N-ERP-558 | B25: Ganesan, Srinivasan_CONTRACTORS_2026-XFR-0024-A | C25: ERP | D25: Hase, Raj | E25: Ganesan, Srinivasan | F25: DeHart, Lynn | G25: CONTRACTORS | H25: GSC AMER: MIRT Replacement - Phase II and deploy to other markets - 1 Offshore contractor. New capability for Late repackaging. This is a solution resource. | K25: 2026-XFR-0024-A | O25: 2026 Budget Transfer | P25: 4/28/26 CHW New add to tie-out 0223 to 0317 Planful Extracts 2/20 Updated per RG - able to leverate existing contractors | R25: 120000 | S25: 0 | Z25: 0 | AA25: 0 | AB25: #N/A | AC25: 0 | AD25: 0 | AE25: 0 | AF25: 0 | AG25: 0 | AH25: =SUM(V25:AG25) -> #N/A | AI25: =ERP[[#This Row],[2026 Working Total]]-ERP[[#This Row],[LE2 Final Submission]] -> #N/A | AJ25: #N/A | AK25: =$AA25 - $AJ25 -> #N/A | AL25: =SUM(ERP[[#This Row],[AP01]:[AP06]])-SUM(ERP[[#This Row],[AP01 LE2]:[AP06 LE2]]) -> 0 | AM25: 120000 | AN25: =ERP[[#This Row],[2026 Working Total to Budget/LE]]-ERP[[#This Row],[Giveback]] -> #N/A | AO25: XFRs not needed in 2026 | AS25: 0 | AT25: 0 | AU25: 0 | AV25: 0 | AW25: 0 | AX25: 0 | AY25: 0 | AZ25: 0 | BA25: 0 | BB25: 0 | BC25: 10000 | BD25: 10000 | BE25: 10000 | BF25: 10000 | BG25: 10000 | BH25: 10000 | BI25: 10000 | BJ25: 10000 | BK25: 10000 | BL25: 10000 | BM25: 10000 | BN25: 10000 | BO25: =SUM(ERP[[#This Row],[2026 AP01]:[2026 AP12]]) -> 120000
